Workbook

Sheet Coverage
A1: # | B1: Resort | C1: Official site status | D1: factsheet (latest yr) | E1: wedding (latest yr) | F1: events (latest yr) | G1: destination_dining (latest yr) | H1: map (latest yr) | I1: dive_map (latest yr) | J1: spa_menu (latest yr) | K1: dining_menu (latest yr) | L1: dive_prices (latest yr) | M1: excursions (latest yr) | N1: kids (latest yr) | O1: villa_plans (latest yr) | P1: all_inclusive (latest yr) | Q1: sustainability (latest yr) | R1: calendar (latest yr) | S1: brochure (latest yr) | T1: press_kit (latest yr) | U1: other (latest yr) | V1: obsolete (latest yr) | W1: Total docs | X1: Current docs | Y1: Latest factsheet | Z1: Gaps (priority 1) | AA1: Rename notes
A2: 1 | B2: Six Senses Laamu | C2: blocked | D2: =IFERROR(IF(_xlfn.MAXIFS(Documents!$E$2:$E$3728,Documents!$A$2:$A$3728,$A2,Documents!$C$2:$C$3728,"factsheet")=0,"",_xlfn.MAXIFS(Documents!$E$2:$E$3728,Documents!$A$2:$A$3728,$A2,Documents!$C$2:$C$3728,"factsheet")),"") | E2: =IFERROR(IF(_xlfn.MAXIFS(Documents!$E$2:$E$3728,Documents!$A$2:$A$3728,$A2,Documents!$C$2:$C$3728,"wedding")=0,"",_xlfn.MAXIFS(Documents!$E$2:$E$3728,Documents!$A$2:$A$3728,$A2,Documents!$C$2:$C$3728,"wedding")),"") | F2: =IFERROR(IF(_xlfn.MAXIFS(Documents!$E$2:$E$3728,Documents!$A$2:$A$3728,$A2,Documents!$C$2:$C$3728,"events")=0,"",_xlfn.MAXIFS(Documents!$E$2:$E$3728,Documents!$A$2:$A$3728,$A2,Documents!$C$2:$C$3728,"events")),"") | G2: =IFERROR(IF(_xlfn.MAXIFS(Documents!$E$2:$E$3728,Documents!$A$2:$A$3728,$A2,Documents!$C$2:$C$3728,"destination_dining")=0,"",_xlfn.MAXIFS(Documents!$E$2:$E$3728,Documents!$A$2:$A$3728,$A2,Documents!$C$2:$C$3728,"destination_dining")),"") | H2: =IFERROR(IF(_xlfn.MAXIFS(Documents!$E$2:$E$3728,Documents!$A$2:$A$3728,$A2,Documents!$C$2:$C$3728,"map")=0,"",_xlfn.MAXIFS(Documents!$E$2:$E$3728,Documents!$A$2:$A$3728,$A2,Documents!$C$2:$C$3728,"map")),"") | I2: =IFERROR(IF(_xlfn.MAXIFS(Documents!$E$2:$E$3728,Documents!$A$2:$A$3728,$A2,Documents!$C$2:$C$3728,"dive_map")=0,"",_xlfn.MAXIFS(Documents!$E$2:$E$3728,Documents!$A$2:$A$3728,$A2,Documents!$C$2:$C$3728,"dive_map")),"") | J2: =IFERROR(IF(_xlfn.MAXIFS(Documents!$E$2:$E$3728,Documents!$A$2:$A$3728,$A2,Documents!$C$2:$C$3728,"spa_menu")=0,"",_xlfn.MAXIFS(Documents!$E$2:$E$3728,Documents!$A$2:$A$3728,$A2,Documents!$C$2:$C$3728,"spa_menu")),"") | K2: =IFERROR(IF(_xlfn.MAXIFS(Documents!$E$2:$E$3728,Documents!$A$2:$A$3728,$A2,Documents!$C$2:$C$3728,"dining_menu")=0,"",_xlfn.MAXIFS(Documents!$E$2:$E$3728,Documents!$A$2:$A$3728,$A2,Documents!$C$2:$C$3728,"dining_menu")),"") | L2: =IFERROR(IF(_xlfn.MAXIFS(Documents!$E$2:$E$3728,Documents!$A$2:$A$3728,$A2,Documents!$C$2:$C$3728,"dive_prices")=0,"",_xlfn.MAXIFS(Documents!$E$2:$E$3728,Documents!$A$2:$A$3728,$A2,Documents!$C$2:$C$3728,"dive_prices")),"") | M2: =IFERROR(IF(_xlfn.MAXIFS(Documents!$E$2:$E$3728,Documents!$A$2:$A$3728,$A2,Documents!$C$2:$C$3728,"excursions")=0,"",_xlfn.MAXIFS(Documents!$E$2:$E$3728,Documents!$A$2:$A$3728,$A2,Documents!$C$2:$C$3728,"excursions")),"") | N2: =IFERROR(IF(_xlfn.MAXIFS(Documents!$E$2:$E$3728,Documents!$A$2:$A$3728,$A2,Documents!$C$2:$C$3728,"kids")=0,"",_xlfn.MAXIFS(Documents!$E$2:$E$3728,Documents!$A$2:$A$3728,$A2,Documents!$C$2:$C$3728,"kids")),"") | O2: =IFERROR(IF(_xlfn.MAXIFS(Documents!$E$2:$E$3728,Documents!$A$2:$A$3728,$A2,Documents!$C$2:$C$3728,"villa_plans")=0,"",_xlfn.MAXIFS(Documents!$E$2:$E$3728,Documents!$A$2:$A$3728,$A2,Documents!$C$2:$C$3728,"villa_plans")),"") | P2: =IFERROR(IF(_xlfn.MAXIFS(Documents!$E$2:$E$3728,Documents!$A$2:$A$3728,$A2,Documents!$C$2:$C$3728,"all_inclusive")=0,"",_xlfn.MAXIFS(Documents!$E$2:$E$3728,Documents!$A$2:$A$3728,$A2,Documents!$C$2:$C$3728,"all_inclusive")),"") | Q2: =IFERROR(IF(_xlfn.MAXIFS(Documents!$E$2:$E$3728,Documents!$A$2:$A$3728,$A2,Documents!$C$2:$C$3728,"sustainability")=0,"",_xlfn.MAXIFS(Documents!$E$2:$E$3728,Documents!$A$2:$A$3728,$A2,Documents!$C$2:$C$3728,"sustainability")),"") | R2: =IFERROR(IF(_xlfn.MAXIFS(Documents!$E$2:$E$3728,Documents!$A$2:$A$3728,$A2,Documents!$C$2:$C$3728,"calendar")=0,"",_xlfn.MAXIFS(Documents!$E$2:$E$3728,Documents!$A$2:$A$3728,$A2,Documents!$C$2:$C$3728,"calendar")),"") | S2: =IFERROR(IF(_xlfn.MAXIFS(Documents!$E$2:$E$3728,Documents!$A$2:$A$3728,$A2,Documents!$C$2:$C$3728,"brochure")=0,"",_xlfn.MAXIFS(Documents!$E$2:$E$3728,Documents!$A$2:$A$3728,$A2,Documents!$C$2:$C$3728,"brochure")),"") | T2: =IFERROR(IF(_xlfn.MAXIFS(Documents!$E$2:$E$3728,Documents!$A$2:$A$3728,$A2,Documents!$C$2:$C$3728,"press_kit")=0,"",_xlfn.MAXIFS(Documents!$E$2:$E$3728,Documents!$A$2:$A$3728,$A2,Documents!$C$2:$C$3728,"press_kit")),"") | U2: =IFERROR(IF(_xlfn.MAXIFS(Documents!$E$2:$E$3728,Documents!$A$2:$A$3728,$A2,Documents!$C$2:$C$3728,"other")=0,"",_xlfn.MAXIFS(Documents!$E$2:$E$3728,Documents!$A$2:$A$3728,$A2,Documents!$C$2:$C$3728,"other")),"") | V2: =IFERROR(IF(_xlfn.MAXIFS(Documents!$E$2:$E$3728,Documents!$A$2:$A$3728,$A2,Documents!$C$2:$C$3728,"obsolete")=0,"",_xlfn.MAXIFS(Documents!$E$2:$E$3728,Documents!$A$2:$A$3728,$A2,Documents!$C$2:$C$3728,"obsolete")),"") | W2: =COUNTIFS(Documents!$A$2:$A$3728,$A2) | X2: =COUNTIFS(Documents!$A$2:$A$3728,$A2,Documents!$R$2:$R$3728,"current") | Z2: factsheet, wedding, events
A3: 2 | B3: Filitheyo Island Resort | C3: blocked-partial | D3: =IFERROR(IF(_xlfn.MAXIFS(Documents!$E$2:$E$3728,Documents!$A$2:$A$3728,$A3,Documents!$C$2:$C$3728,"factsheet")=0,"",_xlfn.MAXIFS(Documents!$E$2:$E$3728,Documents!$A$2:$A$3728,$A3,Documents!$C$2:$C$3728,"factsheet")),"") | E3: =IFERROR(IF(_xlfn.MAXIFS(Documents!$E$2:$E$3728,Documents!$A$2:$A$3728,$A3,Documents!$C$2:$C$3728,"wedding")=0,"",_xlfn.MAXIFS(Documents!$E$2:$E$3728,Documents!$A$2:$A$3728,$A3,Documents!$C$2:$C$3728,"wedding")),"") | F3: =IFERROR(IF(_xlfn.MAXIFS(Documents!$E$2:$E$3728,Documents!$A$2:$A$3728,$A3,Documents!$C$2:$C$3728,"events")=0,"",_xlfn.MAXIFS(Documents!$E$2:$E$3728,Documents!$A$2:$A$3728,$A3,Documents!$C$2:$C$3728,"events")),"") | G3: =IFERROR(IF(_xlfn.MAXIFS(Documents!$E$2:$E$3728,Documents!$A$2:$A$3728,$A3,Documents!$C$2:$C$3728,"destination_dining")=0,"",_xlfn.MAXIFS(Documents!$E$2:$E$3728,Documents!$A$2:$A$3728,$A3,Documents!$C$2:$C$3728,"destination_dining")),"") | H3: =IFERROR(IF(_xlfn.MAXIFS(Documents!$E$2:$E$3728,Documents!$A$2:$A$3728,$A3,Documents!$C$2:$C$3728,"map")=0,"",_xlfn.MAXIFS(Documents!$E$2:$E$3728,Documents!$A$2:$A$3728,$A3,Documents!$C$2:$C$3728,"map")),"") | I3: =IFERROR(IF(_xlfn.MAXIFS(Documents!$E$2:$E$3728,Documents!$A$2:$A$3728,$A3,Documents!$C$2:$C$3728,"dive_map")=0,"",_xlfn.MAXIFS(Documents!$E$2:$E$3728,Documents!$A$2:$A$3728,$A3,Documents!$C$2:$C$3728,"dive_map")),"") | J3: =IFERROR(IF(_xlfn.MAXIFS(Documents!$E$2:$E$3728,Documents!$A$2:$A$3728,$A3,Documents!$C$2:$C$3728,"spa_menu")=0,"",_xlfn.MAXIFS(Documents!$E$2:$E$3728,Documents!$A$2:$A$3728,$A3,Documents!$C$2:$C$3728,"spa_menu")),"") | K3: =IFERROR(IF(_xlfn.MAXIFS(Documents!$E$2:$E$3728,Documents!$A$2:$A$3728,$A3,Documents!$C$2:$C$3728,"dining_menu")=0,"",_xlfn.MAXIFS(Documents!$E$2:$E$3728,Documents!$A$2:$A$3728,$A3,Documents!$C$2:$C$3728,"dining_menu")),"") | L3: =IFERROR(IF(_xlfn.MAXIFS(Documents!$E$2:$E$3728,Documents!$A$2:$A$3728,$A3,Documents!$C$2:$C$3728,"dive_prices")=0,"",_xlfn.MAXIFS(Documents!$E$2:$E$3728,Documents!$A$2:$A$3728,$A3,Documents!$C$2:$C$3728,"dive_prices")),"") | M3: =IFERROR(IF(_xlfn.MAXIFS(Documents!$E$2:$E$3728,Documents!$A$2:$A$3728,$A3,Documents!$C$2:$C$3728,"excursions")=0,"",_xlfn.MAXIFS(Documents!$E$2:$E$3728,Documents!$A$2:$A$3728,$A3,Documents!$C$2:$C$3728,"excursions")),"") | N3: =IFERROR(IF(_xlfn.MAXIFS(Documents!$E$2:$E$3728,Documents!$A$2:$A$3728,$A3,Documents!$C$2:$C$3728,"kids")=0,"",_xlfn.MAXIFS(Documents!$E$2:$E$3728,Documents!$A$2:$A$3728,$A3,Documents!$C$2:$C$3728,"kids")),"") | O3: =IFERROR(IF(_xlfn.MAXIFS(Documents!$E$2:$E$3728,Documents!$A$2:$A$3728,$A3,Documents!$C$2:$C$3728,"villa_plans")=0,"",_xlfn.MAXIFS(Documents!$E$2:$E$3728,Documents!$A$2:$A$3728,$A3,Documents!$C$2:$C$3728,"villa_plans")),"") | P3: =IFERROR(IF(_xlfn.MAXIFS(Documents!$E$2:$E$3728,Documents!$A$2:$A$3728,$A3,Documents!$C$2:$C$3728,"all_inclusive")=0,"",_xlfn.MAXIFS(Documents!$E$2:$E$3728,Documents!$A$2:$A$3728,$A3,Documents!$C$2:$C$3728,"all_inclusive")),"") | Q3: =IFERROR(IF(_xlfn.MAXIFS(Documents!$E$2:$E$3728,Documents!$A$2:$A$3728,$A3,Documents!$C$2:$C$3728,"sustainability")=0,"",_xlfn.MAXIFS(Documents!$E$2:$E$3728,Documents!$A$2:$A$3728,$A3,Documents!$C$2:$C$3728,"sustainability")),"") | R3: =IFERROR(IF(_xlfn.MAXIFS(Documents!$E$2:$E$3728,Documents!$A$2:$A$3728,$A3,Documents!$C$2:$C$3728,"calendar")=0,"",_xlfn.MAXIFS(Documents!$E$2:$E$3728,Documents!$A$2:$A$3728,$A3,Documents!$C$2:$C$3728,"calendar")),"") | S3: =IFERROR(IF(_xlfn.MAXIFS(Documents!$E$2:$E$3728,Documents!$A$2:$A$3728,$A3,Documents!$C$2:$C$3728,"brochure")=0,"",_xlfn.MAXIFS(Documents!$E$2:$E$3728,Documents!$A$2:$A$3728,$A3,Documents!$C$2:$C$3728,"brochure")),"") | T3: =IFERROR(IF(_xlfn.MAXIFS(Documents!$E$2:$E$3728,Documents!$A$2:$A$3728,$A3,Documents!$C$2:$C$3728,"press_kit")=0,"",_xlfn.MAXIFS(Documents!$E$2:$E$3728,Documents!$A$2:$A$3728,$A3,Documents!$C$2:$C$3728,"press_kit")),"") | U3: =IFERROR(IF(_xlfn.MAXIFS(Documents!$E$2:$E$3728,Documents!$A$2:$A$3728,$A3,Documents!$C$2:$C$3728,"other")=0,"",_xlfn.MAXIFS(Documents!$E$2:$E$3728,Documents!$A$2:$A$3728,$A3,Documents!$C$2:$C$3728,"other")),"") | V3: =IFERROR(IF(_xlfn.MAXIFS(Documents!$E$2:$E$3728,Documents!$A$2:$A$3728,$A3,Documents!$C$2:$C$3728,"obsolete")=0,"",_xlfn.MAXIFS(Documents!$E$2:$E$3728,Documents!$A$2:$A$3728,$A3,Documents!$C$2:$C$3728,"obsolete")),"") | W3: =COUNTIFS(Documents!$A$2:$A$3728,$A3) | X3: =COUNTIFS(Documents!$A$2:$A$3728,$A3,Documents!$R$2:$R$3728,"current") | Z3: factsheet, wedding, events
A4: 3 | B4: Adaaran Select Hudhuranfushi | C4: ok | D4: =IFERROR(IF(_xlfn.MAXIFS(Documents!$E$2:$E$3728,Documents!$A$2:$A$3728,$A4,Documents!$C$2:$C$3728,"factsheet")=0,"",_xlfn.MAXIFS(Documents!$E$2:$E$3728,Documents!$A$2:$A$3728,$A4,Documents!$C$2:$C$3728,"factsheet")),"") | E4: =IFERROR(IF(_xlfn.MAXIFS(Documents!$E$2:$E$3728,Documents!$A$2:$A$3728,$A4,Documents!$C$2:$C$3728,"wedding")=0,"",_xlfn.MAXIFS(Documents!$E$2:$E$3728,Documents!$A$2:$A$3728,$A4,Documents!$C$2:$C$3728,"wedding")),"") | F4: =IFERROR(IF(_xlfn.MAXIFS(Documents!$E$2:$E$3728,Documents!$A$2:$A$3728,$A4,Documents!$C$2:$C$3728,"events")=0,"",_xlfn.MAXIFS(Documents!$E$2:$E$3728,Documents!$A$2:$A$3728,$A4,Documents!$C$2:$C$3728,"events")),"") | G4: =IFERROR(IF(_xlfn.MAXIFS(Documents!$E$2:$E$3728,Documents!$A$2:$A$3728,$A4,Documents!$C$2:$C$3728,"destination_dining")=0,"",_xlfn.MAXIFS(Documents!$E$2:$E$3728,Documents!$A$2:$A$3728,$A4,Documents!$C$2:$C$3728,"destination_dining")),"") | H4: =IFERROR(IF(_xlfn.MAXIFS(Documents!$E$2:$E$3728,Documents!$A$2:$A$3728,$A4,Documents!$C$2:$C$3728,"map")=0,"",_xlfn.MAXIFS(Documents!$E$2:$E$3728,Documents!$A$2:$A$3728,$A4,Documents!$C$2:$C$3728,"map")),"") | I4: =IFERROR(IF(_xlfn.MAXIFS(Documents!$E$2:$E$3728,Documents!$A$2:$A$3728,$A4,Documents!$C$2:$C$3728,"dive_map")=0,"",_xlfn.MAXIFS(Documents!$E$2:$E$3728,Documents!$A$2:$A$3728,$A4,Documents!$C$2:$C$3728,"dive_map")),"") | J4: =IFERROR(IF(_xlfn.MAXIFS(Documents!$E$2:$E$3728,Documents!$A$2:$A$3728,$A4,Documents!$C$2:$C$3728,"spa_menu")=0,"",_xlfn.MAXIFS(Documents!$E$2:$E$3728,Documents!$A$2:$A$3728,$A4,Documents!$C$2:$C$3728,"spa_menu")),"") | K4: =IFERROR(IF(_xlfn.MAXIFS(Documents!$E$2:$E$3728,Documents!$A$2:$A$3728,$A4,Documents!$C$2:$C$3728,"dining_menu")=0,"",_xlfn.MAXIFS(Documents!$E$2:$E$3728,Documents!$A$2:$A$3728,$A4,Documents!$C$2:$C$3728,"dining_menu")),"") | L4: =IFERROR(IF(_xlfn.MAXIFS(Documents!$E$2:$E$3728,Documents!$A$2:$A$3728,$A4,Documents!$C$2:$C$3728,"dive_prices")=0,"",_xlfn.MAXIFS(Documents!$E$2:$E$3728,Documents!$A$2:$A$3728,$A4,Documents!$C$2:$C$3728,"dive_prices")),"") | M4: =IFERROR(IF(_xlfn.MAXIFS(Documents!$E$2:$E$3728,Documents!$A$2:$A$3728,$A4,Documents!$C$2:$C$3728,"excursions")=0,"",_xlfn.MAXIFS(Documents!$E$2:$E$3728,Documents!$A$2:$A$3728,$A4,Documents!$C$2:$C$3728,"excursions")),"") | N4: =IFERROR(IF(_xlfn.MAXIFS(Documents!$E$2:$E$3728,Documents!$A$2:$A$3728,$A4,Documents!$C$2:$C$3728,"kids")=0,"",_xlfn.MAXIFS(Documents!$E$2:$E$3728,Documents!$A$2:$A$3728,$A4,Documents!$C$2:$C$3728,"kids")),"") | O4: =IFERROR(IF(_xlfn.MAXIFS(Documents!$E$2:$E$3728,Documents!$A$2:$A$3728,$A4,Documents!$C$2:$C$3728,"villa_plans")=0,"",_xlfn.MAXIFS(Documents!$E$2:$E$3728,Documents!$A$2:$A$3728,$A4,Documents!$C$2:$C$3728,"villa_plans")),"") | P4: =IFERROR(IF(_xlfn.MAXIFS(Documents!$E$2:$E$3728,Documents!$A$2:$A$3728,$A4,Documents!$C$2:$C$3728,"all_inclusive")=0,"",_xlfn.MAXIFS(Documents!$E$2:$E$3728,Documents!$A$2:$A$3728,$A4,Documents!$C$2:$C$3728,"all_inclusive")),"") | Q4: =IFERROR(IF(_xlfn.MAXIFS(Documents!$E$2:$E$3728,Documents!$A$2:$A$3728,$A4,Documents!$C$2:$C$3728,"sustainability")=0,"",_xlfn.MAXIFS(Documents!$E$2:$E$3728,Documents!$A$2:$A$3728,$A4,Documents!$C$2:$C$3728,"sustainability")),"") | R4: =IFERROR(IF(_xlfn.MAXIFS(Documents!$E$2:$E$3728,Documents!$A$2:$A$3728,$A4,Documents!$C$2:$C$3728,"calendar")=0,"",_xlfn.MAXIFS(Documents!$E$2:$E$3728,Documents!$A$2:$A$3728,$A4,Documents!$C$2:$C$3728,"calendar")),"") | S4: =IFERROR(IF(_xlfn.MAXIFS(Documents!$E$2:$E$3728,Documents!$A$2:$A$3728,$A4,Documents!$C$2:$C$3728,"brochure")=0,"",_xlfn.MAXIFS(Documents!$E$2:$E$3728,Documents!$A$2:$A$3728,$A4,Documents!$C$2:$C$3728,"brochure")),"") | T4: =IFERROR(IF(_xlfn.MAXIFS(Documents!$E$2:$E$3728,Documents!$A$2:$A$3728,$A4,Documents!$C$2:$C$3728,"press_kit")=0,"",_xlfn.MAXIFS(Documents!$E$2:$E$3728,Documents!$A$2:$A$3728,$A4,Documents!$C$2:$C$3728,"press_kit")),"") | U4: =IFERROR(IF(_xlfn.MAXIFS(Documents!$E$2:$E$3728,Documents!$A$2:$A$3728,$A4,Documents!$C$2:$C$3728,"other")=0,"",_xlfn.MAXIFS(Documents!$E$2:$E$3728,Documents!$A$2:$A$3728,$A4,Documents!$C$2:$C$3728,"other")),"") | V4: =IFERROR(IF(_xlfn.MAXIFS(Documents!$E$2:$E$3728,Documents!$A$2:$A$3728,$A4,Documents!$C$2:$C$3728,"obsolete")=0,"",_xlfn.MAXIFS(Documents!$E$2:$E$3728,Documents!$A$2:$A$3728,$A4,Documents!$C$2:$C$3728,"obsolete")),"") | W4: =COUNTIFS(Documents!$A$2:$A$3728,$A4) | X4: =COUNTIFS(Documents!$A$2:$A$3728,$A4,Documents!$R$2:$R$3728,"current") | Y4: =HYPERLINK("https://www.adaaran.com/selecthudhuranfushi/view-download/?id=menu-16","2026_document.pdf")
A5: 4 | B5: Ayada Maldives | C5: ok | D5: =IFERROR(IF(_xlfn.MAXIFS(Documents!$E$2:$E$3728,Documents!$A$2:$A$3728,$A5,Documents!$C$2:$C$3728,"factsheet")=0,"",_xlfn.MAXIFS(Documents!$E$2:$E$3728,Documents!$A$2:$A$3728,$A5,Documents!$C$2:$C$3728,"factsheet")),"") | E5: =IFERROR(IF(_xlfn.MAXIFS(Documents!$E$2:$E$3728,Documents!$A$2:$A$3728,$A5,Documents!$C$2:$C$3728,"wedding")=0,"",_xlfn.MAXIFS(Documents!$E$2:$E$3728,Documents!$A$2:$A$3728,$A5,Documents!$C$2:$C$3728,"wedding")),"") | F5: =IFERROR(IF(_xlfn.MAXIFS(Documents!$E$2:$E$3728,Documents!$A$2:$A$3728,$A5,Documents!$C$2:$C$3728,"events")=0,"",_xlfn.MAXIFS(Documents!$E$2:$E$3728,Documents!$A$2:$A$3728,$A5,Documents!$C$2:$C$3728,"events")),"") | G5: =IFERROR(IF(_xlfn.MAXIFS(Documents!$E$2:$E$3728,Documents!$A$2:$A$3728,$A5,Documents!$C$2:$C$3728,"destination_dining")=0,"",_xlfn.MAXIFS(Documents!$E$2:$E$3728,Documents!$A$2:$A$3728,$A5,Documents!$C$2:$C$3728,"destination_dining")),"") | H5: =IFERROR(IF(_xlfn.MAXIFS(Documents!$E$2:$E$3728,Documents!$A$2:$A$3728,$A5,Documents!$C$2:$C$3728,"map")=0,"",_xlfn.MAXIFS(Documents!$E$2:$E$3728,Documents!$A$2:$A$3728,$A5,Documents!$C$2:$C$3728,"map")),"") | I5: =IFERROR(IF(_xlfn.MAXIFS(Documents!$E$2:$E$3728,Documents!$A$2:$A$3728,$A5,Documents!$C$2:$C$3728,"dive_map")=0,"",_xlfn.MAXIFS(Documents!$E$2:$E$3728,Documents!$A$2:$A$3728,$A5,Documents!$C$2:$C$3728,"dive_map")),"") | J5: =IFERROR(IF(_xlfn.MAXIFS(Documents!$E$2:$E$3728,Documents!$A$2:$A$3728,$A5,Documents!$C$2:$C$3728,"spa_menu")=0,"",_xlfn.MAXIFS(Documents!$E$2:$E$3728,Documents!$A$2:$A$3728,$A5,Documents!$C$2:$C$3728,"spa_menu")),"") | K5: =IFERROR(IF(_xlfn.MAXIFS(Documents!$E$2:$E$3728,Documents!$A$2:$A$3728,$A5,Documents!$C$2:$C$3728,"dining_menu")=0,"",_xlfn.MAXIFS(Documents!$E$2:$E$3728,Documents!$A$2:$A$3728,$A5,Documents!$C$2:$C$3728,"dining_menu")),"") | L5: =IFERROR(IF(_xlfn.MAXIFS(Documents!$E$2:$E$3728,Documents!$A$2:$A$3728,$A5,Documents!$C$2:$C$3728,"dive_prices")=0,"",_xlfn.MAXIFS(Documents!$E$2:$E$3728,Documents!$A$2:$A$3728,$A5,Documents!$C$2:$C$3728,"dive_prices")),"") | M5: =IFERROR(IF(_xlfn.MAXIFS(Documents!$E$2:$E$3728,Documents!$A$2:$A$3728,$A5,Documents!$C$2:$C$3728,"excursions")=0,"",_xlfn.MAXIFS(Documents!$E$2:$E$3728,Documents!$A$2:$A$3728,$A5,Documents!$C$2:$C$3728,"excursions")),"") | N5: =IFERROR(IF(_xlfn.MAXIFS(Documents!$E$2:$E$3728,Documents!$A$2:$A$3728,$A5,Documents!$C$2:$C$3728,"kids")=0,"",_xlfn.MAXIFS(Documents!$E$2:$E$3728,Documents!$A$2:$A$3728,$A5,Documents!$C$2:$C$3728,"kids")),"") | O5: =IFERROR(IF(_xlfn.MAXIFS(Documents!$E$2:$E$3728,Documents!$A$2:$A$3728,$A5,Documents!$C$2:$C$3728,"villa_plans")=0,"",_xlfn.MAXIFS(Documents!$E$2:$E$3728,Documents!$A$2:$A$3728,$A5,Documents!$C$2:$C$3728,"villa_plans")),"") | P5: =IFERROR(IF(_xlfn.MAXIFS(Documents!$E$2:$E$3728,Documents!$A$2:$A$3728,$A5,Documents!$C$2:$C$3728,"all_inclusive")=0,"",_xlfn.MAXIFS(Documents!$E$2:$E$3728,Documents!$A$2:$A$3728,$A5,Documents!$C$2:$C$3728,"all_inclusive")),"") | Q5: =IFERROR(IF(_xlfn.MAXIFS(Documents!$E$2:$E$3728,Documents!$A$2:$A$3728,$A5,Documents!$C$2:$C$3728,"sustainability")=0,"",_xlfn.MAXIFS(Documents!$E$2:$E$3728,Documents!$A$2:$A$3728,$A5,Documents!$C$2:$C$3728,"sustainability")),"") | R5: =IFERROR(IF(_xlfn.MAXIFS(Documents!$E$2:$E$3728,Documents!$A$2:$A$3728,$A5,Documents!$C$2:$C$3728,"calendar")=0,"",_xlfn.MAXIFS(Documents!$E$2:$E$3728,Documents!$A$2:$A$3728,$A5,Documents!$C$2:$C$3728,"calendar")),"") | S5: =IFERROR(IF(_xlfn.MAXIFS(Documents!$E$2:$E$3728,Documents!$A$2:$A$3728,$A5,Documents!$C$2:$C$3728,"brochure")=0,"",_xlfn.MAXIFS(Documents!$E$2:$E$3728,Documents!$A$2:$A$3728,$A5,Documents!$C$2:$C$3728,"brochure")),"") | T5: =IFERROR(IF(_xlfn.MAXIFS(Documents!$E$2:$E$3728,Documents!$A$2:$A$3728,$A5,Documents!$C$2:$C$3728,"press_kit")=0,"",_xlfn.MAXIFS(Documents!$E$2:$E$3728,Documents!$A$2:$A$3728,$A5,Documents!$C$2:$C$3728,"press_kit")),"") | U5: =IFERROR(IF(_xlfn.MAXIFS(Documents!$E$2:$E$3728,Documents!$A$2:$A$3728,$A5,Documents!$C$2:$C$3728,"other")=0,"",_xlfn.MAXIFS(Documents!$E$2:$E$3728,Documents!$A$2:$A$3728,$A5,Documents!$C$2:$C$3728,"other")),"") | V5: =IFERROR(IF(_xlfn.MAXIFS(Documents!$E$2:$E$3728,Documents!$A$2:$A$3728,$A5,Documents!$C$2:$C$3728,"obsolete")=0,"",_xlfn.MAXIFS(Documents!$E$2:$E$3728,Documents!$A$2:$A$3728,$A5,Documents!$C$2:$C$3728,"obsolete")),"") | W5: =COUNTIFS(Documents!$A$2:$A$3728,$A5) | X5: =COUNTIFS(Documents!$A$2:$A$3728,$A5,Documents!$R$2:$R$3728,"current") | Y5: =HYPERLINK("https://www.neoscapesmaldives.com/wp-content/uploads/Ayada-Maldives-Factsheet.pdf","2024_Ayada-Maldives-Factsheet.pdf") | Z5: events
A6: 5 | B6: Bolifushi Island Resort | C6: blocked | D6: =IFERROR(IF(_xlfn.MAXIFS(Documents!$E$2:$E$3728,Documents!$A$2:$A$3728,$A6,Documents!$C$2:$C$3728,"factsheet")=0,"",_xlfn.MAXIFS(Documents!$E$2:$E$3728,Documents!$A$2:$A$3728,$A6,Documents!$C$2:$C$3728,"factsheet")),"") | E6: =IFERROR(IF(_xlfn.MAXIFS(Documents!$E$2:$E$3728,Documents!$A$2:$A$3728,$A6,Documents!$C$2:$C$3728,"wedding")=0,"",_xlfn.MAXIFS(Documents!$E$2:$E$3728,Documents!$A$2:$A$3728,$A6,Documents!$C$2:$C$3728,"wedding")),"") | F6: =IFERROR(IF(_xlfn.MAXIFS(Documents!$E$2:$E$3728,Documents!$A$2:$A$3728,$A6,Documents!$C$2:$C$3728,"events")=0,"",_xlfn.MAXIFS(Documents!$E$2:$E$3728,Documents!$A$2:$A$3728,$A6,Documents!$C$2:$C$3728,"events")),"") | G6: =IFERROR(IF(_xlfn.MAXIFS(Documents!$E$2:$E$3728,Documents!$A$2:$A$3728,$A6,Documents!$C$2:$C$3728,"destination_dining")=0,"",_xlfn.MAXIFS(Documents!$E$2:$E$3728,Documents!$A$2:$A$3728,$A6,Documents!$C$2:$C$3728,"destination_dining")),"") | H6: =IFERROR(IF(_xlfn.MAXIFS(Documents!$E$2:$E$3728,Documents!$A$2:$A$3728,$A6,Documents!$C$2:$C$3728,"map")=0,"",_xlfn.MAXIFS(Documents!$E$2:$E$3728,Documents!$A$2:$A$3728,$A6,Documents!$C$2:$C$3728,"map")),"") | I6: =IFERROR(IF(_xlfn.MAXIFS(Documents!$E$2:$E$3728,Documents!$A$2:$A$3728,$A6,Documents!$C$2:$C$3728,"dive_map")=0,"",_xlfn.MAXIFS(Documents!$E$2:$E$3728,Documents!$A$2:$A$3728,$A6,Documents!$C$2:$C$3728,"dive_map")),"") | J6: =IFERROR(IF(_xlfn.MAXIFS(Documents!$E$2:$E$3728,Documents!$A$2:$A$3728,$A6,Documents!$C$2:$C$3728,"spa_menu")=0,"",_xlfn.MAXIFS(Documents!$E$2:$E$3728,Documents!$A$2:$A$3728,$A6,Documents!$C$2:$C$3728,"spa_menu")),"") | K6: =IFERROR(IF(_xlfn.MAXIFS(Documents!$E$2:$E$3728,Documents!$A$2:$A$3728,$A6,Documents!$C$2:$C$3728,"dining_menu")=0,"",_xlfn.MAXIFS(Documents!$E$2:$E$3728,Documents!$A$2:$A$3728,$A6,Documents!$C$2:$C$3728,"dining_menu")),"") | L6: =IFERROR(IF(_xlfn.MAXIFS(Documents!$E$2:$E$3728,Documents!$A$2:$A$3728,$A6,Documents!$C$2:$C$3728,"dive_prices")=0,"",_xlfn.MAXIFS(Documents!$E$2:$E$3728,Documents!$A$2:$A$3728,$A6,Documents!$C$2:$C$3728,"dive_prices")),"") | M6: =IFERROR(IF(_xlfn.MAXIFS(Documents!$E$2:$E$3728,Documents!$A$2:$A$3728,$A6,Documents!$C$2:$C$3728,"excursions")=0,"",_xlfn.MAXIFS(Documents!$E$2:$E$3728,Documents!$A$2:$A$3728,$A6,Documents!$C$2:$C$3728,"excursions")),"") | N6: =IFERROR(IF(_xlfn.MAXIFS(Documents!$E$2:$E$3728,Documents!$A$2:$A$3728,$A6,Documents!$C$2:$C$3728,"kids")=0,"",_xlfn.MAXIFS(Documents!$E$2:$E$3728,Documents!$A$2:$A$3728,$A6,Documents!$C$2:$C$3728,"kids")),"") | O6: =IFERROR(IF(_xlfn.MAXIFS(Documents!$E$2:$E$3728,Documents!$A$2:$A$3728,$A6,Documents!$C$2:$C$3728,"villa_plans")=0,"",_xlfn.MAXIFS(Documents!$E$2:$E$3728,Documents!$A$2:$A$3728,$A6,Documents!$C$2:$C$3728,"villa_plans")),"") | P6: =IFERROR(IF(_xlfn.MAXIFS(Documents!$E$2:$E$3728,Documents!$A$2:$A$3728,$A6,Documents!$C$2:$C$3728,"all_inclusive")=0,"",_xlfn.MAXIFS(Documents!$E$2:$E$3728,Documents!$A$2:$A$3728,$A6,Documents!$C$2:$C$3728,"all_inclusive")),"") | Q6: =IFERROR(IF(_xlfn.MAXIFS(Documents!$E$2:$E$3728,Documents!$A$2:$A$3728,$A6,Documents!$C$2:$C$3728,"sustainability")=0,"",_xlfn.MAXIFS(Documents!$E$2:$E$3728,Documents!$A$2:$A$3728,$A6,Documents!$C$2:$C$3728,"sustainability")),"") | R6: =IFERROR(IF(_xlfn.MAXIFS(Documents!$E$2:$E$3728,Documents!$A$2:$A$3728,$A6,Documents!$C$2:$C$3728,"calendar")=0,"",_xlfn.MAXIFS(Documents!$E$2:$E$3728,Documents!$A$2:$A$3728,$A6,Documents!$C$2:$C$3728,"calendar")),"") | S6: =IFERROR(IF(_xlfn.MAXIFS(Documents!$E$2:$E$3728,Documents!$A$2:$A$3728,$A6,Documents!$C$2:$C$3728,"brochure")=0,"",_xlfn.MAXIFS(Documents!$E$2:$E$3728,Documents!$A$2:$A$3728,$A6,Documents!$C$2:$C$3728,"brochure")),"") | T6: =IFERROR(IF(_xlfn.MAXIFS(Documents!$E$2:$E$3728,Documents!$A$2:$A$3728,$A6,Documents!$C$2:$C$3728,"press_kit")=0,"",_xlfn.MAXIFS(Documents!$E$2:$E$3728,Documents!$A$2:$A$3728,$A6,Documents!$C$2:$C$3728,"press_kit")),"") | U6: =IFERROR(IF(_xlfn.MAXIFS(Documents!$E$2:$E$3728,Documents!$A$2:$A$3728,$A6,Documents!$C$2:$C$3728,"other")=0,"",_xlfn.MAXIFS(Documents!$E$2:$E$3728,Documents!$A$2:$A$3728,$A6,Documents!$C$2:$C$3728,"other")),"") | V6: =IFERROR(IF(_xlfn.MAXIFS(Documents!$E$2:$E$3728,Documents!$A$2:$A$3728,$A6,Documents!$C$2:$C$3728,"obsolete")=0,"",_xlfn.MAXIFS(Documents!$E$2:$E$3728,Documents!$A$2:$A$3728,$A6,Documents!$C$2:$C$3728,"obsolete")),"") | W6: =COUNTIFS(Documents!$A$2:$A$3728,$A6) | X6: =COUNTIFS(Documents!$A$2:$A$3728,$A6,Documents!$R$2:$R$3728,"current") | Y6: =HYPERLINK("https://www.neoscapesmaldives.com/wp-content/uploads/OZEN-RESERVE-BOLIFUSHI-Fact-Sheet.pdf","2023_OZEN-RESERVE-BOLIFUSHI-Fact-Sheet.p") | Z6: wedding, events | AA6: OZEN Reserve Bolifushi (confirm)
A7: 6 | B7: Joali Being Bodufushi | C7: unreachable | D7: =IFERROR(IF(_xlfn.MAXIFS(Documents!$E$2:$E$3728,Documents!$A$2:$A$3728,$A7,Documents!$C$2:$C$3728,"factsheet")=0,"",_xlfn.MAXIFS(Documents!$E$2:$E$3728,Documents!$A$2:$A$3728,$A7,Documents!$C$2:$C$3728,"factsheet")),"") | E7: =IFERROR(IF(_xlfn.MAXIFS(Documents!$E$2:$E$3728,Documents!$A$2:$A$3728,$A7,Documents!$C$2:$C$3728,"wedding")=0,"",_xlfn.MAXIFS(Documents!$E$2:$E$3728,Documents!$A$2:$A$3728,$A7,Documents!$C$2:$C$3728,"wedding")),"") | F7: =IFERROR(IF(_xlfn.MAXIFS(Documents!$E$2:$E$3728,Documents!$A$2:$A$3728,$A7,Documents!$C$2:$C$3728,"events")=0,"",_xlfn.MAXIFS(Documents!$E$2:$E$3728,Documents!$A$2:$A$3728,$A7,Documents!$C$2:$C$3728,"events")),"") | G7: =IFERROR(IF(_xlfn.MAXIFS(Documents!$E$2:$E$3728,Documents!$A$2:$A$3728,$A7,Documents!$C$2:$C$3728,"destination_dining")=0,"",_xlfn.MAXIFS(Documents!$E$2:$E$3728,Documents!$A$2:$A$3728,$A7,Documents!$C$2:$C$3728,"destination_dining")),"") | H7: =IFERROR(IF(_xlfn.MAXIFS(Documents!$E$2:$E$3728,Documents!$A$2:$A$3728,$A7,Documents!$C$2:$C$3728,"map")=0,"",_xlfn.MAXIFS(Documents!$E$2:$E$3728,Documents!$A$2:$A$3728,$A7,Documents!$C$2:$C$3728,"map")),"") | I7: =IFERROR(IF(_xlfn.MAXIFS(Documents!$E$2:$E$3728,Documents!$A$2:$A$3728,$A7,Documents!$C$2:$C$3728,"dive_map")=0,"",_xlfn.MAXIFS(Documents!$E$2:$E$3728,Documents!$A$2:$A$3728,$A7,Documents!$C$2:$C$3728,"dive_map")),"") | J7: =IFERROR(IF(_xlfn.MAXIFS(Documents!$E$2:$E$3728,Documents!$A$2:$A$3728,$A7,Documents!$C$2:$C$3728,"spa_menu")=0,"",_xlfn.MAXIFS(Documents!$E$2:$E$3728,Documents!$A$2:$A$3728,$A7,Documents!$C$2:$C$3728,"spa_menu")),"") | K7: =IFERROR(IF(_xlfn.MAXIFS(Documents!$E$2:$E$3728,Documents!$A$2:$A$3728,$A7,Documents!$C$2:$C$3728,"dining_menu")=0,"",_xlfn.MAXIFS(Documents!$E$2:$E$3728,Documents!$A$2:$A$3728,$A7,Documents!$C$2:$C$3728,"dining_menu")),"") | L7: =IFERROR(IF(_xlfn.MAXIFS(Documents!$E$2:$E$3728,Documents!$A$2:$A$3728,$A7,Documents!$C$2:$C$3728,"dive_prices")=0,"",_xlfn.MAXIFS(Documents!$E$2:$E$3728,Documents!$A$2:$A$3728,$A7,Documents!$C$2:$C$3728,"dive_prices")),"") | M7: =IFERROR(IF(_xlfn.MAXIFS(Documents!$E$2:$E$3728,Documents!$A$2:$A$3728,$A7,Documents!$C$2:$C$3728,"excursions")=0,"",_xlfn.MAXIFS(Documents!$E$2:$E$3728,Documents!$A$2:$A$3728,$A7,Documents!$C$2:$C$3728,"excursions")),"") | N7: =IFERROR(IF(_xlfn.MAXIFS(Documents!$E$2:$E$3728,Documents!$A$2:$A$3728,$A7,Documents!$C$2:$C$3728,"kids")=0,"",_xlfn.MAXIFS(Documents!$E$2:$E$3728,Documents!$A$2:$A$3728,$A7,Documents!$C$2:$C$3728,"kids")),"") | O7: =IFERROR(IF(_xlfn.MAXIFS(Documents!$E$2:$E$3728,Documents!$A$2:$A$3728,$A7,Documents!$C$2:$C$3728,"villa_plans")=0,"",_xlfn.MAXIFS(Documents!$E$2:$E$3728,Documents!$A$2:$A$3728,$A7,Documents!$C$2:$C$3728,"villa_plans")),"") | P7: =IFERROR(IF(_xlfn.MAXIFS(Documents!$E$2:$E$3728,Documents!$A$2:$A$3728,$A7,Documents!$C$2:$C$3728,"all_inclusive")=0,"",_xlfn.MAXIFS(Documents!$E$2:$E$3728,Documents!$A$2:$A$3728,$A7,Documents!$C$2:$C$3728,"all_inclusive")),"") | Q7: =IFERROR(IF(_xlfn.MAXIFS(Documents!$E$2:$E$3728,Documents!$A$2:$A$3728,$A7,Documents!$C$2:$C$3728,"sustainability")=0,"",_xlfn.MAXIFS(Documents!$E$2:$E$3728,Documents!$A$2:$A$3728,$A7,Documents!$C$2:$C$3728,"sustainability")),"") | R7: =IFERROR(IF(_xlfn.MAXIFS(Documents!$E$2:$E$3728,Documents!$A$2:$A$3728,$A7,Documents!$C$2:$C$3728,"calendar")=0,"",_xlfn.MAXIFS(Documents!$E$2:$E$3728,Documents!$A$2:$A$3728,$A7,Documents!$C$2:$C$3728,"calendar")),"") | S7: =IFERROR(IF(_xlfn.MAXIFS(Documents!$E$2:$E$3728,Documents!$A$2:$A$3728,$A7,Documents!$C$2:$C$3728,"brochure")=0,"",_xlfn.MAXIFS(Documents!$E$2:$E$3728,Documents!$A$2:$A$3728,$A7,Documents!$C$2:$C$3728,"brochure")),"") | T7: =IFERROR(IF(_xlfn.MAXIFS(Documents!$E$2:$E$3728,Documents!$A$2:$A$3728,$A7,Documents!$C$2:$C$3728,"press_kit")=0,"",_xlfn.MAXIFS(Documents!$E$2:$E$3728,Documents!$A$2:$A$3728,$A7,Documents!$C$2:$C$3728,"press_kit")),"") | U7: =IFERROR(IF(_xlfn.MAXIFS(Documents!$E$2:$E$3728,Documents!$A$2:$A$3728,$A7,Documents!$C$2:$C$3728,"other")=0,"",_xlfn.MAXIFS(Documents!$E$2:$E$3728,Documents!$A$2:$A$3728,$A7,Documents!$C$2:$C$3728,"other")),"") | V7: =IFERROR(IF(_xlfn.MAXIFS(Documents!$E$2:$E$3728,Documents!$A$2:$A$3728,$A7,Documents!$C$2:$C$3728,"obsolete")=0,"",_xlfn.MAXIFS(Documents!$E$2:$E$3728,Documents!$A$2:$A$3728,$A7,Documents!$C$2:$C$3728,"obsolete")),"") | W7: =COUNTIFS(Documents!$A$2:$A$3728,$A7) | X7: =COUNTIFS(Documents!$A$2:$A$3728,$A7,Documents!$R$2:$R$3728,"current") | Y7: =HYPERLINK("https://www.neoscapesmaldives.com/wp-content/uploads/JoaliBeing_Factsheet_V13.pdf","2023_JoaliBeing_Factsheet_V13.pdf") | Z7: wedding, events
A8: 7 | B8: Joali Muravandhoo | C8: unreachable | D8: =IFERROR(IF(_xlfn.MAXIFS(Documents!$E$2:$E$3728,Documents!$A$2:$A$3728,$A8,Documents!$C$2:$C$3728,"factsheet")=0,"",_xlfn.MAXIFS(Documents!$E$2:$E$3728,Documents!$A$2:$A$3728,$A8,Documents!$C$2:$C$3728,"factsheet")),"") | E8: =IFERROR(IF(_xlfn.MAXIFS(Documents!$E$2:$E$3728,Documents!$A$2:$A$3728,$A8,Documents!$C$2:$C$3728,"wedding")=0,"",_xlfn.MAXIFS(Documents!$E$2:$E$3728,Documents!$A$2:$A$3728,$A8,Documents!$C$2:$C$3728,"wedding")),"") | F8: =IFERROR(IF(_xlfn.MAXIFS(Documents!$E$2:$E$3728,Documents!$A$2:$A$3728,$A8,Documents!$C$2:$C$3728,"events")=0,"",_xlfn.MAXIFS(Documents!$E$2:$E$3728,Documents!$A$2:$A$3728,$A8,Documents!$C$2:$C$3728,"events")),"") | G8: =IFERROR(IF(_xlfn.MAXIFS(Documents!$E$2:$E$3728,Documents!$A$2:$A$3728,$A8,Documents!$C$2:$C$3728,"destination_dining")=0,"",_xlfn.MAXIFS(Documents!$E$2:$E$3728,Documents!$A$2:$A$3728,$A8,Documents!$C$2:$C$3728,"destination_dining")),"") | H8: =IFERROR(IF(_xlfn.MAXIFS(Documents!$E$2:$E$3728,Documents!$A$2:$A$3728,$A8,Documents!$C$2:$C$3728,"map")=0,"",_xlfn.MAXIFS(Documents!$E$2:$E$3728,Documents!$A$2:$A$3728,$A8,Documents!$C$2:$C$3728,"map")),"") | I8: =IFERROR(IF(_xlfn.MAXIFS(Documents!$E$2:$E$3728,Documents!$A$2:$A$3728,$A8,Documents!$C$2:$C$3728,"dive_map")=0,"",_xlfn.MAXIFS(Documents!$E$2:$E$3728,Documents!$A$2:$A$3728,$A8,Documents!$C$2:$C$3728,"dive_map")),"") | J8: =IFERROR(IF(_xlfn.MAXIFS(Documents!$E$2:$E$3728,Documents!$A$2:$A$3728,$A8,Documents!$C$2:$C$3728,"spa_menu")=0,"",_xlfn.MAXIFS(Documents!$E$2:$E$3728,Documents!$A$2:$A$3728,$A8,Documents!$C$2:$C$3728,"spa_menu")),"") | K8: =IFERROR(IF(_xlfn.MAXIFS(Documents!$E$2:$E$3728,Documents!$A$2:$A$3728,$A8,Documents!$C$2:$C$3728,"dining_menu")=0,"",_xlfn.MAXIFS(Documents!$E$2:$E$3728,Documents!$A$2:$A$3728,$A8,Documents!$C$2:$C$3728,"dining_menu")),"") | L8: =IFERROR(IF(_xlfn.MAXIFS(Documents!$E$2:$E$3728,Documents!$A$2:$A$3728,$A8,Documents!$C$2:$C$3728,"dive_prices")=0,"",_xlfn.MAXIFS(Documents!$E$2:$E$3728,Documents!$A$2:$A$3728,$A8,Documents!$C$2:$C$3728,"dive_prices")),"") | M8: =IFERROR(IF(_xlfn.MAXIFS(Documents!$E$2:$E$3728,Documents!$A$2:$A$3728,$A8,Documents!$C$2:$C$3728,"excursions")=0,"",_xlfn.MAXIFS(Documents!$E$2:$E$3728,Documents!$A$2:$A$3728,$A8,Documents!$C$2:$C$3728,"excursions")),"") | N8: =IFERROR(IF(_xlfn.MAXIFS(Documents!$E$2:$E$3728,Documents!$A$2:$A$3728,$A8,Documents!$C$2:$C$3728,"kids")=0,"",_xlfn.MAXIFS(Documents!$E$2:$E$3728,Documents!$A$2:$A$3728,$A8,Documents!$C$2:$C$3728,"kids")),"") | O8: =IFERROR(IF(_xlfn.MAXIFS(Documents!$E$2:$E$3728,Documents!$A$2:$A$3728,$A8,Documents!$C$2:$C$3728,"villa_plans")=0,"",_xlfn.MAXIFS(Documents!$E$2:$E$3728,Documents!$A$2:$A$3728,$A8,Documents!$C$2:$C$3728,"villa_plans")),"") | P8: =IFERROR(IF(_xlfn.MAXIFS(Documents!$E$2:$E$3728,Documents!$A$2:$A$3728,$A8,Documents!$C$2:$C$3728,"all_inclusive")=0,"",_xlfn.MAXIFS(Documents!$E$2:$E$3728,Documents!$A$2:$A$3728,$A8,Documents!$C$2:$C$3728,"all_inclusive")),"") | Q8: =IFERROR(IF(_xlfn.MAXIFS(Documents!$E$2:$E$3728,Documents!$A$2:$A$3728,$A8,Documents!$C$2:$C$3728,"sustainability")=0,"",_xlfn.MAXIFS(Documents!$E$2:$E$3728,Documents!$A$2:$A$3728,$A8,Documents!$C$2:$C$3728,"sustainability")),"") | R8: =IFERROR(IF(_xlfn.MAXIFS(Documents!$E$2:$E$3728,Documents!$A$2:$A$3728,$A8,Documents!$C$2:$C$3728,"calendar")=0,"",_xlfn.MAXIFS(Documents!$E$2:$E$3728,Documents!$A$2:$A$3728,$A8,Documents!$C$2:$C$3728,"calendar")),"") | S8: =IFERROR(IF(_xlfn.MAXIFS(Documents!$E$2:$E$3728,Documents!$A$2:$A$3728,$A8,Documents!$C$2:$C$3728,"brochure")=0,"",_xlfn.MAXIFS(Documents!$E$2:$E$3728,Documents!$A$2:$A$3728,$A8,Documents!$C$2:$C$3728,"brochure")),"") | T8: =IFERROR(IF(_xlfn.MAXIFS(Documents!$E$2:$E$3728,Documents!$A$2:$A$3728,$A8,Documents!$C$2:$C$3728,"press_kit")=0,"",_xlfn.MAXIFS(Documents!$E$2:$E$3728,Documents!$A$2:$A$3728,$A8,Documents!$C$2:$C$3728,"press_kit")),"") | U8: =IFERROR(IF(_xlfn.MAXIFS(Documents!$E$2:$E$3728,Documents!$A$2:$A$3728,$A8,Documents!$C$2:$C$3728,"other")=0,"",_xlfn.MAXIFS(Documents!$E$2:$E$3728,Documents!$A$2:$A$3728,$A8,Documents!$C$2:$C$3728,"other")),"") | V8: =IFERROR(IF(_xlfn.MAXIFS(Documents!$E$2:$E$3728,Documents!$A$2:$A$3728,$A8,Documents!$C$2:$C$3728,"obsolete")=0,"",_xlfn.MAXIFS(Documents!$E$2:$E$3728,Documents!$A$2:$A$3728,$A8,Documents!$C$2:$C$3728,"obsolete")),"") | W8: =COUNTIFS(Documents!$A$2:$A$3728,$A8) | X8: =COUNTIFS(Documents!$A$2:$A$3728,$A8,Documents!$R$2:$R$3728,"current") | Y8: =HYPERLINK("https://www.neoscapesmaldives.com/wp-content/uploads/JOALI-Maldives-Factsheet.pdf","2023_JOALI-Maldives-Factsheet.pdf") | Z8: wedding, events
A9: 8 | B9: Hilton Maldives Amingiri Resort & Spa | C9: unverified | D9: =IFERROR(IF(_xlfn.MAXIFS(Documents!$E$2:$E$3728,Documents!$A$2:$A$3728,$A9,Documents!$C$2:$C$3728,"factsheet")=0,"",_xlfn.MAXIFS(Documents!$E$2:$E$3728,Documents!$A$2:$A$3728,$A9,Documents!$C$2:$C$3728,"factsheet")),"") | E9: =IFERROR(IF(_xlfn.MAXIFS(Documents!$E$2:$E$3728,Documents!$A$2:$A$3728,$A9,Documents!$C$2:$C$3728,"wedding")=0,"",_xlfn.MAXIFS(Documents!$E$2:$E$3728,Documents!$A$2:$A$3728,$A9,Documents!$C$2:$C$3728,"wedding")),"") | F9: =IFERROR(IF(_xlfn.MAXIFS(Documents!$E$2:$E$3728,Documents!$A$2:$A$3728,$A9,Documents!$C$2:$C$3728,"events")=0,"",_xlfn.MAXIFS(Documents!$E$2:$E$3728,Documents!$A$2:$A$3728,$A9,Documents!$C$2:$C$3728,"events")),"") | G9: =IFERROR(IF(_xlfn.MAXIFS(Documents!$E$2:$E$3728,Documents!$A$2:$A$3728,$A9,Documents!$C$2:$C$3728,"destination_dining")=0,"",_xlfn.MAXIFS(Documents!$E$2:$E$3728,Documents!$A$2:$A$3728,$A9,Documents!$C$2:$C$3728,"destination_dining")),"") | H9: =IFERROR(IF(_xlfn.MAXIFS(Documents!$E$2:$E$3728,Documents!$A$2:$A$3728,$A9,Documents!$C$2:$C$3728,"map")=0,"",_xlfn.MAXIFS(Documents!$E$2:$E$3728,Documents!$A$2:$A$3728,$A9,Documents!$C$2:$C$3728,"map")),"") | I9: =IFERROR(IF(_xlfn.MAXIFS(Documents!$E$2:$E$3728,Documents!$A$2:$A$3728,$A9,Documents!$C$2:$C$3728,"dive_map")=0,"",_xlfn.MAXIFS(Documents!$E$2:$E$3728,Documents!$A$2:$A$3728,$A9,Documents!$C$2:$C$3728,"dive_map")),"") | J9: =IFERROR(IF(_xlfn.MAXIFS(Documents!$E$2:$E$3728,Documents!$A$2:$A$3728,$A9,Documents!$C$2:$C$3728,"spa_menu")=0,"",_xlfn.MAXIFS(Documents!$E$2:$E$3728,Documents!$A$2:$A$3728,$A9,Documents!$C$2:$C$3728,"spa_menu")),"") | K9: =IFERROR(IF(_xlfn.MAXIFS(Documents!$E$2:$E$3728,Documents!$A$2:$A$3728,$A9,Documents!$C$2:$C$3728,"dining_menu")=0,"",_xlfn.MAXIFS(Documents!$E$2:$E$3728,Documents!$A$2:$A$3728,$A9,Documents!$C$2:$C$3728,"dining_menu")),"") | L9: =IFERROR(IF(_xlfn.MAXIFS(Documents!$E$2:$E$3728,Documents!$A$2:$A$3728,$A9,Documents!$C$2:$C$3728,"dive_prices")=0,"",_xlfn.MAXIFS(Documents!$E$2:$E$3728,Documents!$A$2:$A$3728,$A9,Documents!$C$2:$C$3728,"dive_prices")),"") | M9: =IFERROR(IF(_xlfn.MAXIFS(Documents!$E$2:$E$3728,Documents!$A$2:$A$3728,$A9,Documents!$C$2:$C$3728,"excursions")=0,"",_xlfn.MAXIFS(Documents!$E$2:$E$3728,Documents!$A$2:$A$3728,$A9,Documents!$C$2:$C$3728,"excursions")),"") | N9: =IFERROR(IF(_xlfn.MAXIFS(Documents!$E$2:$E$3728,Documents!$A$2:$A$3728,$A9,Documents!$C$2:$C$3728,"kids")=0,"",_xlfn.MAXIFS(Documents!$E$2:$E$3728,Documents!$A$2:$A$3728,$A9,Documents!$C$2:$C$3728,"kids")),"") | O9: =IFERROR(IF(_xlfn.MAXIFS(Documents!$E$2:$E$3728,Documents!$A$2:$A$3728,$A9,Documents!$C$2:$C$3728,"villa_plans")=0,"",_xlfn.MAXIFS(Documents!$E$2:$E$3728,Documents!$A$2:$A$3728,$A9,Documents!$C$2:$C$3728,"villa_plans")),"") | P9: =IFERROR(IF(_xlfn.MAXIFS(Documents!$E$2:$E$3728,Documents!$A$2:$A$3728,$A9,Documents!$C$2:$C$3728,"all_inclusive")=0,"",_xlfn.MAXIFS(Documents!$E$2:$E$3728,Documents!$A$2:$A$3728,$A9,Documents!$C$2:$C$3728,"all_inclusive")),"") | Q9: =IFERROR(IF(_xlfn.MAXIFS(Documents!$E$2:$E$3728,Documents!$A$2:$A$3728,$A9,Documents!$C$2:$C$3728,"sustainability")=0,"",_xlfn.MAXIFS(Documents!$E$2:$E$3728,Documents!$A$2:$A$3728,$A9,Documents!$C$2:$C$3728,"sustainability")),"") | R9: =IFERROR(IF(_xlfn.MAXIFS(Documents!$E$2:$E$3728,Documents!$A$2:$A$3728,$A9,Documents!$C$2:$C$3728,"calendar")=0,"",_xlfn.MAXIFS(Documents!$E$2:$E$3728,Documents!$A$2:$A$3728,$A9,Documents!$C$2:$C$3728,"calendar")),"") | S9: =IFERROR(IF(_xlfn.MAXIFS(Documents!$E$2:$E$3728,Documents!$A$2:$A$3728,$A9,Documents!$C$2:$C$3728,"brochure")=0,"",_xlfn.MAXIFS(Documents!$E$2:$E$3728,Documents!$A$2:$A$3728,$A9,Documents!$C$2:$C$3728,"brochure")),"") | T9: =IFERROR(IF(_xlfn.MAXIFS(Documents!$E$2:$E$3728,Documents!$A$2:$A$3728,$A9,Documents!$C$2:$C$3728,"press_kit")=0,"",_xlfn.MAXIFS(Documents!$E$2:$E$3728,Documents!$A$2:$A$3728,$A9,Documents!$C$2:$C$3728,"press_kit")),"") | U9: =IFERROR(IF(_xlfn.MAXIFS(Documents!$E$2:$E$3728,Documents!$A$2:$A$3728,$A9,Documents!$C$2:$C$3728,"other")=0,"",_xlfn.MAXIFS(Documents!$E$2:$E$3728,Documents!$A$2:$A$3728,$A9,Documents!$C$2:$C$3728,"other")),"") | V9: =IFERROR(IF(_xlfn.MAXIFS(Documents!$E$2:$E$3728,Documents!$A$2:$A$3728,$A9,Documents!$C$2:$C$3728,"obsolete")=0,"",_xlfn.MAXIFS(Documents!$E$2:$E$3728,Documents!$A$2:$A$3728,$A9,Documents!$C$2:$C$3728,"obsolete")),"") | W9: =COUNTIFS(Documents!$A$2:$A$3728,$A9) | X9: =COUNTIFS(Documents!$A$2:$A$3728,$A9,Documents!$R$2:$R$3728,"current") | Y9: =HYPERLINK("https://www.neoscapesmaldives.com/wp-content/uploads/MLEAI_Factsheet-March-2025.pdf","2025_MLEAI_Factsheet-March-2025.pdf") | Z9: wedding, events
A10: 9 | B10: Amilla Fushi | C10: ok | D10: =IFERROR(IF(_xlfn.MAXIFS(Documents!$E$2:$E$3728,Documents!$A$2:$A$3728,$A10,Documents!$C$2:$C$3728,"factsheet")=0,"",_xlfn.MAXIFS(Documents!$E$2:$E$3728,Documents!$A$2:$A$3728,$A10,Documents!$C$2:$C$3728,"factsheet")),"") | E10: =IFERROR(IF(_xlfn.MAXIFS(Documents!$E$2:$E$3728,Documents!$A$2:$A$3728,$A10,Documents!$C$2:$C$3728,"wedding")=0,"",_xlfn.MAXIFS(Documents!$E$2:$E$3728,Documents!$A$2:$A$3728,$A10,Documents!$C$2:$C$3728,"wedding")),"") | F10: =IFERROR(IF(_xlfn.MAXIFS(Documents!$E$2:$E$3728,Documents!$A$2:$A$3728,$A10,Documents!$C$2:$C$3728,"events")=0,"",_xlfn.MAXIFS(Documents!$E$2:$E$3728,Documents!$A$2:$A$3728,$A10,Documents!$C$2:$C$3728,"events")),"") | G10: =IFERROR(IF(_xlfn.MAXIFS(Documents!$E$2:$E$3728,Documents!$A$2:$A$3728,$A10,Documents!$C$2:$C$3728,"destination_dining")=0,"",_xlfn.MAXIFS(Documents!$E$2:$E$3728,Documents!$A$2:$A$3728,$A10,Documents!$C$2:$C$3728,"destination_dining")),"") | H10: =IFERROR(IF(_xlfn.MAXIFS(Documents!$E$2:$E$3728,Documents!$A$2:$A$3728,$A10,Documents!$C$2:$C$3728,"map")=0,"",_xlfn.MAXIFS(Documents!$E$2:$E$3728,Documents!$A$2:$A$3728,$A10,Documents!$C$2:$C$3728,"map")),"") | I10: =IFERROR(IF(_xlfn.MAXIFS(Documents!$E$2:$E$3728,Documents!$A$2:$A$3728,$A10,Documents!$C$2:$C$3728,"dive_map")=0,"",_xlfn.MAXIFS(Documents!$E$2:$E$3728,Documents!$A$2:$A$3728,$A10,Documents!$C$2:$C$3728,"dive_map")),"") | J10: =IFERROR(IF(_xlfn.MAXIFS(Documents!$E$2:$E$3728,Documents!$A$2:$A$3728,$A10,Documents!$C$2:$C$3728,"spa_menu")=0,"",_xlfn.MAXIFS(Documents!$E$2:$E$3728,Documents!$A$2:$A$3728,$A10,Documents!$C$2:$C$3728,"spa_menu")),"") | K10: =IFERROR(IF(_xlfn.MAXIFS(Documents!$E$2:$E$3728,Documents!$A$2:$A$3728,$A10,Documents!$C$2:$C$3728,"dining_menu")=0,"",_xlfn.MAXIFS(Documents!$E$2:$E$3728,Documents!$A$2:$A$3728,$A10,Documents!$C$2:$C$3728,"dining_menu")),"") | L10: =IFERROR(IF(_xlfn.MAXIFS(Documents!$E$2:$E$3728,Documents!$A$2:$A$3728,$A10,Documents!$C$2:$C$3728,"dive_prices")=0,"",_xlfn.MAXIFS(Documents!$E$2:$E$3728,Documents!$A$2:$A$3728,$A10,Documents!$C$2:$C$3728,"dive_prices")),"") | M10: =IFERROR(IF(_xlfn.MAXIFS(Documents!$E$2:$E$3728,Documents!$A$2:$A$3728,$A10,Documents!$C$2:$C$3728,"excursions")=0,"",_xlfn.MAXIFS(Documents!$E$2:$E$3728,Documents!$A$2:$A$3728,$A10,Documents!$C$2:$C$3728,"excursions")),"") | N10: =IFERROR(IF(_xlfn.MAXIFS(Documents!$E$2:$E$3728,Documents!$A$2:$A$3728,$A10,Documents!$C$2:$C$3728,"kids")=0,"",_xlfn.MAXIFS(Documents!$E$2:$E$3728,Documents!$A$2:$A$3728,$A10,Documents!$C$2:$C$3728,"kids")),"") | O10: =IFERROR(IF(_xlfn.MAXIFS(Documents!$E$2:$E$3728,Documents!$A$2:$A$3728,$A10,Documents!$C$2:$C$3728,"villa_plans")=0,"",_xlfn.MAXIFS(Documents!$E$2:$E$3728,Documents!$A$2:$A$3728,$A10,Documents!$C$2:$C$3728,"villa_plans")),"") | P10: =IFERROR(IF(_xlfn.MAXIFS(Documents!$E$2:$E$3728,Documents!$A$2:$A$3728,$A10,Documents!$C$2:$C$3728,"all_inclusive")=0,"",_xlfn.MAXIFS(Documents!$E$2:$E$3728,Documents!$A$2:$A$3728,$A10,Documents!$C$2:$C$3728,"all_inclusive")),"") | Q10: =IFERROR(IF(_xlfn.MAXIFS(Documents!$E$2:$E$3728,Documents!$A$2:$A$3728,$A10,Documents!$C$2:$C$3728,"sustainability")=0,"",_xlfn.MAXIFS(Documents!$E$2:$E$3728,Documents!$A$2:$A$3728,$A10,Documents!$C$2:$C$3728,"sustainability")),"") | R10: =IFERROR(IF(_xlfn.MAXIFS(Documents!$E$2:$E$3728,Documents!$A$2:$A$3728,$A10,Documents!$C$2:$C$3728,"calendar")=0,"",_xlfn.MAXIFS(Documents!$E$2:$E$3728,Documents!$A$2:$A$3728,$A10,Documents!$C$2:$C$3728,"calendar")),"") | S10: =IFERROR(IF(_xlfn.MAXIFS(Documents!$E$2:$E$3728,Documents!$A$2:$A$3728,$A10,Documents!$C$2:$C$3728,"brochure")=0,"",_xlfn.MAXIFS(Documents!$E$2:$E$3728,Documents!$A$2:$A$3728,$A10,Documents!$C$2:$C$3728,"brochure")),"") | T10: =IFERROR(IF(_xlfn.MAXIFS(Documents!$E$2:$E$3728,Documents!$A$2:$A$3728,$A10,Documents!$C$2:$C$3728,"press_kit")=0,"",_xlfn.MAXIFS(Documents!$E$2:$E$3728,Documents!$A$2:$A$3728,$A10,Documents!$C$2:$C$3728,"press_kit")),"") | U10: =IFERROR(IF(_xlfn.MAXIFS(Documents!$E$2:$E$3728,Documents!$A$2:$A$3728,$A10,Documents!$C$2:$C$3728,"other")=0,"",_xlfn.MAXIFS(Documents!$E$2:$E$3728,Documents!$A$2:$A$3728,$A10,Documents!$C$2:$C$3728,"other")),"") | V10: =IFERROR(IF(_xlfn.MAXIFS(Documents!$E$2:$E$3728,Documents!$A$2:$A$3728,$A10,Documents!$C$2:$C$3728,"obsolete")=0,"",_xlfn.MAXIFS(Documents!$E$2:$E$3728,Documents!$A$2:$A$3728,$A10,Documents!$C$2:$C$3728,"obsolete")),"") | W10: =COUNTIFS(Documents!$A$2:$A$3728,$A10) | X10: =COUNTIFS(Documents!$A$2:$A$3728,$A10,Documents!$R$2:$R$3728,"current") | Y10: =HYPERLINK("https://amilla.com/wp-content/uploads/Amilla-Maldives_Fact-Sheet_2026.pdf","2026_Amilla-Maldives_Fact-Sheet_2026.pdf") | Z10: events
A11: 10 | B11: Dreamland - The Unique Sea & Lake Resort/Spa | C11: ok | D11: =IFERROR(IF(_xlfn.MAXIFS(Documents!$E$2:$E$3728,Documents!$A$2:$A$3728,$A11,Documents!$C$2:$C$3728,"factsheet")=0,"",_xlfn.MAXIFS(Documents!$E$2:$E$3728,Documents!$A$2:$A$3728,$A11,Documents!$C$2:$C$3728,"factsheet")),"") | E11: =IFERROR(IF(_xlfn.MAXIFS(Documents!$E$2:$E$3728,Documents!$A$2:$A$3728,$A11,Documents!$C$2:$C$3728,"wedding")=0,"",_xlfn.MAXIFS(Documents!$E$2:$E$3728,Documents!$A$2:$A$3728,$A11,Documents!$C$2:$C$3728,"wedding")),"") | F11: =IFERROR(IF(_xlfn.MAXIFS(Documents!$E$2:$E$3728,Documents!$A$2:$A$3728,$A11,Documents!$C$2:$C$3728,"events")=0,"",_xlfn.MAXIFS(Documents!$E$2:$E$3728,Documents!$A$2:$A$3728,$A11,Documents!$C$2:$C$3728,"events")),"") | G11: =IFERROR(IF(_xlfn.MAXIFS(Documents!$E$2:$E$3728,Documents!$A$2:$A$3728,$A11,Documents!$C$2:$C$3728,"destination_dining")=0,"",_xlfn.MAXIFS(Documents!$E$2:$E$3728,Documents!$A$2:$A$3728,$A11,Documents!$C$2:$C$3728,"destination_dining")),"") | H11: =IFERROR(IF(_xlfn.MAXIFS(Documents!$E$2:$E$3728,Documents!$A$2:$A$3728,$A11,Documents!$C$2:$C$3728,"map")=0,"",_xlfn.MAXIFS(Documents!$E$2:$E$3728,Documents!$A$2:$A$3728,$A11,Documents!$C$2:$C$3728,"map")),"") | I11: =IFERROR(IF(_xlfn.MAXIFS(Documents!$E$2:$E$3728,Documents!$A$2:$A$3728,$A11,Documents!$C$2:$C$3728,"dive_map")=0,"",_xlfn.MAXIFS(Documents!$E$2:$E$3728,Documents!$A$2:$A$3728,$A11,Documents!$C$2:$C$3728,"dive_map")),"") | J11: =IFERROR(IF(_xlfn.MAXIFS(Documents!$E$2:$E$3728,Documents!$A$2:$A$3728,$A11,Documents!$C$2:$C$3728,"spa_menu")=0,"",_xlfn.MAXIFS(Documents!$E$2:$E$3728,Documents!$A$2:$A$3728,$A11,Documents!$C$2:$C$3728,"spa_menu")),"") | K11: =IFERROR(IF(_xlfn.MAXIFS(Documents!$E$2:$E$3728,Documents!$A$2:$A$3728,$A11,Documents!$C$2:$C$3728,"dining_menu")=0,"",_xlfn.MAXIFS(Documents!$E$2:$E$3728,Documents!$A$2:$A$3728,$A11,Documents!$C$2:$C$3728,"dining_menu")),"") | L11: =IFERROR(IF(_xlfn.MAXIFS(Documents!$E$2:$E$3728,Documents!$A$2:$A$3728,$A11,Documents!$C$2:$C$3728,"dive_prices")=0,"",_xlfn.MAXIFS(Documents!$E$2:$E$3728,Documents!$A$2:$A$3728,$A11,Documents!$C$2:$C$3728,"dive_prices")),"") | M11: =IFERROR(IF(_xlfn.MAXIFS(Documents!$E$2:$E$3728,Documents!$A$2:$A$3728,$A11,Documents!$C$2:$C$3728,"excursions")=0,"",_xlfn.MAXIFS(Documents!$E$2:$E$3728,Documents!$A$2:$A$3728,$A11,Documents!$C$2:$C$3728,"excursions")),"") | N11: =IFERROR(IF(_xlfn.MAXIFS(Documents!$E$2:$E$3728,Documents!$A$2:$A$3728,$A11,Documents!$C$2:$C$3728,"kids")=0,"",_xlfn.MAXIFS(Documents!$E$2:$E$3728,Documents!$A$2:$A$3728,$A11,Documents!$C$2:$C$3728,"kids")),"") | O11: =IFERROR(IF(_xlfn.MAXIFS(Documents!$E$2:$E$3728,Documents!$A$2:$A$3728,$A11,Documents!$C$2:$C$3728,"villa_plans")=0,"",_xlfn.MAXIFS(Documents!$E$2:$E$3728,Documents!$A$2:$A$3728,$A11,Documents!$C$2:$C$3728,"villa_plans")),"") | P11: =IFERROR(IF(_xlfn.MAXIFS(Documents!$E$2:$E$3728,Documents!$A$2:$A$3728,$A11,Documents!$C$2:$C$3728,"all_inclusive")=0,"",_xlfn.MAXIFS(Documents!$E$2:$E$3728,Documents!$A$2:$A$3728,$A11,Documents!$C$2:$C$3728,"all_inclusive")),"") | Q11: =IFERROR(IF(_xlfn.MAXIFS(Documents!$E$2:$E$3728,Documents!$A$2:$A$3728,$A11,Documents!$C$2:$C$3728,"sustainability")=0,"",_xlfn.MAXIFS(Documents!$E$2:$E$3728,Documents!$A$2:$A$3728,$A11,Documents!$C$2:$C$3728,"sustainability")),"") | R11: =IFERROR(IF(_xlfn.MAXIFS(Documents!$E$2:$E$3728,Documents!$A$2:$A$3728,$A11,Documents!$C$2:$C$3728,"calendar")=0,"",_xlfn.MAXIFS(Documents!$E$2:$E$3728,Documents!$A$2:$A$3728,$A11,Documents!$C$2:$C$3728,"calendar")),"") | S11: =IFERROR(IF(_xlfn.MAXIFS(Documents!$E$2:$E$3728,Documents!$A$2:$A$3728,$A11,Documents!$C$2:$C$3728,"brochure")=0,"",_xlfn.MAXIFS(Documents!$E$2:$E$3728,Documents!$A$2:$A$3728,$A11,Documents!$C$2:$C$3728,"brochure")),"") | T11: =IFERROR(IF(_xlfn.MAXIFS(Documents!$E$2:$E$3728,Documents!$A$2:$A$3728,$A11,Documents!$C$2:$C$3728,"press_kit")=0,"",_xlfn.MAXIFS(Documents!$E$2:$E$3728,Documents!$A$2:$A$3728,$A11,Documents!$C$2:$C$3728,"press_kit")),"") | U11: =IFERROR(IF(_xlfn.MAXIFS(Documents!$E$2:$E$3728,Documents!$A$2:$A$3728,$A11,Documents!$C$2:$C$3728,"other")=0,"",_xlfn.MAXIFS(Documents!$E$2:$E$3728,Documents!$A$2:$A$3728,$A11,Documents!$C$2:$C$3728,"other")),"") | V11: =IFERROR(IF(_xlfn.MAXIFS(Documents!$E$2:$E$3728,Documents!$A$2:$A$3728,$A11,Documents!$C$2:$C$3728,"obsolete")=0,"",_xlfn.MAXIFS(Documents!$E$2:$E$3728,Documents!$A$2:$A$3728,$A11,Documents!$C$2:$C$3728,"obsolete")),"") | W11: =COUNTIFS(Documents!$A$2:$A$3728,$A11) | X11: =COUNTIFS(Documents!$A$2:$A$3728,$A11,Documents!$R$2:$R$3728,"current") | Y11: =HYPERLINK("https://dreamland.com.mv/wp-content/uploads/2024/08/DREAMLAND-GENERAL-INFORMATION-GERMAN-2023.pdf","2023_DREAMLAND-GENERAL-INFORMATION-GERMA") | Z11: events
A12: 11 | B12: Angaga Island Resort and Spa | C12: ok | D12: =IFERROR(IF(_xlfn.MAXIFS(Documents!$E$2:$E$3728,Documents!$A$2:$A$3728,$A12,Documents!$C$2:$C$3728,"factsheet")=0,"",_xlfn.MAXIFS(Documents!$E$2:$E$3728,Documents!$A$2:$A$3728,$A12,Documents!$C$2:$C$3728,"factsheet")),"") | E12: =IFERROR(IF(_xlfn.MAXIFS(Documents!$E$2:$E$3728,Documents!$A$2:$A$3728,$A12,Documents!$C$2:$C$3728,"wedding")=0,"",_xlfn.MAXIFS(Documents!$E$2:$E$3728,Documents!$A$2:$A$3728,$A12,Documents!$C$2:$C$3728,"wedding")),"") | F12: =IFERROR(IF(_xlfn.MAXIFS(Documents!$E$2:$E$3728,Documents!$A$2:$A$3728,$A12,Documents!$C$2:$C$3728,"events")=0,"",_xlfn.MAXIFS(Documents!$E$2:$E$3728,Documents!$A$2:$A$3728,$A12,Documents!$C$2:$C$3728,"events")),"") | G12: =IFERROR(IF(_xlfn.MAXIFS(Documents!$E$2:$E$3728,Documents!$A$2:$A$3728,$A12,Documents!$C$2:$C$3728,"destination_dining")=0,"",_xlfn.MAXIFS(Documents!$E$2:$E$3728,Documents!$A$2:$A$3728,$A12,Documents!$C$2:$C$3728,"destination_dining")),"") | H12: =IFERROR(IF(_xlfn.MAXIFS(Documents!$E$2:$E$3728,Documents!$A$2:$A$3728,$A12,Documents!$C$2:$C$3728,"map")=0,"",_xlfn.MAXIFS(Documents!$E$2:$E$3728,Documents!$A$2:$A$3728,$A12,Documents!$C$2:$C$3728,"map")),"") | I12: =IFERROR(IF(_xlfn.MAXIFS(Documents!$E$2:$E$3728,Documents!$A$2:$A$3728,$A12,Documents!$C$2:$C$3728,"dive_map")=0,"",_xlfn.MAXIFS(Documents!$E$2:$E$3728,Documents!$A$2:$A$3728,$A12,Documents!$C$2:$C$3728,"dive_map")),"") | J12: =IFERROR(IF(_xlfn.MAXIFS(Documents!$E$2:$E$3728,Documents!$A$2:$A$3728,$A12,Documents!$C$2:$C$3728,"spa_menu")=0,"",_xlfn.MAXIFS(Documents!$E$2:$E$3728,Documents!$A$2:$A$3728,$A12,Documents!$C$2:$C$3728,"spa_menu")),"") | K12: =IFERROR(IF(_xlfn.MAXIFS(Documents!$E$2:$E$3728,Documents!$A$2:$A$3728,$A12,Documents!$C$2:$C$3728,"dining_menu")=0,"",_xlfn.MAXIFS(Documents!$E$2:$E$3728,Documents!$A$2:$A$3728,$A12,Documents!$C$2:$C$3728,"dining_menu")),"") | L12: =IFERROR(IF(_xlfn.MAXIFS(Documents!$E$2:$E$3728,Documents!$A$2:$A$3728,$A12,Documents!$C$2:$C$3728,"dive_prices")=0,"",_xlfn.MAXIFS(Documents!$E$2:$E$3728,Documents!$A$2:$A$3728,$A12,Documents!$C$2:$C$3728,"dive_prices")),"") | M12: =IFERROR(IF(_xlfn.MAXIFS(Documents!$E$2:$E$3728,Documents!$A$2:$A$3728,$A12,Documents!$C$2:$C$3728,"excursions")=0,"",_xlfn.MAXIFS(Documents!$E$2:$E$3728,Documents!$A$2:$A$3728,$A12,Documents!$C$2:$C$3728,"excursions")),"") | N12: =IFERROR(IF(_xlfn.MAXIFS(Documents!$E$2:$E$3728,Documents!$A$2:$A$3728,$A12,Documents!$C$2:$C$3728,"kids")=0,"",_xlfn.MAXIFS(Documents!$E$2:$E$3728,Documents!$A$2:$A$3728,$A12,Documents!$C$2:$C$3728,"kids")),"") | O12: =IFERROR(IF(_xlfn.MAXIFS(Documents!$E$2:$E$3728,Documents!$A$2:$A$3728,$A12,Documents!$C$2:$C$3728,"villa_plans")=0,"",_xlfn.MAXIFS(Documents!$E$2:$E$3728,Documents!$A$2:$A$3728,$A12,Documents!$C$2:$C$3728,"villa_plans")),"") | P12: =IFERROR(IF(_xlfn.MAXIFS(Documents!$E$2:$E$3728,Documents!$A$2:$A$3728,$A12,Documents!$C$2:$C$3728,"all_inclusive")=0,"",_xlfn.MAXIFS(Documents!$E$2:$E$3728,Documents!$A$2:$A$3728,$A12,Documents!$C$2:$C$3728,"all_inclusive")),"") | Q12: =IFERROR(IF(_xlfn.MAXIFS(Documents!$E$2:$E$3728,Documents!$A$2:$A$3728,$A12,Documents!$C$2:$C$3728,"sustainability")=0,"",_xlfn.MAXIFS(Documents!$E$2:$E$3728,Documents!$A$2:$A$3728,$A12,Documents!$C$2:$C$3728,"sustainability")),"") | R12: =IFERROR(IF(_xlfn.MAXIFS(Documents!$E$2:$E$3728,Documents!$A$2:$A$3728,$A12,Documents!$C$2:$C$3728,"calendar")=0,"",_xlfn.MAXIFS(Documents!$E$2:$E$3728,Documents!$A$2:$A$3728,$A12,Documents!$C$2:$C$3728,"calendar")),"") | S12: =IFERROR(IF(_xlfn.MAXIFS(Documents!$E$2:$E$3728,Documents!$A$2:$A$3728,$A12,Documents!$C$2:$C$3728,"brochure")=0,"",_xlfn.MAXIFS(Documents!$E$2:$E$3728,Documents!$A$2:$A$3728,$A12,Documents!$C$2:$C$3728,"brochure")),"") | T12: =IFERROR(IF(_xlfn.MAXIFS(Documents!$E$2:$E$3728,Documents!$A$2:$A$3728,$A12,Documents!$C$2:$C$3728,"press_kit")=0,"",_xlfn.MAXIFS(Documents!$E$2:$E$3728,Documents!$A$2:$A$3728,$A12,Documents!$C$2:$C$3728,"press_kit")),"") | U12: =IFERROR(IF(_xlfn.MAXIFS(Documents!$E$2:$E$3728,Documents!$A$2:$A$3728,$A12,Documents!$C$2:$C$3728,"other")=0,"",_xlfn.MAXIFS(Documents!$E$2:$E$3728,Documents!$A$2:$A$3728,$A12,Documents!$C$2:$C$3728,"other")),"") | V12: =IFERROR(IF(_xlfn.MAXIFS(Documents!$E$2:$E$3728,Documents!$A$2:$A$3728,$A12,Documents!$C$2:$C$3728,"obsolete")=0,"",_xlfn.MAXIFS(Documents!$E$2:$E$3728,Documents!$A$2:$A$3728,$A12,Documents!$C$2:$C$3728,"obsolete")),"") | W12: =COUNTIFS(Documents!$A$2:$A$3728,$A12) | X12: =COUNTIFS(Documents!$A$2:$A$3728,$A12,Documents!$R$2:$R$3728,"current") | Y12: =HYPERLINK("https://www.angaga.com.mv/wp-content/uploads/2018/12/GENERAL-INFORMATION.pdf","2018_GENERAL-INFORMATION.pdf") | Z12: events
A13: 12 | B13: Thulhagiri Island Resort & Spa | C13: ok | D13: =IFERROR(IF(_xlfn.MAXIFS(Documents!$E$2:$E$3728,Documents!$A$2:$A$3728,$A13,Documents!$C$2:$C$3728,"factsheet")=0,"",_xlfn.MAXIFS(Documents!$E$2:$E$3728,Documents!$A$2:$A$3728,$A13,Documents!$C$2:$C$3728,"factsheet")),"") | E13: =IFERROR(IF(_xlfn.MAXIFS(Documents!$E$2:$E$3728,Documents!$A$2:$A$3728,$A13,Documents!$C$2:$C$3728,"wedding")=0,"",_xlfn.MAXIFS(Documents!$E$2:$E$3728,Documents!$A$2:$A$3728,$A13,Documents!$C$2:$C$3728,"wedding")),"") | F13: =IFERROR(IF(_xlfn.MAXIFS(Documents!$E$2:$E$3728,Documents!$A$2:$A$3728,$A13,Documents!$C$2:$C$3728,"events")=0,"",_xlfn.MAXIFS(Documents!$E$2:$E$3728,Documents!$A$2:$A$3728,$A13,Documents!$C$2:$C$3728,"events")),"") | G13: =IFERROR(IF(_xlfn.MAXIFS(Documents!$E$2:$E$3728,Documents!$A$2:$A$3728,$A13,Documents!$C$2:$C$3728,"destination_dining")=0,"",_xlfn.MAXIFS(Documents!$E$2:$E$3728,Documents!$A$2:$A$3728,$A13,Documents!$C$2:$C$3728,"destination_dining")),"") | H13: =IFERROR(IF(_xlfn.MAXIFS(Documents!$E$2:$E$3728,Documents!$A$2:$A$3728,$A13,Documents!$C$2:$C$3728,"map")=0,"",_xlfn.MAXIFS(Documents!$E$2:$E$3728,Documents!$A$2:$A$3728,$A13,Documents!$C$2:$C$3728,"map")),"") | I13: =IFERROR(IF(_xlfn.MAXIFS(Documents!$E$2:$E$3728,Documents!$A$2:$A$3728,$A13,Documents!$C$2:$C$3728,"dive_map")=0,"",_xlfn.MAXIFS(Documents!$E$2:$E$3728,Documents!$A$2:$A$3728,$A13,Documents!$C$2:$C$3728,"dive_map")),"") | J13: =IFERROR(IF(_xlfn.MAXIFS(Documents!$E$2:$E$3728,Documents!$A$2:$A$3728,$A13,Documents!$C$2:$C$3728,"spa_menu")=0,"",_xlfn.MAXIFS(Documents!$E$2:$E$3728,Documents!$A$2:$A$3728,$A13,Documents!$C$2:$C$3728,"spa_menu")),"") | K13: =IFERROR(IF(_xlfn.MAXIFS(Documents!$E$2:$E$3728,Documents!$A$2:$A$3728,$A13,Documents!$C$2:$C$3728,"dining_menu")=0,"",_xlfn.MAXIFS(Documents!$E$2:$E$3728,Documents!$A$2:$A$3728,$A13,Documents!$C$2:$C$3728,"dining_menu")),"") | L13: =IFERROR(IF(_xlfn.MAXIFS(Documents!$E$2:$E$3728,Documents!$A$2:$A$3728,$A13,Documents!$C$2:$C$3728,"dive_prices")=0,"",_xlfn.MAXIFS(Documents!$E$2:$E$3728,Documents!$A$2:$A$3728,$A13,Documents!$C$2:$C$3728,"dive_prices")),"") | M13: =IFERROR(IF(_xlfn.MAXIFS(Documents!$E$2:$E$3728,Documents!$A$2:$A$3728,$A13,Documents!$C$2:$C$3728,"excursions")=0,"",_xlfn.MAXIFS(Documents!$E$2:$E$3728,Documents!$A$2:$A$3728,$A13,Documents!$C$2:$C$3728,"excursions")),"") | N13: =IFERROR(IF(_xlfn.MAXIFS(Documents!$E$2:$E$3728,Documents!$A$2:$A$3728,$A13,Documents!$C$2:$C$3728,"kids")=0,"",_xlfn.MAXIFS(Documents!$E$2:$E$3728,Documents!$A$2:$A$3728,$A13,Documents!$C$2:$C$3728,"kids")),"") | O13: =IFERROR(IF(_xlfn.MAXIFS(Documents!$E$2:$E$3728,Documents!$A$2:$A$3728,$A13,Documents!$C$2:$C$3728,"villa_plans")=0,"",_xlfn.MAXIFS(Documents!$E$2:$E$3728,Documents!$A$2:$A$3728,$A13,Documents!$C$2:$C$3728,"villa_plans")),"") | P13: =IFERROR(IF(_xlfn.MAXIFS(Documents!$E$2:$E$3728,Documents!$A$2:$A$3728,$A13,Documents!$C$2:$C$3728,"all_inclusive")=0,"",_xlfn.MAXIFS(Documents!$E$2:$E$3728,Documents!$A$2:$A$3728,$A13,Documents!$C$2:$C$3728,"all_inclusive")),"") | Q13: =IFERROR(IF(_xlfn.MAXIFS(Documents!$E$2:$E$3728,Documents!$A$2:$A$3728,$A13,Documents!$C$2:$C$3728,"sustainability")=0,"",_xlfn.MAXIFS(Documents!$E$2:$E$3728,Documents!$A$2:$A$3728,$A13,Documents!$C$2:$C$3728,"sustainability")),"") | R13: =IFERROR(IF(_xlfn.MAXIFS(Documents!$E$2:$E$3728,Documents!$A$2:$A$3728,$A13,Documents!$C$2:$C$3728,"calendar")=0,"",_xlfn.MAXIFS(Documents!$E$2:$E$3728,Documents!$A$2:$A$3728,$A13,Documents!$C$2:$C$3728,"calendar")),"") | S13: =IFERROR(IF(_xlfn.MAXIFS(Documents!$E$2:$E$3728,Documents!$A$2:$A$3728,$A13,Documents!$C$2:$C$3728,"brochure")=0,"",_xlfn.MAXIFS(Documents!$E$2:$E$3728,Documents!$A$2:$A$3728,$A13,Documents!$C$2:$C$3728,"brochure")),"") | T13: =IFERROR(IF(_xlfn.MAXIFS(Documents!$E$2:$E$3728,Documents!$A$2:$A$3728,$A13,Documents!$C$2:$C$3728,"press_kit")=0,"",_xlfn.MAXIFS(Documents!$E$2:$E$3728,Documents!$A$2:$A$3728,$A13,Documents!$C$2:$C$3728,"press_kit")),"") | U13: =IFERROR(IF(_xlfn.MAXIFS(Documents!$E$2:$E$3728,Documents!$A$2:$A$3728,$A13,Documents!$C$2:$C$3728,"other")=0,"",_xlfn.MAXIFS(Documents!$E$2:$E$3728,Documents!$A$2:$A$3728,$A13,Documents!$C$2:$C$3728,"other")),"") | V13: =IFERROR(IF(_xlfn.MAXIFS(Documents!$E$2:$E$3728,Documents!$A$2:$A$3728,$A13,Documents!$C$2:$C$3728,"obsolete")=0,"",_xlfn.MAXIFS(Documents!$E$2:$E$3728,Documents!$A$2:$A$3728,$A13,Documents!$C$2:$C$3728,"obsolete")),"") | W13: =COUNTIFS(Documents!$A$2:$A$3728,$A13) | X13: =COUNTIFS(Documents!$A$2:$A$3728,$A13,Documents!$R$2:$R$3728,"current") | Z13: factsheet, wedding, events
A14: 13 | B14: Sandies Bathala | C14: ok | D14: =IFERROR(IF(_xlfn.MAXIFS(Documents!$E$2:$E$3728,Documents!$A$2:$A$3728,$A14,Documents!$C$2:$C$3728,"factsheet")=0,"",_xlfn.MAXIFS(Documents!$E$2:$E$3728,Documents!$A$2:$A$3728,$A14,Documents!$C$2:$C$3728,"factsheet")),"") | E14: =IFERROR(IF(_xlfn.MAXIFS(Documents!$E$2:$E$3728,Documents!$A$2:$A$3728,$A14,Documents!$C$2:$C$3728,"wedding")=0,"",_xlfn.MAXIFS(Documents!$E$2:$E$3728,Documents!$A$2:$A$3728,$A14,Documents!$C$2:$C$3728,"wedding")),"") | F14: =IFERROR(IF(_xlfn.MAXIFS(Documents!$E$2:$E$3728,Documents!$A$2:$A$3728,$A14,Documents!$C$2:$C$3728,"events")=0,"",_xlfn.MAXIFS(Documents!$E$2:$E$3728,Documents!$A$2:$A$3728,$A14,Documents!$C$2:$C$3728,"events")),"") | G14: =IFERROR(IF(_xlfn.MAXIFS(Documents!$E$2:$E$3728,Documents!$A$2:$A$3728,$A14,Documents!$C$2:$C$3728,"destination_dining")=0,"",_xlfn.MAXIFS(Documents!$E$2:$E$3728,Documents!$A$2:$A$3728,$A14,Documents!$C$2:$C$3728,"destination_dining")),"") | H14: =IFERROR(IF(_xlfn.MAXIFS(Documents!$E$2:$E$3728,Documents!$A$2:$A$3728,$A14,Documents!$C$2:$C$3728,"map")=0,"",_xlfn.MAXIFS(Documents!$E$2:$E$3728,Documents!$A$2:$A$3728,$A14,Documents!$C$2:$C$3728,"map")),"") | I14: =IFERROR(IF(_xlfn.MAXIFS(Documents!$E$2:$E$3728,Documents!$A$2:$A$3728,$A14,Documents!$C$2:$C$3728,"dive_map")=0,"",_xlfn.MAXIFS(Documents!$E$2:$E$3728,Documents!$A$2:$A$3728,$A14,Documents!$C$2:$C$3728,"dive_map")),"") | J14: =IFERROR(IF(_xlfn.MAXIFS(Documents!$E$2:$E$3728,Documents!$A$2:$A$3728,$A14,Documents!$C$2:$C$3728,"spa_menu")=0,"",_xlfn.MAXIFS(Documents!$E$2:$E$3728,Documents!$A$2:$A$3728,$A14,Documents!$C$2:$C$3728,"spa_menu")),"") | K14: =IFERROR(IF(_xlfn.MAXIFS(Documents!$E$2:$E$3728,Documents!$A$2:$A$3728,$A14,Documents!$C$2:$C$3728,"dining_menu")=0,"",_xlfn.MAXIFS(Documents!$E$2:$E$3728,Documents!$A$2:$A$3728,$A14,Documents!$C$2:$C$3728,"dining_menu")),"") | L14: =IFERROR(IF(_xlfn.MAXIFS(Documents!$E$2:$E$3728,Documents!$A$2:$A$3728,$A14,Documents!$C$2:$C$3728,"dive_prices")=0,"",_xlfn.MAXIFS(Documents!$E$2:$E$3728,Documents!$A$2:$A$3728,$A14,Documents!$C$2:$C$3728,"dive_prices")),"") | M14: =IFERROR(IF(_xlfn.MAXIFS(Documents!$E$2:$E$3728,Documents!$A$2:$A$3728,$A14,Documents!$C$2:$C$3728,"excursions")=0,"",_xlfn.MAXIFS(Documents!$E$2:$E$3728,Documents!$A$2:$A$3728,$A14,Documents!$C$2:$C$3728,"excursions")),"") | N14: =IFERROR(IF(_xlfn.MAXIFS(Documents!$E$2:$E$3728,Documents!$A$2:$A$3728,$A14,Documents!$C$2:$C$3728,"kids")=0,"",_xlfn.MAXIFS(Documents!$E$2:$E$3728,Documents!$A$2:$A$3728,$A14,Documents!$C$2:$C$3728,"kids")),"") | O14: =IFERROR(IF(_xlfn.MAXIFS(Documents!$E$2:$E$3728,Documents!$A$2:$A$3728,$A14,Documents!$C$2:$C$3728,"villa_plans")=0,"",_xlfn.MAXIFS(Documents!$E$2:$E$3728,Documents!$A$2:$A$3728,$A14,Documents!$C$2:$C$3728,"villa_plans")),"") | P14: =IFERROR(IF(_xlfn.MAXIFS(Documents!$E$2:$E$3728,Documents!$A$2:$A$3728,$A14,Documents!$C$2:$C$3728,"all_inclusive")=0,"",_xlfn.MAXIFS(Documents!$E$2:$E$3728,Documents!$A$2:$A$3728,$A14,Documents!$C$2:$C$3728,"all_inclusive")),"") | Q14: =IFERROR(IF(_xlfn.MAXIFS(Documents!$E$2:$E$3728,Documents!$A$2:$A$3728,$A14,Documents!$C$2:$C$3728,"sustainability")=0,"",_xlfn.MAXIFS(Documents!$E$2:$E$3728,Documents!$A$2:$A$3728,$A14,Documents!$C$2:$C$3728,"sustainability")),"") | R14: =IFERROR(IF(_xlfn.MAXIFS(Documents!$E$2:$E$3728,Documents!$A$2:$A$3728,$A14,Documents!$C$2:$C$3728,"calendar")=0,"",_xlfn.MAXIFS(Documents!$E$2:$E$3728,Documents!$A$2:$A$3728,$A14,Documents!$C$2:$C$3728,"calendar")),"") | S14: =IFERROR(IF(_xlfn.MAXIFS(Documents!$E$2:$E$3728,Documents!$A$2:$A$3728,$A14,Documents!$C$2:$C$3728,"brochure")=0,"",_xlfn.MAXIFS(Documents!$E$2:$E$3728,Documents!$A$2:$A$3728,$A14,Documents!$C$2:$C$3728,"brochure")),"") | T14: =IFERROR(IF(_xlfn.MAXIFS(Documents!$E$2:$E$3728,Documents!$A$2:$A$3728,$A14,Documents!$C$2:$C$3728,"press_kit")=0,"",_xlfn.MAXIFS(Documents!$E$2:$E$3728,Documents!$A$2:$A$3728,$A14,Documents!$C$2:$C$3728,"press_kit")),"") | U14: =IFERROR(IF(_xlfn.MAXIFS(Documents!$E$2:$E$3728,Documents!$A$2:$A$3728,$A14,Documents!$C$2:$C$3728,"other")=0,"",_xlfn.MAXIFS(Documents!$E$2:$E$3728,Documents!$A$2:$A$3728,$A14,Documents!$C$2:$C$3728,"other")),"") | V14: =IFERROR(IF(_xlfn.MAXIFS(Documents!$E$2:$E$3728,Documents!$A$2:$A$3728,$A14,Documents!$C$2:$C$3728,"obsolete")=0,"",_xlfn.MAXIFS(Documents!$E$2:$E$3728,Documents!$A$2:$A$3728,$A14,Documents!$C$2:$C$3728,"obsolete")),"") | W14: =COUNTIFS(Documents!$A$2:$A$3728,$A14) | X14: =COUNTIFS(Documents!$A$2:$A$3728,$A14,Documents!$R$2:$R$3728,"current") | Z14: factsheet, wedding
A15: 14 | B15: Baglioni Resort Maldives | C15: blocked | D15: =IFERROR(IF(_xlfn.MAXIFS(Documents!$E$2:$E$3728,Documents!$A$2:$A$3728,$A15,Documents!$C$2:$C$3728,"factsheet")=0,"",_xlfn.MAXIFS(Documents!$E$2:$E$3728,Documents!$A$2:$A$3728,$A15,Documents!$C$2:$C$3728,"factsheet")),"") | E15: =IFERROR(IF(_xlfn.MAXIFS(Documents!$E$2:$E$3728,Documents!$A$2:$A$3728,$A15,Documents!$C$2:$C$3728,"wedding")=0,"",_xlfn.MAXIFS(Documents!$E$2:$E$3728,Documents!$A$2:$A$3728,$A15,Documents!$C$2:$C$3728,"wedding")),"") | F15: =IFERROR(IF(_xlfn.MAXIFS(Documents!$E$2:$E$3728,Documents!$A$2:$A$3728,$A15,Documents!$C$2:$C$3728,"events")=0,"",_xlfn.MAXIFS(Documents!$E$2:$E$3728,Documents!$A$2:$A$3728,$A15,Documents!$C$2:$C$3728,"events")),"") | G15: =IFERROR(IF(_xlfn.MAXIFS(Documents!$E$2:$E$3728,Documents!$A$2:$A$3728,$A15,Documents!$C$2:$C$3728,"destination_dining")=0,"",_xlfn.MAXIFS(Documents!$E$2:$E$3728,Documents!$A$2:$A$3728,$A15,Documents!$C$2:$C$3728,"destination_dining")),"") | H15: =IFERROR(IF(_xlfn.MAXIFS(Documents!$E$2:$E$3728,Documents!$A$2:$A$3728,$A15,Documents!$C$2:$C$3728,"map")=0,"",_xlfn.MAXIFS(Documents!$E$2:$E$3728,Documents!$A$2:$A$3728,$A15,Documents!$C$2:$C$3728,"map")),"") | I15: =IFERROR(IF(_xlfn.MAXIFS(Documents!$E$2:$E$3728,Documents!$A$2:$A$3728,$A15,Documents!$C$2:$C$3728,"dive_map")=0,"",_xlfn.MAXIFS(Documents!$E$2:$E$3728,Documents!$A$2:$A$3728,$A15,Documents!$C$2:$C$3728,"dive_map")),"") | J15: =IFERROR(IF(_xlfn.MAXIFS(Documents!$E$2:$E$3728,Documents!$A$2:$A$3728,$A15,Documents!$C$2:$C$3728,"spa_menu")=0,"",_xlfn.MAXIFS(Documents!$E$2:$E$3728,Documents!$A$2:$A$3728,$A15,Documents!$C$2:$C$3728,"spa_menu")),"") | K15: =IFERROR(IF(_xlfn.MAXIFS(Documents!$E$2:$E$3728,Documents!$A$2:$A$3728,$A15,Documents!$C$2:$C$3728,"dining_menu")=0,"",_xlfn.MAXIFS(Documents!$E$2:$E$3728,Documents!$A$2:$A$3728,$A15,Documents!$C$2:$C$3728,"dining_menu")),"") | L15: =IFERROR(IF(_xlfn.MAXIFS(Documents!$E$2:$E$3728,Documents!$A$2:$A$3728,$A15,Documents!$C$2:$C$3728,"dive_prices")=0,"",_xlfn.MAXIFS(Documents!$E$2:$E$3728,Documents!$A$2:$A$3728,$A15,Documents!$C$2:$C$3728,"dive_prices")),"") | M15: =IFERROR(IF(_xlfn.MAXIFS(Documents!$E$2:$E$3728,Documents!$A$2:$A$3728,$A15,Documents!$C$2:$C$3728,"excursions")=0,"",_xlfn.MAXIFS(Documents!$E$2:$E$3728,Documents!$A$2:$A$3728,$A15,Documents!$C$2:$C$3728,"excursions")),"") | N15: =IFERROR(IF(_xlfn.MAXIFS(Documents!$E$2:$E$3728,Documents!$A$2:$A$3728,$A15,Documents!$C$2:$C$3728,"kids")=0,"",_xlfn.MAXIFS(Documents!$E$2:$E$3728,Documents!$A$2:$A$3728,$A15,Documents!$C$2:$C$3728,"kids")),"") | O15: =IFERROR(IF(_xlfn.MAXIFS(Documents!$E$2:$E$3728,Documents!$A$2:$A$3728,$A15,Documents!$C$2:$C$3728,"villa_plans")=0,"",_xlfn.MAXIFS(Documents!$E$2:$E$3728,Documents!$A$2:$A$3728,$A15,Documents!$C$2:$C$3728,"villa_plans")),"") | P15: =IFERROR(IF(_xlfn.MAXIFS(Documents!$E$2:$E$3728,Documents!$A$2:$A$3728,$A15,Documents!$C$2:$C$3728,"all_inclusive")=0,"",_xlfn.MAXIFS(Documents!$E$2:$E$3728,Documents!$A$2:$A$3728,$A15,Documents!$C$2:$C$3728,"all_inclusive")),"") | Q15: =IFERROR(IF(_xlfn.MAXIFS(Documents!$E$2:$E$3728,Documents!$A$2:$A$3728,$A15,Documents!$C$2:$C$3728,"sustainability")=0,"",_xlfn.MAXIFS(Documents!$E$2:$E$3728,Documents!$A$2:$A$3728,$A15,Documents!$C$2:$C$3728,"sustainability")),"") | R15: =IFERROR(IF(_xlfn.MAXIFS(Documents!$E$2:$E$3728,Documents!$A$2:$A$3728,$A15,Documents!$C$2:$C$3728,"calendar")=0,"",_xlfn.MAXIFS(Documents!$E$2:$E$3728,Documents!$A$2:$A$3728,$A15,Documents!$C$2:$C$3728,"calendar")),"") | S15: =IFERROR(IF(_xlfn.MAXIFS(Documents!$E$2:$E$3728,Documents!$A$2:$A$3728,$A15,Documents!$C$2:$C$3728,"brochure")=0,"",_xlfn.MAXIFS(Documents!$E$2:$E$3728,Documents!$A$2:$A$3728,$A15,Documents!$C$2:$C$3728,"brochure")),"") | T15: =IFERROR(IF(_xlfn.MAXIFS(Documents!$E$2:$E$3728,Documents!$A$2:$A$3728,$A15,Documents!$C$2:$C$3728,"press_kit")=0,"",_xlfn.MAXIFS(Documents!$E$2:$E$3728,Documents!$A$2:$A$3728,$A15,Documents!$C$2:$C$3728,"press_kit")),"") | U15: =IFERROR(IF(_xlfn.MAXIFS(Documents!$E$2:$E$3728,Documents!$A$2:$A$3728,$A15,Documents!$C$2:$C$3728,"other")=0,"",_xlfn.MAXIFS(Documents!$E$2:$E$3728,Documents!$A$2:$A$3728,$A15,Documents!$C$2:$C$3728,"other")),"") | V15: =IFERROR(IF(_xlfn.MAXIFS(Documents!$E$2:$E$3728,Documents!$A$2:$A$3728,$A15,Documents!$C$2:$C$3728,"obsolete")=0,"",_xlfn.MAXIFS(Documents!$E$2:$E$3728,Documents!$A$2:$A$3728,$A15,Documents!$C$2:$C$3728,"obsolete")),"") | W15: =COUNTIFS(Documents!$A$2:$A$3728,$A15) | X15: =COUNTIFS(Documents!$A$2:$A$3728,$A15,Documents!$R$2:$R$3728,"current") | Z15: factsheet, wedding, events
A16: 15 | B16: Alila Kothaifaru Maldives | C16: blocked | D16: =IFERROR(IF(_xlfn.MAXIFS(Documents!$E$2:$E$3728,Documents!$A$2:$A$3728,$A16,Documents!$C$2:$C$3728,"factsheet")=0,"",_xlfn.MAXIFS(Documents!$E$2:$E$3728,Documents!$A$2:$A$3728,$A16,Documents!$C$2:$C$3728,"factsheet")),"") | E16: =IFERROR(IF(_xlfn.MAXIFS(Documents!$E$2:$E$3728,Documents!$A$2:$A$3728,$A16,Documents!$C$2:$C$3728,"wedding")=0,"",_xlfn.MAXIFS(Documents!$E$2:$E$3728,Documents!$A$2:$A$3728,$A16,Documents!$C$2:$C$3728,"wedding")),"") | F16: =IFERROR(IF(_xlfn.MAXIFS(Documents!$E$2:$E$3728,Documents!$A$2:$A$3728,$A16,Documents!$C$2:$C$3728,"events")=0,"",_xlfn.MAXIFS(Documents!$E$2:$E$3728,Documents!$A$2:$A$3728,$A16,Documents!$C$2:$C$3728,"events")),"") | G16: =IFERROR(IF(_xlfn.MAXIFS(Documents!$E$2:$E$3728,Documents!$A$2:$A$3728,$A16,Documents!$C$2:$C$3728,"destination_dining")=0,"",_xlfn.MAXIFS(Documents!$E$2:$E$3728,Documents!$A$2:$A$3728,$A16,Documents!$C$2:$C$3728,"destination_dining")),"") | H16: =IFERROR(IF(_xlfn.MAXIFS(Documents!$E$2:$E$3728,Documents!$A$2:$A$3728,$A16,Documents!$C$2:$C$3728,"map")=0,"",_xlfn.MAXIFS(Documents!$E$2:$E$3728,Documents!$A$2:$A$3728,$A16,Documents!$C$2:$C$3728,"map")),"") | I16: =IFERROR(IF(_xlfn.MAXIFS(Documents!$E$2:$E$3728,Documents!$A$2:$A$3728,$A16,Documents!$C$2:$C$3728,"dive_map")=0,"",_xlfn.MAXIFS(Documents!$E$2:$E$3728,Documents!$A$2:$A$3728,$A16,Documents!$C$2:$C$3728,"dive_map")),"") | J16: =IFERROR(IF(_xlfn.MAXIFS(Documents!$E$2:$E$3728,Documents!$A$2:$A$3728,$A16,Documents!$C$2:$C$3728,"spa_menu")=0,"",_xlfn.MAXIFS(Documents!$E$2:$E$3728,Documents!$A$2:$A$3728,$A16,Documents!$C$2:$C$3728,"spa_menu")),"") | K16: =IFERROR(IF(_xlfn.MAXIFS(Documents!$E$2:$E$3728,Documents!$A$2:$A$3728,$A16,Documents!$C$2:$C$3728,"dining_menu")=0,"",_xlfn.MAXIFS(Documents!$E$2:$E$3728,Documents!$A$2:$A$3728,$A16,Documents!$C$2:$C$3728,"dining_menu")),"") | L16: =IFERROR(IF(_xlfn.MAXIFS(Documents!$E$2:$E$3728,Documents!$A$2:$A$3728,$A16,Documents!$C$2:$C$3728,"dive_prices")=0,"",_xlfn.MAXIFS(Documents!$E$2:$E$3728,Documents!$A$2:$A$3728,$A16,Documents!$C$2:$C$3728,"dive_prices")),"") | M16: =IFERROR(IF(_xlfn.MAXIFS(Documents!$E$2:$E$3728,Documents!$A$2:$A$3728,$A16,Documents!$C$2:$C$3728,"excursions")=0,"",_xlfn.MAXIFS(Documents!$E$2:$E$3728,Documents!$A$2:$A$3728,$A16,Documents!$C$2:$C$3728,"excursions")),"") | N16: =IFERROR(IF(_xlfn.MAXIFS(Documents!$E$2:$E$3728,Documents!$A$2:$A$3728,$A16,Documents!$C$2:$C$3728,"kids")=0,"",_xlfn.MAXIFS(Documents!$E$2:$E$3728,Documents!$A$2:$A$3728,$A16,Documents!$C$2:$C$3728,"kids")),"") | O16: =IFERROR(IF(_xlfn.MAXIFS(Documents!$E$2:$E$3728,Documents!$A$2:$A$3728,$A16,Documents!$C$2:$C$3728,"villa_plans")=0,"",_xlfn.MAXIFS(Documents!$E$2:$E$3728,Documents!$A$2:$A$3728,$A16,Documents!$C$2:$C$3728,"villa_plans")),"") | P16: =IFERROR(IF(_xlfn.MAXIFS(Documents!$E$2:$E$3728,Documents!$A$2:$A$3728,$A16,Documents!$C$2:$C$3728,"all_inclusive")=0,"",_xlfn.MAXIFS(Documents!$E$2:$E$3728,Documents!$A$2:$A$3728,$A16,Documents!$C$2:$C$3728,"all_inclusive")),"") | Q16: =IFERROR(IF(_xlfn.MAXIFS(Documents!$E$2:$E$3728,Documents!$A$2:$A$3728,$A16,Documents!$C$2:$C$3728,"sustainability")=0,"",_xlfn.MAXIFS(Documents!$E$2:$E$3728,Documents!$A$2:$A$3728,$A16,Documents!$C$2:$C$3728,"sustainability")),"") | R16: =IFERROR(IF(_xlfn.MAXIFS(Documents!$E$2:$E$3728,Documents!$A$2:$A$3728,$A16,Documents!$C$2:$C$3728,"calendar")=0,"",_xlfn.MAXIFS(Documents!$E$2:$E$3728,Documents!$A$2:$A$3728,$A16,Documents!$C$2:$C$3728,"calendar")),"") | S16: =IFERROR(IF(_xlfn.MAXIFS(Documents!$E$2:$E$3728,Documents!$A$2:$A$3728,$A16,Documents!$C$2:$C$3728,"brochure")=0,"",_xlfn.MAXIFS(Documents!$E$2:$E$3728,Documents!$A$2:$A$3728,$A16,Documents!$C$2:$C$3728,"brochure")),"") | T16: =IFERROR(IF(_xlfn.MAXIFS(Documents!$E$2:$E$3728,Documents!$A$2:$A$3728,$A16,Documents!$C$2:$C$3728,"press_kit")=0,"",_xlfn.MAXIFS(Documents!$E$2:$E$3728,Documents!$A$2:$A$3728,$A16,Documents!$C$2:$C$3728,"press_kit")),"") | U16: =IFERROR(IF(_xlfn.MAXIFS(Documents!$E$2:$E$3728,Documents!$A$2:$A$3728,$A16,Documents!$C$2:$C$3728,"other")=0,"",_xlfn.MAXIFS(Documents!$E$2:$E$3728,Documents!$A$2:$A$3728,$A16,Documents!$C$2:$C$3728,"other")),"") | V16: =IFERROR(IF(_xlfn.MAXIFS(Documents!$E$2:$E$3728,Documents!$A$2:$A$3728,$A16,Documents!$C$2:$C$3728,"obsolete")=0,"",_xlfn.MAXIFS(Documents!$E$2:$E$3728,Documents!$A$2:$A$3728,$A16,Documents!$C$2:$C$3728,"obsolete")),"") | W16: =COUNTIFS(Documents!$A$2:$A$3728,$A16) | X16: =COUNTIFS(Documents!$A$2:$A$3728,$A16,Documents!$R$2:$R$3728,"current") | Y16: =HYPERLINK("https://www.neoscapesmaldives.com/wp-content/uploads/Alila-Kothaifaru-Maldives-Factsheet-2022.pdf","2022_Alila-Kothaifaru-Maldives-Factsheet") | Z16: wedding, events
A17: 16 | B17: JW Marriott Kaafu Atoll Island Resort | C17: blocked | D17: =IFERROR(IF(_xlfn.MAXIFS(Documents!$E$2:$E$3728,Documents!$A$2:$A$3728,$A17,Documents!$C$2:$C$3728,"factsheet")=0,"",_xlfn.MAXIFS(Documents!$E$2:$E$3728,Documents!$A$2:$A$3728,$A17,Documents!$C$2:$C$3728,"factsheet")),"") | E17: =IFERROR(IF(_xlfn.MAXIFS(Documents!$E$2:$E$3728,Documents!$A$2:$A$3728,$A17,Documents!$C$2:$C$3728,"wedding")=0,"",_xlfn.MAXIFS(Documents!$E$2:$E$3728,Documents!$A$2:$A$3728,$A17,Documents!$C$2:$C$3728,"wedding")),"") | F17: =IFERROR(IF(_xlfn.MAXIFS(Documents!$E$2:$E$3728,Documents!$A$2:$A$3728,$A17,Documents!$C$2:$C$3728,"events")=0,"",_xlfn.MAXIFS(Documents!$E$2:$E$3728,Documents!$A$2:$A$3728,$A17,Documents!$C$2:$C$3728,"events")),"") | G17: =IFERROR(IF(_xlfn.MAXIFS(Documents!$E$2:$E$3728,Documents!$A$2:$A$3728,$A17,Documents!$C$2:$C$3728,"destination_dining")=0,"",_xlfn.MAXIFS(Documents!$E$2:$E$3728,Documents!$A$2:$A$3728,$A17,Documents!$C$2:$C$3728,"destination_dining")),"") | H17: =IFERROR(IF(_xlfn.MAXIFS(Documents!$E$2:$E$3728,Documents!$A$2:$A$3728,$A17,Documents!$C$2:$C$3728,"map")=0,"",_xlfn.MAXIFS(Documents!$E$2:$E$3728,Documents!$A$2:$A$3728,$A17,Documents!$C$2:$C$3728,"map")),"") | I17: =IFERROR(IF(_xlfn.MAXIFS(Documents!$E$2:$E$3728,Documents!$A$2:$A$3728,$A17,Documents!$C$2:$C$3728,"dive_map")=0,"",_xlfn.MAXIFS(Documents!$E$2:$E$3728,Documents!$A$2:$A$3728,$A17,Documents!$C$2:$C$3728,"dive_map")),"") | J17: =IFERROR(IF(_xlfn.MAXIFS(Documents!$E$2:$E$3728,Documents!$A$2:$A$3728,$A17,Documents!$C$2:$C$3728,"spa_menu")=0,"",_xlfn.MAXIFS(Documents!$E$2:$E$3728,Documents!$A$2:$A$3728,$A17,Documents!$C$2:$C$3728,"spa_menu")),"") | K17: =IFERROR(IF(_xlfn.MAXIFS(Documents!$E$2:$E$3728,Documents!$A$2:$A$3728,$A17,Documents!$C$2:$C$3728,"dining_menu")=0,"",_xlfn.MAXIFS(Documents!$E$2:$E$3728,Documents!$A$2:$A$3728,$A17,Documents!$C$2:$C$3728,"dining_menu")),"") | L17: =IFERROR(IF(_xlfn.MAXIFS(Documents!$E$2:$E$3728,Documents!$A$2:$A$3728,$A17,Documents!$C$2:$C$3728,"dive_prices")=0,"",_xlfn.MAXIFS(Documents!$E$2:$E$3728,Documents!$A$2:$A$3728,$A17,Documents!$C$2:$C$3728,"dive_prices")),"") | M17: =IFERROR(IF(_xlfn.MAXIFS(Documents!$E$2:$E$3728,Documents!$A$2:$A$3728,$A17,Documents!$C$2:$C$3728,"excursions")=0,"",_xlfn.MAXIFS(Documents!$E$2:$E$3728,Documents!$A$2:$A$3728,$A17,Documents!$C$2:$C$3728,"excursions")),"") | N17: =IFERROR(IF(_xlfn.MAXIFS(Documents!$E$2:$E$3728,Documents!$A$2:$A$3728,$A17,Documents!$C$2:$C$3728,"kids")=0,"",_xlfn.MAXIFS(Documents!$E$2:$E$3728,Documents!$A$2:$A$3728,$A17,Documents!$C$2:$C$3728,"kids")),"") | O17: =IFERROR(IF(_xlfn.MAXIFS(Documents!$E$2:$E$3728,Documents!$A$2:$A$3728,$A17,Documents!$C$2:$C$3728,"villa_plans")=0,"",_xlfn.MAXIFS(Documents!$E$2:$E$3728,Documents!$A$2:$A$3728,$A17,Documents!$C$2:$C$3728,"villa_plans")),"") | P17: =IFERROR(IF(_xlfn.MAXIFS(Documents!$E$2:$E$3728,Documents!$A$2:$A$3728,$A17,Documents!$C$2:$C$3728,"all_inclusive")=0,"",_xlfn.MAXIFS(Documents!$E$2:$E$3728,Documents!$A$2:$A$3728,$A17,Documents!$C$2:$C$3728,"all_inclusive")),"") | Q17: =IFERROR(IF(_xlfn.MAXIFS(Documents!$E$2:$E$3728,Documents!$A$2:$A$3728,$A17,Documents!$C$2:$C$3728,"sustainability")=0,"",_xlfn.MAXIFS(Documents!$E$2:$E$3728,Documents!$A$2:$A$3728,$A17,Documents!$C$2:$C$3728,"sustainability")),"") | R17: =IFERROR(IF(_xlfn.MAXIFS(Documents!$E$2:$E$3728,Documents!$A$2:$A$3728,$A17,Documents!$C$2:$C$3728,"calendar")=0,"",_xlfn.MAXIFS(Documents!$E$2:$E$3728,Documents!$A$2:$A$3728,$A17,Documents!$C$2:$C$3728,"calendar")),"") | S17: =IFERROR(IF(_xlfn.MAXIFS(Documents!$E$2:$E$3728,Documents!$A$2:$A$3728,$A17,Documents!$C$2:$C$3728,"brochure")=0,"",_xlfn.MAXIFS(Documents!$E$2:$E$3728,Documents!$A$2:$A$3728,$A17,Documents!$C$2:$C$3728,"brochure")),"") | T17: =IFERROR(IF(_xlfn.MAXIFS(Documents!$E$2:$E$3728,Documents!$A$2:$A$3728,$A17,Documents!$C$2:$C$3728,"press_kit")=0,"",_xlfn.MAXIFS(Documents!$E$2:$E$3728,Documents!$A$2:$A$3728,$A17,Documents!$C$2:$C$3728,"press_kit")),"") | U17: =IFERROR(IF(_xlfn.MAXIFS(Documents!$E$2:$E$3728,Documents!$A$2:$A$3728,$A17,Documents!$C$2:$C$3728,"other")=0,"",_xlfn.MAXIFS(Documents!$E$2:$E$3728,Documents!$A$2:$A$3728,$A17,Documents!$C$2:$C$3728,"other")),"") | V17: =IFERROR(IF(_xlfn.MAXIFS(Documents!$E$2:$E$3728,Documents!$A$2:$A$3728,$A17,Documents!$C$2:$C$3728,"obsolete")=0,"",_xlfn.MAXIFS(Documents!$E$2:$E$3728,Documents!$A$2:$A$3728,$A17,Documents!$C$2:$C$3728,"obsolete")),"") | W17: =COUNTIFS(Documents!$A$2:$A$3728,$A17) | X17: =COUNTIFS(Documents!$A$2:$A$3728,$A17,Documents!$R$2:$R$3728,"current") | Z17: factsheet, wedding, events
A18: 17 | B18: Rihiveli Maldives Resort | C18: blocked-partial | D18: =IFERROR(IF(_xlfn.MAXIFS(Documents!$E$2:$E$3728,Documents!$A$2:$A$3728,$A18,Documents!$C$2:$C$3728,"factsheet")=0,"",_xlfn.MAXIFS(Documents!$E$2:$E$3728,Documents!$A$2:$A$3728,$A18,Documents!$C$2:$C$3728,"factsheet")),"") | E18: =IFERROR(IF(_xlfn.MAXIFS(Documents!$E$2:$E$3728,Documents!$A$2:$A$3728,$A18,Documents!$C$2:$C$3728,"wedding")=0,"",_xlfn.MAXIFS(Documents!$E$2:$E$3728,Documents!$A$2:$A$3728,$A18,Documents!$C$2:$C$3728,"wedding")),"") | F18: =IFERROR(IF(_xlfn.MAXIFS(Documents!$E$2:$E$3728,Documents!$A$2:$A$3728,$A18,Documents!$C$2:$C$3728,"events")=0,"",_xlfn.MAXIFS(Documents!$E$2:$E$3728,Documents!$A$2:$A$3728,$A18,Documents!$C$2:$C$3728,"events")),"") | G18: =IFERROR(IF(_xlfn.MAXIFS(Documents!$E$2:$E$3728,Documents!$A$2:$A$3728,$A18,Documents!$C$2:$C$3728,"destination_dining")=0,"",_xlfn.MAXIFS(Documents!$E$2:$E$3728,Documents!$A$2:$A$3728,$A18,Documents!$C$2:$C$3728,"destination_dining")),"") | H18: =IFERROR(IF(_xlfn.MAXIFS(Documents!$E$2:$E$3728,Documents!$A$2:$A$3728,$A18,Documents!$C$2:$C$3728,"map")=0,"",_xlfn.MAXIFS(Documents!$E$2:$E$3728,Documents!$A$2:$A$3728,$A18,Documents!$C$2:$C$3728,"map")),"") | I18: =IFERROR(IF(_xlfn.MAXIFS(Documents!$E$2:$E$3728,Documents!$A$2:$A$3728,$A18,Documents!$C$2:$C$3728,"dive_map")=0,"",_xlfn.MAXIFS(Documents!$E$2:$E$3728,Documents!$A$2:$A$3728,$A18,Documents!$C$2:$C$3728,"dive_map")),"") | J18: =IFERROR(IF(_xlfn.MAXIFS(Documents!$E$2:$E$3728,Documents!$A$2:$A$3728,$A18,Documents!$C$2:$C$3728,"spa_menu")=0,"",_xlfn.MAXIFS(Documents!$E$2:$E$3728,Documents!$A$2:$A$3728,$A18,Documents!$C$2:$C$3728,"spa_menu")),"") | K18: =IFERROR(IF(_xlfn.MAXIFS(Documents!$E$2:$E$3728,Documents!$A$2:$A$3728,$A18,Documents!$C$2:$C$3728,"dining_menu")=0,"",_xlfn.MAXIFS(Documents!$E$2:$E$3728,Documents!$A$2:$A$3728,$A18,Documents!$C$2:$C$3728,"dining_menu")),"") | L18: =IFERROR(IF(_xlfn.MAXIFS(Documents!$E$2:$E$3728,Documents!$A$2:$A$3728,$A18,Documents!$C$2:$C$3728,"dive_prices")=0,"",_xlfn.MAXIFS(Documents!$E$2:$E$3728,Documents!$A$2:$A$3728,$A18,Documents!$C$2:$C$3728,"dive_prices")),"") | M18: =IFERROR(IF(_xlfn.MAXIFS(Documents!$E$2:$E$3728,Documents!$A$2:$A$3728,$A18,Documents!$C$2:$C$3728,"excursions")=0,"",_xlfn.MAXIFS(Documents!$E$2:$E$3728,Documents!$A$2:$A$3728,$A18,Documents!$C$2:$C$3728,"excursions")),"") | N18: =IFERROR(IF(_xlfn.MAXIFS(Documents!$E$2:$E$3728,Documents!$A$2:$A$3728,$A18,Documents!$C$2:$C$3728,"kids")=0,"",_xlfn.MAXIFS(Documents!$E$2:$E$3728,Documents!$A$2:$A$3728,$A18,Documents!$C$2:$C$3728,"kids")),"") | O18: =IFERROR(IF(_xlfn.MAXIFS(Documents!$E$2:$E$3728,Documents!$A$2:$A$3728,$A18,Documents!$C$2:$C$3728,"villa_plans")=0,"",_xlfn.MAXIFS(Documents!$E$2:$E$3728,Documents!$A$2:$A$3728,$A18,Documents!$C$2:$C$3728,"villa_plans")),"") | P18: =IFERROR(IF(_xlfn.MAXIFS(Documents!$E$2:$E$3728,Documents!$A$2:$A$3728,$A18,Documents!$C$2:$C$3728,"all_inclusive")=0,"",_xlfn.MAXIFS(Documents!$E$2:$E$3728,Documents!$A$2:$A$3728,$A18,Documents!$C$2:$C$3728,"all_inclusive")),"") | Q18: =IFERROR(IF(_xlfn.MAXIFS(Documents!$E$2:$E$3728,Documents!$A$2:$A$3728,$A18,Documents!$C$2:$C$3728,"sustainability")=0,"",_xlfn.MAXIFS(Documents!$E$2:$E$3728,Documents!$A$2:$A$3728,$A18,Documents!$C$2:$C$3728,"sustainability")),"") | R18: =IFERROR(IF(_xlfn.MAXIFS(Documents!$E$2:$E$3728,Documents!$A$2:$A$3728,$A18,Documents!$C$2:$C$3728,"calendar")=0,"",_xlfn.MAXIFS(Documents!$E$2:$E$3728,Documents!$A$2:$A$3728,$A18,Documents!$C$2:$C$3728,"calendar")),"") | S18: =IFERROR(IF(_xlfn.MAXIFS(Documents!$E$2:$E$3728,Documents!$A$2:$A$3728,$A18,Documents!$C$2:$C$3728,"brochure")=0,"",_xlfn.MAXIFS(Documents!$E$2:$E$3728,Documents!$A$2:$A$3728,$A18,Documents!$C$2:$C$3728,"brochure")),"") | T18: =IFERROR(IF(_xlfn.MAXIFS(Documents!$E$2:$E$3728,Documents!$A$2:$A$3728,$A18,Documents!$C$2:$C$3728,"press_kit")=0,"",_xlfn.MAXIFS(Documents!$E$2:$E$3728,Documents!$A$2:$A$3728,$A18,Documents!$C$2:$C$3728,"press_kit")),"") | U18: =IFERROR(IF(_xlfn.MAXIFS(Documents!$E$2:$E$3728,Documents!$A$2:$A$3728,$A18,Documents!$C$2:$C$3728,"other")=0,"",_xlfn.MAXIFS(Documents!$E$2:$E$3728,Documents!$A$2:$A$3728,$A18,Documents!$C$2:$C$3728,"other")),"") | V18: =IFERROR(IF(_xlfn.MAXIFS(Documents!$E$2:$E$3728,Documents!$A$2:$A$3728,$A18,Documents!$C$2:$C$3728,"obsolete")=0,"",_xlfn.MAXIFS(Documents!$E$2:$E$3728,Documents!$A$2:$A$3728,$A18,Documents!$C$2:$C$3728,"obsolete")),"") | W18: =COUNTIFS(Documents!$A$2:$A$3728,$A18) | X18: =COUNTIFS(Documents!$A$2:$A$3728,$A18,Documents!$R$2:$R$3728,"current") | Z18: factsheet, wedding, events | AA18: site redirects to expireddomains.com
A19: 18 | B19: JW Marriott Maldives Resort & Spa | C19: blocked | D19: =IFERROR(IF(_xlfn.MAXIFS(Documents!$E$2:$E$3728,Documents!$A$2:$A$3728,$A19,Documents!$C$2:$C$3728,"factsheet")=0,"",_xlfn.MAXIFS(Documents!$E$2:$E$3728,Documents!$A$2:$A$3728,$A19,Documents!$C$2:$C$3728,"factsheet")),"") | E19: =IFERROR(IF(_xlfn.MAXIFS(Documents!$E$2:$E$3728,Documents!$A$2:$A$3728,$A19,Documents!$C$2:$C$3728,"wedding")=0,"",_xlfn.MAXIFS(Documents!$E$2:$E$3728,Documents!$A$2:$A$3728,$A19,Documents!$C$2:$C$3728,"wedding")),"") | F19: =IFERROR(IF(_xlfn.MAXIFS(Documents!$E$2:$E$3728,Documents!$A$2:$A$3728,$A19,Documents!$C$2:$C$3728,"events")=0,"",_xlfn.MAXIFS(Documents!$E$2:$E$3728,Documents!$A$2:$A$3728,$A19,Documents!$C$2:$C$3728,"events")),"") | G19: =IFERROR(IF(_xlfn.MAXIFS(Documents!$E$2:$E$3728,Documents!$A$2:$A$3728,$A19,Documents!$C$2:$C$3728,"destination_dining")=0,"",_xlfn.MAXIFS(Documents!$E$2:$E$3728,Documents!$A$2:$A$3728,$A19,Documents!$C$2:$C$3728,"destination_dining")),"") | H19: =IFERROR(IF(_xlfn.MAXIFS(Documents!$E$2:$E$3728,Documents!$A$2:$A$3728,$A19,Documents!$C$2:$C$3728,"map")=0,"",_xlfn.MAXIFS(Documents!$E$2:$E$3728,Documents!$A$2:$A$3728,$A19,Documents!$C$2:$C$3728,"map")),"") | I19: =IFERROR(IF(_xlfn.MAXIFS(Documents!$E$2:$E$3728,Documents!$A$2:$A$3728,$A19,Documents!$C$2:$C$3728,"dive_map")=0,"",_xlfn.MAXIFS(Documents!$E$2:$E$3728,Documents!$A$2:$A$3728,$A19,Documents!$C$2:$C$3728,"dive_map")),"") | J19: =IFERROR(IF(_xlfn.MAXIFS(Documents!$E$2:$E$3728,Documents!$A$2:$A$3728,$A19,Documents!$C$2:$C$3728,"spa_menu")=0,"",_xlfn.MAXIFS(Documents!$E$2:$E$3728,Documents!$A$2:$A$3728,$A19,Documents!$C$2:$C$3728,"spa_menu")),"") | K19: =IFERROR(IF(_xlfn.MAXIFS(Documents!$E$2:$E$3728,Documents!$A$2:$A$3728,$A19,Documents!$C$2:$C$3728,"dining_menu")=0,"",_xlfn.MAXIFS(Documents!$E$2:$E$3728,Documents!$A$2:$A$3728,$A19,Documents!$C$2:$C$3728,"dining_menu")),"") | L19: =IFERROR(IF(_xlfn.MAXIFS(Documents!$E$2:$E$3728,Documents!$A$2:$A$3728,$A19,Documents!$C$2:$C$3728,"dive_prices")=0,"",_xlfn.MAXIFS(Documents!$E$2:$E$3728,Documents!$A$2:$A$3728,$A19,Documents!$C$2:$C$3728,"dive_prices")),"") | M19: =IFERROR(IF(_xlfn.MAXIFS(Documents!$E$2:$E$3728,Documents!$A$2:$A$3728,$A19,Documents!$C$2:$C$3728,"excursions")=0,"",_xlfn.MAXIFS(Documents!$E$2:$E$3728,Documents!$A$2:$A$3728,$A19,Documents!$C$2:$C$3728,"excursions")),"") | N19: =IFERROR(IF(_xlfn.MAXIFS(Documents!$E$2:$E$3728,Documents!$A$2:$A$3728,$A19,Documents!$C$2:$C$3728,"kids")=0,"",_xlfn.MAXIFS(Documents!$E$2:$E$3728,Documents!$A$2:$A$3728,$A19,Documents!$C$2:$C$3728,"kids")),"") | O19: =IFERROR(IF(_xlfn.MAXIFS(Documents!$E$2:$E$3728,Documents!$A$2:$A$3728,$A19,Documents!$C$2:$C$3728,"villa_plans")=0,"",_xlfn.MAXIFS(Documents!$E$2:$E$3728,Documents!$A$2:$A$3728,$A19,Documents!$C$2:$C$3728,"villa_plans")),"") | P19: =IFERROR(IF(_xlfn.MAXIFS(Documents!$E$2:$E$3728,Documents!$A$2:$A$3728,$A19,Documents!$C$2:$C$3728,"all_inclusive")=0,"",_xlfn.MAXIFS(Documents!$E$2:$E$3728,Documents!$A$2:$A$3728,$A19,Documents!$C$2:$C$3728,"all_inclusive")),"") | Q19: =IFERROR(IF(_xlfn.MAXIFS(Documents!$E$2:$E$3728,Documents!$A$2:$A$3728,$A19,Documents!$C$2:$C$3728,"sustainability")=0,"",_xlfn.MAXIFS(Documents!$E$2:$E$3728,Documents!$A$2:$A$3728,$A19,Documents!$C$2:$C$3728,"sustainability")),"") | R19: =IFERROR(IF(_xlfn.MAXIFS(Documents!$E$2:$E$3728,Documents!$A$2:$A$3728,$A19,Documents!$C$2:$C$3728,"calendar")=0,"",_xlfn.MAXIFS(Documents!$E$2:$E$3728,Documents!$A$2:$A$3728,$A19,Documents!$C$2:$C$3728,"calendar")),"") | S19: =IFERROR(IF(_xlfn.MAXIFS(Documents!$E$2:$E$3728,Documents!$A$2:$A$3728,$A19,Documents!$C$2:$C$3728,"brochure")=0,"",_xlfn.MAXIFS(Documents!$E$2:$E$3728,Documents!$A$2:$A$3728,$A19,Documents!$C$2:$C$3728,"brochure")),"") | T19: =IFERROR(IF(_xlfn.MAXIFS(Documents!$E$2:$E$3728,Documents!$A$2:$A$3728,$A19,Documents!$C$2:$C$3728,"press_kit")=0,"",_xlfn.MAXIFS(Documents!$E$2:$E$3728,Documents!$A$2:$A$3728,$A19,Documents!$C$2:$C$3728,"press_kit")),"") | U19: =IFERROR(IF(_xlfn.MAXIFS(Documents!$E$2:$E$3728,Documents!$A$2:$A$3728,$A19,Documents!$C$2:$C$3728,"other")=0,"",_xlfn.MAXIFS(Documents!$E$2:$E$3728,Documents!$A$2:$A$3728,$A19,Documents!$C$2:$C$3728,"other")),"") | V19: =IFERROR(IF(_xlfn.MAXIFS(Documents!$E$2:$E$3728,Documents!$A$2:$A$3728,$A19,Documents!$C$2:$C$3728,"obsolete")=0,"",_xlfn.MAXIFS(Documents!$E$2:$E$3728,Documents!$A$2:$A$3728,$A19,Documents!$C$2:$C$3728,"obsolete")),"") | W19: =COUNTIFS(Documents!$A$2:$A$3728,$A19) | X19: =COUNTIFS(Documents!$A$2:$A$3728,$A19,Documents!$R$2:$R$3728,"current") | Y19: =HYPERLINK("https://www.neoscapesmaldives.com/wp-content/uploads/JW-Marriott-Maldives-Resort-Spa-Factsheet-2023.pdf","2023_JW-Marriott-Maldives-Resort-Spa-Fac") | Z19: wedding, events
A20: 19 | B20: The Residence Maldives | C20: ok | D20: =IFERROR(IF(_xlfn.MAXIFS(Documents!$E$2:$E$3728,Documents!$A$2:$A$3728,$A20,Documents!$C$2:$C$3728,"factsheet")=0,"",_xlfn.MAXIFS(Documents!$E$2:$E$3728,Documents!$A$2:$A$3728,$A20,Documents!$C$2:$C$3728,"factsheet")),"") | E20: =IFERROR(IF(_xlfn.MAXIFS(Documents!$E$2:$E$3728,Documents!$A$2:$A$3728,$A20,Documents!$C$2:$C$3728,"wedding")=0,"",_xlfn.MAXIFS(Documents!$E$2:$E$3728,Documents!$A$2:$A$3728,$A20,Documents!$C$2:$C$3728,"wedding")),"") | F20: =IFERROR(IF(_xlfn.MAXIFS(Documents!$E$2:$E$3728,Documents!$A$2:$A$3728,$A20,Documents!$C$2:$C$3728,"events")=0,"",_xlfn.MAXIFS(Documents!$E$2:$E$3728,Documents!$A$2:$A$3728,$A20,Documents!$C$2:$C$3728,"events")),"") | G20: =IFERROR(IF(_xlfn.MAXIFS(Documents!$E$2:$E$3728,Documents!$A$2:$A$3728,$A20,Documents!$C$2:$C$3728,"destination_dining")=0,"",_xlfn.MAXIFS(Documents!$E$2:$E$3728,Documents!$A$2:$A$3728,$A20,Documents!$C$2:$C$3728,"destination_dining")),"") | H20: =IFERROR(IF(_xlfn.MAXIFS(Documents!$E$2:$E$3728,Documents!$A$2:$A$3728,$A20,Documents!$C$2:$C$3728,"map")=0,"",_xlfn.MAXIFS(Documents!$E$2:$E$3728,Documents!$A$2:$A$3728,$A20,Documents!$C$2:$C$3728,"map")),"") | I20: =IFERROR(IF(_xlfn.MAXIFS(Documents!$E$2:$E$3728,Documents!$A$2:$A$3728,$A20,Documents!$C$2:$C$3728,"dive_map")=0,"",_xlfn.MAXIFS(Documents!$E$2:$E$3728,Documents!$A$2:$A$3728,$A20,Documents!$C$2:$C$3728,"dive_map")),"") | J20: =IFERROR(IF(_xlfn.MAXIFS(Documents!$E$2:$E$3728,Documents!$A$2:$A$3728,$A20,Documents!$C$2:$C$3728,"spa_menu")=0,"",_xlfn.MAXIFS(Documents!$E$2:$E$3728,Documents!$A$2:$A$3728,$A20,Documents!$C$2:$C$3728,"spa_menu")),"") | K20: =IFERROR(IF(_xlfn.MAXIFS(Documents!$E$2:$E$3728,Documents!$A$2:$A$3728,$A20,Documents!$C$2:$C$3728,"dining_menu")=0,"",_xlfn.MAXIFS(Documents!$E$2:$E$3728,Documents!$A$2:$A$3728,$A20,Documents!$C$2:$C$3728,"dining_menu")),"") | L20: =IFERROR(IF(_xlfn.MAXIFS(Documents!$E$2:$E$3728,Documents!$A$2:$A$3728,$A20,Documents!$C$2:$C$3728,"dive_prices")=0,"",_xlfn.MAXIFS(Documents!$E$2:$E$3728,Documents!$A$2:$A$3728,$A20,Documents!$C$2:$C$3728,"dive_prices")),"") | M20: =IFERROR(IF(_xlfn.MAXIFS(Documents!$E$2:$E$3728,Documents!$A$2:$A$3728,$A20,Documents!$C$2:$C$3728,"excursions")=0,"",_xlfn.MAXIFS(Documents!$E$2:$E$3728,Documents!$A$2:$A$3728,$A20,Documents!$C$2:$C$3728,"excursions")),"") | N20: =IFERROR(IF(_xlfn.MAXIFS(Documents!$E$2:$E$3728,Documents!$A$2:$A$3728,$A20,Documents!$C$2:$C$3728,"kids")=0,"",_xlfn.MAXIFS(Documents!$E$2:$E$3728,Documents!$A$2:$A$3728,$A20,Documents!$C$2:$C$3728,"kids")),"") | O20: =IFERROR(IF(_xlfn.MAXIFS(Documents!$E$2:$E$3728,Documents!$A$2:$A$3728,$A20,Documents!$C$2:$C$3728,"villa_plans")=0,"",_xlfn.MAXIFS(Documents!$E$2:$E$3728,Documents!$A$2:$A$3728,$A20,Documents!$C$2:$C$3728,"villa_plans")),"") | P20: =IFERROR(IF(_xlfn.MAXIFS(Documents!$E$2:$E$3728,Documents!$A$2:$A$3728,$A20,Documents!$C$2:$C$3728,"all_inclusive")=0,"",_xlfn.MAXIFS(Documents!$E$2:$E$3728,Documents!$A$2:$A$3728,$A20,Documents!$C$2:$C$3728,"all_inclusive")),"") | Q20: =IFERROR(IF(_xlfn.MAXIFS(Documents!$E$2:$E$3728,Documents!$A$2:$A$3728,$A20,Documents!$C$2:$C$3728,"sustainability")=0,"",_xlfn.MAXIFS(Documents!$E$2:$E$3728,Documents!$A$2:$A$3728,$A20,Documents!$C$2:$C$3728,"sustainability")),"") | R20: =IFERROR(IF(_xlfn.MAXIFS(Documents!$E$2:$E$3728,Documents!$A$2:$A$3728,$A20,Documents!$C$2:$C$3728,"calendar")=0,"",_xlfn.MAXIFS(Documents!$E$2:$E$3728,Documents!$A$2:$A$3728,$A20,Documents!$C$2:$C$3728,"calendar")),"") | S20: =IFERROR(IF(_xlfn.MAXIFS(Documents!$E$2:$E$3728,Documents!$A$2:$A$3728,$A20,Documents!$C$2:$C$3728,"brochure")=0,"",_xlfn.MAXIFS(Documents!$E$2:$E$3728,Documents!$A$2:$A$3728,$A20,Documents!$C$2:$C$3728,"brochure")),"") | T20: =IFERROR(IF(_xlfn.MAXIFS(Documents!$E$2:$E$3728,Documents!$A$2:$A$3728,$A20,Documents!$C$2:$C$3728,"press_kit")=0,"",_xlfn.MAXIFS(Documents!$E$2:$E$3728,Documents!$A$2:$A$3728,$A20,Documents!$C$2:$C$3728,"press_kit")),"") | U20: =IFERROR(IF(_xlfn.MAXIFS(Documents!$E$2:$E$3728,Documents!$A$2:$A$3728,$A20,Documents!$C$2:$C$3728,"other")=0,"",_xlfn.MAXIFS(Documents!$E$2:$E$3728,Documents!$A$2:$A$3728,$A20,Documents!$C$2:$C$3728,"other")),"") | V20: =IFERROR(IF(_xlfn.MAXIFS(Documents!$E$2:$E$3728,Documents!$A$2:$A$3728,$A20,Documents!$C$2:$C$3728,"obsolete")=0,"",_xlfn.MAXIFS(Documents!$E$2:$E$3728,Documents!$A$2:$A$3728,$A20,Documents!$C$2:$C$3728,"obsolete")),"") | W20: =COUNTIFS(Documents!$A$2:$A$3728,$A20) | X20: =COUNTIFS(Documents!$A$2:$A$3728,$A20,Documents!$R$2:$R$3728,"current") | Z20: factsheet
A21: 20 | B21: The Residence Maldives At Dhigurah | C21: ok | D21: =IFERROR(IF(_xlfn.MAXIFS(Documents!$E$2:$E$3728,Documents!$A$2:$A$3728,$A21,Documents!$C$2:$C$3728,"factsheet")=0,"",_xlfn.MAXIFS(Documents!$E$2:$E$3728,Documents!$A$2:$A$3728,$A21,Documents!$C$2:$C$3728,"factsheet")),"") | E21: =IFERROR(IF(_xlfn.MAXIFS(Documents!$E$2:$E$3728,Documents!$A$2:$A$3728,$A21,Documents!$C$2:$C$3728,"wedding")=0,"",_xlfn.MAXIFS(Documents!$E$2:$E$3728,Documents!$A$2:$A$3728,$A21,Documents!$C$2:$C$3728,"wedding")),"") | F21: =IFERROR(IF(_xlfn.MAXIFS(Documents!$E$2:$E$3728,Documents!$A$2:$A$3728,$A21,Documents!$C$2:$C$3728,"events")=0,"",_xlfn.MAXIFS(Documents!$E$2:$E$3728,Documents!$A$2:$A$3728,$A21,Documents!$C$2:$C$3728,"events")),"") | G21: =IFERROR(IF(_xlfn.MAXIFS(Documents!$E$2:$E$3728,Documents!$A$2:$A$3728,$A21,Documents!$C$2:$C$3728,"destination_dining")=0,"",_xlfn.MAXIFS(Documents!$E$2:$E$3728,Documents!$A$2:$A$3728,$A21,Documents!$C$2:$C$3728,"destination_dining")),"") | H21: =IFERROR(IF(_xlfn.MAXIFS(Documents!$E$2:$E$3728,Documents!$A$2:$A$3728,$A21,Documents!$C$2:$C$3728,"map")=0,"",_xlfn.MAXIFS(Documents!$E$2:$E$3728,Documents!$A$2:$A$3728,$A21,Documents!$C$2:$C$3728,"map")),"") | I21: =IFERROR(IF(_xlfn.MAXIFS(Documents!$E$2:$E$3728,Documents!$A$2:$A$3728,$A21,Documents!$C$2:$C$3728,"dive_map")=0,"",_xlfn.MAXIFS(Documents!$E$2:$E$3728,Documents!$A$2:$A$3728,$A21,Documents!$C$2:$C$3728,"dive_map")),"") | J21: =IFERROR(IF(_xlfn.MAXIFS(Documents!$E$2:$E$3728,Documents!$A$2:$A$3728,$A21,Documents!$C$2:$C$3728,"spa_menu")=0,"",_xlfn.MAXIFS(Documents!$E$2:$E$3728,Documents!$A$2:$A$3728,$A21,Documents!$C$2:$C$3728,"spa_menu")),"") | K21: =IFERROR(IF(_xlfn.MAXIFS(Documents!$E$2:$E$3728,Documents!$A$2:$A$3728,$A21,Documents!$C$2:$C$3728,"dining_menu")=0,"",_xlfn.MAXIFS(Documents!$E$2:$E$3728,Documents!$A$2:$A$3728,$A21,Documents!$C$2:$C$3728,"dining_menu")),"") | L21: =IFERROR(IF(_xlfn.MAXIFS(Documents!$E$2:$E$3728,Documents!$A$2:$A$3728,$A21,Documents!$C$2:$C$3728,"dive_prices")=0,"",_xlfn.MAXIFS(Documents!$E$2:$E$3728,Documents!$A$2:$A$3728,$A21,Documents!$C$2:$C$3728,"dive_prices")),"") | M21: =IFERROR(IF(_xlfn.MAXIFS(Documents!$E$2:$E$3728,Documents!$A$2:$A$3728,$A21,Documents!$C$2:$C$3728,"excursions")=0,"",_xlfn.MAXIFS(Documents!$E$2:$E$3728,Documents!$A$2:$A$3728,$A21,Documents!$C$2:$C$3728,"excursions")),"") | N21: =IFERROR(IF(_xlfn.MAXIFS(Documents!$E$2:$E$3728,Documents!$A$2:$A$3728,$A21,Documents!$C$2:$C$3728,"kids")=0,"",_xlfn.MAXIFS(Documents!$E$2:$E$3728,Documents!$A$2:$A$3728,$A21,Documents!$C$2:$C$3728,"kids")),"") | O21: =IFERROR(IF(_xlfn.MAXIFS(Documents!$E$2:$E$3728,Documents!$A$2:$A$3728,$A21,Documents!$C$2:$C$3728,"villa_plans")=0,"",_xlfn.MAXIFS(Documents!$E$2:$E$3728,Documents!$A$2:$A$3728,$A21,Documents!$C$2:$C$3728,"villa_plans")),"") | P21: =IFERROR(IF(_xlfn.MAXIFS(Documents!$E$2:$E$3728,Documents!$A$2:$A$3728,$A21,Documents!$C$2:$C$3728,"all_inclusive")=0,"",_xlfn.MAXIFS(Documents!$E$2:$E$3728,Documents!$A$2:$A$3728,$A21,Documents!$C$2:$C$3728,"all_inclusive")),"") | Q21: =IFERROR(IF(_xlfn.MAXIFS(Documents!$E$2:$E$3728,Documents!$A$2:$A$3728,$A21,Documents!$C$2:$C$3728,"sustainability")=0,"",_xlfn.MAXIFS(Documents!$E$2:$E$3728,Documents!$A$2:$A$3728,$A21,Documents!$C$2:$C$3728,"sustainability")),"") | R21: =IFERROR(IF(_xlfn.MAXIFS(Documents!$E$2:$E$3728,Documents!$A$2:$A$3728,$A21,Documents!$C$2:$C$3728,"calendar")=0,"",_xlfn.MAXIFS(Documents!$E$2:$E$3728,Documents!$A$2:$A$3728,$A21,Documents!$C$2:$C$3728,"calendar")),"") | S21: =IFERROR(IF(_xlfn.MAXIFS(Documents!$E$2:$E$3728,Documents!$A$2:$A$3728,$A21,Documents!$C$2:$C$3728,"brochure")=0,"",_xlfn.MAXIFS(Documents!$E$2:$E$3728,Documents!$A$2:$A$3728,$A21,Documents!$C$2:$C$3728,"brochure")),"") | T21: =IFERROR(IF(_xlfn.MAXIFS(Documents!$E$2:$E$3728,Documents!$A$2:$A$3728,$A21,Documents!$C$2:$C$3728,"press_kit")=0,"",_xlfn.MAXIFS(Documents!$E$2:$E$3728,Documents!$A$2:$A$3728,$A21,Documents!$C$2:$C$3728,"press_kit")),"") | U21: =IFERROR(IF(_xlfn.MAXIFS(Documents!$E$2:$E$3728,Documents!$A$2:$A$3728,$A21,Documents!$C$2:$C$3728,"other")=0,"",_xlfn.MAXIFS(Documents!$E$2:$E$3728,Documents!$A$2:$A$3728,$A21,Documents!$C$2:$C$3728,"other")),"") | V21: =IFERROR(IF(_xlfn.MAXIFS(Documents!$E$2:$E$3728,Documents!$A$2:$A$3728,$A21,Documents!$C$2:$C$3728,"obsolete")=0,"",_xlfn.MAXIFS(Documents!$E$2:$E$3728,Documents!$A$2:$A$3728,$A21,Documents!$C$2:$C$3728,"obsolete")),"") | W21: =COUNTIFS(Documents!$A$2:$A$3728,$A21) | X21: =COUNTIFS(Documents!$A$2:$A$3728,$A21,Documents!$R$2:$R$3728,"current") | Z21: factsheet, events
A22: 21 | B22: Brennia Kottefaru | C22: ok | D22: =IFERROR(IF(_xlfn.MAXIFS(Documents!$E$2:$E$3728,Documents!$A$2:$A$3728,$A22,Documents!$C$2:$C$3728,"factsheet")=0,"",_xlfn.MAXIFS(Documents!$E$2:$E$3728,Documents!$A$2:$A$3728,$A22,Documents!$C$2:$C$3728,"factsheet")),"") | E22: =IFERROR(IF(_xlfn.MAXIFS(Documents!$E$2:$E$3728,Documents!$A$2:$A$3728,$A22,Documents!$C$2:$C$3728,"wedding")=0,"",_xlfn.MAXIFS(Documents!$E$2:$E$3728,Documents!$A$2:$A$3728,$A22,Documents!$C$2:$C$3728,"wedding")),"") | F22: =IFERROR(IF(_xlfn.MAXIFS(Documents!$E$2:$E$3728,Documents!$A$2:$A$3728,$A22,Documents!$C$2:$C$3728,"events")=0,"",_xlfn.MAXIFS(Documents!$E$2:$E$3728,Documents!$A$2:$A$3728,$A22,Documents!$C$2:$C$3728,"events")),"") | G22: =IFERROR(IF(_xlfn.MAXIFS(Documents!$E$2:$E$3728,Documents!$A$2:$A$3728,$A22,Documents!$C$2:$C$3728,"destination_dining")=0,"",_xlfn.MAXIFS(Documents!$E$2:$E$3728,Documents!$A$2:$A$3728,$A22,Documents!$C$2:$C$3728,"destination_dining")),"") | H22: =IFERROR(IF(_xlfn.MAXIFS(Documents!$E$2:$E$3728,Documents!$A$2:$A$3728,$A22,Documents!$C$2:$C$3728,"map")=0,"",_xlfn.MAXIFS(Documents!$E$2:$E$3728,Documents!$A$2:$A$3728,$A22,Documents!$C$2:$C$3728,"map")),"") | I22: =IFERROR(IF(_xlfn.MAXIFS(Documents!$E$2:$E$3728,Documents!$A$2:$A$3728,$A22,Documents!$C$2:$C$3728,"dive_map")=0,"",_xlfn.MAXIFS(Documents!$E$2:$E$3728,Documents!$A$2:$A$3728,$A22,Documents!$C$2:$C$3728,"dive_map")),"") | J22: =IFERROR(IF(_xlfn.MAXIFS(Documents!$E$2:$E$3728,Documents!$A$2:$A$3728,$A22,Documents!$C$2:$C$3728,"spa_menu")=0,"",_xlfn.MAXIFS(Documents!$E$2:$E$3728,Documents!$A$2:$A$3728,$A22,Documents!$C$2:$C$3728,"spa_menu")),"") | K22: =IFERROR(IF(_xlfn.MAXIFS(Documents!$E$2:$E$3728,Documents!$A$2:$A$3728,$A22,Documents!$C$2:$C$3728,"dining_menu")=0,"",_xlfn.MAXIFS(Documents!$E$2:$E$3728,Documents!$A$2:$A$3728,$A22,Documents!$C$2:$C$3728,"dining_menu")),"") | L22: =IFERROR(IF(_xlfn.MAXIFS(Documents!$E$2:$E$3728,Documents!$A$2:$A$3728,$A22,Documents!$C$2:$C$3728,"dive_prices")=0,"",_xlfn.MAXIFS(Documents!$E$2:$E$3728,Documents!$A$2:$A$3728,$A22,Documents!$C$2:$C$3728,"dive_prices")),"") | M22: =IFERROR(IF(_xlfn.MAXIFS(Documents!$E$2:$E$3728,Documents!$A$2:$A$3728,$A22,Documents!$C$2:$C$3728,"excursions")=0,"",_xlfn.MAXIFS(Documents!$E$2:$E$3728,Documents!$A$2:$A$3728,$A22,Documents!$C$2:$C$3728,"excursions")),"") | N22: =IFERROR(IF(_xlfn.MAXIFS(Documents!$E$2:$E$3728,Documents!$A$2:$A$3728,$A22,Documents!$C$2:$C$3728,"kids")=0,"",_xlfn.MAXIFS(Documents!$E$2:$E$3728,Documents!$A$2:$A$3728,$A22,Documents!$C$2:$C$3728,"kids")),"") | O22: =IFERROR(IF(_xlfn.MAXIFS(Documents!$E$2:$E$3728,Documents!$A$2:$A$3728,$A22,Documents!$C$2:$C$3728,"villa_plans")=0,"",_xlfn.MAXIFS(Documents!$E$2:$E$3728,Documents!$A$2:$A$3728,$A22,Documents!$C$2:$C$3728,"villa_plans")),"") | P22: =IFERROR(IF(_xlfn.MAXIFS(Documents!$E$2:$E$3728,Documents!$A$2:$A$3728,$A22,Documents!$C$2:$C$3728,"all_inclusive")=0,"",_xlfn.MAXIFS(Documents!$E$2:$E$3728,Documents!$A$2:$A$3728,$A22,Documents!$C$2:$C$3728,"all_inclusive")),"") | Q22: =IFERROR(IF(_xlfn.MAXIFS(Documents!$E$2:$E$3728,Documents!$A$2:$A$3728,$A22,Documents!$C$2:$C$3728,"sustainability")=0,"",_xlfn.MAXIFS(Documents!$E$2:$E$3728,Documents!$A$2:$A$3728,$A22,Documents!$C$2:$C$3728,"sustainability")),"") | R22: =IFERROR(IF(_xlfn.MAXIFS(Documents!$E$2:$E$3728,Documents!$A$2:$A$3728,$A22,Documents!$C$2:$C$3728,"calendar")=0,"",_xlfn.MAXIFS(Documents!$E$2:$E$3728,Documents!$A$2:$A$3728,$A22,Documents!$C$2:$C$3728,"calendar")),"") | S22: =IFERROR(IF(_xlfn.MAXIFS(Documents!$E$2:$E$3728,Documents!$A$2:$A$3728,$A22,Documents!$C$2:$C$3728,"brochure")=0,"",_xlfn.MAXIFS(Documents!$E$2:$E$3728,Documents!$A$2:$A$3728,$A22,Documents!$C$2:$C$3728,"brochure")),"") | T22: =IFERROR(IF(_xlfn.MAXIFS(Documents!$E$2:$E$3728,Documents!$A$2:$A$3728,$A22,Documents!$C$2:$C$3728,"press_kit")=0,"",_xlfn.MAXIFS(Documents!$E$2:$E$3728,Documents!$A$2:$A$3728,$A22,Documents!$C$2:$C$3728,"press_kit")),"") | U22: =IFERROR(IF(_xlfn.MAXIFS(Documents!$E$2:$E$3728,Documents!$A$2:$A$3728,$A22,Documents!$C$2:$C$3728,"other")=0,"",_xlfn.MAXIFS(Documents!$E$2:$E$3728,Documents!$A$2:$A$3728,$A22,Documents!$C$2:$C$3728,"other")),"") | V22: =IFERROR(IF(_xlfn.MAXIFS(Documents!$E$2:$E$3728,Documents!$A$2:$A$3728,$A22,Documents!$C$2:$C$3728,"obsolete")=0,"",_xlfn.MAXIFS(Documents!$E$2:$E$3728,Documents!$A$2:$A$3728,$A22,Documents!$C$2:$C$3728,"obsolete")),"") | W22: =COUNTIFS(Documents!$A$2:$A$3728,$A22) | X22: =COUNTIFS(Documents!$A$2:$A$3728,$A22,Documents!$R$2:$R$3728,"current") | Y22: =HYPERLINK("https://www.neoscapesmaldives.com/wp-content/uploads/English-Fact-Sheet-Resort-Map.pdf","2025_English-Fact-Sheet-Resort-Map.pdf") | Z22: wedding, events
A23: 22 | B23: Barceló Whale Lagoon Maldives | C23: unverified | D23: =IFERROR(IF(_xlfn.MAXIFS(Documents!$E$2:$E$3728,Documents!$A$2:$A$3728,$A23,Documents!$C$2:$C$3728,"factsheet")=0,"",_xlfn.MAXIFS(Documents!$E$2:$E$3728,Documents!$A$2:$A$3728,$A23,Documents!$C$2:$C$3728,"factsheet")),"") | E23: =IFERROR(IF(_xlfn.MAXIFS(Documents!$E$2:$E$3728,Documents!$A$2:$A$3728,$A23,Documents!$C$2:$C$3728,"wedding")=0,"",_xlfn.MAXIFS(Documents!$E$2:$E$3728,Documents!$A$2:$A$3728,$A23,Documents!$C$2:$C$3728,"wedding")),"") | F23: =IFERROR(IF(_xlfn.MAXIFS(Documents!$E$2:$E$3728,Documents!$A$2:$A$3728,$A23,Documents!$C$2:$C$3728,"events")=0,"",_xlfn.MAXIFS(Documents!$E$2:$E$3728,Documents!$A$2:$A$3728,$A23,Documents!$C$2:$C$3728,"events")),"") | G23: =IFERROR(IF(_xlfn.MAXIFS(Documents!$E$2:$E$3728,Documents!$A$2:$A$3728,$A23,Documents!$C$2:$C$3728,"destination_dining")=0,"",_xlfn.MAXIFS(Documents!$E$2:$E$3728,Documents!$A$2:$A$3728,$A23,Documents!$C$2:$C$3728,"destination_dining")),"") | H23: =IFERROR(IF(_xlfn.MAXIFS(Documents!$E$2:$E$3728,Documents!$A$2:$A$3728,$A23,Documents!$C$2:$C$3728,"map")=0,"",_xlfn.MAXIFS(Documents!$E$2:$E$3728,Documents!$A$2:$A$3728,$A23,Documents!$C$2:$C$3728,"map")),"") | I23: =IFERROR(IF(_xlfn.MAXIFS(Documents!$E$2:$E$3728,Documents!$A$2:$A$3728,$A23,Documents!$C$2:$C$3728,"dive_map")=0,"",_xlfn.MAXIFS(Documents!$E$2:$E$3728,Documents!$A$2:$A$3728,$A23,Documents!$C$2:$C$3728,"dive_map")),"") | J23: =IFERROR(IF(_xlfn.MAXIFS(Documents!$E$2:$E$3728,Documents!$A$2:$A$3728,$A23,Documents!$C$2:$C$3728,"spa_menu")=0,"",_xlfn.MAXIFS(Documents!$E$2:$E$3728,Documents!$A$2:$A$3728,$A23,Documents!$C$2:$C$3728,"spa_menu")),"") | K23: =IFERROR(IF(_xlfn.MAXIFS(Documents!$E$2:$E$3728,Documents!$A$2:$A$3728,$A23,Documents!$C$2:$C$3728,"dining_menu")=0,"",_xlfn.MAXIFS(Documents!$E$2:$E$3728,Documents!$A$2:$A$3728,$A23,Documents!$C$2:$C$3728,"dining_menu")),"") | L23: =IFERROR(IF(_xlfn.MAXIFS(Documents!$E$2:$E$3728,Documents!$A$2:$A$3728,$A23,Documents!$C$2:$C$3728,"dive_prices")=0,"",_xlfn.MAXIFS(Documents!$E$2:$E$3728,Documents!$A$2:$A$3728,$A23,Documents!$C$2:$C$3728,"dive_prices")),"") | M23: =IFERROR(IF(_xlfn.MAXIFS(Documents!$E$2:$E$3728,Documents!$A$2:$A$3728,$A23,Documents!$C$2:$C$3728,"excursions")=0,"",_xlfn.MAXIFS(Documents!$E$2:$E$3728,Documents!$A$2:$A$3728,$A23,Documents!$C$2:$C$3728,"excursions")),"") | N23: =IFERROR(IF(_xlfn.MAXIFS(Documents!$E$2:$E$3728,Documents!$A$2:$A$3728,$A23,Documents!$C$2:$C$3728,"kids")=0,"",_xlfn.MAXIFS(Documents!$E$2:$E$3728,Documents!$A$2:$A$3728,$A23,Documents!$C$2:$C$3728,"kids")),"") | O23: =IFERROR(IF(_xlfn.MAXIFS(Documents!$E$2:$E$3728,Documents!$A$2:$A$3728,$A23,Documents!$C$2:$C$3728,"villa_plans")=0,"",_xlfn.MAXIFS(Documents!$E$2:$E$3728,Documents!$A$2:$A$3728,$A23,Documents!$C$2:$C$3728,"villa_plans")),"") | P23: =IFERROR(IF(_xlfn.MAXIFS(Documents!$E$2:$E$3728,Documents!$A$2:$A$3728,$A23,Documents!$C$2:$C$3728,"all_inclusive")=0,"",_xlfn.MAXIFS(Documents!$E$2:$E$3728,Documents!$A$2:$A$3728,$A23,Documents!$C$2:$C$3728,"all_inclusive")),"") | Q23: =IFERROR(IF(_xlfn.MAXIFS(Documents!$E$2:$E$3728,Documents!$A$2:$A$3728,$A23,Documents!$C$2:$C$3728,"sustainability")=0,"",_xlfn.MAXIFS(Documents!$E$2:$E$3728,Documents!$A$2:$A$3728,$A23,Documents!$C$2:$C$3728,"sustainability")),"") | R23: =IFERROR(IF(_xlfn.MAXIFS(Documents!$E$2:$E$3728,Documents!$A$2:$A$3728,$A23,Documents!$C$2:$C$3728,"calendar")=0,"",_xlfn.MAXIFS(Documents!$E$2:$E$3728,Documents!$A$2:$A$3728,$A23,Documents!$C$2:$C$3728,"calendar")),"") | S23: =IFERROR(IF(_xlfn.MAXIFS(Documents!$E$2:$E$3728,Documents!$A$2:$A$3728,$A23,Documents!$C$2:$C$3728,"brochure")=0,"",_xlfn.MAXIFS(Documents!$E$2:$E$3728,Documents!$A$2:$A$3728,$A23,Documents!$C$2:$C$3728,"brochure")),"") | T23: =IFERROR(IF(_xlfn.MAXIFS(Documents!$E$2:$E$3728,Documents!$A$2:$A$3728,$A23,Documents!$C$2:$C$3728,"press_kit")=0,"",_xlfn.MAXIFS(Documents!$E$2:$E$3728,Documents!$A$2:$A$3728,$A23,Documents!$C$2:$C$3728,"press_kit")),"") | U23: =IFERROR(IF(_xlfn.MAXIFS(Documents!$E$2:$E$3728,Documents!$A$2:$A$3728,$A23,Documents!$C$2:$C$3728,"other")=0,"",_xlfn.MAXIFS(Documents!$E$2:$E$3728,Documents!$A$2:$A$3728,$A23,Documents!$C$2:$C$3728,"other")),"") | V23: =IFERROR(IF(_xlfn.MAXIFS(Documents!$E$2:$E$3728,Documents!$A$2:$A$3728,$A23,Documents!$C$2:$C$3728,"obsolete")=0,"",_xlfn.MAXIFS(Documents!$E$2:$E$3728,Documents!$A$2:$A$3728,$A23,Documents!$C$2:$C$3728,"obsolete")),"") | W23: =COUNTIFS(Documents!$A$2:$A$3728,$A23) | X23: =COUNTIFS(Documents!$A$2:$A$3728,$A23,Documents!$R$2:$R$3728,"current") | Y23: =HYPERLINK("https://www.neoscapesmaldives.com/wp-content/uploads/Factsheet_MWLM_March2026_Digital-updated.pdf","2026_Factsheet_MWLM_March2026_Digital-up") | Z23: wedding, events | AA23: Meliá Whale Lagoon Maldives
A24: 23 | B24: Nooe Maldives Kunavashi | C24: ok | D24: =IFERROR(IF(_xlfn.MAXIFS(Documents!$E$2:$E$3728,Documents!$A$2:$A$3728,$A24,Documents!$C$2:$C$3728,"factsheet")=0,"",_xlfn.MAXIFS(Documents!$E$2:$E$3728,Documents!$A$2:$A$3728,$A24,Documents!$C$2:$C$3728,"factsheet")),"") | E24: =IFERROR(IF(_xlfn.MAXIFS(Documents!$E$2:$E$3728,Documents!$A$2:$A$3728,$A24,Documents!$C$2:$C$3728,"wedding")=0,"",_xlfn.MAXIFS(Documents!$E$2:$E$3728,Documents!$A$2:$A$3728,$A24,Documents!$C$2:$C$3728,"wedding")),"") | F24: =IFERROR(IF(_xlfn.MAXIFS(Documents!$E$2:$E$3728,Documents!$A$2:$A$3728,$A24,Documents!$C$2:$C$3728,"events")=0,"",_xlfn.MAXIFS(Documents!$E$2:$E$3728,Documents!$A$2:$A$3728,$A24,Documents!$C$2:$C$3728,"events")),"") | G24: =IFERROR(IF(_xlfn.MAXIFS(Documents!$E$2:$E$3728,Documents!$A$2:$A$3728,$A24,Documents!$C$2:$C$3728,"destination_dining")=0,"",_xlfn.MAXIFS(Documents!$E$2:$E$3728,Documents!$A$2:$A$3728,$A24,Documents!$C$2:$C$3728,"destination_dining")),"") | H24: =IFERROR(IF(_xlfn.MAXIFS(Documents!$E$2:$E$3728,Documents!$A$2:$A$3728,$A24,Documents!$C$2:$C$3728,"map")=0,"",_xlfn.MAXIFS(Documents!$E$2:$E$3728,Documents!$A$2:$A$3728,$A24,Documents!$C$2:$C$3728,"map")),"") | I24: =IFERROR(IF(_xlfn.MAXIFS(Documents!$E$2:$E$3728,Documents!$A$2:$A$3728,$A24,Documents!$C$2:$C$3728,"dive_map")=0,"",_xlfn.MAXIFS(Documents!$E$2:$E$3728,Documents!$A$2:$A$3728,$A24,Documents!$C$2:$C$3728,"dive_map")),"") | J24: =IFERROR(IF(_xlfn.MAXIFS(Documents!$E$2:$E$3728,Documents!$A$2:$A$3728,$A24,Documents!$C$2:$C$3728,"spa_menu")=0,"",_xlfn.MAXIFS(Documents!$E$2:$E$3728,Documents!$A$2:$A$3728,$A24,Documents!$C$2:$C$3728,"spa_menu")),"") | K24: =IFERROR(IF(_xlfn.MAXIFS(Documents!$E$2:$E$3728,Documents!$A$2:$A$3728,$A24,Documents!$C$2:$C$3728,"dining_menu")=0,"",_xlfn.MAXIFS(Documents!$E$2:$E$3728,Documents!$A$2:$A$3728,$A24,Documents!$C$2:$C$3728,"dining_menu")),"") | L24: =IFERROR(IF(_xlfn.MAXIFS(Documents!$E$2:$E$3728,Documents!$A$2:$A$3728,$A24,Documents!$C$2:$C$3728,"dive_prices")=0,"",_xlfn.MAXIFS(Documents!$E$2:$E$3728,Documents!$A$2:$A$3728,$A24,Documents!$C$2:$C$3728,"dive_prices")),"") | M24: =IFERROR(IF(_xlfn.MAXIFS(Documents!$E$2:$E$3728,Documents!$A$2:$A$3728,$A24,Documents!$C$2:$C$3728,"excursions")=0,"",_xlfn.MAXIFS(Documents!$E$2:$E$3728,Documents!$A$2:$A$3728,$A24,Documents!$C$2:$C$3728,"excursions")),"") | N24: =IFERROR(IF(_xlfn.MAXIFS(Documents!$E$2:$E$3728,Documents!$A$2:$A$3728,$A24,Documents!$C$2:$C$3728,"kids")=0,"",_xlfn.MAXIFS(Documents!$E$2:$E$3728,Documents!$A$2:$A$3728,$A24,Documents!$C$2:$C$3728,"kids")),"") | O24: =IFERROR(IF(_xlfn.MAXIFS(Documents!$E$2:$E$3728,Documents!$A$2:$A$3728,$A24,Documents!$C$2:$C$3728,"villa_plans")=0,"",_xlfn.MAXIFS(Documents!$E$2:$E$3728,Documents!$A$2:$A$3728,$A24,Documents!$C$2:$C$3728,"villa_plans")),"") | P24: =IFERROR(IF(_xlfn.MAXIFS(Documents!$E$2:$E$3728,Documents!$A$2:$A$3728,$A24,Documents!$C$2:$C$3728,"all_inclusive")=0,"",_xlfn.MAXIFS(Documents!$E$2:$E$3728,Documents!$A$2:$A$3728,$A24,Documents!$C$2:$C$3728,"all_inclusive")),"") | Q24: =IFERROR(IF(_xlfn.MAXIFS(Documents!$E$2:$E$3728,Documents!$A$2:$A$3728,$A24,Documents!$C$2:$C$3728,"sustainability")=0,"",_xlfn.MAXIFS(Documents!$E$2:$E$3728,Documents!$A$2:$A$3728,$A24,Documents!$C$2:$C$3728,"sustainability")),"") | R24: =IFERROR(IF(_xlfn.MAXIFS(Documents!$E$2:$E$3728,Documents!$A$2:$A$3728,$A24,Documents!$C$2:$C$3728,"calendar")=0,"",_xlfn.MAXIFS(Documents!$E$2:$E$3728,Documents!$A$2:$A$3728,$A24,Documents!$C$2:$C$3728,"calendar")),"") | S24: =IFERROR(IF(_xlfn.MAXIFS(Documents!$E$2:$E$3728,Documents!$A$2:$A$3728,$A24,Documents!$C$2:$C$3728,"brochure")=0,"",_xlfn.MAXIFS(Documents!$E$2:$E$3728,Documents!$A$2:$A$3728,$A24,Documents!$C$2:$C$3728,"brochure")),"") | T24: =IFERROR(IF(_xlfn.MAXIFS(Documents!$E$2:$E$3728,Documents!$A$2:$A$3728,$A24,Documents!$C$2:$C$3728,"press_kit")=0,"",_xlfn.MAXIFS(Documents!$E$2:$E$3728,Documents!$A$2:$A$3728,$A24,Documents!$C$2:$C$3728,"press_kit")),"") | U24: =IFERROR(IF(_xlfn.MAXIFS(Documents!$E$2:$E$3728,Documents!$A$2:$A$3728,$A24,Documents!$C$2:$C$3728,"other")=0,"",_xlfn.MAXIFS(Documents!$E$2:$E$3728,Documents!$A$2:$A$3728,$A24,Documents!$C$2:$C$3728,"other")),"") | V24: =IFERROR(IF(_xlfn.MAXIFS(Documents!$E$2:$E$3728,Documents!$A$2:$A$3728,$A24,Documents!$C$2:$C$3728,"obsolete")=0,"",_xlfn.MAXIFS(Documents!$E$2:$E$3728,Documents!$A$2:$A$3728,$A24,Documents!$C$2:$C$3728,"obsolete")),"") | W24: =COUNTIFS(Documents!$A$2:$A$3728,$A24) | X24: =COUNTIFS(Documents!$A$2:$A$3728,$A24,Documents!$R$2:$R$3728,"current") | Y24: =HYPERLINK("https://www.neoscapesmaldives.com/wp-content/uploads/NOOE-Maldives-Kunaavashi_Fact-Sheet-2024.pdf","2024_NOOE-Maldives-Kunaavashi_Fact-Sheet") | Z24: wedding, events
A25: 24 | B25: Canareef Resort Maldives | C25: ok | D25: =IFERROR(IF(_xlfn.MAXIFS(Documents!$E$2:$E$3728,Documents!$A$2:$A$3728,$A25,Documents!$C$2:$C$3728,"factsheet")=0,"",_xlfn.MAXIFS(Documents!$E$2:$E$3728,Documents!$A$2:$A$3728,$A25,Documents!$C$2:$C$3728,"factsheet")),"") | E25: =IFERROR(IF(_xlfn.MAXIFS(Documents!$E$2:$E$3728,Documents!$A$2:$A$3728,$A25,Documents!$C$2:$C$3728,"wedding")=0,"",_xlfn.MAXIFS(Documents!$E$2:$E$3728,Documents!$A$2:$A$3728,$A25,Documents!$C$2:$C$3728,"wedding")),"") | F25: =IFERROR(IF(_xlfn.MAXIFS(Documents!$E$2:$E$3728,Documents!$A$2:$A$3728,$A25,Documents!$C$2:$C$3728,"events")=0,"",_xlfn.MAXIFS(Documents!$E$2:$E$3728,Documents!$A$2:$A$3728,$A25,Documents!$C$2:$C$3728,"events")),"") | G25: =IFERROR(IF(_xlfn.MAXIFS(Documents!$E$2:$E$3728,Documents!$A$2:$A$3728,$A25,Documents!$C$2:$C$3728,"destination_dining")=0,"",_xlfn.MAXIFS(Documents!$E$2:$E$3728,Documents!$A$2:$A$3728,$A25,Documents!$C$2:$C$3728,"destination_dining")),"") | H25: =IFERROR(IF(_xlfn.MAXIFS(Documents!$E$2:$E$3728,Documents!$A$2:$A$3728,$A25,Documents!$C$2:$C$3728,"map")=0,"",_xlfn.MAXIFS(Documents!$E$2:$E$3728,Documents!$A$2:$A$3728,$A25,Documents!$C$2:$C$3728,"map")),"") | I25: =IFERROR(IF(_xlfn.MAXIFS(Documents!$E$2:$E$3728,Documents!$A$2:$A$3728,$A25,Documents!$C$2:$C$3728,"dive_map")=0,"",_xlfn.MAXIFS(Documents!$E$2:$E$3728,Documents!$A$2:$A$3728,$A25,Documents!$C$2:$C$3728,"dive_map")),"") | J25: =IFERROR(IF(_xlfn.MAXIFS(Documents!$E$2:$E$3728,Documents!$A$2:$A$3728,$A25,Documents!$C$2:$C$3728,"spa_menu")=0,"",_xlfn.MAXIFS(Documents!$E$2:$E$3728,Documents!$A$2:$A$3728,$A25,Documents!$C$2:$C$3728,"spa_menu")),"") | K25: =IFERROR(IF(_xlfn.MAXIFS(Documents!$E$2:$E$3728,Documents!$A$2:$A$3728,$A25,Documents!$C$2:$C$3728,"dining_menu")=0,"",_xlfn.MAXIFS(Documents!$E$2:$E$3728,Documents!$A$2:$A$3728,$A25,Documents!$C$2:$C$3728,"dining_menu")),"") | L25: =IFERROR(IF(_xlfn.MAXIFS(Documents!$E$2:$E$3728,Documents!$A$2:$A$3728,$A25,Documents!$C$2:$C$3728,"dive_prices")=0,"",_xlfn.MAXIFS(Documents!$E$2:$E$3728,Documents!$A$2:$A$3728,$A25,Documents!$C$2:$C$3728,"dive_prices")),"") | M25: =IFERROR(IF(_xlfn.MAXIFS(Documents!$E$2:$E$3728,Documents!$A$2:$A$3728,$A25,Documents!$C$2:$C$3728,"excursions")=0,"",_xlfn.MAXIFS(Documents!$E$2:$E$3728,Documents!$A$2:$A$3728,$A25,Documents!$C$2:$C$3728,"excursions")),"") | N25: =IFERROR(IF(_xlfn.MAXIFS(Documents!$E$2:$E$3728,Documents!$A$2:$A$3728,$A25,Documents!$C$2:$C$3728,"kids")=0,"",_xlfn.MAXIFS(Documents!$E$2:$E$3728,Documents!$A$2:$A$3728,$A25,Documents!$C$2:$C$3728,"kids")),"") | O25: =IFERROR(IF(_xlfn.MAXIFS(Documents!$E$2:$E$3728,Documents!$A$2:$A$3728,$A25,Documents!$C$2:$C$3728,"villa_plans")=0,"",_xlfn.MAXIFS(Documents!$E$2:$E$3728,Documents!$A$2:$A$3728,$A25,Documents!$C$2:$C$3728,"villa_plans")),"") | P25: =IFERROR(IF(_xlfn.MAXIFS(Documents!$E$2:$E$3728,Documents!$A$2:$A$3728,$A25,Documents!$C$2:$C$3728,"all_inclusive")=0,"",_xlfn.MAXIFS(Documents!$E$2:$E$3728,Documents!$A$2:$A$3728,$A25,Documents!$C$2:$C$3728,"all_inclusive")),"") | Q25: =IFERROR(IF(_xlfn.MAXIFS(Documents!$E$2:$E$3728,Documents!$A$2:$A$3728,$A25,Documents!$C$2:$C$3728,"sustainability")=0,"",_xlfn.MAXIFS(Documents!$E$2:$E$3728,Documents!$A$2:$A$3728,$A25,Documents!$C$2:$C$3728,"sustainability")),"") | R25: =IFERROR(IF(_xlfn.MAXIFS(Documents!$E$2:$E$3728,Documents!$A$2:$A$3728,$A25,Documents!$C$2:$C$3728,"calendar")=0,"",_xlfn.MAXIFS(Documents!$E$2:$E$3728,Documents!$A$2:$A$3728,$A25,Documents!$C$2:$C$3728,"calendar")),"") | S25: =IFERROR(IF(_xlfn.MAXIFS(Documents!$E$2:$E$3728,Documents!$A$2:$A$3728,$A25,Documents!$C$2:$C$3728,"brochure")=0,"",_xlfn.MAXIFS(Documents!$E$2:$E$3728,Documents!$A$2:$A$3728,$A25,Documents!$C$2:$C$3728,"brochure")),"") | T25: =IFERROR(IF(_xlfn.MAXIFS(Documents!$E$2:$E$3728,Documents!$A$2:$A$3728,$A25,Documents!$C$2:$C$3728,"press_kit")=0,"",_xlfn.MAXIFS(Documents!$E$2:$E$3728,Documents!$A$2:$A$3728,$A25,Documents!$C$2:$C$3728,"press_kit")),"") | U25: =IFERROR(IF(_xlfn.MAXIFS(Documents!$E$2:$E$3728,Documents!$A$2:$A$3728,$A25,Documents!$C$2:$C$3728,"other")=0,"",_xlfn.MAXIFS(Documents!$E$2:$E$3728,Documents!$A$2:$A$3728,$A25,Documents!$C$2:$C$3728,"other")),"") | V25: =IFERROR(IF(_xlfn.MAXIFS(Documents!$E$2:$E$3728,Documents!$A$2:$A$3728,$A25,Documents!$C$2:$C$3728,"obsolete")=0,"",_xlfn.MAXIFS(Documents!$E$2:$E$3728,Documents!$A$2:$A$3728,$A25,Documents!$C$2:$C$3728,"obsolete")),"") | W25: =COUNTIFS(Documents!$A$2:$A$3728,$A25) | X25: =COUNTIFS(Documents!$A$2:$A$3728,$A25,Documents!$R$2:$R$3728,"current") | Z25: factsheet, wedding, events
A26: 25 | B26: Raffles Maldives Meradhoo Resort | C26: blocked | D26: =IFERROR(IF(_xlfn.MAXIFS(Documents!$E$2:$E$3728,Documents!$A$2:$A$3728,$A26,Documents!$C$2:$C$3728,"factsheet")=0,"",_xlfn.MAXIFS(Documents!$E$2:$E$3728,Documents!$A$2:$A$3728,$A26,Documents!$C$2:$C$3728,"factsheet")),"") | E26: =IFERROR(IF(_xlfn.MAXIFS(Documents!$E$2:$E$3728,Documents!$A$2:$A$3728,$A26,Documents!$C$2:$C$3728,"wedding")=0,"",_xlfn.MAXIFS(Documents!$E$2:$E$3728,Documents!$A$2:$A$3728,$A26,Documents!$C$2:$C$3728,"wedding")),"") | F26: =IFERROR(IF(_xlfn.MAXIFS(Documents!$E$2:$E$3728,Documents!$A$2:$A$3728,$A26,Documents!$C$2:$C$3728,"events")=0,"",_xlfn.MAXIFS(Documents!$E$2:$E$3728,Documents!$A$2:$A$3728,$A26,Documents!$C$2:$C$3728,"events")),"") | G26: =IFERROR(IF(_xlfn.MAXIFS(Documents!$E$2:$E$3728,Documents!$A$2:$A$3728,$A26,Documents!$C$2:$C$3728,"destination_dining")=0,"",_xlfn.MAXIFS(Documents!$E$2:$E$3728,Documents!$A$2:$A$3728,$A26,Documents!$C$2:$C$3728,"destination_dining")),"") | H26: =IFERROR(IF(_xlfn.MAXIFS(Documents!$E$2:$E$3728,Documents!$A$2:$A$3728,$A26,Documents!$C$2:$C$3728,"map")=0,"",_xlfn.MAXIFS(Documents!$E$2:$E$3728,Documents!$A$2:$A$3728,$A26,Documents!$C$2:$C$3728,"map")),"") | I26: =IFERROR(IF(_xlfn.MAXIFS(Documents!$E$2:$E$3728,Documents!$A$2:$A$3728,$A26,Documents!$C$2:$C$3728,"dive_map")=0,"",_xlfn.MAXIFS(Documents!$E$2:$E$3728,Documents!$A$2:$A$3728,$A26,Documents!$C$2:$C$3728,"dive_map")),"") | J26: =IFERROR(IF(_xlfn.MAXIFS(Documents!$E$2:$E$3728,Documents!$A$2:$A$3728,$A26,Documents!$C$2:$C$3728,"spa_menu")=0,"",_xlfn.MAXIFS(Documents!$E$2:$E$3728,Documents!$A$2:$A$3728,$A26,Documents!$C$2:$C$3728,"spa_menu")),"") | K26: =IFERROR(IF(_xlfn.MAXIFS(Documents!$E$2:$E$3728,Documents!$A$2:$A$3728,$A26,Documents!$C$2:$C$3728,"dining_menu")=0,"",_xlfn.MAXIFS(Documents!$E$2:$E$3728,Documents!$A$2:$A$3728,$A26,Documents!$C$2:$C$3728,"dining_menu")),"") | L26: =IFERROR(IF(_xlfn.MAXIFS(Documents!$E$2:$E$3728,Documents!$A$2:$A$3728,$A26,Documents!$C$2:$C$3728,"dive_prices")=0,"",_xlfn.MAXIFS(Documents!$E$2:$E$3728,Documents!$A$2:$A$3728,$A26,Documents!$C$2:$C$3728,"dive_prices")),"") | M26: =IFERROR(IF(_xlfn.MAXIFS(Documents!$E$2:$E$3728,Documents!$A$2:$A$3728,$A26,Documents!$C$2:$C$3728,"excursions")=0,"",_xlfn.MAXIFS(Documents!$E$2:$E$3728,Documents!$A$2:$A$3728,$A26,Documents!$C$2:$C$3728,"excursions")),"") | N26: =IFERROR(IF(_xlfn.MAXIFS(Documents!$E$2:$E$3728,Documents!$A$2:$A$3728,$A26,Documents!$C$2:$C$3728,"kids")=0,"",_xlfn.MAXIFS(Documents!$E$2:$E$3728,Documents!$A$2:$A$3728,$A26,Documents!$C$2:$C$3728,"kids")),"") | O26: =IFERROR(IF(_xlfn.MAXIFS(Documents!$E$2:$E$3728,Documents!$A$2:$A$3728,$A26,Documents!$C$2:$C$3728,"villa_plans")=0,"",_xlfn.MAXIFS(Documents!$E$2:$E$3728,Documents!$A$2:$A$3728,$A26,Documents!$C$2:$C$3728,"villa_plans")),"") | P26: =IFERROR(IF(_xlfn.MAXIFS(Documents!$E$2:$E$3728,Documents!$A$2:$A$3728,$A26,Documents!$C$2:$C$3728,"all_inclusive")=0,"",_xlfn.MAXIFS(Documents!$E$2:$E$3728,Documents!$A$2:$A$3728,$A26,Documents!$C$2:$C$3728,"all_inclusive")),"") | Q26: =IFERROR(IF(_xlfn.MAXIFS(Documents!$E$2:$E$3728,Documents!$A$2:$A$3728,$A26,Documents!$C$2:$C$3728,"sustainability")=0,"",_xlfn.MAXIFS(Documents!$E$2:$E$3728,Documents!$A$2:$A$3728,$A26,Documents!$C$2:$C$3728,"sustainability")),"") | R26: =IFERROR(IF(_xlfn.MAXIFS(Documents!$E$2:$E$3728,Documents!$A$2:$A$3728,$A26,Documents!$C$2:$C$3728,"calendar")=0,"",_xlfn.MAXIFS(Documents!$E$2:$E$3728,Documents!$A$2:$A$3728,$A26,Documents!$C$2:$C$3728,"calendar")),"") | S26: =IFERROR(IF(_xlfn.MAXIFS(Documents!$E$2:$E$3728,Documents!$A$2:$A$3728,$A26,Documents!$C$2:$C$3728,"brochure")=0,"",_xlfn.MAXIFS(Documents!$E$2:$E$3728,Documents!$A$2:$A$3728,$A26,Documents!$C$2:$C$3728,"brochure")),"") | T26: =IFERROR(IF(_xlfn.MAXIFS(Documents!$E$2:$E$3728,Documents!$A$2:$A$3728,$A26,Documents!$C$2:$C$3728,"press_kit")=0,"",_xlfn.MAXIFS(Documents!$E$2:$E$3728,Documents!$A$2:$A$3728,$A26,Documents!$C$2:$C$3728,"press_kit")),"") | U26: =IFERROR(IF(_xlfn.MAXIFS(Documents!$E$2:$E$3728,Documents!$A$2:$A$3728,$A26,Documents!$C$2:$C$3728,"other")=0,"",_xlfn.MAXIFS(Documents!$E$2:$E$3728,Documents!$A$2:$A$3728,$A26,Documents!$C$2:$C$3728,"other")),"") | V26: =IFERROR(IF(_xlfn.MAXIFS(Documents!$E$2:$E$3728,Documents!$A$2:$A$3728,$A26,Documents!$C$2:$C$3728,"obsolete")=0,"",_xlfn.MAXIFS(Documents!$E$2:$E$3728,Documents!$A$2:$A$3728,$A26,Documents!$C$2:$C$3728,"obsolete")),"") | W26: =COUNTIFS(Documents!$A$2:$A$3728,$A26) | X26: =COUNTIFS(Documents!$A$2:$A$3728,$A26,Documents!$R$2:$R$3728,"current") | Y26: =HYPERLINK("https://www.neoscapesmaldives.com/wp-content/uploads/Halcyon-Maldives-Factsheet-2026.pdf","2026_Halcyon-Maldives-Factsheet-2026.pdf") | Z26: wedding, events | AA26: Halcyon Maldives
A27: 26 | B27: Centara Ras Fushi Resort & Spa | C27: ok | D27: =IFERROR(IF(_xlfn.MAXIFS(Documents!$E$2:$E$3728,Documents!$A$2:$A$3728,$A27,Documents!$C$2:$C$3728,"factsheet")=0,"",_xlfn.MAXIFS(Documents!$E$2:$E$3728,Documents!$A$2:$A$3728,$A27,Documents!$C$2:$C$3728,"factsheet")),"") | E27: =IFERROR(IF(_xlfn.MAXIFS(Documents!$E$2:$E$3728,Documents!$A$2:$A$3728,$A27,Documents!$C$2:$C$3728,"wedding")=0,"",_xlfn.MAXIFS(Documents!$E$2:$E$3728,Documents!$A$2:$A$3728,$A27,Documents!$C$2:$C$3728,"wedding")),"") | F27: =IFERROR(IF(_xlfn.MAXIFS(Documents!$E$2:$E$3728,Documents!$A$2:$A$3728,$A27,Documents!$C$2:$C$3728,"events")=0,"",_xlfn.MAXIFS(Documents!$E$2:$E$3728,Documents!$A$2:$A$3728,$A27,Documents!$C$2:$C$3728,"events")),"") | G27: =IFERROR(IF(_xlfn.MAXIFS(Documents!$E$2:$E$3728,Documents!$A$2:$A$3728,$A27,Documents!$C$2:$C$3728,"destination_dining")=0,"",_xlfn.MAXIFS(Documents!$E$2:$E$3728,Documents!$A$2:$A$3728,$A27,Documents!$C$2:$C$3728,"destination_dining")),"") | H27: =IFERROR(IF(_xlfn.MAXIFS(Documents!$E$2:$E$3728,Documents!$A$2:$A$3728,$A27,Documents!$C$2:$C$3728,"map")=0,"",_xlfn.MAXIFS(Documents!$E$2:$E$3728,Documents!$A$2:$A$3728,$A27,Documents!$C$2:$C$3728,"map")),"") | I27: =IFERROR(IF(_xlfn.MAXIFS(Documents!$E$2:$E$3728,Documents!$A$2:$A$3728,$A27,Documents!$C$2:$C$3728,"dive_map")=0,"",_xlfn.MAXIFS(Documents!$E$2:$E$3728,Documents!$A$2:$A$3728,$A27,Documents!$C$2:$C$3728,"dive_map")),"") | J27: =IFERROR(IF(_xlfn.MAXIFS(Documents!$E$2:$E$3728,Documents!$A$2:$A$3728,$A27,Documents!$C$2:$C$3728,"spa_menu")=0,"",_xlfn.MAXIFS(Documents!$E$2:$E$3728,Documents!$A$2:$A$3728,$A27,Documents!$C$2:$C$3728,"spa_menu")),"") | K27: =IFERROR(IF(_xlfn.MAXIFS(Documents!$E$2:$E$3728,Documents!$A$2:$A$3728,$A27,Documents!$C$2:$C$3728,"dining_menu")=0,"",_xlfn.MAXIFS(Documents!$E$2:$E$3728,Documents!$A$2:$A$3728,$A27,Documents!$C$2:$C$3728,"dining_menu")),"") | L27: =IFERROR(IF(_xlfn.MAXIFS(Documents!$E$2:$E$3728,Documents!$A$2:$A$3728,$A27,Documents!$C$2:$C$3728,"dive_prices")=0,"",_xlfn.MAXIFS(Documents!$E$2:$E$3728,Documents!$A$2:$A$3728,$A27,Documents!$C$2:$C$3728,"dive_prices")),"") | M27: =IFERROR(IF(_xlfn.MAXIFS(Documents!$E$2:$E$3728,Documents!$A$2:$A$3728,$A27,Documents!$C$2:$C$3728,"excursions")=0,"",_xlfn.MAXIFS(Documents!$E$2:$E$3728,Documents!$A$2:$A$3728,$A27,Documents!$C$2:$C$3728,"excursions")),"") | N27: =IFERROR(IF(_xlfn.MAXIFS(Documents!$E$2:$E$3728,Documents!$A$2:$A$3728,$A27,Documents!$C$2:$C$3728,"kids")=0,"",_xlfn.MAXIFS(Documents!$E$2:$E$3728,Documents!$A$2:$A$3728,$A27,Documents!$C$2:$C$3728,"kids")),"") | O27: =IFERROR(IF(_xlfn.MAXIFS(Documents!$E$2:$E$3728,Documents!$A$2:$A$3728,$A27,Documents!$C$2:$C$3728,"villa_plans")=0,"",_xlfn.MAXIFS(Documents!$E$2:$E$3728,Documents!$A$2:$A$3728,$A27,Documents!$C$2:$C$3728,"villa_plans")),"") | P27: =IFERROR(IF(_xlfn.MAXIFS(Documents!$E$2:$E$3728,Documents!$A$2:$A$3728,$A27,Documents!$C$2:$C$3728,"all_inclusive")=0,"",_xlfn.MAXIFS(Documents!$E$2:$E$3728,Documents!$A$2:$A$3728,$A27,Documents!$C$2:$C$3728,"all_inclusive")),"") | Q27: =IFERROR(IF(_xlfn.MAXIFS(Documents!$E$2:$E$3728,Documents!$A$2:$A$3728,$A27,Documents!$C$2:$C$3728,"sustainability")=0,"",_xlfn.MAXIFS(Documents!$E$2:$E$3728,Documents!$A$2:$A$3728,$A27,Documents!$C$2:$C$3728,"sustainability")),"") | R27: =IFERROR(IF(_xlfn.MAXIFS(Documents!$E$2:$E$3728,Documents!$A$2:$A$3728,$A27,Documents!$C$2:$C$3728,"calendar")=0,"",_xlfn.MAXIFS(Documents!$E$2:$E$3728,Documents!$A$2:$A$3728,$A27,Documents!$C$2:$C$3728,"calendar")),"") | S27: =IFERROR(IF(_xlfn.MAXIFS(Documents!$E$2:$E$3728,Documents!$A$2:$A$3728,$A27,Documents!$C$2:$C$3728,"brochure")=0,"",_xlfn.MAXIFS(Documents!$E$2:$E$3728,Documents!$A$2:$A$3728,$A27,Documents!$C$2:$C$3728,"brochure")),"") | T27: =IFERROR(IF(_xlfn.MAXIFS(Documents!$E$2:$E$3728,Documents!$A$2:$A$3728,$A27,Documents!$C$2:$C$3728,"press_kit")=0,"",_xlfn.MAXIFS(Documents!$E$2:$E$3728,Documents!$A$2:$A$3728,$A27,Documents!$C$2:$C$3728,"press_kit")),"") | U27: =IFERROR(IF(_xlfn.MAXIFS(Documents!$E$2:$E$3728,Documents!$A$2:$A$3728,$A27,Documents!$C$2:$C$3728,"other")=0,"",_xlfn.MAXIFS(Documents!$E$2:$E$3728,Documents!$A$2:$A$3728,$A27,Documents!$C$2:$C$3728,"other")),"") | V27: =IFERROR(IF(_xlfn.MAXIFS(Documents!$E$2:$E$3728,Documents!$A$2:$A$3728,$A27,Documents!$C$2:$C$3728,"obsolete")=0,"",_xlfn.MAXIFS(Documents!$E$2:$E$3728,Documents!$A$2:$A$3728,$A27,Documents!$C$2:$C$3728,"obsolete")),"") | W27: =COUNTIFS(Documents!$A$2:$A$3728,$A27) | X27: =COUNTIFS(Documents!$A$2:$A$3728,$A27,Documents!$R$2:$R$3728,"current") | Y27: =HYPERLINK("https://www.centarahotelsresorts.com/centara/sites/centara-centara/files/2025-12/609_CRF_Factsheet_Y251203.pdf","2025_609_CRF_Factsheet_Y251203.pdf") | Z27: events
A28: 27 | B28: Grand Park Kodhipparu Maldives | C28: ok | D28: =IFERROR(IF(_xlfn.MAXIFS(Documents!$E$2:$E$3728,Documents!$A$2:$A$3728,$A28,Documents!$C$2:$C$3728,"factsheet")=0,"",_xlfn.MAXIFS(Documents!$E$2:$E$3728,Documents!$A$2:$A$3728,$A28,Documents!$C$2:$C$3728,"factsheet")),"") | E28: =IFERROR(IF(_xlfn.MAXIFS(Documents!$E$2:$E$3728,Documents!$A$2:$A$3728,$A28,Documents!$C$2:$C$3728,"wedding")=0,"",_xlfn.MAXIFS(Documents!$E$2:$E$3728,Documents!$A$2:$A$3728,$A28,Documents!$C$2:$C$3728,"wedding")),"") | F28: =IFERROR(IF(_xlfn.MAXIFS(Documents!$E$2:$E$3728,Documents!$A$2:$A$3728,$A28,Documents!$C$2:$C$3728,"events")=0,"",_xlfn.MAXIFS(Documents!$E$2:$E$3728,Documents!$A$2:$A$3728,$A28,Documents!$C$2:$C$3728,"events")),"") | G28: =IFERROR(IF(_xlfn.MAXIFS(Documents!$E$2:$E$3728,Documents!$A$2:$A$3728,$A28,Documents!$C$2:$C$3728,"destination_dining")=0,"",_xlfn.MAXIFS(Documents!$E$2:$E$3728,Documents!$A$2:$A$3728,$A28,Documents!$C$2:$C$3728,"destination_dining")),"") | H28: =IFERROR(IF(_xlfn.MAXIFS(Documents!$E$2:$E$3728,Documents!$A$2:$A$3728,$A28,Documents!$C$2:$C$3728,"map")=0,"",_xlfn.MAXIFS(Documents!$E$2:$E$3728,Documents!$A$2:$A$3728,$A28,Documents!$C$2:$C$3728,"map")),"") | I28: =IFERROR(IF(_xlfn.MAXIFS(Documents!$E$2:$E$3728,Documents!$A$2:$A$3728,$A28,Documents!$C$2:$C$3728,"dive_map")=0,"",_xlfn.MAXIFS(Documents!$E$2:$E$3728,Documents!$A$2:$A$3728,$A28,Documents!$C$2:$C$3728,"dive_map")),"") | J28: =IFERROR(IF(_xlfn.MAXIFS(Documents!$E$2:$E$3728,Documents!$A$2:$A$3728,$A28,Documents!$C$2:$C$3728,"spa_menu")=0,"",_xlfn.MAXIFS(Documents!$E$2:$E$3728,Documents!$A$2:$A$3728,$A28,Documents!$C$2:$C$3728,"spa_menu")),"") | K28: =IFERROR(IF(_xlfn.MAXIFS(Documents!$E$2:$E$3728,Documents!$A$2:$A$3728,$A28,Documents!$C$2:$C$3728,"dining_menu")=0,"",_xlfn.MAXIFS(Documents!$E$2:$E$3728,Documents!$A$2:$A$3728,$A28,Documents!$C$2:$C$3728,"dining_menu")),"") | L28: =IFERROR(IF(_xlfn.MAXIFS(Documents!$E$2:$E$3728,Documents!$A$2:$A$3728,$A28,Documents!$C$2:$C$3728,"dive_prices")=0,"",_xlfn.MAXIFS(Documents!$E$2:$E$3728,Documents!$A$2:$A$3728,$A28,Documents!$C$2:$C$3728,"dive_prices")),"") | M28: =IFERROR(IF(_xlfn.MAXIFS(Documents!$E$2:$E$3728,Documents!$A$2:$A$3728,$A28,Documents!$C$2:$C$3728,"excursions")=0,"",_xlfn.MAXIFS(Documents!$E$2:$E$3728,Documents!$A$2:$A$3728,$A28,Documents!$C$2:$C$3728,"excursions")),"") | N28: =IFERROR(IF(_xlfn.MAXIFS(Documents!$E$2:$E$3728,Documents!$A$2:$A$3728,$A28,Documents!$C$2:$C$3728,"kids")=0,"",_xlfn.MAXIFS(Documents!$E$2:$E$3728,Documents!$A$2:$A$3728,$A28,Documents!$C$2:$C$3728,"kids")),"") | O28: =IFERROR(IF(_xlfn.MAXIFS(Documents!$E$2:$E$3728,Documents!$A$2:$A$3728,$A28,Documents!$C$2:$C$3728,"villa_plans")=0,"",_xlfn.MAXIFS(Documents!$E$2:$E$3728,Documents!$A$2:$A$3728,$A28,Documents!$C$2:$C$3728,"villa_plans")),"") | P28: =IFERROR(IF(_xlfn.MAXIFS(Documents!$E$2:$E$3728,Documents!$A$2:$A$3728,$A28,Documents!$C$2:$C$3728,"all_inclusive")=0,"",_xlfn.MAXIFS(Documents!$E$2:$E$3728,Documents!$A$2:$A$3728,$A28,Documents!$C$2:$C$3728,"all_inclusive")),"") | Q28: =IFERROR(IF(_xlfn.MAXIFS(Documents!$E$2:$E$3728,Documents!$A$2:$A$3728,$A28,Documents!$C$2:$C$3728,"sustainability")=0,"",_xlfn.MAXIFS(Documents!$E$2:$E$3728,Documents!$A$2:$A$3728,$A28,Documents!$C$2:$C$3728,"sustainability")),"") | R28: =IFERROR(IF(_xlfn.MAXIFS(Documents!$E$2:$E$3728,Documents!$A$2:$A$3728,$A28,Documents!$C$2:$C$3728,"calendar")=0,"",_xlfn.MAXIFS(Documents!$E$2:$E$3728,Documents!$A$2:$A$3728,$A28,Documents!$C$2:$C$3728,"calendar")),"") | S28: =IFERROR(IF(_xlfn.MAXIFS(Documents!$E$2:$E$3728,Documents!$A$2:$A$3728,$A28,Documents!$C$2:$C$3728,"brochure")=0,"",_xlfn.MAXIFS(Documents!$E$2:$E$3728,Documents!$A$2:$A$3728,$A28,Documents!$C$2:$C$3728,"brochure")),"") | T28: =IFERROR(IF(_xlfn.MAXIFS(Documents!$E$2:$E$3728,Documents!$A$2:$A$3728,$A28,Documents!$C$2:$C$3728,"press_kit")=0,"",_xlfn.MAXIFS(Documents!$E$2:$E$3728,Documents!$A$2:$A$3728,$A28,Documents!$C$2:$C$3728,"press_kit")),"") | U28: =IFERROR(IF(_xlfn.MAXIFS(Documents!$E$2:$E$3728,Documents!$A$2:$A$3728,$A28,Documents!$C$2:$C$3728,"other")=0,"",_xlfn.MAXIFS(Documents!$E$2:$E$3728,Documents!$A$2:$A$3728,$A28,Documents!$C$2:$C$3728,"other")),"") | V28: =IFERROR(IF(_xlfn.MAXIFS(Documents!$E$2:$E$3728,Documents!$A$2:$A$3728,$A28,Documents!$C$2:$C$3728,"obsolete")=0,"",_xlfn.MAXIFS(Documents!$E$2:$E$3728,Documents!$A$2:$A$3728,$A28,Documents!$C$2:$C$3728,"obsolete")),"") | W28: =COUNTIFS(Documents!$A$2:$A$3728,$A28) | X28: =COUNTIFS(Documents!$A$2:$A$3728,$A28,Documents!$R$2:$R$3728,"current") | Y28: =HYPERLINK("https://maldives.ru/doc/GrandPark-Kodiparru-Resort-Factsheet-2023.pdf","2023_GrandPark-Kodiparru-Resort-Factshee") | Z28: wedding
A29: 28 | B29: Kudadoo Maldives Private island | C29: ok | D29: =IFERROR(IF(_xlfn.MAXIFS(Documents!$E$2:$E$3728,Documents!$A$2:$A$3728,$A29,Documents!$C$2:$C$3728,"factsheet")=0,"",_xlfn.MAXIFS(Documents!$E$2:$E$3728,Documents!$A$2:$A$3728,$A29,Documents!$C$2:$C$3728,"factsheet")),"") | E29: =IFERROR(IF(_xlfn.MAXIFS(Documents!$E$2:$E$3728,Documents!$A$2:$A$3728,$A29,Documents!$C$2:$C$3728,"wedding")=0,"",_xlfn.MAXIFS(Documents!$E$2:$E$3728,Documents!$A$2:$A$3728,$A29,Documents!$C$2:$C$3728,"wedding")),"") | F29: =IFERROR(IF(_xlfn.MAXIFS(Documents!$E$2:$E$3728,Documents!$A$2:$A$3728,$A29,Documents!$C$2:$C$3728,"events")=0,"",_xlfn.MAXIFS(Documents!$E$2:$E$3728,Documents!$A$2:$A$3728,$A29,Documents!$C$2:$C$3728,"events")),"") | G29: =IFERROR(IF(_xlfn.MAXIFS(Documents!$E$2:$E$3728,Documents!$A$2:$A$3728,$A29,Documents!$C$2:$C$3728,"destination_dining")=0,"",_xlfn.MAXIFS(Documents!$E$2:$E$3728,Documents!$A$2:$A$3728,$A29,Documents!$C$2:$C$3728,"destination_dining")),"") | H29: =IFERROR(IF(_xlfn.MAXIFS(Documents!$E$2:$E$3728,Documents!$A$2:$A$3728,$A29,Documents!$C$2:$C$3728,"map")=0,"",_xlfn.MAXIFS(Documents!$E$2:$E$3728,Documents!$A$2:$A$3728,$A29,Documents!$C$2:$C$3728,"map")),"") | I29: =IFERROR(IF(_xlfn.MAXIFS(Documents!$E$2:$E$3728,Documents!$A$2:$A$3728,$A29,Documents!$C$2:$C$3728,"dive_map")=0,"",_xlfn.MAXIFS(Documents!$E$2:$E$3728,Documents!$A$2:$A$3728,$A29,Documents!$C$2:$C$3728,"dive_map")),"") | J29: =IFERROR(IF(_xlfn.MAXIFS(Documents!$E$2:$E$3728,Documents!$A$2:$A$3728,$A29,Documents!$C$2:$C$3728,"spa_menu")=0,"",_xlfn.MAXIFS(Documents!$E$2:$E$3728,Documents!$A$2:$A$3728,$A29,Documents!$C$2:$C$3728,"spa_menu")),"") | K29: =IFERROR(IF(_xlfn.MAXIFS(Documents!$E$2:$E$3728,Documents!$A$2:$A$3728,$A29,Documents!$C$2:$C$3728,"dining_menu")=0,"",_xlfn.MAXIFS(Documents!$E$2:$E$3728,Documents!$A$2:$A$3728,$A29,Documents!$C$2:$C$3728,"dining_menu")),"") | L29: =IFERROR(IF(_xlfn.MAXIFS(Documents!$E$2:$E$3728,Documents!$A$2:$A$3728,$A29,Documents!$C$2:$C$3728,"dive_prices")=0,"",_xlfn.MAXIFS(Documents!$E$2:$E$3728,Documents!$A$2:$A$3728,$A29,Documents!$C$2:$C$3728,"dive_prices")),"") | M29: =IFERROR(IF(_xlfn.MAXIFS(Documents!$E$2:$E$3728,Documents!$A$2:$A$3728,$A29,Documents!$C$2:$C$3728,"excursions")=0,"",_xlfn.MAXIFS(Documents!$E$2:$E$3728,Documents!$A$2:$A$3728,$A29,Documents!$C$2:$C$3728,"excursions")),"") | N29: =IFERROR(IF(_xlfn.MAXIFS(Documents!$E$2:$E$3728,Documents!$A$2:$A$3728,$A29,Documents!$C$2:$C$3728,"kids")=0,"",_xlfn.MAXIFS(Documents!$E$2:$E$3728,Documents!$A$2:$A$3728,$A29,Documents!$C$2:$C$3728,"kids")),"") | O29: =IFERROR(IF(_xlfn.MAXIFS(Documents!$E$2:$E$3728,Documents!$A$2:$A$3728,$A29,Documents!$C$2:$C$3728,"villa_plans")=0,"",_xlfn.MAXIFS(Documents!$E$2:$E$3728,Documents!$A$2:$A$3728,$A29,Documents!$C$2:$C$3728,"villa_plans")),"") | P29: =IFERROR(IF(_xlfn.MAXIFS(Documents!$E$2:$E$3728,Documents!$A$2:$A$3728,$A29,Documents!$C$2:$C$3728,"all_inclusive")=0,"",_xlfn.MAXIFS(Documents!$E$2:$E$3728,Documents!$A$2:$A$3728,$A29,Documents!$C$2:$C$3728,"all_inclusive")),"") | Q29: =IFERROR(IF(_xlfn.MAXIFS(Documents!$E$2:$E$3728,Documents!$A$2:$A$3728,$A29,Documents!$C$2:$C$3728,"sustainability")=0,"",_xlfn.MAXIFS(Documents!$E$2:$E$3728,Documents!$A$2:$A$3728,$A29,Documents!$C$2:$C$3728,"sustainability")),"") | R29: =IFERROR(IF(_xlfn.MAXIFS(Documents!$E$2:$E$3728,Documents!$A$2:$A$3728,$A29,Documents!$C$2:$C$3728,"calendar")=0,"",_xlfn.MAXIFS(Documents!$E$2:$E$3728,Documents!$A$2:$A$3728,$A29,Documents!$C$2:$C$3728,"calendar")),"") | S29: =IFERROR(IF(_xlfn.MAXIFS(Documents!$E$2:$E$3728,Documents!$A$2:$A$3728,$A29,Documents!$C$2:$C$3728,"brochure")=0,"",_xlfn.MAXIFS(Documents!$E$2:$E$3728,Documents!$A$2:$A$3728,$A29,Documents!$C$2:$C$3728,"brochure")),"") | T29: =IFERROR(IF(_xlfn.MAXIFS(Documents!$E$2:$E$3728,Documents!$A$2:$A$3728,$A29,Documents!$C$2:$C$3728,"press_kit")=0,"",_xlfn.MAXIFS(Documents!$E$2:$E$3728,Documents!$A$2:$A$3728,$A29,Documents!$C$2:$C$3728,"press_kit")),"") | U29: =IFERROR(IF(_xlfn.MAXIFS(Documents!$E$2:$E$3728,Documents!$A$2:$A$3728,$A29,Documents!$C$2:$C$3728,"other")=0,"",_xlfn.MAXIFS(Documents!$E$2:$E$3728,Documents!$A$2:$A$3728,$A29,Documents!$C$2:$C$3728,"other")),"") | V29: =IFERROR(IF(_xlfn.MAXIFS(Documents!$E$2:$E$3728,Documents!$A$2:$A$3728,$A29,Documents!$C$2:$C$3728,"obsolete")=0,"",_xlfn.MAXIFS(Documents!$E$2:$E$3728,Documents!$A$2:$A$3728,$A29,Documents!$C$2:$C$3728,"obsolete")),"") | W29: =COUNTIFS(Documents!$A$2:$A$3728,$A29) | X29: =COUNTIFS(Documents!$A$2:$A$3728,$A29,Documents!$R$2:$R$3728,"current") | Y29: =HYPERLINK("https://sales.crownandchamparesorts.com/wp-content/uploads/2025/12/KudadooFactsheet110125103126Ver0526255.pdf","2025_KudadooFactsheet110125103126Ver0526") | Z29: wedding, events
A30: 29 | B30: Dheruhfinolhu by Jawakara Islands Maldives | C30: ok | D30: =IFERROR(IF(_xlfn.MAXIFS(Documents!$E$2:$E$3728,Documents!$A$2:$A$3728,$A30,Documents!$C$2:$C$3728,"factsheet")=0,"",_xlfn.MAXIFS(Documents!$E$2:$E$3728,Documents!$A$2:$A$3728,$A30,Documents!$C$2:$C$3728,"factsheet")),"") | E30: =IFERROR(IF(_xlfn.MAXIFS(Documents!$E$2:$E$3728,Documents!$A$2:$A$3728,$A30,Documents!$C$2:$C$3728,"wedding")=0,"",_xlfn.MAXIFS(Documents!$E$2:$E$3728,Documents!$A$2:$A$3728,$A30,Documents!$C$2:$C$3728,"wedding")),"") | F30: =IFERROR(IF(_xlfn.MAXIFS(Documents!$E$2:$E$3728,Documents!$A$2:$A$3728,$A30,Documents!$C$2:$C$3728,"events")=0,"",_xlfn.MAXIFS(Documents!$E$2:$E$3728,Documents!$A$2:$A$3728,$A30,Documents!$C$2:$C$3728,"events")),"") | G30: =IFERROR(IF(_xlfn.MAXIFS(Documents!$E$2:$E$3728,Documents!$A$2:$A$3728,$A30,Documents!$C$2:$C$3728,"destination_dining")=0,"",_xlfn.MAXIFS(Documents!$E$2:$E$3728,Documents!$A$2:$A$3728,$A30,Documents!$C$2:$C$3728,"destination_dining")),"") | H30: =IFERROR(IF(_xlfn.MAXIFS(Documents!$E$2:$E$3728,Documents!$A$2:$A$3728,$A30,Documents!$C$2:$C$3728,"map")=0,"",_xlfn.MAXIFS(Documents!$E$2:$E$3728,Documents!$A$2:$A$3728,$A30,Documents!$C$2:$C$3728,"map")),"") | I30: =IFERROR(IF(_xlfn.MAXIFS(Documents!$E$2:$E$3728,Documents!$A$2:$A$3728,$A30,Documents!$C$2:$C$3728,"dive_map")=0,"",_xlfn.MAXIFS(Documents!$E$2:$E$3728,Documents!$A$2:$A$3728,$A30,Documents!$C$2:$C$3728,"dive_map")),"") | J30: =IFERROR(IF(_xlfn.MAXIFS(Documents!$E$2:$E$3728,Documents!$A$2:$A$3728,$A30,Documents!$C$2:$C$3728,"spa_menu")=0,"",_xlfn.MAXIFS(Documents!$E$2:$E$3728,Documents!$A$2:$A$3728,$A30,Documents!$C$2:$C$3728,"spa_menu")),"") | K30: =IFERROR(IF(_xlfn.MAXIFS(Documents!$E$2:$E$3728,Documents!$A$2:$A$3728,$A30,Documents!$C$2:$C$3728,"dining_menu")=0,"",_xlfn.MAXIFS(Documents!$E$2:$E$3728,Documents!$A$2:$A$3728,$A30,Documents!$C$2:$C$3728,"dining_menu")),"") | L30: =IFERROR(IF(_xlfn.MAXIFS(Documents!$E$2:$E$3728,Documents!$A$2:$A$3728,$A30,Documents!$C$2:$C$3728,"dive_prices")=0,"",_xlfn.MAXIFS(Documents!$E$2:$E$3728,Documents!$A$2:$A$3728,$A30,Documents!$C$2:$C$3728,"dive_prices")),"") | M30: =IFERROR(IF(_xlfn.MAXIFS(Documents!$E$2:$E$3728,Documents!$A$2:$A$3728,$A30,Documents!$C$2:$C$3728,"excursions")=0,"",_xlfn.MAXIFS(Documents!$E$2:$E$3728,Documents!$A$2:$A$3728,$A30,Documents!$C$2:$C$3728,"excursions")),"") | N30: =IFERROR(IF(_xlfn.MAXIFS(Documents!$E$2:$E$3728,Documents!$A$2:$A$3728,$A30,Documents!$C$2:$C$3728,"kids")=0,"",_xlfn.MAXIFS(Documents!$E$2:$E$3728,Documents!$A$2:$A$3728,$A30,Documents!$C$2:$C$3728,"kids")),"") | O30: =IFERROR(IF(_xlfn.MAXIFS(Documents!$E$2:$E$3728,Documents!$A$2:$A$3728,$A30,Documents!$C$2:$C$3728,"villa_plans")=0,"",_xlfn.MAXIFS(Documents!$E$2:$E$3728,Documents!$A$2:$A$3728,$A30,Documents!$C$2:$C$3728,"villa_plans")),"") | P30: =IFERROR(IF(_xlfn.MAXIFS(Documents!$E$2:$E$3728,Documents!$A$2:$A$3728,$A30,Documents!$C$2:$C$3728,"all_inclusive")=0,"",_xlfn.MAXIFS(Documents!$E$2:$E$3728,Documents!$A$2:$A$3728,$A30,Documents!$C$2:$C$3728,"all_inclusive")),"") | Q30: =IFERROR(IF(_xlfn.MAXIFS(Documents!$E$2:$E$3728,Documents!$A$2:$A$3728,$A30,Documents!$C$2:$C$3728,"sustainability")=0,"",_xlfn.MAXIFS(Documents!$E$2:$E$3728,Documents!$A$2:$A$3728,$A30,Documents!$C$2:$C$3728,"sustainability")),"") | R30: =IFERROR(IF(_xlfn.MAXIFS(Documents!$E$2:$E$3728,Documents!$A$2:$A$3728,$A30,Documents!$C$2:$C$3728,"calendar")=0,"",_xlfn.MAXIFS(Documents!$E$2:$E$3728,Documents!$A$2:$A$3728,$A30,Documents!$C$2:$C$3728,"calendar")),"") | S30: =IFERROR(IF(_xlfn.MAXIFS(Documents!$E$2:$E$3728,Documents!$A$2:$A$3728,$A30,Documents!$C$2:$C$3728,"brochure")=0,"",_xlfn.MAXIFS(Documents!$E$2:$E$3728,Documents!$A$2:$A$3728,$A30,Documents!$C$2:$C$3728,"brochure")),"") | T30: =IFERROR(IF(_xlfn.MAXIFS(Documents!$E$2:$E$3728,Documents!$A$2:$A$3728,$A30,Documents!$C$2:$C$3728,"press_kit")=0,"",_xlfn.MAXIFS(Documents!$E$2:$E$3728,Documents!$A$2:$A$3728,$A30,Documents!$C$2:$C$3728,"press_kit")),"") | U30: =IFERROR(IF(_xlfn.MAXIFS(Documents!$E$2:$E$3728,Documents!$A$2:$A$3728,$A30,Documents!$C$2:$C$3728,"other")=0,"",_xlfn.MAXIFS(Documents!$E$2:$E$3728,Documents!$A$2:$A$3728,$A30,Documents!$C$2:$C$3728,"other")),"") | V30: =IFERROR(IF(_xlfn.MAXIFS(Documents!$E$2:$E$3728,Documents!$A$2:$A$3728,$A30,Documents!$C$2:$C$3728,"obsolete")=0,"",_xlfn.MAXIFS(Documents!$E$2:$E$3728,Documents!$A$2:$A$3728,$A30,Documents!$C$2:$C$3728,"obsolete")),"") | W30: =COUNTIFS(Documents!$A$2:$A$3728,$A30) | X30: =COUNTIFS(Documents!$A$2:$A$3728,$A30,Documents!$R$2:$R$3728,"current") | Z30: factsheet, wedding, events | AA30: Jawakara Islands (shared documents)
A31: 30 | B31: Hurawalhi Island Resort | C31: ok | D31: =IFERROR(IF(_xlfn.MAXIFS(Documents!$E$2:$E$3728,Documents!$A$2:$A$3728,$A31,Documents!$C$2:$C$3728,"factsheet")=0,"",_xlfn.MAXIFS(Documents!$E$2:$E$3728,Documents!$A$2:$A$3728,$A31,Documents!$C$2:$C$3728,"factsheet")),"") | E31: =IFERROR(IF(_xlfn.MAXIFS(Documents!$E$2:$E$3728,Documents!$A$2:$A$3728,$A31,Documents!$C$2:$C$3728,"wedding")=0,"",_xlfn.MAXIFS(Documents!$E$2:$E$3728,Documents!$A$2:$A$3728,$A31,Documents!$C$2:$C$3728,"wedding")),"") | F31: =IFERROR(IF(_xlfn.MAXIFS(Documents!$E$2:$E$3728,Documents!$A$2:$A$3728,$A31,Documents!$C$2:$C$3728,"events")=0,"",_xlfn.MAXIFS(Documents!$E$2:$E$3728,Documents!$A$2:$A$3728,$A31,Documents!$C$2:$C$3728,"events")),"") | G31: =IFERROR(IF(_xlfn.MAXIFS(Documents!$E$2:$E$3728,Documents!$A$2:$A$3728,$A31,Documents!$C$2:$C$3728,"destination_dining")=0,"",_xlfn.MAXIFS(Documents!$E$2:$E$3728,Documents!$A$2:$A$3728,$A31,Documents!$C$2:$C$3728,"destination_dining")),"") | H31: =IFERROR(IF(_xlfn.MAXIFS(Documents!$E$2:$E$3728,Documents!$A$2:$A$3728,$A31,Documents!$C$2:$C$3728,"map")=0,"",_xlfn.MAXIFS(Documents!$E$2:$E$3728,Documents!$A$2:$A$3728,$A31,Documents!$C$2:$C$3728,"map")),"") | I31: =IFERROR(IF(_xlfn.MAXIFS(Documents!$E$2:$E$3728,Documents!$A$2:$A$3728,$A31,Documents!$C$2:$C$3728,"dive_map")=0,"",_xlfn.MAXIFS(Documents!$E$2:$E$3728,Documents!$A$2:$A$3728,$A31,Documents!$C$2:$C$3728,"dive_map")),"") | J31: =IFERROR(IF(_xlfn.MAXIFS(Documents!$E$2:$E$3728,Documents!$A$2:$A$3728,$A31,Documents!$C$2:$C$3728,"spa_menu")=0,"",_xlfn.MAXIFS(Documents!$E$2:$E$3728,Documents!$A$2:$A$3728,$A31,Documents!$C$2:$C$3728,"spa_menu")),"") | K31: =IFERROR(IF(_xlfn.MAXIFS(Documents!$E$2:$E$3728,Documents!$A$2:$A$3728,$A31,Documents!$C$2:$C$3728,"dining_menu")=0,"",_xlfn.MAXIFS(Documents!$E$2:$E$3728,Documents!$A$2:$A$3728,$A31,Documents!$C$2:$C$3728,"dining_menu")),"") | L31: =IFERROR(IF(_xlfn.MAXIFS(Documents!$E$2:$E$3728,Documents!$A$2:$A$3728,$A31,Documents!$C$2:$C$3728,"dive_prices")=0,"",_xlfn.MAXIFS(Documents!$E$2:$E$3728,Documents!$A$2:$A$3728,$A31,Documents!$C$2:$C$3728,"dive_prices")),"") | M31: =IFERROR(IF(_xlfn.MAXIFS(Documents!$E$2:$E$3728,Documents!$A$2:$A$3728,$A31,Documents!$C$2:$C$3728,"excursions")=0,"",_xlfn.MAXIFS(Documents!$E$2:$E$3728,Documents!$A$2:$A$3728,$A31,Documents!$C$2:$C$3728,"excursions")),"") | N31: =IFERROR(IF(_xlfn.MAXIFS(Documents!$E$2:$E$3728,Documents!$A$2:$A$3728,$A31,Documents!$C$2:$C$3728,"kids")=0,"",_xlfn.MAXIFS(Documents!$E$2:$E$3728,Documents!$A$2:$A$3728,$A31,Documents!$C$2:$C$3728,"kids")),"") | O31: =IFERROR(IF(_xlfn.MAXIFS(Documents!$E$2:$E$3728,Documents!$A$2:$A$3728,$A31,Documents!$C$2:$C$3728,"villa_plans")=0,"",_xlfn.MAXIFS(Documents!$E$2:$E$3728,Documents!$A$2:$A$3728,$A31,Documents!$C$2:$C$3728,"villa_plans")),"") | P31: =IFERROR(IF(_xlfn.MAXIFS(Documents!$E$2:$E$3728,Documents!$A$2:$A$3728,$A31,Documents!$C$2:$C$3728,"all_inclusive")=0,"",_xlfn.MAXIFS(Documents!$E$2:$E$3728,Documents!$A$2:$A$3728,$A31,Documents!$C$2:$C$3728,"all_inclusive")),"") | Q31: =IFERROR(IF(_xlfn.MAXIFS(Documents!$E$2:$E$3728,Documents!$A$2:$A$3728,$A31,Documents!$C$2:$C$3728,"sustainability")=0,"",_xlfn.MAXIFS(Documents!$E$2:$E$3728,Documents!$A$2:$A$3728,$A31,Documents!$C$2:$C$3728,"sustainability")),"") | R31: =IFERROR(IF(_xlfn.MAXIFS(Documents!$E$2:$E$3728,Documents!$A$2:$A$3728,$A31,Documents!$C$2:$C$3728,"calendar")=0,"",_xlfn.MAXIFS(Documents!$E$2:$E$3728,Documents!$A$2:$A$3728,$A31,Documents!$C$2:$C$3728,"calendar")),"") | S31: =IFERROR(IF(_xlfn.MAXIFS(Documents!$E$2:$E$3728,Documents!$A$2:$A$3728,$A31,Documents!$C$2:$C$3728,"brochure")=0,"",_xlfn.MAXIFS(Documents!$E$2:$E$3728,Documents!$A$2:$A$3728,$A31,Documents!$C$2:$C$3728,"brochure")),"") | T31: =IFERROR(IF(_xlfn.MAXIFS(Documents!$E$2:$E$3728,Documents!$A$2:$A$3728,$A31,Documents!$C$2:$C$3728,"press_kit")=0,"",_xlfn.MAXIFS(Documents!$E$2:$E$3728,Documents!$A$2:$A$3728,$A31,Documents!$C$2:$C$3728,"press_kit")),"") | U31: =IFERROR(IF(_xlfn.MAXIFS(Documents!$E$2:$E$3728,Documents!$A$2:$A$3728,$A31,Documents!$C$2:$C$3728,"other")=0,"",_xlfn.MAXIFS(Documents!$E$2:$E$3728,Documents!$A$2:$A$3728,$A31,Documents!$C$2:$C$3728,"other")),"") | V31: =IFERROR(IF(_xlfn.MAXIFS(Documents!$E$2:$E$3728,Documents!$A$2:$A$3728,$A31,Documents!$C$2:$C$3728,"obsolete")=0,"",_xlfn.MAXIFS(Documents!$E$2:$E$3728,Documents!$A$2:$A$3728,$A31,Documents!$C$2:$C$3728,"obsolete")),"") | W31: =COUNTIFS(Documents!$A$2:$A$3728,$A31) | X31: =COUNTIFS(Documents!$A$2:$A$3728,$A31,Documents!$R$2:$R$3728,"current") | Y31: =HYPERLINK("https://sales.crownandchamparesorts.com/wp-content/uploads/2023/08/FactSheetHurawalhi110123103124Ver030123.pdf","2023_FactSheetHurawalhi110123103124Ver03") | Z31: events
A32: 31 | B32: Innahura Maldives Resort | C32: ok | D32: =IFERROR(IF(_xlfn.MAXIFS(Documents!$E$2:$E$3728,Documents!$A$2:$A$3728,$A32,Documents!$C$2:$C$3728,"factsheet")=0,"",_xlfn.MAXIFS(Documents!$E$2:$E$3728,Documents!$A$2:$A$3728,$A32,Documents!$C$2:$C$3728,"factsheet")),"") | E32: =IFERROR(IF(_xlfn.MAXIFS(Documents!$E$2:$E$3728,Documents!$A$2:$A$3728,$A32,Documents!$C$2:$C$3728,"wedding")=0,"",_xlfn.MAXIFS(Documents!$E$2:$E$3728,Documents!$A$2:$A$3728,$A32,Documents!$C$2:$C$3728,"wedding")),"") | F32: =IFERROR(IF(_xlfn.MAXIFS(Documents!$E$2:$E$3728,Documents!$A$2:$A$3728,$A32,Documents!$C$2:$C$3728,"events")=0,"",_xlfn.MAXIFS(Documents!$E$2:$E$3728,Documents!$A$2:$A$3728,$A32,Documents!$C$2:$C$3728,"events")),"") | G32: =IFERROR(IF(_xlfn.MAXIFS(Documents!$E$2:$E$3728,Documents!$A$2:$A$3728,$A32,Documents!$C$2:$C$3728,"destination_dining")=0,"",_xlfn.MAXIFS(Documents!$E$2:$E$3728,Documents!$A$2:$A$3728,$A32,Documents!$C$2:$C$3728,"destination_dining")),"") | H32: =IFERROR(IF(_xlfn.MAXIFS(Documents!$E$2:$E$3728,Documents!$A$2:$A$3728,$A32,Documents!$C$2:$C$3728,"map")=0,"",_xlfn.MAXIFS(Documents!$E$2:$E$3728,Documents!$A$2:$A$3728,$A32,Documents!$C$2:$C$3728,"map")),"") | I32: =IFERROR(IF(_xlfn.MAXIFS(Documents!$E$2:$E$3728,Documents!$A$2:$A$3728,$A32,Documents!$C$2:$C$3728,"dive_map")=0,"",_xlfn.MAXIFS(Documents!$E$2:$E$3728,Documents!$A$2:$A$3728,$A32,Documents!$C$2:$C$3728,"dive_map")),"") | J32: =IFERROR(IF(_xlfn.MAXIFS(Documents!$E$2:$E$3728,Documents!$A$2:$A$3728,$A32,Documents!$C$2:$C$3728,"spa_menu")=0,"",_xlfn.MAXIFS(Documents!$E$2:$E$3728,Documents!$A$2:$A$3728,$A32,Documents!$C$2:$C$3728,"spa_menu")),"") | K32: =IFERROR(IF(_xlfn.MAXIFS(Documents!$E$2:$E$3728,Documents!$A$2:$A$3728,$A32,Documents!$C$2:$C$3728,"dining_menu")=0,"",_xlfn.MAXIFS(Documents!$E$2:$E$3728,Documents!$A$2:$A$3728,$A32,Documents!$C$2:$C$3728,"dining_menu")),"") | L32: =IFERROR(IF(_xlfn.MAXIFS(Documents!$E$2:$E$3728,Documents!$A$2:$A$3728,$A32,Documents!$C$2:$C$3728,"dive_prices")=0,"",_xlfn.MAXIFS(Documents!$E$2:$E$3728,Documents!$A$2:$A$3728,$A32,Documents!$C$2:$C$3728,"dive_prices")),"") | M32: =IFERROR(IF(_xlfn.MAXIFS(Documents!$E$2:$E$3728,Documents!$A$2:$A$3728,$A32,Documents!$C$2:$C$3728,"excursions")=0,"",_xlfn.MAXIFS(Documents!$E$2:$E$3728,Documents!$A$2:$A$3728,$A32,Documents!$C$2:$C$3728,"excursions")),"") | N32: =IFERROR(IF(_xlfn.MAXIFS(Documents!$E$2:$E$3728,Documents!$A$2:$A$3728,$A32,Documents!$C$2:$C$3728,"kids")=0,"",_xlfn.MAXIFS(Documents!$E$2:$E$3728,Documents!$A$2:$A$3728,$A32,Documents!$C$2:$C$3728,"kids")),"") | O32: =IFERROR(IF(_xlfn.MAXIFS(Documents!$E$2:$E$3728,Documents!$A$2:$A$3728,$A32,Documents!$C$2:$C$3728,"villa_plans")=0,"",_xlfn.MAXIFS(Documents!$E$2:$E$3728,Documents!$A$2:$A$3728,$A32,Documents!$C$2:$C$3728,"villa_plans")),"") | P32: =IFERROR(IF(_xlfn.MAXIFS(Documents!$E$2:$E$3728,Documents!$A$2:$A$3728,$A32,Documents!$C$2:$C$3728,"all_inclusive")=0,"",_xlfn.MAXIFS(Documents!$E$2:$E$3728,Documents!$A$2:$A$3728,$A32,Documents!$C$2:$C$3728,"all_inclusive")),"") | Q32: =IFERROR(IF(_xlfn.MAXIFS(Documents!$E$2:$E$3728,Documents!$A$2:$A$3728,$A32,Documents!$C$2:$C$3728,"sustainability")=0,"",_xlfn.MAXIFS(Documents!$E$2:$E$3728,Documents!$A$2:$A$3728,$A32,Documents!$C$2:$C$3728,"sustainability")),"") | R32: =IFERROR(IF(_xlfn.MAXIFS(Documents!$E$2:$E$3728,Documents!$A$2:$A$3728,$A32,Documents!$C$2:$C$3728,"calendar")=0,"",_xlfn.MAXIFS(Documents!$E$2:$E$3728,Documents!$A$2:$A$3728,$A32,Documents!$C$2:$C$3728,"calendar")),"") | S32: =IFERROR(IF(_xlfn.MAXIFS(Documents!$E$2:$E$3728,Documents!$A$2:$A$3728,$A32,Documents!$C$2:$C$3728,"brochure")=0,"",_xlfn.MAXIFS(Documents!$E$2:$E$3728,Documents!$A$2:$A$3728,$A32,Documents!$C$2:$C$3728,"brochure")),"") | T32: =IFERROR(IF(_xlfn.MAXIFS(Documents!$E$2:$E$3728,Documents!$A$2:$A$3728,$A32,Documents!$C$2:$C$3728,"press_kit")=0,"",_xlfn.MAXIFS(Documents!$E$2:$E$3728,Documents!$A$2:$A$3728,$A32,Documents!$C$2:$C$3728,"press_kit")),"") | U32: =IFERROR(IF(_xlfn.MAXIFS(Documents!$E$2:$E$3728,Documents!$A$2:$A$3728,$A32,Documents!$C$2:$C$3728,"other")=0,"",_xlfn.MAXIFS(Documents!$E$2:$E$3728,Documents!$A$2:$A$3728,$A32,Documents!$C$2:$C$3728,"other")),"") | V32: =IFERROR(IF(_xlfn.MAXIFS(Documents!$E$2:$E$3728,Documents!$A$2:$A$3728,$A32,Documents!$C$2:$C$3728,"obsolete")=0,"",_xlfn.MAXIFS(Documents!$E$2:$E$3728,Documents!$A$2:$A$3728,$A32,Documents!$C$2:$C$3728,"obsolete")),"") | W32: =COUNTIFS(Documents!$A$2:$A$3728,$A32) | X32: =COUNTIFS(Documents!$A$2:$A$3728,$A32,Documents!$R$2:$R$3728,"current") | Y32: =HYPERLINK("https://sales.crownandchamparesorts.com/wp-content/uploads/2023/08/FactSheetInnahura110121103122Ver110121.pdf","2021_FactSheetInnahura110121103122Ver110") | Z32: wedding, events
A33: 32 | B33: Cocoon Maldives | C33: ok | D33: =IFERROR(IF(_xlfn.MAXIFS(Documents!$E$2:$E$3728,Documents!$A$2:$A$3728,$A33,Documents!$C$2:$C$3728,"factsheet")=0,"",_xlfn.MAXIFS(Documents!$E$2:$E$3728,Documents!$A$2:$A$3728,$A33,Documents!$C$2:$C$3728,"factsheet")),"") | E33: =IFERROR(IF(_xlfn.MAXIFS(Documents!$E$2:$E$3728,Documents!$A$2:$A$3728,$A33,Documents!$C$2:$C$3728,"wedding")=0,"",_xlfn.MAXIFS(Documents!$E$2:$E$3728,Documents!$A$2:$A$3728,$A33,Documents!$C$2:$C$3728,"wedding")),"") | F33: =IFERROR(IF(_xlfn.MAXIFS(Documents!$E$2:$E$3728,Documents!$A$2:$A$3728,$A33,Documents!$C$2:$C$3728,"events")=0,"",_xlfn.MAXIFS(Documents!$E$2:$E$3728,Documents!$A$2:$A$3728,$A33,Documents!$C$2:$C$3728,"events")),"") | G33: =IFERROR(IF(_xlfn.MAXIFS(Documents!$E$2:$E$3728,Documents!$A$2:$A$3728,$A33,Documents!$C$2:$C$3728,"destination_dining")=0,"",_xlfn.MAXIFS(Documents!$E$2:$E$3728,Documents!$A$2:$A$3728,$A33,Documents!$C$2:$C$3728,"destination_dining")),"") | H33: =IFERROR(IF(_xlfn.MAXIFS(Documents!$E$2:$E$3728,Documents!$A$2:$A$3728,$A33,Documents!$C$2:$C$3728,"map")=0,"",_xlfn.MAXIFS(Documents!$E$2:$E$3728,Documents!$A$2:$A$3728,$A33,Documents!$C$2:$C$3728,"map")),"") | I33: =IFERROR(IF(_xlfn.MAXIFS(Documents!$E$2:$E$3728,Documents!$A$2:$A$3728,$A33,Documents!$C$2:$C$3728,"dive_map")=0,"",_xlfn.MAXIFS(Documents!$E$2:$E$3728,Documents!$A$2:$A$3728,$A33,Documents!$C$2:$C$3728,"dive_map")),"") | J33: =IFERROR(IF(_xlfn.MAXIFS(Documents!$E$2:$E$3728,Documents!$A$2:$A$3728,$A33,Documents!$C$2:$C$3728,"spa_menu")=0,"",_xlfn.MAXIFS(Documents!$E$2:$E$3728,Documents!$A$2:$A$3728,$A33,Documents!$C$2:$C$3728,"spa_menu")),"") | K33: =IFERROR(IF(_xlfn.MAXIFS(Documents!$E$2:$E$3728,Documents!$A$2:$A$3728,$A33,Documents!$C$2:$C$3728,"dining_menu")=0,"",_xlfn.MAXIFS(Documents!$E$2:$E$3728,Documents!$A$2:$A$3728,$A33,Documents!$C$2:$C$3728,"dining_menu")),"") | L33: =IFERROR(IF(_xlfn.MAXIFS(Documents!$E$2:$E$3728,Documents!$A$2:$A$3728,$A33,Documents!$C$2:$C$3728,"dive_prices")=0,"",_xlfn.MAXIFS(Documents!$E$2:$E$3728,Documents!$A$2:$A$3728,$A33,Documents!$C$2:$C$3728,"dive_prices")),"") | M33: =IFERROR(IF(_xlfn.MAXIFS(Documents!$E$2:$E$3728,Documents!$A$2:$A$3728,$A33,Documents!$C$2:$C$3728,"excursions")=0,"",_xlfn.MAXIFS(Documents!$E$2:$E$3728,Documents!$A$2:$A$3728,$A33,Documents!$C$2:$C$3728,"excursions")),"") | N33: =IFERROR(IF(_xlfn.MAXIFS(Documents!$E$2:$E$3728,Documents!$A$2:$A$3728,$A33,Documents!$C$2:$C$3728,"kids")=0,"",_xlfn.MAXIFS(Documents!$E$2:$E$3728,Documents!$A$2:$A$3728,$A33,Documents!$C$2:$C$3728,"kids")),"") | O33: =IFERROR(IF(_xlfn.MAXIFS(Documents!$E$2:$E$3728,Documents!$A$2:$A$3728,$A33,Documents!$C$2:$C$3728,"villa_plans")=0,"",_xlfn.MAXIFS(Documents!$E$2:$E$3728,Documents!$A$2:$A$3728,$A33,Documents!$C$2:$C$3728,"villa_plans")),"") | P33: =IFERROR(IF(_xlfn.MAXIFS(Documents!$E$2:$E$3728,Documents!$A$2:$A$3728,$A33,Documents!$C$2:$C$3728,"all_inclusive")=0,"",_xlfn.MAXIFS(Documents!$E$2:$E$3728,Documents!$A$2:$A$3728,$A33,Documents!$C$2:$C$3728,"all_inclusive")),"") | Q33: =IFERROR(IF(_xlfn.MAXIFS(Documents!$E$2:$E$3728,Documents!$A$2:$A$3728,$A33,Documents!$C$2:$C$3728,"sustainability")=0,"",_xlfn.MAXIFS(Documents!$E$2:$E$3728,Documents!$A$2:$A$3728,$A33,Documents!$C$2:$C$3728,"sustainability")),"") | R33: =IFERROR(IF(_xlfn.MAXIFS(Documents!$E$2:$E$3728,Documents!$A$2:$A$3728,$A33,Documents!$C$2:$C$3728,"calendar")=0,"",_xlfn.MAXIFS(Documents!$E$2:$E$3728,Documents!$A$2:$A$3728,$A33,Documents!$C$2:$C$3728,"calendar")),"") | S33: =IFERROR(IF(_xlfn.MAXIFS(Documents!$E$2:$E$3728,Documents!$A$2:$A$3728,$A33,Documents!$C$2:$C$3728,"brochure")=0,"",_xlfn.MAXIFS(Documents!$E$2:$E$3728,Documents!$A$2:$A$3728,$A33,Documents!$C$2:$C$3728,"brochure")),"") | T33: =IFERROR(IF(_xlfn.MAXIFS(Documents!$E$2:$E$3728,Documents!$A$2:$A$3728,$A33,Documents!$C$2:$C$3728,"press_kit")=0,"",_xlfn.MAXIFS(Documents!$E$2:$E$3728,Documents!$A$2:$A$3728,$A33,Documents!$C$2:$C$3728,"press_kit")),"") | U33: =IFERROR(IF(_xlfn.MAXIFS(Documents!$E$2:$E$3728,Documents!$A$2:$A$3728,$A33,Documents!$C$2:$C$3728,"other")=0,"",_xlfn.MAXIFS(Documents!$E$2:$E$3728,Documents!$A$2:$A$3728,$A33,Documents!$C$2:$C$3728,"other")),"") | V33: =IFERROR(IF(_xlfn.MAXIFS(Documents!$E$2:$E$3728,Documents!$A$2:$A$3728,$A33,Documents!$C$2:$C$3728,"obsolete")=0,"",_xlfn.MAXIFS(Documents!$E$2:$E$3728,Documents!$A$2:$A$3728,$A33,Documents!$C$2:$C$3728,"obsolete")),"") | W33: =COUNTIFS(Documents!$A$2:$A$3728,$A33) | X33: =COUNTIFS(Documents!$A$2:$A$3728,$A33,Documents!$R$2:$R$3728,"current") | Y33: =HYPERLINK("https://www.neoscapesmaldives.com/wp-content/uploads/Cocoon-Maldives-_-Fact-Sheet.pdf","2025_Cocoon-Maldives-_-Fact-Sheet.pdf") | Z33: wedding, events
A34: 33 | B34: Dhigali Maldives | C34: ok | D34: =IFERROR(IF(_xlfn.MAXIFS(Documents!$E$2:$E$3728,Documents!$A$2:$A$3728,$A34,Documents!$C$2:$C$3728,"factsheet")=0,"",_xlfn.MAXIFS(Documents!$E$2:$E$3728,Documents!$A$2:$A$3728,$A34,Documents!$C$2:$C$3728,"factsheet")),"") | E34: =IFERROR(IF(_xlfn.MAXIFS(Documents!$E$2:$E$3728,Documents!$A$2:$A$3728,$A34,Documents!$C$2:$C$3728,"wedding")=0,"",_xlfn.MAXIFS(Documents!$E$2:$E$3728,Documents!$A$2:$A$3728,$A34,Documents!$C$2:$C$3728,"wedding")),"") | F34: =IFERROR(IF(_xlfn.MAXIFS(Documents!$E$2:$E$3728,Documents!$A$2:$A$3728,$A34,Documents!$C$2:$C$3728,"events")=0,"",_xlfn.MAXIFS(Documents!$E$2:$E$3728,Documents!$A$2:$A$3728,$A34,Documents!$C$2:$C$3728,"events")),"") | G34: =IFERROR(IF(_xlfn.MAXIFS(Documents!$E$2:$E$3728,Documents!$A$2:$A$3728,$A34,Documents!$C$2:$C$3728,"destination_dining")=0,"",_xlfn.MAXIFS(Documents!$E$2:$E$3728,Documents!$A$2:$A$3728,$A34,Documents!$C$2:$C$3728,"destination_dining")),"") | H34: =IFERROR(IF(_xlfn.MAXIFS(Documents!$E$2:$E$3728,Documents!$A$2:$A$3728,$A34,Documents!$C$2:$C$3728,"map")=0,"",_xlfn.MAXIFS(Documents!$E$2:$E$3728,Documents!$A$2:$A$3728,$A34,Documents!$C$2:$C$3728,"map")),"") | I34: =IFERROR(IF(_xlfn.MAXIFS(Documents!$E$2:$E$3728,Documents!$A$2:$A$3728,$A34,Documents!$C$2:$C$3728,"dive_map")=0,"",_xlfn.MAXIFS(Documents!$E$2:$E$3728,Documents!$A$2:$A$3728,$A34,Documents!$C$2:$C$3728,"dive_map")),"") | J34: =IFERROR(IF(_xlfn.MAXIFS(Documents!$E$2:$E$3728,Documents!$A$2:$A$3728,$A34,Documents!$C$2:$C$3728,"spa_menu")=0,"",_xlfn.MAXIFS(Documents!$E$2:$E$3728,Documents!$A$2:$A$3728,$A34,Documents!$C$2:$C$3728,"spa_menu")),"") | K34: =IFERROR(IF(_xlfn.MAXIFS(Documents!$E$2:$E$3728,Documents!$A$2:$A$3728,$A34,Documents!$C$2:$C$3728,"dining_menu")=0,"",_xlfn.MAXIFS(Documents!$E$2:$E$3728,Documents!$A$2:$A$3728,$A34,Documents!$C$2:$C$3728,"dining_menu")),"") | L34: =IFERROR(IF(_xlfn.MAXIFS(Documents!$E$2:$E$3728,Documents!$A$2:$A$3728,$A34,Documents!$C$2:$C$3728,"dive_prices")=0,"",_xlfn.MAXIFS(Documents!$E$2:$E$3728,Documents!$A$2:$A$3728,$A34,Documents!$C$2:$C$3728,"dive_prices")),"") | M34: =IFERROR(IF(_xlfn.MAXIFS(Documents!$E$2:$E$3728,Documents!$A$2:$A$3728,$A34,Documents!$C$2:$C$3728,"excursions")=0,"",_xlfn.MAXIFS(Documents!$E$2:$E$3728,Documents!$A$2:$A$3728,$A34,Documents!$C$2:$C$3728,"excursions")),"") | N34: =IFERROR(IF(_xlfn.MAXIFS(Documents!$E$2:$E$3728,Documents!$A$2:$A$3728,$A34,Documents!$C$2:$C$3728,"kids")=0,"",_xlfn.MAXIFS(Documents!$E$2:$E$3728,Documents!$A$2:$A$3728,$A34,Documents!$C$2:$C$3728,"kids")),"") | O34: =IFERROR(IF(_xlfn.MAXIFS(Documents!$E$2:$E$3728,Documents!$A$2:$A$3728,$A34,Documents!$C$2:$C$3728,"villa_plans")=0,"",_xlfn.MAXIFS(Documents!$E$2:$E$3728,Documents!$A$2:$A$3728,$A34,Documents!$C$2:$C$3728,"villa_plans")),"") | P34: =IFERROR(IF(_xlfn.MAXIFS(Documents!$E$2:$E$3728,Documents!$A$2:$A$3728,$A34,Documents!$C$2:$C$3728,"all_inclusive")=0,"",_xlfn.MAXIFS(Documents!$E$2:$E$3728,Documents!$A$2:$A$3728,$A34,Documents!$C$2:$C$3728,"all_inclusive")),"") | Q34: =IFERROR(IF(_xlfn.MAXIFS(Documents!$E$2:$E$3728,Documents!$A$2:$A$3728,$A34,Documents!$C$2:$C$3728,"sustainability")=0,"",_xlfn.MAXIFS(Documents!$E$2:$E$3728,Documents!$A$2:$A$3728,$A34,Documents!$C$2:$C$3728,"sustainability")),"") | R34: =IFERROR(IF(_xlfn.MAXIFS(Documents!$E$2:$E$3728,Documents!$A$2:$A$3728,$A34,Documents!$C$2:$C$3728,"calendar")=0,"",_xlfn.MAXIFS(Documents!$E$2:$E$3728,Documents!$A$2:$A$3728,$A34,Documents!$C$2:$C$3728,"calendar")),"") | S34: =IFERROR(IF(_xlfn.MAXIFS(Documents!$E$2:$E$3728,Documents!$A$2:$A$3728,$A34,Documents!$C$2:$C$3728,"brochure")=0,"",_xlfn.MAXIFS(Documents!$E$2:$E$3728,Documents!$A$2:$A$3728,$A34,Documents!$C$2:$C$3728,"brochure")),"") | T34: =IFERROR(IF(_xlfn.MAXIFS(Documents!$E$2:$E$3728,Documents!$A$2:$A$3728,$A34,Documents!$C$2:$C$3728,"press_kit")=0,"",_xlfn.MAXIFS(Documents!$E$2:$E$3728,Documents!$A$2:$A$3728,$A34,Documents!$C$2:$C$3728,"press_kit")),"") | U34: =IFERROR(IF(_xlfn.MAXIFS(Documents!$E$2:$E$3728,Documents!$A$2:$A$3728,$A34,Documents!$C$2:$C$3728,"other")=0,"",_xlfn.MAXIFS(Documents!$E$2:$E$3728,Documents!$A$2:$A$3728,$A34,Documents!$C$2:$C$3728,"other")),"") | V34: =IFERROR(IF(_xlfn.MAXIFS(Documents!$E$2:$E$3728,Documents!$A$2:$A$3728,$A34,Documents!$C$2:$C$3728,"obsolete")=0,"",_xlfn.MAXIFS(Documents!$E$2:$E$3728,Documents!$A$2:$A$3728,$A34,Documents!$C$2:$C$3728,"obsolete")),"") | W34: =COUNTIFS(Documents!$A$2:$A$3728,$A34) | X34: =COUNTIFS(Documents!$A$2:$A$3728,$A34,Documents!$R$2:$R$3728,"current") | Y34: =HYPERLINK("https://www.nivadhigali.com/wp-content/uploads/2026/01/DHIGALI_Factsheet.pdf","2026_DHIGALI_Factsheet.pdf") | Z34: events | AA34: NIVA Dhigali; site redirects to www.nivadhigali.com
A35: 34 | B35: Adaaran Select Meedhupparu | C35: ok | D35: =IFERROR(IF(_xlfn.MAXIFS(Documents!$E$2:$E$3728,Documents!$A$2:$A$3728,$A35,Documents!$C$2:$C$3728,"factsheet")=0,"",_xlfn.MAXIFS(Documents!$E$2:$E$3728,Documents!$A$2:$A$3728,$A35,Documents!$C$2:$C$3728,"factsheet")),"") | E35: =IFERROR(IF(_xlfn.MAXIFS(Documents!$E$2:$E$3728,Documents!$A$2:$A$3728,$A35,Documents!$C$2:$C$3728,"wedding")=0,"",_xlfn.MAXIFS(Documents!$E$2:$E$3728,Documents!$A$2:$A$3728,$A35,Documents!$C$2:$C$3728,"wedding")),"") | F35: =IFERROR(IF(_xlfn.MAXIFS(Documents!$E$2:$E$3728,Documents!$A$2:$A$3728,$A35,Documents!$C$2:$C$3728,"events")=0,"",_xlfn.MAXIFS(Documents!$E$2:$E$3728,Documents!$A$2:$A$3728,$A35,Documents!$C$2:$C$3728,"events")),"") | G35: =IFERROR(IF(_xlfn.MAXIFS(Documents!$E$2:$E$3728,Documents!$A$2:$A$3728,$A35,Documents!$C$2:$C$3728,"destination_dining")=0,"",_xlfn.MAXIFS(Documents!$E$2:$E$3728,Documents!$A$2:$A$3728,$A35,Documents!$C$2:$C$3728,"destination_dining")),"") | H35: =IFERROR(IF(_xlfn.MAXIFS(Documents!$E$2:$E$3728,Documents!$A$2:$A$3728,$A35,Documents!$C$2:$C$3728,"map")=0,"",_xlfn.MAXIFS(Documents!$E$2:$E$3728,Documents!$A$2:$A$3728,$A35,Documents!$C$2:$C$3728,"map")),"") | I35: =IFERROR(IF(_xlfn.MAXIFS(Documents!$E$2:$E$3728,Documents!$A$2:$A$3728,$A35,Documents!$C$2:$C$3728,"dive_map")=0,"",_xlfn.MAXIFS(Documents!$E$2:$E$3728,Documents!$A$2:$A$3728,$A35,Documents!$C$2:$C$3728,"dive_map")),"") | J35: =IFERROR(IF(_xlfn.MAXIFS(Documents!$E$2:$E$3728,Documents!$A$2:$A$3728,$A35,Documents!$C$2:$C$3728,"spa_menu")=0,"",_xlfn.MAXIFS(Documents!$E$2:$E$3728,Documents!$A$2:$A$3728,$A35,Documents!$C$2:$C$3728,"spa_menu")),"") | K35: =IFERROR(IF(_xlfn.MAXIFS(Documents!$E$2:$E$3728,Documents!$A$2:$A$3728,$A35,Documents!$C$2:$C$3728,"dining_menu")=0,"",_xlfn.MAXIFS(Documents!$E$2:$E$3728,Documents!$A$2:$A$3728,$A35,Documents!$C$2:$C$3728,"dining_menu")),"") | L35: =IFERROR(IF(_xlfn.MAXIFS(Documents!$E$2:$E$3728,Documents!$A$2:$A$3728,$A35,Documents!$C$2:$C$3728,"dive_prices")=0,"",_xlfn.MAXIFS(Documents!$E$2:$E$3728,Documents!$A$2:$A$3728,$A35,Documents!$C$2:$C$3728,"dive_prices")),"") | M35: =IFERROR(IF(_xlfn.MAXIFS(Documents!$E$2:$E$3728,Documents!$A$2:$A$3728,$A35,Documents!$C$2:$C$3728,"excursions")=0,"",_xlfn.MAXIFS(Documents!$E$2:$E$3728,Documents!$A$2:$A$3728,$A35,Documents!$C$2:$C$3728,"excursions")),"") | N35: =IFERROR(IF(_xlfn.MAXIFS(Documents!$E$2:$E$3728,Documents!$A$2:$A$3728,$A35,Documents!$C$2:$C$3728,"kids")=0,"",_xlfn.MAXIFS(Documents!$E$2:$E$3728,Documents!$A$2:$A$3728,$A35,Documents!$C$2:$C$3728,"kids")),"") | O35: =IFERROR(IF(_xlfn.MAXIFS(Documents!$E$2:$E$3728,Documents!$A$2:$A$3728,$A35,Documents!$C$2:$C$3728,"villa_plans")=0,"",_xlfn.MAXIFS(Documents!$E$2:$E$3728,Documents!$A$2:$A$3728,$A35,Documents!$C$2:$C$3728,"villa_plans")),"") | P35: =IFERROR(IF(_xlfn.MAXIFS(Documents!$E$2:$E$3728,Documents!$A$2:$A$3728,$A35,Documents!$C$2:$C$3728,"all_inclusive")=0,"",_xlfn.MAXIFS(Documents!$E$2:$E$3728,Documents!$A$2:$A$3728,$A35,Documents!$C$2:$C$3728,"all_inclusive")),"") | Q35: =IFERROR(IF(_xlfn.MAXIFS(Documents!$E$2:$E$3728,Documents!$A$2:$A$3728,$A35,Documents!$C$2:$C$3728,"sustainability")=0,"",_xlfn.MAXIFS(Documents!$E$2:$E$3728,Documents!$A$2:$A$3728,$A35,Documents!$C$2:$C$3728,"sustainability")),"") | R35: =IFERROR(IF(_xlfn.MAXIFS(Documents!$E$2:$E$3728,Documents!$A$2:$A$3728,$A35,Documents!$C$2:$C$3728,"calendar")=0,"",_xlfn.MAXIFS(Documents!$E$2:$E$3728,Documents!$A$2:$A$3728,$A35,Documents!$C$2:$C$3728,"calendar")),"") | S35: =IFERROR(IF(_xlfn.MAXIFS(Documents!$E$2:$E$3728,Documents!$A$2:$A$3728,$A35,Documents!$C$2:$C$3728,"brochure")=0,"",_xlfn.MAXIFS(Documents!$E$2:$E$3728,Documents!$A$2:$A$3728,$A35,Documents!$C$2:$C$3728,"brochure")),"") | T35: =IFERROR(IF(_xlfn.MAXIFS(Documents!$E$2:$E$3728,Documents!$A$2:$A$3728,$A35,Documents!$C$2:$C$3728,"press_kit")=0,"",_xlfn.MAXIFS(Documents!$E$2:$E$3728,Documents!$A$2:$A$3728,$A35,Documents!$C$2:$C$3728,"press_kit")),"") | U35: =IFERROR(IF(_xlfn.MAXIFS(Documents!$E$2:$E$3728,Documents!$A$2:$A$3728,$A35,Documents!$C$2:$C$3728,"other")=0,"",_xlfn.MAXIFS(Documents!$E$2:$E$3728,Documents!$A$2:$A$3728,$A35,Documents!$C$2:$C$3728,"other")),"") | V35: =IFERROR(IF(_xlfn.MAXIFS(Documents!$E$2:$E$3728,Documents!$A$2:$A$3728,$A35,Documents!$C$2:$C$3728,"obsolete")=0,"",_xlfn.MAXIFS(Documents!$E$2:$E$3728,Documents!$A$2:$A$3728,$A35,Documents!$C$2:$C$3728,"obsolete")),"") | W35: =COUNTIFS(Documents!$A$2:$A$3728,$A35) | X35: =COUNTIFS(Documents!$A$2:$A$3728,$A35,Documents!$R$2:$R$3728,"current") | Y35: =HYPERLINK("https://www.adaaran.com/selectmeedhupparu/view-download/?id=asm-factsheet","2026_document.pdf") | Z35: events
A36: 35 | B36: Heritance Aarah | C36: ok | D36: =IFERROR(IF(_xlfn.MAXIFS(Documents!$E$2:$E$3728,Documents!$A$2:$A$3728,$A36,Documents!$C$2:$C$3728,"factsheet")=0,"",_xlfn.MAXIFS(Documents!$E$2:$E$3728,Documents!$A$2:$A$3728,$A36,Documents!$C$2:$C$3728,"factsheet")),"") | E36: =IFERROR(IF(_xlfn.MAXIFS(Documents!$E$2:$E$3728,Documents!$A$2:$A$3728,$A36,Documents!$C$2:$C$3728,"wedding")=0,"",_xlfn.MAXIFS(Documents!$E$2:$E$3728,Documents!$A$2:$A$3728,$A36,Documents!$C$2:$C$3728,"wedding")),"") | F36: =IFERROR(IF(_xlfn.MAXIFS(Documents!$E$2:$E$3728,Documents!$A$2:$A$3728,$A36,Documents!$C$2:$C$3728,"events")=0,"",_xlfn.MAXIFS(Documents!$E$2:$E$3728,Documents!$A$2:$A$3728,$A36,Documents!$C$2:$C$3728,"events")),"") | G36: =IFERROR(IF(_xlfn.MAXIFS(Documents!$E$2:$E$3728,Documents!$A$2:$A$3728,$A36,Documents!$C$2:$C$3728,"destination_dining")=0,"",_xlfn.MAXIFS(Documents!$E$2:$E$3728,Documents!$A$2:$A$3728,$A36,Documents!$C$2:$C$3728,"destination_dining")),"") | H36: =IFERROR(IF(_xlfn.MAXIFS(Documents!$E$2:$E$3728,Documents!$A$2:$A$3728,$A36,Documents!$C$2:$C$3728,"map")=0,"",_xlfn.MAXIFS(Documents!$E$2:$E$3728,Documents!$A$2:$A$3728,$A36,Documents!$C$2:$C$3728,"map")),"") | I36: =IFERROR(IF(_xlfn.MAXIFS(Documents!$E$2:$E$3728,Documents!$A$2:$A$3728,$A36,Documents!$C$2:$C$3728,"dive_map")=0,"",_xlfn.MAXIFS(Documents!$E$2:$E$3728,Documents!$A$2:$A$3728,$A36,Documents!$C$2:$C$3728,"dive_map")),"") | J36: =IFERROR(IF(_xlfn.MAXIFS(Documents!$E$2:$E$3728,Documents!$A$2:$A$3728,$A36,Documents!$C$2:$C$3728,"spa_menu")=0,"",_xlfn.MAXIFS(Documents!$E$2:$E$3728,Documents!$A$2:$A$3728,$A36,Documents!$C$2:$C$3728,"spa_menu")),"") | K36: =IFERROR(IF(_xlfn.MAXIFS(Documents!$E$2:$E$3728,Documents!$A$2:$A$3728,$A36,Documents!$C$2:$C$3728,"dining_menu")=0,"",_xlfn.MAXIFS(Documents!$E$2:$E$3728,Documents!$A$2:$A$3728,$A36,Documents!$C$2:$C$3728,"dining_menu")),"") | L36: =IFERROR(IF(_xlfn.MAXIFS(Documents!$E$2:$E$3728,Documents!$A$2:$A$3728,$A36,Documents!$C$2:$C$3728,"dive_prices")=0,"",_xlfn.MAXIFS(Documents!$E$2:$E$3728,Documents!$A$2:$A$3728,$A36,Documents!$C$2:$C$3728,"dive_prices")),"") | M36: =IFERROR(IF(_xlfn.MAXIFS(Documents!$E$2:$E$3728,Documents!$A$2:$A$3728,$A36,Documents!$C$2:$C$3728,"excursions")=0,"",_xlfn.MAXIFS(Documents!$E$2:$E$3728,Documents!$A$2:$A$3728,$A36,Documents!$C$2:$C$3728,"excursions")),"") | N36: =IFERROR(IF(_xlfn.MAXIFS(Documents!$E$2:$E$3728,Documents!$A$2:$A$3728,$A36,Documents!$C$2:$C$3728,"kids")=0,"",_xlfn.MAXIFS(Documents!$E$2:$E$3728,Documents!$A$2:$A$3728,$A36,Documents!$C$2:$C$3728,"kids")),"") | O36: =IFERROR(IF(_xlfn.MAXIFS(Documents!$E$2:$E$3728,Documents!$A$2:$A$3728,$A36,Documents!$C$2:$C$3728,"villa_plans")=0,"",_xlfn.MAXIFS(Documents!$E$2:$E$3728,Documents!$A$2:$A$3728,$A36,Documents!$C$2:$C$3728,"villa_plans")),"") | P36: =IFERROR(IF(_xlfn.MAXIFS(Documents!$E$2:$E$3728,Documents!$A$2:$A$3728,$A36,Documents!$C$2:$C$3728,"all_inclusive")=0,"",_xlfn.MAXIFS(Documents!$E$2:$E$3728,Documents!$A$2:$A$3728,$A36,Documents!$C$2:$C$3728,"all_inclusive")),"") | Q36: =IFERROR(IF(_xlfn.MAXIFS(Documents!$E$2:$E$3728,Documents!$A$2:$A$3728,$A36,Documents!$C$2:$C$3728,"sustainability")=0,"",_xlfn.MAXIFS(Documents!$E$2:$E$3728,Documents!$A$2:$A$3728,$A36,Documents!$C$2:$C$3728,"sustainability")),"") | R36: =IFERROR(IF(_xlfn.MAXIFS(Documents!$E$2:$E$3728,Documents!$A$2:$A$3728,$A36,Documents!$C$2:$C$3728,"calendar")=0,"",_xlfn.MAXIFS(Documents!$E$2:$E$3728,Documents!$A$2:$A$3728,$A36,Documents!$C$2:$C$3728,"calendar")),"") | S36: =IFERROR(IF(_xlfn.MAXIFS(Documents!$E$2:$E$3728,Documents!$A$2:$A$3728,$A36,Documents!$C$2:$C$3728,"brochure")=0,"",_xlfn.MAXIFS(Documents!$E$2:$E$3728,Documents!$A$2:$A$3728,$A36,Documents!$C$2:$C$3728,"brochure")),"") | T36: =IFERROR(IF(_xlfn.MAXIFS(Documents!$E$2:$E$3728,Documents!$A$2:$A$3728,$A36,Documents!$C$2:$C$3728,"press_kit")=0,"",_xlfn.MAXIFS(Documents!$E$2:$E$3728,Documents!$A$2:$A$3728,$A36,Documents!$C$2:$C$3728,"press_kit")),"") | U36: =IFERROR(IF(_xlfn.MAXIFS(Documents!$E$2:$E$3728,Documents!$A$2:$A$3728,$A36,Documents!$C$2:$C$3728,"other")=0,"",_xlfn.MAXIFS(Documents!$E$2:$E$3728,Documents!$A$2:$A$3728,$A36,Documents!$C$2:$C$3728,"other")),"") | V36: =IFERROR(IF(_xlfn.MAXIFS(Documents!$E$2:$E$3728,Documents!$A$2:$A$3728,$A36,Documents!$C$2:$C$3728,"obsolete")=0,"",_xlfn.MAXIFS(Documents!$E$2:$E$3728,Documents!$A$2:$A$3728,$A36,Documents!$C$2:$C$3728,"obsolete")),"") | W36: =COUNTIFS(Documents!$A$2:$A$3728,$A36) | X36: =COUNTIFS(Documents!$A$2:$A$3728,$A36,Documents!$R$2:$R$3728,"current") | Y36: =HYPERLINK("https://heritancehotels.eme-devops.com/sites/2/2026/09/Heritance-Aarah-Fact-Sheet.pdf","2026_Heritance-Aarah-Fact-Sheet.pdf") | Z36: events
A37: 36 | B37: Coastline Residences | C37: unverified | D37: =IFERROR(IF(_xlfn.MAXIFS(Documents!$E$2:$E$3728,Documents!$A$2:$A$3728,$A37,Documents!$C$2:$C$3728,"factsheet")=0,"",_xlfn.MAXIFS(Documents!$E$2:$E$3728,Documents!$A$2:$A$3728,$A37,Documents!$C$2:$C$3728,"factsheet")),"") | E37: =IFERROR(IF(_xlfn.MAXIFS(Documents!$E$2:$E$3728,Documents!$A$2:$A$3728,$A37,Documents!$C$2:$C$3728,"wedding")=0,"",_xlfn.MAXIFS(Documents!$E$2:$E$3728,Documents!$A$2:$A$3728,$A37,Documents!$C$2:$C$3728,"wedding")),"") | F37: =IFERROR(IF(_xlfn.MAXIFS(Documents!$E$2:$E$3728,Documents!$A$2:$A$3728,$A37,Documents!$C$2:$C$3728,"events")=0,"",_xlfn.MAXIFS(Documents!$E$2:$E$3728,Documents!$A$2:$A$3728,$A37,Documents!$C$2:$C$3728,"events")),"") | G37: =IFERROR(IF(_xlfn.MAXIFS(Documents!$E$2:$E$3728,Documents!$A$2:$A$3728,$A37,Documents!$C$2:$C$3728,"destination_dining")=0,"",_xlfn.MAXIFS(Documents!$E$2:$E$3728,Documents!$A$2:$A$3728,$A37,Documents!$C$2:$C$3728,"destination_dining")),"") | H37: =IFERROR(IF(_xlfn.MAXIFS(Documents!$E$2:$E$3728,Documents!$A$2:$A$3728,$A37,Documents!$C$2:$C$3728,"map")=0,"",_xlfn.MAXIFS(Documents!$E$2:$E$3728,Documents!$A$2:$A$3728,$A37,Documents!$C$2:$C$3728,"map")),"") | I37: =IFERROR(IF(_xlfn.MAXIFS(Documents!$E$2:$E$3728,Documents!$A$2:$A$3728,$A37,Documents!$C$2:$C$3728,"dive_map")=0,"",_xlfn.MAXIFS(Documents!$E$2:$E$3728,Documents!$A$2:$A$3728,$A37,Documents!$C$2:$C$3728,"dive_map")),"") | J37: =IFERROR(IF(_xlfn.MAXIFS(Documents!$E$2:$E$3728,Documents!$A$2:$A$3728,$A37,Documents!$C$2:$C$3728,"spa_menu")=0,"",_xlfn.MAXIFS(Documents!$E$2:$E$3728,Documents!$A$2:$A$3728,$A37,Documents!$C$2:$C$3728,"spa_menu")),"") | K37: =IFERROR(IF(_xlfn.MAXIFS(Documents!$E$2:$E$3728,Documents!$A$2:$A$3728,$A37,Documents!$C$2:$C$3728,"dining_menu")=0,"",_xlfn.MAXIFS(Documents!$E$2:$E$3728,Documents!$A$2:$A$3728,$A37,Documents!$C$2:$C$3728,"dining_menu")),"") | L37: =IFERROR(IF(_xlfn.MAXIFS(Documents!$E$2:$E$3728,Documents!$A$2:$A$3728,$A37,Documents!$C$2:$C$3728,"dive_prices")=0,"",_xlfn.MAXIFS(Documents!$E$2:$E$3728,Documents!$A$2:$A$3728,$A37,Documents!$C$2:$C$3728,"dive_prices")),"") | M37: =IFERROR(IF(_xlfn.MAXIFS(Documents!$E$2:$E$3728,Documents!$A$2:$A$3728,$A37,Documents!$C$2:$C$3728,"excursions")=0,"",_xlfn.MAXIFS(Documents!$E$2:$E$3728,Documents!$A$2:$A$3728,$A37,Documents!$C$2:$C$3728,"excursions")),"") | N37: =IFERROR(IF(_xlfn.MAXIFS(Documents!$E$2:$E$3728,Documents!$A$2:$A$3728,$A37,Documents!$C$2:$C$3728,"kids")=0,"",_xlfn.MAXIFS(Documents!$E$2:$E$3728,Documents!$A$2:$A$3728,$A37,Documents!$C$2:$C$3728,"kids")),"") | O37: =IFERROR(IF(_xlfn.MAXIFS(Documents!$E$2:$E$3728,Documents!$A$2:$A$3728,$A37,Documents!$C$2:$C$3728,"villa_plans")=0,"",_xlfn.MAXIFS(Documents!$E$2:$E$3728,Documents!$A$2:$A$3728,$A37,Documents!$C$2:$C$3728,"villa_plans")),"") | P37: =IFERROR(IF(_xlfn.MAXIFS(Documents!$E$2:$E$3728,Documents!$A$2:$A$3728,$A37,Documents!$C$2:$C$3728,"all_inclusive")=0,"",_xlfn.MAXIFS(Documents!$E$2:$E$3728,Documents!$A$2:$A$3728,$A37,Documents!$C$2:$C$3728,"all_inclusive")),"") | Q37: =IFERROR(IF(_xlfn.MAXIFS(Documents!$E$2:$E$3728,Documents!$A$2:$A$3728,$A37,Documents!$C$2:$C$3728,"sustainability")=0,"",_xlfn.MAXIFS(Documents!$E$2:$E$3728,Documents!$A$2:$A$3728,$A37,Documents!$C$2:$C$3728,"sustainability")),"") | R37: =IFERROR(IF(_xlfn.MAXIFS(Documents!$E$2:$E$3728,Documents!$A$2:$A$3728,$A37,Documents!$C$2:$C$3728,"calendar")=0,"",_xlfn.MAXIFS(Documents!$E$2:$E$3728,Documents!$A$2:$A$3728,$A37,Documents!$C$2:$C$3728,"calendar")),"") | S37: =IFERROR(IF(_xlfn.MAXIFS(Documents!$E$2:$E$3728,Documents!$A$2:$A$3728,$A37,Documents!$C$2:$C$3728,"brochure")=0,"",_xlfn.MAXIFS(Documents!$E$2:$E$3728,Documents!$A$2:$A$3728,$A37,Documents!$C$2:$C$3728,"brochure")),"") | T37: =IFERROR(IF(_xlfn.MAXIFS(Documents!$E$2:$E$3728,Documents!$A$2:$A$3728,$A37,Documents!$C$2:$C$3728,"press_kit")=0,"",_xlfn.MAXIFS(Documents!$E$2:$E$3728,Documents!$A$2:$A$3728,$A37,Documents!$C$2:$C$3728,"press_kit")),"") | U37: =IFERROR(IF(_xlfn.MAXIFS(Documents!$E$2:$E$3728,Documents!$A$2:$A$3728,$A37,Documents!$C$2:$C$3728,"other")=0,"",_xlfn.MAXIFS(Documents!$E$2:$E$3728,Documents!$A$2:$A$3728,$A37,Documents!$C$2:$C$3728,"other")),"") | V37: =IFERROR(IF(_xlfn.MAXIFS(Documents!$E$2:$E$3728,Documents!$A$2:$A$3728,$A37,Documents!$C$2:$C$3728,"obsolete")=0,"",_xlfn.MAXIFS(Documents!$E$2:$E$3728,Documents!$A$2:$A$3728,$A37,Documents!$C$2:$C$3728,"obsolete")),"") | W37: =COUNTIFS(Documents!$A$2:$A$3728,$A37) | X37: =COUNTIFS(Documents!$A$2:$A$3728,$A37,Documents!$R$2:$R$3728,"current") | Z37: factsheet, wedding, events
A38: 37 | B38: The Ritz Carlton Maldives Fari Islands | C38: unreachable | D38: =IFERROR(IF(_xlfn.MAXIFS(Documents!$E$2:$E$3728,Documents!$A$2:$A$3728,$A38,Documents!$C$2:$C$3728,"factsheet")=0,"",_xlfn.MAXIFS(Documents!$E$2:$E$3728,Documents!$A$2:$A$3728,$A38,Documents!$C$2:$C$3728,"factsheet")),"") | E38: =IFERROR(IF(_xlfn.MAXIFS(Documents!$E$2:$E$3728,Documents!$A$2:$A$3728,$A38,Documents!$C$2:$C$3728,"wedding")=0,"",_xlfn.MAXIFS(Documents!$E$2:$E$3728,Documents!$A$2:$A$3728,$A38,Documents!$C$2:$C$3728,"wedding")),"") | F38: =IFERROR(IF(_xlfn.MAXIFS(Documents!$E$2:$E$3728,Documents!$A$2:$A$3728,$A38,Documents!$C$2:$C$3728,"events")=0,"",_xlfn.MAXIFS(Documents!$E$2:$E$3728,Documents!$A$2:$A$3728,$A38,Documents!$C$2:$C$3728,"events")),"") | G38: =IFERROR(IF(_xlfn.MAXIFS(Documents!$E$2:$E$3728,Documents!$A$2:$A$3728,$A38,Documents!$C$2:$C$3728,"destination_dining")=0,"",_xlfn.MAXIFS(Documents!$E$2:$E$3728,Documents!$A$2:$A$3728,$A38,Documents!$C$2:$C$3728,"destination_dining")),"") | H38: =IFERROR(IF(_xlfn.MAXIFS(Documents!$E$2:$E$3728,Documents!$A$2:$A$3728,$A38,Documents!$C$2:$C$3728,"map")=0,"",_xlfn.MAXIFS(Documents!$E$2:$E$3728,Documents!$A$2:$A$3728,$A38,Documents!$C$2:$C$3728,"map")),"") | I38: =IFERROR(IF(_xlfn.MAXIFS(Documents!$E$2:$E$3728,Documents!$A$2:$A$3728,$A38,Documents!$C$2:$C$3728,"dive_map")=0,"",_xlfn.MAXIFS(Documents!$E$2:$E$3728,Documents!$A$2:$A$3728,$A38,Documents!$C$2:$C$3728,"dive_map")),"") | J38: =IFERROR(IF(_xlfn.MAXIFS(Documents!$E$2:$E$3728,Documents!$A$2:$A$3728,$A38,Documents!$C$2:$C$3728,"spa_menu")=0,"",_xlfn.MAXIFS(Documents!$E$2:$E$3728,Documents!$A$2:$A$3728,$A38,Documents!$C$2:$C$3728,"spa_menu")),"") | K38: =IFERROR(IF(_xlfn.MAXIFS(Documents!$E$2:$E$3728,Documents!$A$2:$A$3728,$A38,Documents!$C$2:$C$3728,"dining_menu")=0,"",_xlfn.MAXIFS(Documents!$E$2:$E$3728,Documents!$A$2:$A$3728,$A38,Documents!$C$2:$C$3728,"dining_menu")),"") | L38: =IFERROR(IF(_xlfn.MAXIFS(Documents!$E$2:$E$3728,Documents!$A$2:$A$3728,$A38,Documents!$C$2:$C$3728,"dive_prices")=0,"",_xlfn.MAXIFS(Documents!$E$2:$E$3728,Documents!$A$2:$A$3728,$A38,Documents!$C$2:$C$3728,"dive_prices")),"") | M38: =IFERROR(IF(_xlfn.MAXIFS(Documents!$E$2:$E$3728,Documents!$A$2:$A$3728,$A38,Documents!$C$2:$C$3728,"excursions")=0,"",_xlfn.MAXIFS(Documents!$E$2:$E$3728,Documents!$A$2:$A$3728,$A38,Documents!$C$2:$C$3728,"excursions")),"") | N38: =IFERROR(IF(_xlfn.MAXIFS(Documents!$E$2:$E$3728,Documents!$A$2:$A$3728,$A38,Documents!$C$2:$C$3728,"kids")=0,"",_xlfn.MAXIFS(Documents!$E$2:$E$3728,Documents!$A$2:$A$3728,$A38,Documents!$C$2:$C$3728,"kids")),"") | O38: =IFERROR(IF(_xlfn.MAXIFS(Documents!$E$2:$E$3728,Documents!$A$2:$A$3728,$A38,Documents!$C$2:$C$3728,"villa_plans")=0,"",_xlfn.MAXIFS(Documents!$E$2:$E$3728,Documents!$A$2:$A$3728,$A38,Documents!$C$2:$C$3728,"villa_plans")),"") | P38: =IFERROR(IF(_xlfn.MAXIFS(Documents!$E$2:$E$3728,Documents!$A$2:$A$3728,$A38,Documents!$C$2:$C$3728,"all_inclusive")=0,"",_xlfn.MAXIFS(Documents!$E$2:$E$3728,Documents!$A$2:$A$3728,$A38,Documents!$C$2:$C$3728,"all_inclusive")),"") | Q38: =IFERROR(IF(_xlfn.MAXIFS(Documents!$E$2:$E$3728,Documents!$A$2:$A$3728,$A38,Documents!$C$2:$C$3728,"sustainability")=0,"",_xlfn.MAXIFS(Documents!$E$2:$E$3728,Documents!$A$2:$A$3728,$A38,Documents!$C$2:$C$3728,"sustainability")),"") | R38: =IFERROR(IF(_xlfn.MAXIFS(Documents!$E$2:$E$3728,Documents!$A$2:$A$3728,$A38,Documents!$C$2:$C$3728,"calendar")=0,"",_xlfn.MAXIFS(Documents!$E$2:$E$3728,Documents!$A$2:$A$3728,$A38,Documents!$C$2:$C$3728,"calendar")),"") | S38: =IFERROR(IF(_xlfn.MAXIFS(Documents!$E$2:$E$3728,Documents!$A$2:$A$3728,$A38,Documents!$C$2:$C$3728,"brochure")=0,"",_xlfn.MAXIFS(Documents!$E$2:$E$3728,Documents!$A$2:$A$3728,$A38,Documents!$C$2:$C$3728,"brochure")),"") | T38: =IFERROR(IF(_xlfn.MAXIFS(Documents!$E$2:$E$3728,Documents!$A$2:$A$3728,$A38,Documents!$C$2:$C$3728,"press_kit")=0,"",_xlfn.MAXIFS(Documents!$E$2:$E$3728,Documents!$A$2:$A$3728,$A38,Documents!$C$2:$C$3728,"press_kit")),"") | U38: =IFERROR(IF(_xlfn.MAXIFS(Documents!$E$2:$E$3728,Documents!$A$2:$A$3728,$A38,Documents!$C$2:$C$3728,"other")=0,"",_xlfn.MAXIFS(Documents!$E$2:$E$3728,Documents!$A$2:$A$3728,$A38,Documents!$C$2:$C$3728,"other")),"") | V38: =IFERROR(IF(_xlfn.MAXIFS(Documents!$E$2:$E$3728,Documents!$A$2:$A$3728,$A38,Documents!$C$2:$C$3728,"obsolete")=0,"",_xlfn.MAXIFS(Documents!$E$2:$E$3728,Documents!$A$2:$A$3728,$A38,Documents!$C$2:$C$3728,"obsolete")),"") | W38: =COUNTIFS(Documents!$A$2:$A$3728,$A38) | X38: =COUNTIFS(Documents!$A$2:$A$3728,$A38,Documents!$R$2:$R$3728,"current") | Y38: =HYPERLINK("https://www.neoscapesmaldives.com/wp-content/uploads/The-Ritz-Carlton-Maldives-Factsheet.pdf","2021_The-Ritz-Carlton-Maldives-Factsheet") | Z38: wedding, events
A39: 38 | B39: Veligandu Maldives Resort Island | C39: ok | D39: =IFERROR(IF(_xlfn.MAXIFS(Documents!$E$2:$E$3728,Documents!$A$2:$A$3728,$A39,Documents!$C$2:$C$3728,"factsheet")=0,"",_xlfn.MAXIFS(Documents!$E$2:$E$3728,Documents!$A$2:$A$3728,$A39,Documents!$C$2:$C$3728,"factsheet")),"") | E39: =IFERROR(IF(_xlfn.MAXIFS(Documents!$E$2:$E$3728,Documents!$A$2:$A$3728,$A39,Documents!$C$2:$C$3728,"wedding")=0,"",_xlfn.MAXIFS(Documents!$E$2:$E$3728,Documents!$A$2:$A$3728,$A39,Documents!$C$2:$C$3728,"wedding")),"") | F39: =IFERROR(IF(_xlfn.MAXIFS(Documents!$E$2:$E$3728,Documents!$A$2:$A$3728,$A39,Documents!$C$2:$C$3728,"events")=0,"",_xlfn.MAXIFS(Documents!$E$2:$E$3728,Documents!$A$2:$A$3728,$A39,Documents!$C$2:$C$3728,"events")),"") | G39: =IFERROR(IF(_xlfn.MAXIFS(Documents!$E$2:$E$3728,Documents!$A$2:$A$3728,$A39,Documents!$C$2:$C$3728,"destination_dining")=0,"",_xlfn.MAXIFS(Documents!$E$2:$E$3728,Documents!$A$2:$A$3728,$A39,Documents!$C$2:$C$3728,"destination_dining")),"") | H39: =IFERROR(IF(_xlfn.MAXIFS(Documents!$E$2:$E$3728,Documents!$A$2:$A$3728,$A39,Documents!$C$2:$C$3728,"map")=0,"",_xlfn.MAXIFS(Documents!$E$2:$E$3728,Documents!$A$2:$A$3728,$A39,Documents!$C$2:$C$3728,"map")),"") | I39: =IFERROR(IF(_xlfn.MAXIFS(Documents!$E$2:$E$3728,Documents!$A$2:$A$3728,$A39,Documents!$C$2:$C$3728,"dive_map")=0,"",_xlfn.MAXIFS(Documents!$E$2:$E$3728,Documents!$A$2:$A$3728,$A39,Documents!$C$2:$C$3728,"dive_map")),"") | J39: =IFERROR(IF(_xlfn.MAXIFS(Documents!$E$2:$E$3728,Documents!$A$2:$A$3728,$A39,Documents!$C$2:$C$3728,"spa_menu")=0,"",_xlfn.MAXIFS(Documents!$E$2:$E$3728,Documents!$A$2:$A$3728,$A39,Documents!$C$2:$C$3728,"spa_menu")),"") | K39: =IFERROR(IF(_xlfn.MAXIFS(Documents!$E$2:$E$3728,Documents!$A$2:$A$3728,$A39,Documents!$C$2:$C$3728,"dining_menu")=0,"",_xlfn.MAXIFS(Documents!$E$2:$E$3728,Documents!$A$2:$A$3728,$A39,Documents!$C$2:$C$3728,"dining_menu")),"") | L39: =IFERROR(IF(_xlfn.MAXIFS(Documents!$E$2:$E$3728,Documents!$A$2:$A$3728,$A39,Documents!$C$2:$C$3728,"dive_prices")=0,"",_xlfn.MAXIFS(Documents!$E$2:$E$3728,Documents!$A$2:$A$3728,$A39,Documents!$C$2:$C$3728,"dive_prices")),"") | M39: =IFERROR(IF(_xlfn.MAXIFS(Documents!$E$2:$E$3728,Documents!$A$2:$A$3728,$A39,Documents!$C$2:$C$3728,"excursions")=0,"",_xlfn.MAXIFS(Documents!$E$2:$E$3728,Documents!$A$2:$A$3728,$A39,Documents!$C$2:$C$3728,"excursions")),"") | N39: =IFERROR(IF(_xlfn.MAXIFS(Documents!$E$2:$E$3728,Documents!$A$2:$A$3728,$A39,Documents!$C$2:$C$3728,"kids")=0,"",_xlfn.MAXIFS(Documents!$E$2:$E$3728,Documents!$A$2:$A$3728,$A39,Documents!$C$2:$C$3728,"kids")),"") | O39: =IFERROR(IF(_xlfn.MAXIFS(Documents!$E$2:$E$3728,Documents!$A$2:$A$3728,$A39,Documents!$C$2:$C$3728,"villa_plans")=0,"",_xlfn.MAXIFS(Documents!$E$2:$E$3728,Documents!$A$2:$A$3728,$A39,Documents!$C$2:$C$3728,"villa_plans")),"") | P39: =IFERROR(IF(_xlfn.MAXIFS(Documents!$E$2:$E$3728,Documents!$A$2:$A$3728,$A39,Documents!$C$2:$C$3728,"all_inclusive")=0,"",_xlfn.MAXIFS(Documents!$E$2:$E$3728,Documents!$A$2:$A$3728,$A39,Documents!$C$2:$C$3728,"all_inclusive")),"") | Q39: =IFERROR(IF(_xlfn.MAXIFS(Documents!$E$2:$E$3728,Documents!$A$2:$A$3728,$A39,Documents!$C$2:$C$3728,"sustainability")=0,"",_xlfn.MAXIFS(Documents!$E$2:$E$3728,Documents!$A$2:$A$3728,$A39,Documents!$C$2:$C$3728,"sustainability")),"") | R39: =IFERROR(IF(_xlfn.MAXIFS(Documents!$E$2:$E$3728,Documents!$A$2:$A$3728,$A39,Documents!$C$2:$C$3728,"calendar")=0,"",_xlfn.MAXIFS(Documents!$E$2:$E$3728,Documents!$A$2:$A$3728,$A39,Documents!$C$2:$C$3728,"calendar")),"") | S39: =IFERROR(IF(_xlfn.MAXIFS(Documents!$E$2:$E$3728,Documents!$A$2:$A$3728,$A39,Documents!$C$2:$C$3728,"brochure")=0,"",_xlfn.MAXIFS(Documents!$E$2:$E$3728,Documents!$A$2:$A$3728,$A39,Documents!$C$2:$C$3728,"brochure")),"") | T39: =IFERROR(IF(_xlfn.MAXIFS(Documents!$E$2:$E$3728,Documents!$A$2:$A$3728,$A39,Documents!$C$2:$C$3728,"press_kit")=0,"",_xlfn.MAXIFS(Documents!$E$2:$E$3728,Documents!$A$2:$A$3728,$A39,Documents!$C$2:$C$3728,"press_kit")),"") | U39: =IFERROR(IF(_xlfn.MAXIFS(Documents!$E$2:$E$3728,Documents!$A$2:$A$3728,$A39,Documents!$C$2:$C$3728,"other")=0,"",_xlfn.MAXIFS(Documents!$E$2:$E$3728,Documents!$A$2:$A$3728,$A39,Documents!$C$2:$C$3728,"other")),"") | V39: =IFERROR(IF(_xlfn.MAXIFS(Documents!$E$2:$E$3728,Documents!$A$2:$A$3728,$A39,Documents!$C$2:$C$3728,"obsolete")=0,"",_xlfn.MAXIFS(Documents!$E$2:$E$3728,Documents!$A$2:$A$3728,$A39,Documents!$C$2:$C$3728,"obsolete")),"") | W39: =COUNTIFS(Documents!$A$2:$A$3728,$A39) | X39: =COUNTIFS(Documents!$A$2:$A$3728,$A39,Documents!$R$2:$R$3728,"current") | Y39: =HYPERLINK("https://veligandu.com/wp-content/uploads/2025/06/Factsheet-W25-26S26Ver17062025.pdf","2026_Factsheet-W25-26S26Ver17062025.pdf") | Z39: events | AA39: 'Veli' in Crown & Champa filenames
A40: 39 | B40: NH Collection Maldives Havodda Resort | C40: blocked | D40: =IFERROR(IF(_xlfn.MAXIFS(Documents!$E$2:$E$3728,Documents!$A$2:$A$3728,$A40,Documents!$C$2:$C$3728,"factsheet")=0,"",_xlfn.MAXIFS(Documents!$E$2:$E$3728,Documents!$A$2:$A$3728,$A40,Documents!$C$2:$C$3728,"factsheet")),"") | E40: =IFERROR(IF(_xlfn.MAXIFS(Documents!$E$2:$E$3728,Documents!$A$2:$A$3728,$A40,Documents!$C$2:$C$3728,"wedding")=0,"",_xlfn.MAXIFS(Documents!$E$2:$E$3728,Documents!$A$2:$A$3728,$A40,Documents!$C$2:$C$3728,"wedding")),"") | F40: =IFERROR(IF(_xlfn.MAXIFS(Documents!$E$2:$E$3728,Documents!$A$2:$A$3728,$A40,Documents!$C$2:$C$3728,"events")=0,"",_xlfn.MAXIFS(Documents!$E$2:$E$3728,Documents!$A$2:$A$3728,$A40,Documents!$C$2:$C$3728,"events")),"") | G40: =IFERROR(IF(_xlfn.MAXIFS(Documents!$E$2:$E$3728,Documents!$A$2:$A$3728,$A40,Documents!$C$2:$C$3728,"destination_dining")=0,"",_xlfn.MAXIFS(Documents!$E$2:$E$3728,Documents!$A$2:$A$3728,$A40,Documents!$C$2:$C$3728,"destination_dining")),"") | H40: =IFERROR(IF(_xlfn.MAXIFS(Documents!$E$2:$E$3728,Documents!$A$2:$A$3728,$A40,Documents!$C$2:$C$3728,"map")=0,"",_xlfn.MAXIFS(Documents!$E$2:$E$3728,Documents!$A$2:$A$3728,$A40,Documents!$C$2:$C$3728,"map")),"") | I40: =IFERROR(IF(_xlfn.MAXIFS(Documents!$E$2:$E$3728,Documents!$A$2:$A$3728,$A40,Documents!$C$2:$C$3728,"dive_map")=0,"",_xlfn.MAXIFS(Documents!$E$2:$E$3728,Documents!$A$2:$A$3728,$A40,Documents!$C$2:$C$3728,"dive_map")),"") | J40: =IFERROR(IF(_xlfn.MAXIFS(Documents!$E$2:$E$3728,Documents!$A$2:$A$3728,$A40,Documents!$C$2:$C$3728,"spa_menu")=0,"",_xlfn.MAXIFS(Documents!$E$2:$E$3728,Documents!$A$2:$A$3728,$A40,Documents!$C$2:$C$3728,"spa_menu")),"") | K40: =IFERROR(IF(_xlfn.MAXIFS(Documents!$E$2:$E$3728,Documents!$A$2:$A$3728,$A40,Documents!$C$2:$C$3728,"dining_menu")=0,"",_xlfn.MAXIFS(Documents!$E$2:$E$3728,Documents!$A$2:$A$3728,$A40,Documents!$C$2:$C$3728,"dining_menu")),"") | L40: =IFERROR(IF(_xlfn.MAXIFS(Documents!$E$2:$E$3728,Documents!$A$2:$A$3728,$A40,Documents!$C$2:$C$3728,"dive_prices")=0,"",_xlfn.MAXIFS(Documents!$E$2:$E$3728,Documents!$A$2:$A$3728,$A40,Documents!$C$2:$C$3728,"dive_prices")),"") | M40: =IFERROR(IF(_xlfn.MAXIFS(Documents!$E$2:$E$3728,Documents!$A$2:$A$3728,$A40,Documents!$C$2:$C$3728,"excursions")=0,"",_xlfn.MAXIFS(Documents!$E$2:$E$3728,Documents!$A$2:$A$3728,$A40,Documents!$C$2:$C$3728,"excursions")),"") | N40: =IFERROR(IF(_xlfn.MAXIFS(Documents!$E$2:$E$3728,Documents!$A$2:$A$3728,$A40,Documents!$C$2:$C$3728,"kids")=0,"",_xlfn.MAXIFS(Documents!$E$2:$E$3728,Documents!$A$2:$A$3728,$A40,Documents!$C$2:$C$3728,"kids")),"") | O40: =IFERROR(IF(_xlfn.MAXIFS(Documents!$E$2:$E$3728,Documents!$A$2:$A$3728,$A40,Documents!$C$2:$C$3728,"villa_plans")=0,"",_xlfn.MAXIFS(Documents!$E$2:$E$3728,Documents!$A$2:$A$3728,$A40,Documents!$C$2:$C$3728,"villa_plans")),"") | P40: =IFERROR(IF(_xlfn.MAXIFS(Documents!$E$2:$E$3728,Documents!$A$2:$A$3728,$A40,Documents!$C$2:$C$3728,"all_inclusive")=0,"",_xlfn.MAXIFS(Documents!$E$2:$E$3728,Documents!$A$2:$A$3728,$A40,Documents!$C$2:$C$3728,"all_inclusive")),"") | Q40: =IFERROR(IF(_xlfn.MAXIFS(Documents!$E$2:$E$3728,Documents!$A$2:$A$3728,$A40,Documents!$C$2:$C$3728,"sustainability")=0,"",_xlfn.MAXIFS(Documents!$E$2:$E$3728,Documents!$A$2:$A$3728,$A40,Documents!$C$2:$C$3728,"sustainability")),"") | R40: =IFERROR(IF(_xlfn.MAXIFS(Documents!$E$2:$E$3728,Documents!$A$2:$A$3728,$A40,Documents!$C$2:$C$3728,"calendar")=0,"",_xlfn.MAXIFS(Documents!$E$2:$E$3728,Documents!$A$2:$A$3728,$A40,Documents!$C$2:$C$3728,"calendar")),"") | S40: =IFERROR(IF(_xlfn.MAXIFS(Documents!$E$2:$E$3728,Documents!$A$2:$A$3728,$A40,Documents!$C$2:$C$3728,"brochure")=0,"",_xlfn.MAXIFS(Documents!$E$2:$E$3728,Documents!$A$2:$A$3728,$A40,Documents!$C$2:$C$3728,"brochure")),"") | T40: =IFERROR(IF(_xlfn.MAXIFS(Documents!$E$2:$E$3728,Documents!$A$2:$A$3728,$A40,Documents!$C$2:$C$3728,"press_kit")=0,"",_xlfn.MAXIFS(Documents!$E$2:$E$3728,Documents!$A$2:$A$3728,$A40,Documents!$C$2:$C$3728,"press_kit")),"") | U40: =IFERROR(IF(_xlfn.MAXIFS(Documents!$E$2:$E$3728,Documents!$A$2:$A$3728,$A40,Documents!$C$2:$C$3728,"other")=0,"",_xlfn.MAXIFS(Documents!$E$2:$E$3728,Documents!$A$2:$A$3728,$A40,Documents!$C$2:$C$3728,"other")),"") | V40: =IFERROR(IF(_xlfn.MAXIFS(Documents!$E$2:$E$3728,Documents!$A$2:$A$3728,$A40,Documents!$C$2:$C$3728,"obsolete")=0,"",_xlfn.MAXIFS(Documents!$E$2:$E$3728,Documents!$A$2:$A$3728,$A40,Documents!$C$2:$C$3728,"obsolete")),"") | W40: =COUNTIFS(Documents!$A$2:$A$3728,$A40) | X40: =COUNTIFS(Documents!$A$2:$A$3728,$A40,Documents!$R$2:$R$3728,"current") | Y40: =HYPERLINK("https://neoscapesmaldives.com/wp-content/uploads/Amari-Havodda-Factsheet.pdf","2018_Amari-Havodda-Factsheet.pdf") | Z40: wedding, events | AA40: Amari Havodda (older name)
A41: 40 | B41: Le Méridien Maldives Resort and Spa | C41: blocked | D41: =IFERROR(IF(_xlfn.MAXIFS(Documents!$E$2:$E$3728,Documents!$A$2:$A$3728,$A41,Documents!$C$2:$C$3728,"factsheet")=0,"",_xlfn.MAXIFS(Documents!$E$2:$E$3728,Documents!$A$2:$A$3728,$A41,Documents!$C$2:$C$3728,"factsheet")),"") | E41: =IFERROR(IF(_xlfn.MAXIFS(Documents!$E$2:$E$3728,Documents!$A$2:$A$3728,$A41,Documents!$C$2:$C$3728,"wedding")=0,"",_xlfn.MAXIFS(Documents!$E$2:$E$3728,Documents!$A$2:$A$3728,$A41,Documents!$C$2:$C$3728,"wedding")),"") | F41: =IFERROR(IF(_xlfn.MAXIFS(Documents!$E$2:$E$3728,Documents!$A$2:$A$3728,$A41,Documents!$C$2:$C$3728,"events")=0,"",_xlfn.MAXIFS(Documents!$E$2:$E$3728,Documents!$A$2:$A$3728,$A41,Documents!$C$2:$C$3728,"events")),"") | G41: =IFERROR(IF(_xlfn.MAXIFS(Documents!$E$2:$E$3728,Documents!$A$2:$A$3728,$A41,Documents!$C$2:$C$3728,"destination_dining")=0,"",_xlfn.MAXIFS(Documents!$E$2:$E$3728,Documents!$A$2:$A$3728,$A41,Documents!$C$2:$C$3728,"destination_dining")),"") | H41: =IFERROR(IF(_xlfn.MAXIFS(Documents!$E$2:$E$3728,Documents!$A$2:$A$3728,$A41,Documents!$C$2:$C$3728,"map")=0,"",_xlfn.MAXIFS(Documents!$E$2:$E$3728,Documents!$A$2:$A$3728,$A41,Documents!$C$2:$C$3728,"map")),"") | I41: =IFERROR(IF(_xlfn.MAXIFS(Documents!$E$2:$E$3728,Documents!$A$2:$A$3728,$A41,Documents!$C$2:$C$3728,"dive_map")=0,"",_xlfn.MAXIFS(Documents!$E$2:$E$3728,Documents!$A$2:$A$3728,$A41,Documents!$C$2:$C$3728,"dive_map")),"") | J41: =IFERROR(IF(_xlfn.MAXIFS(Documents!$E$2:$E$3728,Documents!$A$2:$A$3728,$A41,Documents!$C$2:$C$3728,"spa_menu")=0,"",_xlfn.MAXIFS(Documents!$E$2:$E$3728,Documents!$A$2:$A$3728,$A41,Documents!$C$2:$C$3728,"spa_menu")),"") | K41: =IFERROR(IF(_xlfn.MAXIFS(Documents!$E$2:$E$3728,Documents!$A$2:$A$3728,$A41,Documents!$C$2:$C$3728,"dining_menu")=0,"",_xlfn.MAXIFS(Documents!$E$2:$E$3728,Documents!$A$2:$A$3728,$A41,Documents!$C$2:$C$3728,"dining_menu")),"") | L41: =IFERROR(IF(_xlfn.MAXIFS(Documents!$E$2:$E$3728,Documents!$A$2:$A$3728,$A41,Documents!$C$2:$C$3728,"dive_prices")=0,"",_xlfn.MAXIFS(Documents!$E$2:$E$3728,Documents!$A$2:$A$3728,$A41,Documents!$C$2:$C$3728,"dive_prices")),"") | M41: =IFERROR(IF(_xlfn.MAXIFS(Documents!$E$2:$E$3728,Documents!$A$2:$A$3728,$A41,Documents!$C$2:$C$3728,"excursions")=0,"",_xlfn.MAXIFS(Documents!$E$2:$E$3728,Documents!$A$2:$A$3728,$A41,Documents!$C$2:$C$3728,"excursions")),"") | N41: =IFERROR(IF(_xlfn.MAXIFS(Documents!$E$2:$E$3728,Documents!$A$2:$A$3728,$A41,Documents!$C$2:$C$3728,"kids")=0,"",_xlfn.MAXIFS(Documents!$E$2:$E$3728,Documents!$A$2:$A$3728,$A41,Documents!$C$2:$C$3728,"kids")),"") | O41: =IFERROR(IF(_xlfn.MAXIFS(Documents!$E$2:$E$3728,Documents!$A$2:$A$3728,$A41,Documents!$C$2:$C$3728,"villa_plans")=0,"",_xlfn.MAXIFS(Documents!$E$2:$E$3728,Documents!$A$2:$A$3728,$A41,Documents!$C$2:$C$3728,"villa_plans")),"") | P41: =IFERROR(IF(_xlfn.MAXIFS(Documents!$E$2:$E$3728,Documents!$A$2:$A$3728,$A41,Documents!$C$2:$C$3728,"all_inclusive")=0,"",_xlfn.MAXIFS(Documents!$E$2:$E$3728,Documents!$A$2:$A$3728,$A41,Documents!$C$2:$C$3728,"all_inclusive")),"") | Q41: =IFERROR(IF(_xlfn.MAXIFS(Documents!$E$2:$E$3728,Documents!$A$2:$A$3728,$A41,Documents!$C$2:$C$3728,"sustainability")=0,"",_xlfn.MAXIFS(Documents!$E$2:$E$3728,Documents!$A$2:$A$3728,$A41,Documents!$C$2:$C$3728,"sustainability")),"") | R41: =IFERROR(IF(_xlfn.MAXIFS(Documents!$E$2:$E$3728,Documents!$A$2:$A$3728,$A41,Documents!$C$2:$C$3728,"calendar")=0,"",_xlfn.MAXIFS(Documents!$E$2:$E$3728,Documents!$A$2:$A$3728,$A41,Documents!$C$2:$C$3728,"calendar")),"") | S41: =IFERROR(IF(_xlfn.MAXIFS(Documents!$E$2:$E$3728,Documents!$A$2:$A$3728,$A41,Documents!$C$2:$C$3728,"brochure")=0,"",_xlfn.MAXIFS(Documents!$E$2:$E$3728,Documents!$A$2:$A$3728,$A41,Documents!$C$2:$C$3728,"brochure")),"") | T41: =IFERROR(IF(_xlfn.MAXIFS(Documents!$E$2:$E$3728,Documents!$A$2:$A$3728,$A41,Documents!$C$2:$C$3728,"press_kit")=0,"",_xlfn.MAXIFS(Documents!$E$2:$E$3728,Documents!$A$2:$A$3728,$A41,Documents!$C$2:$C$3728,"press_kit")),"") | U41: =IFERROR(IF(_xlfn.MAXIFS(Documents!$E$2:$E$3728,Documents!$A$2:$A$3728,$A41,Documents!$C$2:$C$3728,"other")=0,"",_xlfn.MAXIFS(Documents!$E$2:$E$3728,Documents!$A$2:$A$3728,$A41,Documents!$C$2:$C$3728,"other")),"") | V41: =IFERROR(IF(_xlfn.MAXIFS(Documents!$E$2:$E$3728,Documents!$A$2:$A$3728,$A41,Documents!$C$2:$C$3728,"obsolete")=0,"",_xlfn.MAXIFS(Documents!$E$2:$E$3728,Documents!$A$2:$A$3728,$A41,Documents!$C$2:$C$3728,"obsolete")),"") | W41: =COUNTIFS(Documents!$A$2:$A$3728,$A41) | X41: =COUNTIFS(Documents!$A$2:$A$3728,$A41,Documents!$R$2:$R$3728,"current") | Y41: =HYPERLINK("https://www.neoscapesmaldives.com/wp-content/uploads/Resort-Factsheet-Le-Meridien-Maldives.pdf","2021_Resort-Factsheet-Le-Meridien-Maldiv") | Z41: wedding, events
A42: 41 | B42: Ozen By Atmosphere At Maadhoo | C42: unverified | D42: =IFERROR(IF(_xlfn.MAXIFS(Documents!$E$2:$E$3728,Documents!$A$2:$A$3728,$A42,Documents!$C$2:$C$3728,"factsheet")=0,"",_xlfn.MAXIFS(Documents!$E$2:$E$3728,Documents!$A$2:$A$3728,$A42,Documents!$C$2:$C$3728,"factsheet")),"") | E42: =IFERROR(IF(_xlfn.MAXIFS(Documents!$E$2:$E$3728,Documents!$A$2:$A$3728,$A42,Documents!$C$2:$C$3728,"wedding")=0,"",_xlfn.MAXIFS(Documents!$E$2:$E$3728,Documents!$A$2:$A$3728,$A42,Documents!$C$2:$C$3728,"wedding")),"") | F42: =IFERROR(IF(_xlfn.MAXIFS(Documents!$E$2:$E$3728,Documents!$A$2:$A$3728,$A42,Documents!$C$2:$C$3728,"events")=0,"",_xlfn.MAXIFS(Documents!$E$2:$E$3728,Documents!$A$2:$A$3728,$A42,Documents!$C$2:$C$3728,"events")),"") | G42: =IFERROR(IF(_xlfn.MAXIFS(Documents!$E$2:$E$3728,Documents!$A$2:$A$3728,$A42,Documents!$C$2:$C$3728,"destination_dining")=0,"",_xlfn.MAXIFS(Documents!$E$2:$E$3728,Documents!$A$2:$A$3728,$A42,Documents!$C$2:$C$3728,"destination_dining")),"") | H42: =IFERROR(IF(_xlfn.MAXIFS(Documents!$E$2:$E$3728,Documents!$A$2:$A$3728,$A42,Documents!$C$2:$C$3728,"map")=0,"",_xlfn.MAXIFS(Documents!$E$2:$E$3728,Documents!$A$2:$A$3728,$A42,Documents!$C$2:$C$3728,"map")),"") | I42: =IFERROR(IF(_xlfn.MAXIFS(Documents!$E$2:$E$3728,Documents!$A$2:$A$3728,$A42,Documents!$C$2:$C$3728,"dive_map")=0,"",_xlfn.MAXIFS(Documents!$E$2:$E$3728,Documents!$A$2:$A$3728,$A42,Documents!$C$2:$C$3728,"dive_map")),"") | J42: =IFERROR(IF(_xlfn.MAXIFS(Documents!$E$2:$E$3728,Documents!$A$2:$A$3728,$A42,Documents!$C$2:$C$3728,"spa_menu")=0,"",_xlfn.MAXIFS(Documents!$E$2:$E$3728,Documents!$A$2:$A$3728,$A42,Documents!$C$2:$C$3728,"spa_menu")),"") | K42: =IFERROR(IF(_xlfn.MAXIFS(Documents!$E$2:$E$3728,Documents!$A$2:$A$3728,$A42,Documents!$C$2:$C$3728,"dining_menu")=0,"",_xlfn.MAXIFS(Documents!$E$2:$E$3728,Documents!$A$2:$A$3728,$A42,Documents!$C$2:$C$3728,"dining_menu")),"") | L42: =IFERROR(IF(_xlfn.MAXIFS(Documents!$E$2:$E$3728,Documents!$A$2:$A$3728,$A42,Documents!$C$2:$C$3728,"dive_prices")=0,"",_xlfn.MAXIFS(Documents!$E$2:$E$3728,Documents!$A$2:$A$3728,$A42,Documents!$C$2:$C$3728,"dive_prices")),"") | M42: =IFERROR(IF(_xlfn.MAXIFS(Documents!$E$2:$E$3728,Documents!$A$2:$A$3728,$A42,Documents!$C$2:$C$3728,"excursions")=0,"",_xlfn.MAXIFS(Documents!$E$2:$E$3728,Documents!$A$2:$A$3728,$A42,Documents!$C$2:$C$3728,"excursions")),"") | N42: =IFERROR(IF(_xlfn.MAXIFS(Documents!$E$2:$E$3728,Documents!$A$2:$A$3728,$A42,Documents!$C$2:$C$3728,"kids")=0,"",_xlfn.MAXIFS(Documents!$E$2:$E$3728,Documents!$A$2:$A$3728,$A42,Documents!$C$2:$C$3728,"kids")),"") | O42: =IFERROR(IF(_xlfn.MAXIFS(Documents!$E$2:$E$3728,Documents!$A$2:$A$3728,$A42,Documents!$C$2:$C$3728,"villa_plans")=0,"",_xlfn.MAXIFS(Documents!$E$2:$E$3728,Documents!$A$2:$A$3728,$A42,Documents!$C$2:$C$3728,"villa_plans")),"") | P42: =IFERROR(IF(_xlfn.MAXIFS(Documents!$E$2:$E$3728,Documents!$A$2:$A$3728,$A42,Documents!$C$2:$C$3728,"all_inclusive")=0,"",_xlfn.MAXIFS(Documents!$E$2:$E$3728,Documents!$A$2:$A$3728,$A42,Documents!$C$2:$C$3728,"all_inclusive")),"") | Q42: =IFERROR(IF(_xlfn.MAXIFS(Documents!$E$2:$E$3728,Documents!$A$2:$A$3728,$A42,Documents!$C$2:$C$3728,"sustainability")=0,"",_xlfn.MAXIFS(Documents!$E$2:$E$3728,Documents!$A$2:$A$3728,$A42,Documents!$C$2:$C$3728,"sustainability")),"") | R42: =IFERROR(IF(_xlfn.MAXIFS(Documents!$E$2:$E$3728,Documents!$A$2:$A$3728,$A42,Documents!$C$2:$C$3728,"calendar")=0,"",_xlfn.MAXIFS(Documents!$E$2:$E$3728,Documents!$A$2:$A$3728,$A42,Documents!$C$2:$C$3728,"calendar")),"") | S42: =IFERROR(IF(_xlfn.MAXIFS(Documents!$E$2:$E$3728,Documents!$A$2:$A$3728,$A42,Documents!$C$2:$C$3728,"brochure")=0,"",_xlfn.MAXIFS(Documents!$E$2:$E$3728,Documents!$A$2:$A$3728,$A42,Documents!$C$2:$C$3728,"brochure")),"") | T42: =IFERROR(IF(_xlfn.MAXIFS(Documents!$E$2:$E$3728,Documents!$A$2:$A$3728,$A42,Documents!$C$2:$C$3728,"press_kit")=0,"",_xlfn.MAXIFS(Documents!$E$2:$E$3728,Documents!$A$2:$A$3728,$A42,Documents!$C$2:$C$3728,"press_kit")),"") | U42: =IFERROR(IF(_xlfn.MAXIFS(Documents!$E$2:$E$3728,Documents!$A$2:$A$3728,$A42,Documents!$C$2:$C$3728,"other")=0,"",_xlfn.MAXIFS(Documents!$E$2:$E$3728,Documents!$A$2:$A$3728,$A42,Documents!$C$2:$C$3728,"other")),"") | V42: =IFERROR(IF(_xlfn.MAXIFS(Documents!$E$2:$E$3728,Documents!$A$2:$A$3728,$A42,Documents!$C$2:$C$3728,"obsolete")=0,"",_xlfn.MAXIFS(Documents!$E$2:$E$3728,Documents!$A$2:$A$3728,$A42,Documents!$C$2:$C$3728,"obsolete")),"") | W42: =COUNTIFS(Documents!$A$2:$A$3728,$A42) | X42: =COUNTIFS(Documents!$A$2:$A$3728,$A42,Documents!$R$2:$R$3728,"current") | Y42: =HYPERLINK("https://www.neoscapesmaldives.com/wp-content/uploads/OZEN-LIFE-MAADHOO-Fact-Sheet-2025.pdf","2025_OZEN-LIFE-MAADHOO-Fact-Sheet-2025.p") | Z42: wedding, events | AA42: OZEN Life Maadhoo
A43: 42 | B43: Dhiggiri Tourist Resort | C43: ok | D43: =IFERROR(IF(_xlfn.MAXIFS(Documents!$E$2:$E$3728,Documents!$A$2:$A$3728,$A43,Documents!$C$2:$C$3728,"factsheet")=0,"",_xlfn.MAXIFS(Documents!$E$2:$E$3728,Documents!$A$2:$A$3728,$A43,Documents!$C$2:$C$3728,"factsheet")),"") | E43: =IFERROR(IF(_xlfn.MAXIFS(Documents!$E$2:$E$3728,Documents!$A$2:$A$3728,$A43,Documents!$C$2:$C$3728,"wedding")=0,"",_xlfn.MAXIFS(Documents!$E$2:$E$3728,Documents!$A$2:$A$3728,$A43,Documents!$C$2:$C$3728,"wedding")),"") | F43: =IFERROR(IF(_xlfn.MAXIFS(Documents!$E$2:$E$3728,Documents!$A$2:$A$3728,$A43,Documents!$C$2:$C$3728,"events")=0,"",_xlfn.MAXIFS(Documents!$E$2:$E$3728,Documents!$A$2:$A$3728,$A43,Documents!$C$2:$C$3728,"events")),"") | G43: =IFERROR(IF(_xlfn.MAXIFS(Documents!$E$2:$E$3728,Documents!$A$2:$A$3728,$A43,Documents!$C$2:$C$3728,"destination_dining")=0,"",_xlfn.MAXIFS(Documents!$E$2:$E$3728,Documents!$A$2:$A$3728,$A43,Documents!$C$2:$C$3728,"destination_dining")),"") | H43: =IFERROR(IF(_xlfn.MAXIFS(Documents!$E$2:$E$3728,Documents!$A$2:$A$3728,$A43,Documents!$C$2:$C$3728,"map")=0,"",_xlfn.MAXIFS(Documents!$E$2:$E$3728,Documents!$A$2:$A$3728,$A43,Documents!$C$2:$C$3728,"map")),"") | I43: =IFERROR(IF(_xlfn.MAXIFS(Documents!$E$2:$E$3728,Documents!$A$2:$A$3728,$A43,Documents!$C$2:$C$3728,"dive_map")=0,"",_xlfn.MAXIFS(Documents!$E$2:$E$3728,Documents!$A$2:$A$3728,$A43,Documents!$C$2:$C$3728,"dive_map")),"") | J43: =IFERROR(IF(_xlfn.MAXIFS(Documents!$E$2:$E$3728,Documents!$A$2:$A$3728,$A43,Documents!$C$2:$C$3728,"spa_menu")=0,"",_xlfn.MAXIFS(Documents!$E$2:$E$3728,Documents!$A$2:$A$3728,$A43,Documents!$C$2:$C$3728,"spa_menu")),"") | K43: =IFERROR(IF(_xlfn.MAXIFS(Documents!$E$2:$E$3728,Documents!$A$2:$A$3728,$A43,Documents!$C$2:$C$3728,"dining_menu")=0,"",_xlfn.MAXIFS(Documents!$E$2:$E$3728,Documents!$A$2:$A$3728,$A43,Documents!$C$2:$C$3728,"dining_menu")),"") | L43: =IFERROR(IF(_xlfn.MAXIFS(Documents!$E$2:$E$3728,Documents!$A$2:$A$3728,$A43,Documents!$C$2:$C$3728,"dive_prices")=0,"",_xlfn.MAXIFS(Documents!$E$2:$E$3728,Documents!$A$2:$A$3728,$A43,Documents!$C$2:$C$3728,"dive_prices")),"") | M43: =IFERROR(IF(_xlfn.MAXIFS(Documents!$E$2:$E$3728,Documents!$A$2:$A$3728,$A43,Documents!$C$2:$C$3728,"excursions")=0,"",_xlfn.MAXIFS(Documents!$E$2:$E$3728,Documents!$A$2:$A$3728,$A43,Documents!$C$2:$C$3728,"excursions")),"") | N43: =IFERROR(IF(_xlfn.MAXIFS(Documents!$E$2:$E$3728,Documents!$A$2:$A$3728,$A43,Documents!$C$2:$C$3728,"kids")=0,"",_xlfn.MAXIFS(Documents!$E$2:$E$3728,Documents!$A$2:$A$3728,$A43,Documents!$C$2:$C$3728,"kids")),"") | O43: =IFERROR(IF(_xlfn.MAXIFS(Documents!$E$2:$E$3728,Documents!$A$2:$A$3728,$A43,Documents!$C$2:$C$3728,"villa_plans")=0,"",_xlfn.MAXIFS(Documents!$E$2:$E$3728,Documents!$A$2:$A$3728,$A43,Documents!$C$2:$C$3728,"villa_plans")),"") | P43: =IFERROR(IF(_xlfn.MAXIFS(Documents!$E$2:$E$3728,Documents!$A$2:$A$3728,$A43,Documents!$C$2:$C$3728,"all_inclusive")=0,"",_xlfn.MAXIFS(Documents!$E$2:$E$3728,Documents!$A$2:$A$3728,$A43,Documents!$C$2:$C$3728,"all_inclusive")),"") | Q43: =IFERROR(IF(_xlfn.MAXIFS(Documents!$E$2:$E$3728,Documents!$A$2:$A$3728,$A43,Documents!$C$2:$C$3728,"sustainability")=0,"",_xlfn.MAXIFS(Documents!$E$2:$E$3728,Documents!$A$2:$A$3728,$A43,Documents!$C$2:$C$3728,"sustainability")),"") | R43: =IFERROR(IF(_xlfn.MAXIFS(Documents!$E$2:$E$3728,Documents!$A$2:$A$3728,$A43,Documents!$C$2:$C$3728,"calendar")=0,"",_xlfn.MAXIFS(Documents!$E$2:$E$3728,Documents!$A$2:$A$3728,$A43,Documents!$C$2:$C$3728,"calendar")),"") | S43: =IFERROR(IF(_xlfn.MAXIFS(Documents!$E$2:$E$3728,Documents!$A$2:$A$3728,$A43,Documents!$C$2:$C$3728,"brochure")=0,"",_xlfn.MAXIFS(Documents!$E$2:$E$3728,Documents!$A$2:$A$3728,$A43,Documents!$C$2:$C$3728,"brochure")),"") | T43: =IFERROR(IF(_xlfn.MAXIFS(Documents!$E$2:$E$3728,Documents!$A$2:$A$3728,$A43,Documents!$C$2:$C$3728,"press_kit")=0,"",_xlfn.MAXIFS(Documents!$E$2:$E$3728,Documents!$A$2:$A$3728,$A43,Documents!$C$2:$C$3728,"press_kit")),"") | U43: =IFERROR(IF(_xlfn.MAXIFS(Documents!$E$2:$E$3728,Documents!$A$2:$A$3728,$A43,Documents!$C$2:$C$3728,"other")=0,"",_xlfn.MAXIFS(Documents!$E$2:$E$3728,Documents!$A$2:$A$3728,$A43,Documents!$C$2:$C$3728,"other")),"") | V43: =IFERROR(IF(_xlfn.MAXIFS(Documents!$E$2:$E$3728,Documents!$A$2:$A$3728,$A43,Documents!$C$2:$C$3728,"obsolete")=0,"",_xlfn.MAXIFS(Documents!$E$2:$E$3728,Documents!$A$2:$A$3728,$A43,Documents!$C$2:$C$3728,"obsolete")),"") | W43: =COUNTIFS(Documents!$A$2:$A$3728,$A43) | X43: =COUNTIFS(Documents!$A$2:$A$3728,$A43,Documents!$R$2:$R$3728,"current") | Z43: factsheet, wedding, events
