Workbook

Sheet Coverage
A1: # | B1: Resort | C1: Official site status | D1: factsheet (latest yr) | E1: wedding (latest yr) | F1: events (latest yr) | G1: map (latest yr) | H1: dive_map (latest yr) | I1: spa_menu (latest yr) | J1: dining_menu (latest yr) | K1: dive_prices (latest yr) | L1: excursions (latest yr) | M1: kids (latest yr) | N1: villa_plans (latest yr) | O1: all_inclusive (latest yr) | P1: sustainability (latest yr) | Q1: calendar (latest yr) | R1: brochure (latest yr) | S1: press_kit (latest yr) | T1: other (latest yr) | U1: obsolete (latest yr) | V1: Total docs | W1: Current docs | X1: Latest factsheet | Y1: Gaps (priority 1) | Z1: Rename notes
A2: 1 | B2: Six Senses Laamu | C2: blocked | D2: =IFERROR(IF(maxifs(Documents!$E$2:$E$1421,Documents!$A$2:$A$1421,$A2,Documents!$C$2:$C$1421,"factsheet")=0,"",maxifs(Documents!$E$2:$E$1421,Documents!$A$2:$A$1421,$A2,Documents!$C$2:$C$1421,"factsheet")),"") | E2: =IFERROR(IF(maxifs(Documents!$E$2:$E$1421,Documents!$A$2:$A$1421,$A2,Documents!$C$2:$C$1421,"wedding")=0,"",maxifs(Documents!$E$2:$E$1421,Documents!$A$2:$A$1421,$A2,Documents!$C$2:$C$1421,"wedding")),"") | F2: =IFERROR(IF(maxifs(Documents!$E$2:$E$1421,Documents!$A$2:$A$1421,$A2,Documents!$C$2:$C$1421,"events")=0,"",maxifs(Documents!$E$2:$E$1421,Documents!$A$2:$A$1421,$A2,Documents!$C$2:$C$1421,"events")),"") | G2: =IFERROR(IF(maxifs(Documents!$E$2:$E$1421,Documents!$A$2:$A$1421,$A2,Documents!$C$2:$C$1421,"map")=0,"",maxifs(Documents!$E$2:$E$1421,Documents!$A$2:$A$1421,$A2,Documents!$C$2:$C$1421,"map")),"") | H2: =IFERROR(IF(maxifs(Documents!$E$2:$E$1421,Documents!$A$2:$A$1421,$A2,Documents!$C$2:$C$1421,"dive_map")=0,"",maxifs(Documents!$E$2:$E$1421,Documents!$A$2:$A$1421,$A2,Documents!$C$2:$C$1421,"dive_map")),"") | I2: =IFERROR(IF(maxifs(Documents!$E$2:$E$1421,Documents!$A$2:$A$1421,$A2,Documents!$C$2:$C$1421,"spa_menu")=0,"",maxifs(Documents!$E$2:$E$1421,Documents!$A$2:$A$1421,$A2,Documents!$C$2:$C$1421,"spa_menu")),"") | J2: =IFERROR(IF(maxifs(Documents!$E$2:$E$1421,Documents!$A$2:$A$1421,$A2,Documents!$C$2:$C$1421,"dining_menu")=0,"",maxifs(Documents!$E$2:$E$1421,Documents!$A$2:$A$1421,$A2,Documents!$C$2:$C$1421,"dining_menu")),"") | K2: =IFERROR(IF(maxifs(Documents!$E$2:$E$1421,Documents!$A$2:$A$1421,$A2,Documents!$C$2:$C$1421,"dive_prices")=0,"",maxifs(Documents!$E$2:$E$1421,Documents!$A$2:$A$1421,$A2,Documents!$C$2:$C$1421,"dive_prices")),"") | L2: =IFERROR(IF(maxifs(Documents!$E$2:$E$1421,Documents!$A$2:$A$1421,$A2,Documents!$C$2:$C$1421,"excursions")=0,"",maxifs(Documents!$E$2:$E$1421,Documents!$A$2:$A$1421,$A2,Documents!$C$2:$C$1421,"excursions")),"") | M2: =IFERROR(IF(maxifs(Documents!$E$2:$E$1421,Documents!$A$2:$A$1421,$A2,Documents!$C$2:$C$1421,"kids")=0,"",maxifs(Documents!$E$2:$E$1421,Documents!$A$2:$A$1421,$A2,Documents!$C$2:$C$1421,"kids")),"") | N2: =IFERROR(IF(maxifs(Documents!$E$2:$E$1421,Documents!$A$2:$A$1421,$A2,Documents!$C$2:$C$1421,"villa_plans")=0,"",maxifs(Documents!$E$2:$E$1421,Documents!$A$2:$A$1421,$A2,Documents!$C$2:$C$1421,"villa_plans")),"") | O2: =IFERROR(IF(maxifs(Documents!$E$2:$E$1421,Documents!$A$2:$A$1421,$A2,Documents!$C$2:$C$1421,"all_inclusive")=0,"",maxifs(Documents!$E$2:$E$1421,Documents!$A$2:$A$1421,$A2,Documents!$C$2:$C$1421,"all_inclusive")),"") | P2: =IFERROR(IF(maxifs(Documents!$E$2:$E$1421,Documents!$A$2:$A$1421,$A2,Documents!$C$2:$C$1421,"sustainability")=0,"",maxifs(Documents!$E$2:$E$1421,Documents!$A$2:$A$1421,$A2,Documents!$C$2:$C$1421,"sustainability")),"") | Q2: =IFERROR(IF(maxifs(Documents!$E$2:$E$1421,Documents!$A$2:$A$1421,$A2,Documents!$C$2:$C$1421,"calendar")=0,"",maxifs(Documents!$E$2:$E$1421,Documents!$A$2:$A$1421,$A2,Documents!$C$2:$C$1421,"calendar")),"") | R2: =IFERROR(IF(maxifs(Documents!$E$2:$E$1421,Documents!$A$2:$A$1421,$A2,Documents!$C$2:$C$1421,"brochure")=0,"",maxifs(Documents!$E$2:$E$1421,Documents!$A$2:$A$1421,$A2,Documents!$C$2:$C$1421,"brochure")),"") | S2: =IFERROR(IF(maxifs(Documents!$E$2:$E$1421,Documents!$A$2:$A$1421,$A2,Documents!$C$2:$C$1421,"press_kit")=0,"",maxifs(Documents!$E$2:$E$1421,Documents!$A$2:$A$1421,$A2,Documents!$C$2:$C$1421,"press_kit")),"") | T2: =IFERROR(IF(maxifs(Documents!$E$2:$E$1421,Documents!$A$2:$A$1421,$A2,Documents!$C$2:$C$1421,"other")=0,"",maxifs(Documents!$E$2:$E$1421,Documents!$A$2:$A$1421,$A2,Documents!$C$2:$C$1421,"other")),"") | U2: =IFERROR(IF(maxifs(Documents!$E$2:$E$1421,Documents!$A$2:$A$1421,$A2,Documents!$C$2:$C$1421,"obsolete")=0,"",maxifs(Documents!$E$2:$E$1421,Documents!$A$2:$A$1421,$A2,Documents!$C$2:$C$1421,"obsolete")),"") | V2: =COUNTIFS(Documents!$A$2:$A$1421,$A2) -> 4 | W2: =COUNTIFS(Documents!$A$2:$A$1421,$A2,Documents!$R$2:$R$1421,"current") -> 2 | X2: =HYPERLINK("https://sales.crownandchamparesorts.com/wp-content/uploads/2026/04/NalaMaldivesFactsheet011125311026Ver030426.pdf","2025_NalaMaldivesFactsheet011125311026Ve") -> 2025_NalaMaldivesFactsheet011125311026Ve | Y2: wedding, events
A3: 2 | B3: Filitheyo Island Resort | C3: unverified | D3: =IFERROR(IF(maxifs(Documents!$E$2:$E$1421,Documents!$A$2:$A$1421,$A3,Documents!$C$2:$C$1421,"factsheet")=0,"",maxifs(Documents!$E$2:$E$1421,Documents!$A$2:$A$1421,$A3,Documents!$C$2:$C$1421,"factsheet")),"") | E3: =IFERROR(IF(maxifs(Documents!$E$2:$E$1421,Documents!$A$2:$A$1421,$A3,Documents!$C$2:$C$1421,"wedding")=0,"",maxifs(Documents!$E$2:$E$1421,Documents!$A$2:$A$1421,$A3,Documents!$C$2:$C$1421,"wedding")),"") | F3: =IFERROR(IF(maxifs(Documents!$E$2:$E$1421,Documents!$A$2:$A$1421,$A3,Documents!$C$2:$C$1421,"events")=0,"",maxifs(Documents!$E$2:$E$1421,Documents!$A$2:$A$1421,$A3,Documents!$C$2:$C$1421,"events")),"") | G3: =IFERROR(IF(maxifs(Documents!$E$2:$E$1421,Documents!$A$2:$A$1421,$A3,Documents!$C$2:$C$1421,"map")=0,"",maxifs(Documents!$E$2:$E$1421,Documents!$A$2:$A$1421,$A3,Documents!$C$2:$C$1421,"map")),"") | H3: =IFERROR(IF(maxifs(Documents!$E$2:$E$1421,Documents!$A$2:$A$1421,$A3,Documents!$C$2:$C$1421,"dive_map")=0,"",maxifs(Documents!$E$2:$E$1421,Documents!$A$2:$A$1421,$A3,Documents!$C$2:$C$1421,"dive_map")),"") | I3: =IFERROR(IF(maxifs(Documents!$E$2:$E$1421,Documents!$A$2:$A$1421,$A3,Documents!$C$2:$C$1421,"spa_menu")=0,"",maxifs(Documents!$E$2:$E$1421,Documents!$A$2:$A$1421,$A3,Documents!$C$2:$C$1421,"spa_menu")),"") | J3: =IFERROR(IF(maxifs(Documents!$E$2:$E$1421,Documents!$A$2:$A$1421,$A3,Documents!$C$2:$C$1421,"dining_menu")=0,"",maxifs(Documents!$E$2:$E$1421,Documents!$A$2:$A$1421,$A3,Documents!$C$2:$C$1421,"dining_menu")),"") | K3: =IFERROR(IF(maxifs(Documents!$E$2:$E$1421,Documents!$A$2:$A$1421,$A3,Documents!$C$2:$C$1421,"dive_prices")=0,"",maxifs(Documents!$E$2:$E$1421,Documents!$A$2:$A$1421,$A3,Documents!$C$2:$C$1421,"dive_prices")),"") | L3: =IFERROR(IF(maxifs(Documents!$E$2:$E$1421,Documents!$A$2:$A$1421,$A3,Documents!$C$2:$C$1421,"excursions")=0,"",maxifs(Documents!$E$2:$E$1421,Documents!$A$2:$A$1421,$A3,Documents!$C$2:$C$1421,"excursions")),"") | M3: =IFERROR(IF(maxifs(Documents!$E$2:$E$1421,Documents!$A$2:$A$1421,$A3,Documents!$C$2:$C$1421,"kids")=0,"",maxifs(Documents!$E$2:$E$1421,Documents!$A$2:$A$1421,$A3,Documents!$C$2:$C$1421,"kids")),"") | N3: =IFERROR(IF(maxifs(Documents!$E$2:$E$1421,Documents!$A$2:$A$1421,$A3,Documents!$C$2:$C$1421,"villa_plans")=0,"",maxifs(Documents!$E$2:$E$1421,Documents!$A$2:$A$1421,$A3,Documents!$C$2:$C$1421,"villa_plans")),"") | O3: =IFERROR(IF(maxifs(Documents!$E$2:$E$1421,Documents!$A$2:$A$1421,$A3,Documents!$C$2:$C$1421,"all_inclusive")=0,"",maxifs(Documents!$E$2:$E$1421,Documents!$A$2:$A$1421,$A3,Documents!$C$2:$C$1421,"all_inclusive")),"") | P3: =IFERROR(IF(maxifs(Documents!$E$2:$E$1421,Documents!$A$2:$A$1421,$A3,Documents!$C$2:$C$1421,"sustainability")=0,"",maxifs(Documents!$E$2:$E$1421,Documents!$A$2:$A$1421,$A3,Documents!$C$2:$C$1421,"sustainability")),"") | Q3: =IFERROR(IF(maxifs(Documents!$E$2:$E$1421,Documents!$A$2:$A$1421,$A3,Documents!$C$2:$C$1421,"calendar")=0,"",maxifs(Documents!$E$2:$E$1421,Documents!$A$2:$A$1421,$A3,Documents!$C$2:$C$1421,"calendar")),"") | R3: =IFERROR(IF(maxifs(Documents!$E$2:$E$1421,Documents!$A$2:$A$1421,$A3,Documents!$C$2:$C$1421,"brochure")=0,"",maxifs(Documents!$E$2:$E$1421,Documents!$A$2:$A$1421,$A3,Documents!$C$2:$C$1421,"brochure")),"") | S3: =IFERROR(IF(maxifs(Documents!$E$2:$E$1421,Documents!$A$2:$A$1421,$A3,Documents!$C$2:$C$1421,"press_kit")=0,"",maxifs(Documents!$E$2:$E$1421,Documents!$A$2:$A$1421,$A3,Documents!$C$2:$C$1421,"press_kit")),"") | T3: =IFERROR(IF(maxifs(Documents!$E$2:$E$1421,Documents!$A$2:$A$1421,$A3,Documents!$C$2:$C$1421,"other")=0,"",maxifs(Documents!$E$2:$E$1421,Documents!$A$2:$A$1421,$A3,Documents!$C$2:$C$1421,"other")),"") | U3: =IFERROR(IF(maxifs(Documents!$E$2:$E$1421,Documents!$A$2:$A$1421,$A3,Documents!$C$2:$C$1421,"obsolete")=0,"",maxifs(Documents!$E$2:$E$1421,Documents!$A$2:$A$1421,$A3,Documents!$C$2:$C$1421,"obsolete")),"") | V3: =COUNTIFS(Documents!$A$2:$A$1421,$A3) -> 0 | W3: =COUNTIFS(Documents!$A$2:$A$1421,$A3,Documents!$R$2:$R$1421,"current") -> 0 | Y3: factsheet, wedding, events
A4: 3 | B4: Adaaran Select Hudhuranfushi | C4: ok | D4: =IFERROR(IF(maxifs(Documents!$E$2:$E$1421,Documents!$A$2:$A$1421,$A4,Documents!$C$2:$C$1421,"factsheet")=0,"",maxifs(Documents!$E$2:$E$1421,Documents!$A$2:$A$1421,$A4,Documents!$C$2:$C$1421,"factsheet")),"") | E4: =IFERROR(IF(maxifs(Documents!$E$2:$E$1421,Documents!$A$2:$A$1421,$A4,Documents!$C$2:$C$1421,"wedding")=0,"",maxifs(Documents!$E$2:$E$1421,Documents!$A$2:$A$1421,$A4,Documents!$C$2:$C$1421,"wedding")),"") | F4: =IFERROR(IF(maxifs(Documents!$E$2:$E$1421,Documents!$A$2:$A$1421,$A4,Documents!$C$2:$C$1421,"events")=0,"",maxifs(Documents!$E$2:$E$1421,Documents!$A$2:$A$1421,$A4,Documents!$C$2:$C$1421,"events")),"") | G4: =IFERROR(IF(maxifs(Documents!$E$2:$E$1421,Documents!$A$2:$A$1421,$A4,Documents!$C$2:$C$1421,"map")=0,"",maxifs(Documents!$E$2:$E$1421,Documents!$A$2:$A$1421,$A4,Documents!$C$2:$C$1421,"map")),"") | H4: =IFERROR(IF(maxifs(Documents!$E$2:$E$1421,Documents!$A$2:$A$1421,$A4,Documents!$C$2:$C$1421,"dive_map")=0,"",maxifs(Documents!$E$2:$E$1421,Documents!$A$2:$A$1421,$A4,Documents!$C$2:$C$1421,"dive_map")),"") | I4: =IFERROR(IF(maxifs(Documents!$E$2:$E$1421,Documents!$A$2:$A$1421,$A4,Documents!$C$2:$C$1421,"spa_menu")=0,"",maxifs(Documents!$E$2:$E$1421,Documents!$A$2:$A$1421,$A4,Documents!$C$2:$C$1421,"spa_menu")),"") | J4: =IFERROR(IF(maxifs(Documents!$E$2:$E$1421,Documents!$A$2:$A$1421,$A4,Documents!$C$2:$C$1421,"dining_menu")=0,"",maxifs(Documents!$E$2:$E$1421,Documents!$A$2:$A$1421,$A4,Documents!$C$2:$C$1421,"dining_menu")),"") | K4: =IFERROR(IF(maxifs(Documents!$E$2:$E$1421,Documents!$A$2:$A$1421,$A4,Documents!$C$2:$C$1421,"dive_prices")=0,"",maxifs(Documents!$E$2:$E$1421,Documents!$A$2:$A$1421,$A4,Documents!$C$2:$C$1421,"dive_prices")),"") | L4: =IFERROR(IF(maxifs(Documents!$E$2:$E$1421,Documents!$A$2:$A$1421,$A4,Documents!$C$2:$C$1421,"excursions")=0,"",maxifs(Documents!$E$2:$E$1421,Documents!$A$2:$A$1421,$A4,Documents!$C$2:$C$1421,"excursions")),"") | M4: =IFERROR(IF(maxifs(Documents!$E$2:$E$1421,Documents!$A$2:$A$1421,$A4,Documents!$C$2:$C$1421,"kids")=0,"",maxifs(Documents!$E$2:$E$1421,Documents!$A$2:$A$1421,$A4,Documents!$C$2:$C$1421,"kids")),"") | N4: =IFERROR(IF(maxifs(Documents!$E$2:$E$1421,Documents!$A$2:$A$1421,$A4,Documents!$C$2:$C$1421,"villa_plans")=0,"",maxifs(Documents!$E$2:$E$1421,Documents!$A$2:$A$1421,$A4,Documents!$C$2:$C$1421,"villa_plans")),"") | O4: =IFERROR(IF(maxifs(Documents!$E$2:$E$1421,Documents!$A$2:$A$1421,$A4,Documents!$C$2:$C$1421,"all_inclusive")=0,"",maxifs(Documents!$E$2:$E$1421,Documents!$A$2:$A$1421,$A4,Documents!$C$2:$C$1421,"all_inclusive")),"") | P4: =IFERROR(IF(maxifs(Documents!$E$2:$E$1421,Documents!$A$2:$A$1421,$A4,Documents!$C$2:$C$1421,"sustainability")=0,"",maxifs(Documents!$E$2:$E$1421,Documents!$A$2:$A$1421,$A4,Documents!$C$2:$C$1421,"sustainability")),"") | Q4: =IFERROR(IF(maxifs(Documents!$E$2:$E$1421,Documents!$A$2:$A$1421,$A4,Documents!$C$2:$C$1421,"calendar")=0,"",maxifs(Documents!$E$2:$E$1421,Documents!$A$2:$A$1421,$A4,Documents!$C$2:$C$1421,"calendar")),"") | R4: =IFERROR(IF(maxifs(Documents!$E$2:$E$1421,Documents!$A$2:$A$1421,$A4,Documents!$C$2:$C$1421,"brochure")=0,"",maxifs(Documents!$E$2:$E$1421,Documents!$A$2:$A$1421,$A4,Documents!$C$2:$C$1421,"brochure")),"") | S4: =IFERROR(IF(maxifs(Documents!$E$2:$E$1421,Documents!$A$2:$A$1421,$A4,Documents!$C$2:$C$1421,"press_kit")=0,"",maxifs(Documents!$E$2:$E$1421,Documents!$A$2:$A$1421,$A4,Documents!$C$2:$C$1421,"press_kit")),"") | T4: =IFERROR(IF(maxifs(Documents!$E$2:$E$1421,Documents!$A$2:$A$1421,$A4,Documents!$C$2:$C$1421,"other")=0,"",maxifs(Documents!$E$2:$E$1421,Documents!$A$2:$A$1421,$A4,Documents!$C$2:$C$1421,"other")),"") | U4: =IFERROR(IF(maxifs(Documents!$E$2:$E$1421,Documents!$A$2:$A$1421,$A4,Documents!$C$2:$C$1421,"obsolete")=0,"",maxifs(Documents!$E$2:$E$1421,Documents!$A$2:$A$1421,$A4,Documents!$C$2:$C$1421,"obsolete")),"") | V4: =COUNTIFS(Documents!$A$2:$A$1421,$A4) -> 21 | W4: =COUNTIFS(Documents!$A$2:$A$1421,$A4,Documents!$R$2:$R$1421,"current") -> 15 | X4: =HYPERLINK("https://www.adaaran.com/selecthudhuranfushi/view-download/?id=menu-16","2026_document.pdf") -> 2026_document.pdf
A5: 4 | B5: Ayada Maldives | C5: ok | D5: =IFERROR(IF(maxifs(Documents!$E$2:$E$1421,Documents!$A$2:$A$1421,$A5,Documents!$C$2:$C$1421,"factsheet")=0,"",maxifs(Documents!$E$2:$E$1421,Documents!$A$2:$A$1421,$A5,Documents!$C$2:$C$1421,"factsheet")),"") | E5: =IFERROR(IF(maxifs(Documents!$E$2:$E$1421,Documents!$A$2:$A$1421,$A5,Documents!$C$2:$C$1421,"wedding")=0,"",maxifs(Documents!$E$2:$E$1421,Documents!$A$2:$A$1421,$A5,Documents!$C$2:$C$1421,"wedding")),"") | F5: =IFERROR(IF(maxifs(Documents!$E$2:$E$1421,Documents!$A$2:$A$1421,$A5,Documents!$C$2:$C$1421,"events")=0,"",maxifs(Documents!$E$2:$E$1421,Documents!$A$2:$A$1421,$A5,Documents!$C$2:$C$1421,"events")),"") | G5: =IFERROR(IF(maxifs(Documents!$E$2:$E$1421,Documents!$A$2:$A$1421,$A5,Documents!$C$2:$C$1421,"map")=0,"",maxifs(Documents!$E$2:$E$1421,Documents!$A$2:$A$1421,$A5,Documents!$C$2:$C$1421,"map")),"") | H5: =IFERROR(IF(maxifs(Documents!$E$2:$E$1421,Documents!$A$2:$A$1421,$A5,Documents!$C$2:$C$1421,"dive_map")=0,"",maxifs(Documents!$E$2:$E$1421,Documents!$A$2:$A$1421,$A5,Documents!$C$2:$C$1421,"dive_map")),"") | I5: =IFERROR(IF(maxifs(Documents!$E$2:$E$1421,Documents!$A$2:$A$1421,$A5,Documents!$C$2:$C$1421,"spa_menu")=0,"",maxifs(Documents!$E$2:$E$1421,Documents!$A$2:$A$1421,$A5,Documents!$C$2:$C$1421,"spa_menu")),"") | J5: =IFERROR(IF(maxifs(Documents!$E$2:$E$1421,Documents!$A$2:$A$1421,$A5,Documents!$C$2:$C$1421,"dining_menu")=0,"",maxifs(Documents!$E$2:$E$1421,Documents!$A$2:$A$1421,$A5,Documents!$C$2:$C$1421,"dining_menu")),"") | K5: =IFERROR(IF(maxifs(Documents!$E$2:$E$1421,Documents!$A$2:$A$1421,$A5,Documents!$C$2:$C$1421,"dive_prices")=0,"",maxifs(Documents!$E$2:$E$1421,Documents!$A$2:$A$1421,$A5,Documents!$C$2:$C$1421,"dive_prices")),"") | L5: =IFERROR(IF(maxifs(Documents!$E$2:$E$1421,Documents!$A$2:$A$1421,$A5,Documents!$C$2:$C$1421,"excursions")=0,"",maxifs(Documents!$E$2:$E$1421,Documents!$A$2:$A$1421,$A5,Documents!$C$2:$C$1421,"excursions")),"") | M5: =IFERROR(IF(maxifs(Documents!$E$2:$E$1421,Documents!$A$2:$A$1421,$A5,Documents!$C$2:$C$1421,"kids")=0,"",maxifs(Documents!$E$2:$E$1421,Documents!$A$2:$A$1421,$A5,Documents!$C$2:$C$1421,"kids")),"") | N5: =IFERROR(IF(maxifs(Documents!$E$2:$E$1421,Documents!$A$2:$A$1421,$A5,Documents!$C$2:$C$1421,"villa_plans")=0,"",maxifs(Documents!$E$2:$E$1421,Documents!$A$2:$A$1421,$A5,Documents!$C$2:$C$1421,"villa_plans")),"") | O5: =IFERROR(IF(maxifs(Documents!$E$2:$E$1421,Documents!$A$2:$A$1421,$A5,Documents!$C$2:$C$1421,"all_inclusive")=0,"",maxifs(Documents!$E$2:$E$1421,Documents!$A$2:$A$1421,$A5,Documents!$C$2:$C$1421,"all_inclusive")),"") | P5: =IFERROR(IF(maxifs(Documents!$E$2:$E$1421,Documents!$A$2:$A$1421,$A5,Documents!$C$2:$C$1421,"sustainability")=0,"",maxifs(Documents!$E$2:$E$1421,Documents!$A$2:$A$1421,$A5,Documents!$C$2:$C$1421,"sustainability")),"") | Q5: =IFERROR(IF(maxifs(Documents!$E$2:$E$1421,Documents!$A$2:$A$1421,$A5,Documents!$C$2:$C$1421,"calendar")=0,"",maxifs(Documents!$E$2:$E$1421,Documents!$A$2:$A$1421,$A5,Documents!$C$2:$C$1421,"calendar")),"") | R5: =IFERROR(IF(maxifs(Documents!$E$2:$E$1421,Documents!$A$2:$A$1421,$A5,Documents!$C$2:$C$1421,"brochure")=0,"",maxifs(Documents!$E$2:$E$1421,Documents!$A$2:$A$1421,$A5,Documents!$C$2:$C$1421,"brochure")),"") | S5: =IFERROR(IF(maxifs(Documents!$E$2:$E$1421,Documents!$A$2:$A$1421,$A5,Documents!$C$2:$C$1421,"press_kit")=0,"",maxifs(Documents!$E$2:$E$1421,Documents!$A$2:$A$1421,$A5,Documents!$C$2:$C$1421,"press_kit")),"") | T5: =IFERROR(IF(maxifs(Documents!$E$2:$E$1421,Documents!$A$2:$A$1421,$A5,Documents!$C$2:$C$1421,"other")=0,"",maxifs(Documents!$E$2:$E$1421,Documents!$A$2:$A$1421,$A5,Documents!$C$2:$C$1421,"other")),"") | U5: =IFERROR(IF(maxifs(Documents!$E$2:$E$1421,Documents!$A$2:$A$1421,$A5,Documents!$C$2:$C$1421,"obsolete")=0,"",maxifs(Documents!$E$2:$E$1421,Documents!$A$2:$A$1421,$A5,Documents!$C$2:$C$1421,"obsolete")),"") | V5: =COUNTIFS(Documents!$A$2:$A$1421,$A5) -> 30 | W5: =COUNTIFS(Documents!$A$2:$A$1421,$A5,Documents!$R$2:$R$1421,"current") -> 2 | X5: =HYPERLINK("https://www.neoscapesmaldives.com/wp-content/uploads/Ayada-Maldives-Factsheet.pdf","2024_Ayada-Maldives-Factsheet.pdf") -> 2024_Ayada-Maldives-Factsheet.pdf | Y5: events
A6: 5 | B6: Bolifushi Island Resort | C6: blocked | D6: =IFERROR(IF(maxifs(Documents!$E$2:$E$1421,Documents!$A$2:$A$1421,$A6,Documents!$C$2:$C$1421,"factsheet")=0,"",maxifs(Documents!$E$2:$E$1421,Documents!$A$2:$A$1421,$A6,Documents!$C$2:$C$1421,"factsheet")),"") | E6: =IFERROR(IF(maxifs(Documents!$E$2:$E$1421,Documents!$A$2:$A$1421,$A6,Documents!$C$2:$C$1421,"wedding")=0,"",maxifs(Documents!$E$2:$E$1421,Documents!$A$2:$A$1421,$A6,Documents!$C$2:$C$1421,"wedding")),"") | F6: =IFERROR(IF(maxifs(Documents!$E$2:$E$1421,Documents!$A$2:$A$1421,$A6,Documents!$C$2:$C$1421,"events")=0,"",maxifs(Documents!$E$2:$E$1421,Documents!$A$2:$A$1421,$A6,Documents!$C$2:$C$1421,"events")),"") | G6: =IFERROR(IF(maxifs(Documents!$E$2:$E$1421,Documents!$A$2:$A$1421,$A6,Documents!$C$2:$C$1421,"map")=0,"",maxifs(Documents!$E$2:$E$1421,Documents!$A$2:$A$1421,$A6,Documents!$C$2:$C$1421,"map")),"") | H6: =IFERROR(IF(maxifs(Documents!$E$2:$E$1421,Documents!$A$2:$A$1421,$A6,Documents!$C$2:$C$1421,"dive_map")=0,"",maxifs(Documents!$E$2:$E$1421,Documents!$A$2:$A$1421,$A6,Documents!$C$2:$C$1421,"dive_map")),"") | I6: =IFERROR(IF(maxifs(Documents!$E$2:$E$1421,Documents!$A$2:$A$1421,$A6,Documents!$C$2:$C$1421,"spa_menu")=0,"",maxifs(Documents!$E$2:$E$1421,Documents!$A$2:$A$1421,$A6,Documents!$C$2:$C$1421,"spa_menu")),"") | J6: =IFERROR(IF(maxifs(Documents!$E$2:$E$1421,Documents!$A$2:$A$1421,$A6,Documents!$C$2:$C$1421,"dining_menu")=0,"",maxifs(Documents!$E$2:$E$1421,Documents!$A$2:$A$1421,$A6,Documents!$C$2:$C$1421,"dining_menu")),"") | K6: =IFERROR(IF(maxifs(Documents!$E$2:$E$1421,Documents!$A$2:$A$1421,$A6,Documents!$C$2:$C$1421,"dive_prices")=0,"",maxifs(Documents!$E$2:$E$1421,Documents!$A$2:$A$1421,$A6,Documents!$C$2:$C$1421,"dive_prices")),"") | L6: =IFERROR(IF(maxifs(Documents!$E$2:$E$1421,Documents!$A$2:$A$1421,$A6,Documents!$C$2:$C$1421,"excursions")=0,"",maxifs(Documents!$E$2:$E$1421,Documents!$A$2:$A$1421,$A6,Documents!$C$2:$C$1421,"excursions")),"") | M6: =IFERROR(IF(maxifs(Documents!$E$2:$E$1421,Documents!$A$2:$A$1421,$A6,Documents!$C$2:$C$1421,"kids")=0,"",maxifs(Documents!$E$2:$E$1421,Documents!$A$2:$A$1421,$A6,Documents!$C$2:$C$1421,"kids")),"") | N6: =IFERROR(IF(maxifs(Documents!$E$2:$E$1421,Documents!$A$2:$A$1421,$A6,Documents!$C$2:$C$1421,"villa_plans")=0,"",maxifs(Documents!$E$2:$E$1421,Documents!$A$2:$A$1421,$A6,Documents!$C$2:$C$1421,"villa_plans")),"") | O6: =IFERROR(IF(maxifs(Documents!$E$2:$E$1421,Documents!$A$2:$A$1421,$A6,Documents!$C$2:$C$1421,"all_inclusive")=0,"",maxifs(Documents!$E$2:$E$1421,Documents!$A$2:$A$1421,$A6,Documents!$C$2:$C$1421,"all_inclusive")),"") | P6: =IFERROR(IF(maxifs(Documents!$E$2:$E$1421,Documents!$A$2:$A$1421,$A6,Documents!$C$2:$C$1421,"sustainability")=0,"",maxifs(Documents!$E$2:$E$1421,Documents!$A$2:$A$1421,$A6,Documents!$C$2:$C$1421,"sustainability")),"") | Q6: =IFERROR(IF(maxifs(Documents!$E$2:$E$1421,Documents!$A$2:$A$1421,$A6,Documents!$C$2:$C$1421,"calendar")=0,"",maxifs(Documents!$E$2:$E$1421,Documents!$A$2:$A$1421,$A6,Documents!$C$2:$C$1421,"calendar")),"") | R6: =IFERROR(IF(maxifs(Documents!$E$2:$E$1421,Documents!$A$2:$A$1421,$A6,Documents!$C$2:$C$1421,"brochure")=0,"",maxifs(Documents!$E$2:$E$1421,Documents!$A$2:$A$1421,$A6,Documents!$C$2:$C$1421,"brochure")),"") | S6: =IFERROR(IF(maxifs(Documents!$E$2:$E$1421,Documents!$A$2:$A$1421,$A6,Documents!$C$2:$C$1421,"press_kit")=0,"",maxifs(Documents!$E$2:$E$1421,Documents!$A$2:$A$1421,$A6,Documents!$C$2:$C$1421,"press_kit")),"") | T6: =IFERROR(IF(maxifs(Documents!$E$2:$E$1421,Documents!$A$2:$A$1421,$A6,Documents!$C$2:$C$1421,"other")=0,"",maxifs(Documents!$E$2:$E$1421,Documents!$A$2:$A$1421,$A6,Documents!$C$2:$C$1421,"other")),"") | U6: =IFERROR(IF(maxifs(Documents!$E$2:$E$1421,Documents!$A$2:$A$1421,$A6,Documents!$C$2:$C$1421,"obsolete")=0,"",maxifs(Documents!$E$2:$E$1421,Documents!$A$2:$A$1421,$A6,Documents!$C$2:$C$1421,"obsolete")),"") | V6: =COUNTIFS(Documents!$A$2:$A$1421,$A6) -> 2 | W6: =COUNTIFS(Documents!$A$2:$A$1421,$A6,Documents!$R$2:$R$1421,"current") -> 0 | X6: =HYPERLINK("https://www.neoscapesmaldives.com/wp-content/uploads/OZEN-RESERVE-BOLIFUSHI-Fact-Sheet.pdf","2023_OZEN-RESERVE-BOLIFUSHI-Fact-Sheet.p") -> 2023_OZEN-RESERVE-BOLIFUSHI-Fact-Sheet.p | Y6: wedding, events | Z6: OZEN Reserve Bolifushi (confirm)
A7: 6 | B7: Joali Being Bodufushi | C7: unreachable | D7: =IFERROR(IF(maxifs(Documents!$E$2:$E$1421,Documents!$A$2:$A$1421,$A7,Documents!$C$2:$C$1421,"factsheet")=0,"",maxifs(Documents!$E$2:$E$1421,Documents!$A$2:$A$1421,$A7,Documents!$C$2:$C$1421,"factsheet")),"") | E7: =IFERROR(IF(maxifs(Documents!$E$2:$E$1421,Documents!$A$2:$A$1421,$A7,Documents!$C$2:$C$1421,"wedding")=0,"",maxifs(Documents!$E$2:$E$1421,Documents!$A$2:$A$1421,$A7,Documents!$C$2:$C$1421,"wedding")),"") | F7: =IFERROR(IF(maxifs(Documents!$E$2:$E$1421,Documents!$A$2:$A$1421,$A7,Documents!$C$2:$C$1421,"events")=0,"",maxifs(Documents!$E$2:$E$1421,Documents!$A$2:$A$1421,$A7,Documents!$C$2:$C$1421,"events")),"") | G7: =IFERROR(IF(maxifs(Documents!$E$2:$E$1421,Documents!$A$2:$A$1421,$A7,Documents!$C$2:$C$1421,"map")=0,"",maxifs(Documents!$E$2:$E$1421,Documents!$A$2:$A$1421,$A7,Documents!$C$2:$C$1421,"map")),"") | H7: =IFERROR(IF(maxifs(Documents!$E$2:$E$1421,Documents!$A$2:$A$1421,$A7,Documents!$C$2:$C$1421,"dive_map")=0,"",maxifs(Documents!$E$2:$E$1421,Documents!$A$2:$A$1421,$A7,Documents!$C$2:$C$1421,"dive_map")),"") | I7: =IFERROR(IF(maxifs(Documents!$E$2:$E$1421,Documents!$A$2:$A$1421,$A7,Documents!$C$2:$C$1421,"spa_menu")=0,"",maxifs(Documents!$E$2:$E$1421,Documents!$A$2:$A$1421,$A7,Documents!$C$2:$C$1421,"spa_menu")),"") | J7: =IFERROR(IF(maxifs(Documents!$E$2:$E$1421,Documents!$A$2:$A$1421,$A7,Documents!$C$2:$C$1421,"dining_menu")=0,"",maxifs(Documents!$E$2:$E$1421,Documents!$A$2:$A$1421,$A7,Documents!$C$2:$C$1421,"dining_menu")),"") | K7: =IFERROR(IF(maxifs(Documents!$E$2:$E$1421,Documents!$A$2:$A$1421,$A7,Documents!$C$2:$C$1421,"dive_prices")=0,"",maxifs(Documents!$E$2:$E$1421,Documents!$A$2:$A$1421,$A7,Documents!$C$2:$C$1421,"dive_prices")),"") | L7: =IFERROR(IF(maxifs(Documents!$E$2:$E$1421,Documents!$A$2:$A$1421,$A7,Documents!$C$2:$C$1421,"excursions")=0,"",maxifs(Documents!$E$2:$E$1421,Documents!$A$2:$A$1421,$A7,Documents!$C$2:$C$1421,"excursions")),"") | M7: =IFERROR(IF(maxifs(Documents!$E$2:$E$1421,Documents!$A$2:$A$1421,$A7,Documents!$C$2:$C$1421,"kids")=0,"",maxifs(Documents!$E$2:$E$1421,Documents!$A$2:$A$1421,$A7,Documents!$C$2:$C$1421,"kids")),"") | N7: =IFERROR(IF(maxifs(Documents!$E$2:$E$1421,Documents!$A$2:$A$1421,$A7,Documents!$C$2:$C$1421,"villa_plans")=0,"",maxifs(Documents!$E$2:$E$1421,Documents!$A$2:$A$1421,$A7,Documents!$C$2:$C$1421,"villa_plans")),"") | O7: =IFERROR(IF(maxifs(Documents!$E$2:$E$1421,Documents!$A$2:$A$1421,$A7,Documents!$C$2:$C$1421,"all_inclusive")=0,"",maxifs(Documents!$E$2:$E$1421,Documents!$A$2:$A$1421,$A7,Documents!$C$2:$C$1421,"all_inclusive")),"") | P7: =IFERROR(IF(maxifs(Documents!$E$2:$E$1421,Documents!$A$2:$A$1421,$A7,Documents!$C$2:$C$1421,"sustainability")=0,"",maxifs(Documents!$E$2:$E$1421,Documents!$A$2:$A$1421,$A7,Documents!$C$2:$C$1421,"sustainability")),"") | Q7: =IFERROR(IF(maxifs(Documents!$E$2:$E$1421,Documents!$A$2:$A$1421,$A7,Documents!$C$2:$C$1421,"calendar")=0,"",maxifs(Documents!$E$2:$E$1421,Documents!$A$2:$A$1421,$A7,Documents!$C$2:$C$1421,"calendar")),"") | R7: =IFERROR(IF(maxifs(Documents!$E$2:$E$1421,Documents!$A$2:$A$1421,$A7,Documents!$C$2:$C$1421,"brochure")=0,"",maxifs(Documents!$E$2:$E$1421,Documents!$A$2:$A$1421,$A7,Documents!$C$2:$C$1421,"brochure")),"") | S7: =IFERROR(IF(maxifs(Documents!$E$2:$E$1421,Documents!$A$2:$A$1421,$A7,Documents!$C$2:$C$1421,"press_kit")=0,"",maxifs(Documents!$E$2:$E$1421,Documents!$A$2:$A$1421,$A7,Documents!$C$2:$C$1421,"press_kit")),"") | T7: =IFERROR(IF(maxifs(Documents!$E$2:$E$1421,Documents!$A$2:$A$1421,$A7,Documents!$C$2:$C$1421,"other")=0,"",maxifs(Documents!$E$2:$E$1421,Documents!$A$2:$A$1421,$A7,Documents!$C$2:$C$1421,"other")),"") | U7: =IFERROR(IF(maxifs(Documents!$E$2:$E$1421,Documents!$A$2:$A$1421,$A7,Documents!$C$2:$C$1421,"obsolete")=0,"",maxifs(Documents!$E$2:$E$1421,Documents!$A$2:$A$1421,$A7,Documents!$C$2:$C$1421,"obsolete")),"") | V7: =COUNTIFS(Documents!$A$2:$A$1421,$A7) -> 2 | W7: =COUNTIFS(Documents!$A$2:$A$1421,$A7,Documents!$R$2:$R$1421,"current") -> 1 | X7: =HYPERLINK("https://www.neoscapesmaldives.com/wp-content/uploads/JoaliBeing_Factsheet_V13.pdf","2025_JoaliBeing_Factsheet_V13.pdf") -> 2025_JoaliBeing_Factsheet_V13.pdf | Y7: wedding, events
A8: 7 | B8: Joali Muravandhoo | C8: unreachable | D8: =IFERROR(IF(maxifs(Documents!$E$2:$E$1421,Documents!$A$2:$A$1421,$A8,Documents!$C$2:$C$1421,"factsheet")=0,"",maxifs(Documents!$E$2:$E$1421,Documents!$A$2:$A$1421,$A8,Documents!$C$2:$C$1421,"factsheet")),"") | E8: =IFERROR(IF(maxifs(Documents!$E$2:$E$1421,Documents!$A$2:$A$1421,$A8,Documents!$C$2:$C$1421,"wedding")=0,"",maxifs(Documents!$E$2:$E$1421,Documents!$A$2:$A$1421,$A8,Documents!$C$2:$C$1421,"wedding")),"") | F8: =IFERROR(IF(maxifs(Documents!$E$2:$E$1421,Documents!$A$2:$A$1421,$A8,Documents!$C$2:$C$1421,"events")=0,"",maxifs(Documents!$E$2:$E$1421,Documents!$A$2:$A$1421,$A8,Documents!$C$2:$C$1421,"events")),"") | G8: =IFERROR(IF(maxifs(Documents!$E$2:$E$1421,Documents!$A$2:$A$1421,$A8,Documents!$C$2:$C$1421,"map")=0,"",maxifs(Documents!$E$2:$E$1421,Documents!$A$2:$A$1421,$A8,Documents!$C$2:$C$1421,"map")),"") | H8: =IFERROR(IF(maxifs(Documents!$E$2:$E$1421,Documents!$A$2:$A$1421,$A8,Documents!$C$2:$C$1421,"dive_map")=0,"",maxifs(Documents!$E$2:$E$1421,Documents!$A$2:$A$1421,$A8,Documents!$C$2:$C$1421,"dive_map")),"") | I8: =IFERROR(IF(maxifs(Documents!$E$2:$E$1421,Documents!$A$2:$A$1421,$A8,Documents!$C$2:$C$1421,"spa_menu")=0,"",maxifs(Documents!$E$2:$E$1421,Documents!$A$2:$A$1421,$A8,Documents!$C$2:$C$1421,"spa_menu")),"") | J8: =IFERROR(IF(maxifs(Documents!$E$2:$E$1421,Documents!$A$2:$A$1421,$A8,Documents!$C$2:$C$1421,"dining_menu")=0,"",maxifs(Documents!$E$2:$E$1421,Documents!$A$2:$A$1421,$A8,Documents!$C$2:$C$1421,"dining_menu")),"") | K8: =IFERROR(IF(maxifs(Documents!$E$2:$E$1421,Documents!$A$2:$A$1421,$A8,Documents!$C$2:$C$1421,"dive_prices")=0,"",maxifs(Documents!$E$2:$E$1421,Documents!$A$2:$A$1421,$A8,Documents!$C$2:$C$1421,"dive_prices")),"") | L8: =IFERROR(IF(maxifs(Documents!$E$2:$E$1421,Documents!$A$2:$A$1421,$A8,Documents!$C$2:$C$1421,"excursions")=0,"",maxifs(Documents!$E$2:$E$1421,Documents!$A$2:$A$1421,$A8,Documents!$C$2:$C$1421,"excursions")),"") | M8: =IFERROR(IF(maxifs(Documents!$E$2:$E$1421,Documents!$A$2:$A$1421,$A8,Documents!$C$2:$C$1421,"kids")=0,"",maxifs(Documents!$E$2:$E$1421,Documents!$A$2:$A$1421,$A8,Documents!$C$2:$C$1421,"kids")),"") | N8: =IFERROR(IF(maxifs(Documents!$E$2:$E$1421,Documents!$A$2:$A$1421,$A8,Documents!$C$2:$C$1421,"villa_plans")=0,"",maxifs(Documents!$E$2:$E$1421,Documents!$A$2:$A$1421,$A8,Documents!$C$2:$C$1421,"villa_plans")),"") | O8: =IFERROR(IF(maxifs(Documents!$E$2:$E$1421,Documents!$A$2:$A$1421,$A8,Documents!$C$2:$C$1421,"all_inclusive")=0,"",maxifs(Documents!$E$2:$E$1421,Documents!$A$2:$A$1421,$A8,Documents!$C$2:$C$1421,"all_inclusive")),"") | P8: =IFERROR(IF(maxifs(Documents!$E$2:$E$1421,Documents!$A$2:$A$1421,$A8,Documents!$C$2:$C$1421,"sustainability")=0,"",maxifs(Documents!$E$2:$E$1421,Documents!$A$2:$A$1421,$A8,Documents!$C$2:$C$1421,"sustainability")),"") | Q8: =IFERROR(IF(maxifs(Documents!$E$2:$E$1421,Documents!$A$2:$A$1421,$A8,Documents!$C$2:$C$1421,"calendar")=0,"",maxifs(Documents!$E$2:$E$1421,Documents!$A$2:$A$1421,$A8,Documents!$C$2:$C$1421,"calendar")),"") | R8: =IFERROR(IF(maxifs(Documents!$E$2:$E$1421,Documents!$A$2:$A$1421,$A8,Documents!$C$2:$C$1421,"brochure")=0,"",maxifs(Documents!$E$2:$E$1421,Documents!$A$2:$A$1421,$A8,Documents!$C$2:$C$1421,"brochure")),"") | S8: =IFERROR(IF(maxifs(Documents!$E$2:$E$1421,Documents!$A$2:$A$1421,$A8,Documents!$C$2:$C$1421,"press_kit")=0,"",maxifs(Documents!$E$2:$E$1421,Documents!$A$2:$A$1421,$A8,Documents!$C$2:$C$1421,"press_kit")),"") | T8: =IFERROR(IF(maxifs(Documents!$E$2:$E$1421,Documents!$A$2:$A$1421,$A8,Documents!$C$2:$C$1421,"other")=0,"",maxifs(Documents!$E$2:$E$1421,Documents!$A$2:$A$1421,$A8,Documents!$C$2:$C$1421,"other")),"") | U8: =IFERROR(IF(maxifs(Documents!$E$2:$E$1421,Documents!$A$2:$A$1421,$A8,Documents!$C$2:$C$1421,"obsolete")=0,"",maxifs(Documents!$E$2:$E$1421,Documents!$A$2:$A$1421,$A8,Documents!$C$2:$C$1421,"obsolete")),"") | V8: =COUNTIFS(Documents!$A$2:$A$1421,$A8) -> 5 | W8: =COUNTIFS(Documents!$A$2:$A$1421,$A8,Documents!$R$2:$R$1421,"current") -> 3 | X8: =HYPERLINK("https://www.neoscapesmaldives.com/wp-content/uploads/JOALI-Maldives-Factsheet.pdf","2023_JOALI-Maldives-Factsheet.pdf") -> 2023_JOALI-Maldives-Factsheet.pdf | Y8: wedding, events
A9: 8 | B9: Hilton Maldives Amingiri Resort & Spa | C9: unverified | D9: =IFERROR(IF(maxifs(Documents!$E$2:$E$1421,Documents!$A$2:$A$1421,$A9,Documents!$C$2:$C$1421,"factsheet")=0,"",maxifs(Documents!$E$2:$E$1421,Documents!$A$2:$A$1421,$A9,Documents!$C$2:$C$1421,"factsheet")),"") | E9: =IFERROR(IF(maxifs(Documents!$E$2:$E$1421,Documents!$A$2:$A$1421,$A9,Documents!$C$2:$C$1421,"wedding")=0,"",maxifs(Documents!$E$2:$E$1421,Documents!$A$2:$A$1421,$A9,Documents!$C$2:$C$1421,"wedding")),"") | F9: =IFERROR(IF(maxifs(Documents!$E$2:$E$1421,Documents!$A$2:$A$1421,$A9,Documents!$C$2:$C$1421,"events")=0,"",maxifs(Documents!$E$2:$E$1421,Documents!$A$2:$A$1421,$A9,Documents!$C$2:$C$1421,"events")),"") | G9: =IFERROR(IF(maxifs(Documents!$E$2:$E$1421,Documents!$A$2:$A$1421,$A9,Documents!$C$2:$C$1421,"map")=0,"",maxifs(Documents!$E$2:$E$1421,Documents!$A$2:$A$1421,$A9,Documents!$C$2:$C$1421,"map")),"") | H9: =IFERROR(IF(maxifs(Documents!$E$2:$E$1421,Documents!$A$2:$A$1421,$A9,Documents!$C$2:$C$1421,"dive_map")=0,"",maxifs(Documents!$E$2:$E$1421,Documents!$A$2:$A$1421,$A9,Documents!$C$2:$C$1421,"dive_map")),"") | I9: =IFERROR(IF(maxifs(Documents!$E$2:$E$1421,Documents!$A$2:$A$1421,$A9,Documents!$C$2:$C$1421,"spa_menu")=0,"",maxifs(Documents!$E$2:$E$1421,Documents!$A$2:$A$1421,$A9,Documents!$C$2:$C$1421,"spa_menu")),"") | J9: =IFERROR(IF(maxifs(Documents!$E$2:$E$1421,Documents!$A$2:$A$1421,$A9,Documents!$C$2:$C$1421,"dining_menu")=0,"",maxifs(Documents!$E$2:$E$1421,Documents!$A$2:$A$1421,$A9,Documents!$C$2:$C$1421,"dining_menu")),"") | K9: =IFERROR(IF(maxifs(Documents!$E$2:$E$1421,Documents!$A$2:$A$1421,$A9,Documents!$C$2:$C$1421,"dive_prices")=0,"",maxifs(Documents!$E$2:$E$1421,Documents!$A$2:$A$1421,$A9,Documents!$C$2:$C$1421,"dive_prices")),"") | L9: =IFERROR(IF(maxifs(Documents!$E$2:$E$1421,Documents!$A$2:$A$1421,$A9,Documents!$C$2:$C$1421,"excursions")=0,"",maxifs(Documents!$E$2:$E$1421,Documents!$A$2:$A$1421,$A9,Documents!$C$2:$C$1421,"excursions")),"") | M9: =IFERROR(IF(maxifs(Documents!$E$2:$E$1421,Documents!$A$2:$A$1421,$A9,Documents!$C$2:$C$1421,"kids")=0,"",maxifs(Documents!$E$2:$E$1421,Documents!$A$2:$A$1421,$A9,Documents!$C$2:$C$1421,"kids")),"") | N9: =IFERROR(IF(maxifs(Documents!$E$2:$E$1421,Documents!$A$2:$A$1421,$A9,Documents!$C$2:$C$1421,"villa_plans")=0,"",maxifs(Documents!$E$2:$E$1421,Documents!$A$2:$A$1421,$A9,Documents!$C$2:$C$1421,"villa_plans")),"") | O9: =IFERROR(IF(maxifs(Documents!$E$2:$E$1421,Documents!$A$2:$A$1421,$A9,Documents!$C$2:$C$1421,"all_inclusive")=0,"",maxifs(Documents!$E$2:$E$1421,Documents!$A$2:$A$1421,$A9,Documents!$C$2:$C$1421,"all_inclusive")),"") | P9: =IFERROR(IF(maxifs(Documents!$E$2:$E$1421,Documents!$A$2:$A$1421,$A9,Documents!$C$2:$C$1421,"sustainability")=0,"",maxifs(Documents!$E$2:$E$1421,Documents!$A$2:$A$1421,$A9,Documents!$C$2:$C$1421,"sustainability")),"") | Q9: =IFERROR(IF(maxifs(Documents!$E$2:$E$1421,Documents!$A$2:$A$1421,$A9,Documents!$C$2:$C$1421,"calendar")=0,"",maxifs(Documents!$E$2:$E$1421,Documents!$A$2:$A$1421,$A9,Documents!$C$2:$C$1421,"calendar")),"") | R9: =IFERROR(IF(maxifs(Documents!$E$2:$E$1421,Documents!$A$2:$A$1421,$A9,Documents!$C$2:$C$1421,"brochure")=0,"",maxifs(Documents!$E$2:$E$1421,Documents!$A$2:$A$1421,$A9,Documents!$C$2:$C$1421,"brochure")),"") | S9: =IFERROR(IF(maxifs(Documents!$E$2:$E$1421,Documents!$A$2:$A$1421,$A9,Documents!$C$2:$C$1421,"press_kit")=0,"",maxifs(Documents!$E$2:$E$1421,Documents!$A$2:$A$1421,$A9,Documents!$C$2:$C$1421,"press_kit")),"") | T9: =IFERROR(IF(maxifs(Documents!$E$2:$E$1421,Documents!$A$2:$A$1421,$A9,Documents!$C$2:$C$1421,"other")=0,"",maxifs(Documents!$E$2:$E$1421,Documents!$A$2:$A$1421,$A9,Documents!$C$2:$C$1421,"other")),"") | U9: =IFERROR(IF(maxifs(Documents!$E$2:$E$1421,Documents!$A$2:$A$1421,$A9,Documents!$C$2:$C$1421,"obsolete")=0,"",maxifs(Documents!$E$2:$E$1421,Documents!$A$2:$A$1421,$A9,Documents!$C$2:$C$1421,"obsolete")),"") | V9: =COUNTIFS(Documents!$A$2:$A$1421,$A9) -> 3 | W9: =COUNTIFS(Documents!$A$2:$A$1421,$A9,Documents!$R$2:$R$1421,"current") -> 2 | X9: =HYPERLINK("https://www.neoscapesmaldives.com/wp-content/uploads/MLEAI_Factsheet-March-2025.pdf","2025_MLEAI_Factsheet-March-2025.pdf") -> 2025_MLEAI_Factsheet-March-2025.pdf | Y9: wedding, events
A10: 9 | B10: Amilla Fushi | C10: ok | D10: =IFERROR(IF(maxifs(Documents!$E$2:$E$1421,Documents!$A$2:$A$1421,$A10,Documents!$C$2:$C$1421,"factsheet")=0,"",maxifs(Documents!$E$2:$E$1421,Documents!$A$2:$A$1421,$A10,Documents!$C$2:$C$1421,"factsheet")),"") | E10: =IFERROR(IF(maxifs(Documents!$E$2:$E$1421,Documents!$A$2:$A$1421,$A10,Documents!$C$2:$C$1421,"wedding")=0,"",maxifs(Documents!$E$2:$E$1421,Documents!$A$2:$A$1421,$A10,Documents!$C$2:$C$1421,"wedding")),"") | F10: =IFERROR(IF(maxifs(Documents!$E$2:$E$1421,Documents!$A$2:$A$1421,$A10,Documents!$C$2:$C$1421,"events")=0,"",maxifs(Documents!$E$2:$E$1421,Documents!$A$2:$A$1421,$A10,Documents!$C$2:$C$1421,"events")),"") | G10: =IFERROR(IF(maxifs(Documents!$E$2:$E$1421,Documents!$A$2:$A$1421,$A10,Documents!$C$2:$C$1421,"map")=0,"",maxifs(Documents!$E$2:$E$1421,Documents!$A$2:$A$1421,$A10,Documents!$C$2:$C$1421,"map")),"") | H10: =IFERROR(IF(maxifs(Documents!$E$2:$E$1421,Documents!$A$2:$A$1421,$A10,Documents!$C$2:$C$1421,"dive_map")=0,"",maxifs(Documents!$E$2:$E$1421,Documents!$A$2:$A$1421,$A10,Documents!$C$2:$C$1421,"dive_map")),"") | I10: =IFERROR(IF(maxifs(Documents!$E$2:$E$1421,Documents!$A$2:$A$1421,$A10,Documents!$C$2:$C$1421,"spa_menu")=0,"",maxifs(Documents!$E$2:$E$1421,Documents!$A$2:$A$1421,$A10,Documents!$C$2:$C$1421,"spa_menu")),"") | J10: =IFERROR(IF(maxifs(Documents!$E$2:$E$1421,Documents!$A$2:$A$1421,$A10,Documents!$C$2:$C$1421,"dining_menu")=0,"",maxifs(Documents!$E$2:$E$1421,Documents!$A$2:$A$1421,$A10,Documents!$C$2:$C$1421,"dining_menu")),"") | K10: =IFERROR(IF(maxifs(Documents!$E$2:$E$1421,Documents!$A$2:$A$1421,$A10,Documents!$C$2:$C$1421,"dive_prices")=0,"",maxifs(Documents!$E$2:$E$1421,Documents!$A$2:$A$1421,$A10,Documents!$C$2:$C$1421,"dive_prices")),"") | L10: =IFERROR(IF(maxifs(Documents!$E$2:$E$1421,Documents!$A$2:$A$1421,$A10,Documents!$C$2:$C$1421,"excursions")=0,"",maxifs(Documents!$E$2:$E$1421,Documents!$A$2:$A$1421,$A10,Documents!$C$2:$C$1421,"excursions")),"") | M10: =IFERROR(IF(maxifs(Documents!$E$2:$E$1421,Documents!$A$2:$A$1421,$A10,Documents!$C$2:$C$1421,"kids")=0,"",maxifs(Documents!$E$2:$E$1421,Documents!$A$2:$A$1421,$A10,Documents!$C$2:$C$1421,"kids")),"") | N10: =IFERROR(IF(maxifs(Documents!$E$2:$E$1421,Documents!$A$2:$A$1421,$A10,Documents!$C$2:$C$1421,"villa_plans")=0,"",maxifs(Documents!$E$2:$E$1421,Documents!$A$2:$A$1421,$A10,Documents!$C$2:$C$1421,"villa_plans")),"") | O10: =IFERROR(IF(maxifs(Documents!$E$2:$E$1421,Documents!$A$2:$A$1421,$A10,Documents!$C$2:$C$1421,"all_inclusive")=0,"",maxifs(Documents!$E$2:$E$1421,Documents!$A$2:$A$1421,$A10,Documents!$C$2:$C$1421,"all_inclusive")),"") | P10: =IFERROR(IF(maxifs(Documents!$E$2:$E$1421,Documents!$A$2:$A$1421,$A10,Documents!$C$2:$C$1421,"sustainability")=0,"",maxifs(Documents!$E$2:$E$1421,Documents!$A$2:$A$1421,$A10,Documents!$C$2:$C$1421,"sustainability")),"") | Q10: =IFERROR(IF(maxifs(Documents!$E$2:$E$1421,Documents!$A$2:$A$1421,$A10,Documents!$C$2:$C$1421,"calendar")=0,"",maxifs(Documents!$E$2:$E$1421,Documents!$A$2:$A$1421,$A10,Documents!$C$2:$C$1421,"calendar")),"") | R10: =IFERROR(IF(maxifs(Documents!$E$2:$E$1421,Documents!$A$2:$A$1421,$A10,Documents!$C$2:$C$1421,"brochure")=0,"",maxifs(Documents!$E$2:$E$1421,Documents!$A$2:$A$1421,$A10,Documents!$C$2:$C$1421,"brochure")),"") | S10: =IFERROR(IF(maxifs(Documents!$E$2:$E$1421,Documents!$A$2:$A$1421,$A10,Documents!$C$2:$C$1421,"press_kit")=0,"",maxifs(Documents!$E$2:$E$1421,Documents!$A$2:$A$1421,$A10,Documents!$C$2:$C$1421,"press_kit")),"") | T10: =IFERROR(IF(maxifs(Documents!$E$2:$E$1421,Documents!$A$2:$A$1421,$A10,Documents!$C$2:$C$1421,"other")=0,"",maxifs(Documents!$E$2:$E$1421,Documents!$A$2:$A$1421,$A10,Documents!$C$2:$C$1421,"other")),"") | U10: =IFERROR(IF(maxifs(Documents!$E$2:$E$1421,Documents!$A$2:$A$1421,$A10,Documents!$C$2:$C$1421,"obsolete")=0,"",maxifs(Documents!$E$2:$E$1421,Documents!$A$2:$A$1421,$A10,Documents!$C$2:$C$1421,"obsolete")),"") | V10: =COUNTIFS(Documents!$A$2:$A$1421,$A10) -> 93 | W10: =COUNTIFS(Documents!$A$2:$A$1421,$A10,Documents!$R$2:$R$1421,"current") -> 43 | X10: =HYPERLINK("https://amilla.com/wp-content/uploads/Amilla-Maldives_Fact-Sheet_2026.pdf","2026_Amilla-Maldives_Fact-Sheet_2026.pdf") -> 2026_Amilla-Maldives_Fact-Sheet_2026.pdf | Y10: events
A11: 10 | B11: Dreamland - The Unique Sea & Lake Resort/Spa | C11: ok | D11: =IFERROR(IF(maxifs(Documents!$E$2:$E$1421,Documents!$A$2:$A$1421,$A11,Documents!$C$2:$C$1421,"factsheet")=0,"",maxifs(Documents!$E$2:$E$1421,Documents!$A$2:$A$1421,$A11,Documents!$C$2:$C$1421,"factsheet")),"") | E11: =IFERROR(IF(maxifs(Documents!$E$2:$E$1421,Documents!$A$2:$A$1421,$A11,Documents!$C$2:$C$1421,"wedding")=0,"",maxifs(Documents!$E$2:$E$1421,Documents!$A$2:$A$1421,$A11,Documents!$C$2:$C$1421,"wedding")),"") | F11: =IFERROR(IF(maxifs(Documents!$E$2:$E$1421,Documents!$A$2:$A$1421,$A11,Documents!$C$2:$C$1421,"events")=0,"",maxifs(Documents!$E$2:$E$1421,Documents!$A$2:$A$1421,$A11,Documents!$C$2:$C$1421,"events")),"") | G11: =IFERROR(IF(maxifs(Documents!$E$2:$E$1421,Documents!$A$2:$A$1421,$A11,Documents!$C$2:$C$1421,"map")=0,"",maxifs(Documents!$E$2:$E$1421,Documents!$A$2:$A$1421,$A11,Documents!$C$2:$C$1421,"map")),"") | H11: =IFERROR(IF(maxifs(Documents!$E$2:$E$1421,Documents!$A$2:$A$1421,$A11,Documents!$C$2:$C$1421,"dive_map")=0,"",maxifs(Documents!$E$2:$E$1421,Documents!$A$2:$A$1421,$A11,Documents!$C$2:$C$1421,"dive_map")),"") | I11: =IFERROR(IF(maxifs(Documents!$E$2:$E$1421,Documents!$A$2:$A$1421,$A11,Documents!$C$2:$C$1421,"spa_menu")=0,"",maxifs(Documents!$E$2:$E$1421,Documents!$A$2:$A$1421,$A11,Documents!$C$2:$C$1421,"spa_menu")),"") | J11: =IFERROR(IF(maxifs(Documents!$E$2:$E$1421,Documents!$A$2:$A$1421,$A11,Documents!$C$2:$C$1421,"dining_menu")=0,"",maxifs(Documents!$E$2:$E$1421,Documents!$A$2:$A$1421,$A11,Documents!$C$2:$C$1421,"dining_menu")),"") | K11: =IFERROR(IF(maxifs(Documents!$E$2:$E$1421,Documents!$A$2:$A$1421,$A11,Documents!$C$2:$C$1421,"dive_prices")=0,"",maxifs(Documents!$E$2:$E$1421,Documents!$A$2:$A$1421,$A11,Documents!$C$2:$C$1421,"dive_prices")),"") | L11: =IFERROR(IF(maxifs(Documents!$E$2:$E$1421,Documents!$A$2:$A$1421,$A11,Documents!$C$2:$C$1421,"excursions")=0,"",maxifs(Documents!$E$2:$E$1421,Documents!$A$2:$A$1421,$A11,Documents!$C$2:$C$1421,"excursions")),"") | M11: =IFERROR(IF(maxifs(Documents!$E$2:$E$1421,Documents!$A$2:$A$1421,$A11,Documents!$C$2:$C$1421,"kids")=0,"",maxifs(Documents!$E$2:$E$1421,Documents!$A$2:$A$1421,$A11,Documents!$C$2:$C$1421,"kids")),"") | N11: =IFERROR(IF(maxifs(Documents!$E$2:$E$1421,Documents!$A$2:$A$1421,$A11,Documents!$C$2:$C$1421,"villa_plans")=0,"",maxifs(Documents!$E$2:$E$1421,Documents!$A$2:$A$1421,$A11,Documents!$C$2:$C$1421,"villa_plans")),"") | O11: =IFERROR(IF(maxifs(Documents!$E$2:$E$1421,Documents!$A$2:$A$1421,$A11,Documents!$C$2:$C$1421,"all_inclusive")=0,"",maxifs(Documents!$E$2:$E$1421,Documents!$A$2:$A$1421,$A11,Documents!$C$2:$C$1421,"all_inclusive")),"") | P11: =IFERROR(IF(maxifs(Documents!$E$2:$E$1421,Documents!$A$2:$A$1421,$A11,Documents!$C$2:$C$1421,"sustainability")=0,"",maxifs(Documents!$E$2:$E$1421,Documents!$A$2:$A$1421,$A11,Documents!$C$2:$C$1421,"sustainability")),"") | Q11: =IFERROR(IF(maxifs(Documents!$E$2:$E$1421,Documents!$A$2:$A$1421,$A11,Documents!$C$2:$C$1421,"calendar")=0,"",maxifs(Documents!$E$2:$E$1421,Documents!$A$2:$A$1421,$A11,Documents!$C$2:$C$1421,"calendar")),"") | R11: =IFERROR(IF(maxifs(Documents!$E$2:$E$1421,Documents!$A$2:$A$1421,$A11,Documents!$C$2:$C$1421,"brochure")=0,"",maxifs(Documents!$E$2:$E$1421,Documents!$A$2:$A$1421,$A11,Documents!$C$2:$C$1421,"brochure")),"") | S11: =IFERROR(IF(maxifs(Documents!$E$2:$E$1421,Documents!$A$2:$A$1421,$A11,Documents!$C$2:$C$1421,"press_kit")=0,"",maxifs(Documents!$E$2:$E$1421,Documents!$A$2:$A$1421,$A11,Documents!$C$2:$C$1421,"press_kit")),"") | T11: =IFERROR(IF(maxifs(Documents!$E$2:$E$1421,Documents!$A$2:$A$1421,$A11,Documents!$C$2:$C$1421,"other")=0,"",maxifs(Documents!$E$2:$E$1421,Documents!$A$2:$A$1421,$A11,Documents!$C$2:$C$1421,"other")),"") | U11: =IFERROR(IF(maxifs(Documents!$E$2:$E$1421,Documents!$A$2:$A$1421,$A11,Documents!$C$2:$C$1421,"obsolete")=0,"",maxifs(Documents!$E$2:$E$1421,Documents!$A$2:$A$1421,$A11,Documents!$C$2:$C$1421,"obsolete")),"") | V11: =COUNTIFS(Documents!$A$2:$A$1421,$A11) -> 22 | W11: =COUNTIFS(Documents!$A$2:$A$1421,$A11,Documents!$R$2:$R$1421,"current") -> 0 | X11: =HYPERLINK("https://dreamland.com.mv/wp-content/uploads/2024/08/DREAMLAND-GENERAL-INFORMATION-GERMAN-2023.pdf","2023_DREAMLAND-GENERAL-INFORMATION-GERMA") -> 2023_DREAMLAND-GENERAL-INFORMATION-GERMA | Y11: events
A12: 11 | B12: Angaga Island Resort and Spa | C12: ok | D12: =IFERROR(IF(maxifs(Documents!$E$2:$E$1421,Documents!$A$2:$A$1421,$A12,Documents!$C$2:$C$1421,"factsheet")=0,"",maxifs(Documents!$E$2:$E$1421,Documents!$A$2:$A$1421,$A12,Documents!$C$2:$C$1421,"factsheet")),"") | E12: =IFERROR(IF(maxifs(Documents!$E$2:$E$1421,Documents!$A$2:$A$1421,$A12,Documents!$C$2:$C$1421,"wedding")=0,"",maxifs(Documents!$E$2:$E$1421,Documents!$A$2:$A$1421,$A12,Documents!$C$2:$C$1421,"wedding")),"") | F12: =IFERROR(IF(maxifs(Documents!$E$2:$E$1421,Documents!$A$2:$A$1421,$A12,Documents!$C$2:$C$1421,"events")=0,"",maxifs(Documents!$E$2:$E$1421,Documents!$A$2:$A$1421,$A12,Documents!$C$2:$C$1421,"events")),"") | G12: =IFERROR(IF(maxifs(Documents!$E$2:$E$1421,Documents!$A$2:$A$1421,$A12,Documents!$C$2:$C$1421,"map")=0,"",maxifs(Documents!$E$2:$E$1421,Documents!$A$2:$A$1421,$A12,Documents!$C$2:$C$1421,"map")),"") | H12: =IFERROR(IF(maxifs(Documents!$E$2:$E$1421,Documents!$A$2:$A$1421,$A12,Documents!$C$2:$C$1421,"dive_map")=0,"",maxifs(Documents!$E$2:$E$1421,Documents!$A$2:$A$1421,$A12,Documents!$C$2:$C$1421,"dive_map")),"") | I12: =IFERROR(IF(maxifs(Documents!$E$2:$E$1421,Documents!$A$2:$A$1421,$A12,Documents!$C$2:$C$1421,"spa_menu")=0,"",maxifs(Documents!$E$2:$E$1421,Documents!$A$2:$A$1421,$A12,Documents!$C$2:$C$1421,"spa_menu")),"") | J12: =IFERROR(IF(maxifs(Documents!$E$2:$E$1421,Documents!$A$2:$A$1421,$A12,Documents!$C$2:$C$1421,"dining_menu")=0,"",maxifs(Documents!$E$2:$E$1421,Documents!$A$2:$A$1421,$A12,Documents!$C$2:$C$1421,"dining_menu")),"") | K12: =IFERROR(IF(maxifs(Documents!$E$2:$E$1421,Documents!$A$2:$A$1421,$A12,Documents!$C$2:$C$1421,"dive_prices")=0,"",maxifs(Documents!$E$2:$E$1421,Documents!$A$2:$A$1421,$A12,Documents!$C$2:$C$1421,"dive_prices")),"") | L12: =IFERROR(IF(maxifs(Documents!$E$2:$E$1421,Documents!$A$2:$A$1421,$A12,Documents!$C$2:$C$1421,"excursions")=0,"",maxifs(Documents!$E$2:$E$1421,Documents!$A$2:$A$1421,$A12,Documents!$C$2:$C$1421,"excursions")),"") | M12: =IFERROR(IF(maxifs(Documents!$E$2:$E$1421,Documents!$A$2:$A$1421,$A12,Documents!$C$2:$C$1421,"kids")=0,"",maxifs(Documents!$E$2:$E$1421,Documents!$A$2:$A$1421,$A12,Documents!$C$2:$C$1421,"kids")),"") | N12: =IFERROR(IF(maxifs(Documents!$E$2:$E$1421,Documents!$A$2:$A$1421,$A12,Documents!$C$2:$C$1421,"villa_plans")=0,"",maxifs(Documents!$E$2:$E$1421,Documents!$A$2:$A$1421,$A12,Documents!$C$2:$C$1421,"villa_plans")),"") | O12: =IFERROR(IF(maxifs(Documents!$E$2:$E$1421,Documents!$A$2:$A$1421,$A12,Documents!$C$2:$C$1421,"all_inclusive")=0,"",maxifs(Documents!$E$2:$E$1421,Documents!$A$2:$A$1421,$A12,Documents!$C$2:$C$1421,"all_inclusive")),"") | P12: =IFERROR(IF(maxifs(Documents!$E$2:$E$1421,Documents!$A$2:$A$1421,$A12,Documents!$C$2:$C$1421,"sustainability")=0,"",maxifs(Documents!$E$2:$E$1421,Documents!$A$2:$A$1421,$A12,Documents!$C$2:$C$1421,"sustainability")),"") | Q12: =IFERROR(IF(maxifs(Documents!$E$2:$E$1421,Documents!$A$2:$A$1421,$A12,Documents!$C$2:$C$1421,"calendar")=0,"",maxifs(Documents!$E$2:$E$1421,Documents!$A$2:$A$1421,$A12,Documents!$C$2:$C$1421,"calendar")),"") | R12: =IFERROR(IF(maxifs(Documents!$E$2:$E$1421,Documents!$A$2:$A$1421,$A12,Documents!$C$2:$C$1421,"brochure")=0,"",maxifs(Documents!$E$2:$E$1421,Documents!$A$2:$A$1421,$A12,Documents!$C$2:$C$1421,"brochure")),"") | S12: =IFERROR(IF(maxifs(Documents!$E$2:$E$1421,Documents!$A$2:$A$1421,$A12,Documents!$C$2:$C$1421,"press_kit")=0,"",maxifs(Documents!$E$2:$E$1421,Documents!$A$2:$A$1421,$A12,Documents!$C$2:$C$1421,"press_kit")),"") | T12: =IFERROR(IF(maxifs(Documents!$E$2:$E$1421,Documents!$A$2:$A$1421,$A12,Documents!$C$2:$C$1421,"other")=0,"",maxifs(Documents!$E$2:$E$1421,Documents!$A$2:$A$1421,$A12,Documents!$C$2:$C$1421,"other")),"") | U12: =IFERROR(IF(maxifs(Documents!$E$2:$E$1421,Documents!$A$2:$A$1421,$A12,Documents!$C$2:$C$1421,"obsolete")=0,"",maxifs(Documents!$E$2:$E$1421,Documents!$A$2:$A$1421,$A12,Documents!$C$2:$C$1421,"obsolete")),"") | V12: =COUNTIFS(Documents!$A$2:$A$1421,$A12) -> 27 | W12: =COUNTIFS(Documents!$A$2:$A$1421,$A12,Documents!$R$2:$R$1421,"current") -> 5 | X12: =HYPERLINK("https://www.angaga.com.mv/wp-content/uploads/2018/12/GENERAL-INFORMATION.pdf","2018_GENERAL-INFORMATION.pdf") -> 2018_GENERAL-INFORMATION.pdf | Y12: events
A13: 12 | B13: Thulhagiri Island Resort & Spa | C13: ok | D13: =IFERROR(IF(maxifs(Documents!$E$2:$E$1421,Documents!$A$2:$A$1421,$A13,Documents!$C$2:$C$1421,"factsheet")=0,"",maxifs(Documents!$E$2:$E$1421,Documents!$A$2:$A$1421,$A13,Documents!$C$2:$C$1421,"factsheet")),"") | E13: =IFERROR(IF(maxifs(Documents!$E$2:$E$1421,Documents!$A$2:$A$1421,$A13,Documents!$C$2:$C$1421,"wedding")=0,"",maxifs(Documents!$E$2:$E$1421,Documents!$A$2:$A$1421,$A13,Documents!$C$2:$C$1421,"wedding")),"") | F13: =IFERROR(IF(maxifs(Documents!$E$2:$E$1421,Documents!$A$2:$A$1421,$A13,Documents!$C$2:$C$1421,"events")=0,"",maxifs(Documents!$E$2:$E$1421,Documents!$A$2:$A$1421,$A13,Documents!$C$2:$C$1421,"events")),"") | G13: =IFERROR(IF(maxifs(Documents!$E$2:$E$1421,Documents!$A$2:$A$1421,$A13,Documents!$C$2:$C$1421,"map")=0,"",maxifs(Documents!$E$2:$E$1421,Documents!$A$2:$A$1421,$A13,Documents!$C$2:$C$1421,"map")),"") | H13: =IFERROR(IF(maxifs(Documents!$E$2:$E$1421,Documents!$A$2:$A$1421,$A13,Documents!$C$2:$C$1421,"dive_map")=0,"",maxifs(Documents!$E$2:$E$1421,Documents!$A$2:$A$1421,$A13,Documents!$C$2:$C$1421,"dive_map")),"") | I13: =IFERROR(IF(maxifs(Documents!$E$2:$E$1421,Documents!$A$2:$A$1421,$A13,Documents!$C$2:$C$1421,"spa_menu")=0,"",maxifs(Documents!$E$2:$E$1421,Documents!$A$2:$A$1421,$A13,Documents!$C$2:$C$1421,"spa_menu")),"") | J13: =IFERROR(IF(maxifs(Documents!$E$2:$E$1421,Documents!$A$2:$A$1421,$A13,Documents!$C$2:$C$1421,"dining_menu")=0,"",maxifs(Documents!$E$2:$E$1421,Documents!$A$2:$A$1421,$A13,Documents!$C$2:$C$1421,"dining_menu")),"") | K13: =IFERROR(IF(maxifs(Documents!$E$2:$E$1421,Documents!$A$2:$A$1421,$A13,Documents!$C$2:$C$1421,"dive_prices")=0,"",maxifs(Documents!$E$2:$E$1421,Documents!$A$2:$A$1421,$A13,Documents!$C$2:$C$1421,"dive_prices")),"") | L13: =IFERROR(IF(maxifs(Documents!$E$2:$E$1421,Documents!$A$2:$A$1421,$A13,Documents!$C$2:$C$1421,"excursions")=0,"",maxifs(Documents!$E$2:$E$1421,Documents!$A$2:$A$1421,$A13,Documents!$C$2:$C$1421,"excursions")),"") | M13: =IFERROR(IF(maxifs(Documents!$E$2:$E$1421,Documents!$A$2:$A$1421,$A13,Documents!$C$2:$C$1421,"kids")=0,"",maxifs(Documents!$E$2:$E$1421,Documents!$A$2:$A$1421,$A13,Documents!$C$2:$C$1421,"kids")),"") | N13: =IFERROR(IF(maxifs(Documents!$E$2:$E$1421,Documents!$A$2:$A$1421,$A13,Documents!$C$2:$C$1421,"villa_plans")=0,"",maxifs(Documents!$E$2:$E$1421,Documents!$A$2:$A$1421,$A13,Documents!$C$2:$C$1421,"villa_plans")),"") | O13: =IFERROR(IF(maxifs(Documents!$E$2:$E$1421,Documents!$A$2:$A$1421,$A13,Documents!$C$2:$C$1421,"all_inclusive")=0,"",maxifs(Documents!$E$2:$E$1421,Documents!$A$2:$A$1421,$A13,Documents!$C$2:$C$1421,"all_inclusive")),"") | P13: =IFERROR(IF(maxifs(Documents!$E$2:$E$1421,Documents!$A$2:$A$1421,$A13,Documents!$C$2:$C$1421,"sustainability")=0,"",maxifs(Documents!$E$2:$E$1421,Documents!$A$2:$A$1421,$A13,Documents!$C$2:$C$1421,"sustainability")),"") | Q13: =IFERROR(IF(maxifs(Documents!$E$2:$E$1421,Documents!$A$2:$A$1421,$A13,Documents!$C$2:$C$1421,"calendar")=0,"",maxifs(Documents!$E$2:$E$1421,Documents!$A$2:$A$1421,$A13,Documents!$C$2:$C$1421,"calendar")),"") | R13: =IFERROR(IF(maxifs(Documents!$E$2:$E$1421,Documents!$A$2:$A$1421,$A13,Documents!$C$2:$C$1421,"brochure")=0,"",maxifs(Documents!$E$2:$E$1421,Documents!$A$2:$A$1421,$A13,Documents!$C$2:$C$1421,"brochure")),"") | S13: =IFERROR(IF(maxifs(Documents!$E$2:$E$1421,Documents!$A$2:$A$1421,$A13,Documents!$C$2:$C$1421,"press_kit")=0,"",maxifs(Documents!$E$2:$E$1421,Documents!$A$2:$A$1421,$A13,Documents!$C$2:$C$1421,"press_kit")),"") | T13: =IFERROR(IF(maxifs(Documents!$E$2:$E$1421,Documents!$A$2:$A$1421,$A13,Documents!$C$2:$C$1421,"other")=0,"",maxifs(Documents!$E$2:$E$1421,Documents!$A$2:$A$1421,$A13,Documents!$C$2:$C$1421,"other")),"") | U13: =IFERROR(IF(maxifs(Documents!$E$2:$E$1421,Documents!$A$2:$A$1421,$A13,Documents!$C$2:$C$1421,"obsolete")=0,"",maxifs(Documents!$E$2:$E$1421,Documents!$A$2:$A$1421,$A13,Documents!$C$2:$C$1421,"obsolete")),"") | V13: =COUNTIFS(Documents!$A$2:$A$1421,$A13) -> 19 | W13: =COUNTIFS(Documents!$A$2:$A$1421,$A13,Documents!$R$2:$R$1421,"current") -> 9 | Y13: factsheet, events
A14: 13 | B14: Sandies Bathala | C14: ok | D14: =IFERROR(IF(maxifs(Documents!$E$2:$E$1421,Documents!$A$2:$A$1421,$A14,Documents!$C$2:$C$1421,"factsheet")=0,"",maxifs(Documents!$E$2:$E$1421,Documents!$A$2:$A$1421,$A14,Documents!$C$2:$C$1421,"factsheet")),"") | E14: =IFERROR(IF(maxifs(Documents!$E$2:$E$1421,Documents!$A$2:$A$1421,$A14,Documents!$C$2:$C$1421,"wedding")=0,"",maxifs(Documents!$E$2:$E$1421,Documents!$A$2:$A$1421,$A14,Documents!$C$2:$C$1421,"wedding")),"") | F14: =IFERROR(IF(maxifs(Documents!$E$2:$E$1421,Documents!$A$2:$A$1421,$A14,Documents!$C$2:$C$1421,"events")=0,"",maxifs(Documents!$E$2:$E$1421,Documents!$A$2:$A$1421,$A14,Documents!$C$2:$C$1421,"events")),"") | G14: =IFERROR(IF(maxifs(Documents!$E$2:$E$1421,Documents!$A$2:$A$1421,$A14,Documents!$C$2:$C$1421,"map")=0,"",maxifs(Documents!$E$2:$E$1421,Documents!$A$2:$A$1421,$A14,Documents!$C$2:$C$1421,"map")),"") | H14: =IFERROR(IF(maxifs(Documents!$E$2:$E$1421,Documents!$A$2:$A$1421,$A14,Documents!$C$2:$C$1421,"dive_map")=0,"",maxifs(Documents!$E$2:$E$1421,Documents!$A$2:$A$1421,$A14,Documents!$C$2:$C$1421,"dive_map")),"") | I14: =IFERROR(IF(maxifs(Documents!$E$2:$E$1421,Documents!$A$2:$A$1421,$A14,Documents!$C$2:$C$1421,"spa_menu")=0,"",maxifs(Documents!$E$2:$E$1421,Documents!$A$2:$A$1421,$A14,Documents!$C$2:$C$1421,"spa_menu")),"") | J14: =IFERROR(IF(maxifs(Documents!$E$2:$E$1421,Documents!$A$2:$A$1421,$A14,Documents!$C$2:$C$1421,"dining_menu")=0,"",maxifs(Documents!$E$2:$E$1421,Documents!$A$2:$A$1421,$A14,Documents!$C$2:$C$1421,"dining_menu")),"") | K14: =IFERROR(IF(maxifs(Documents!$E$2:$E$1421,Documents!$A$2:$A$1421,$A14,Documents!$C$2:$C$1421,"dive_prices")=0,"",maxifs(Documents!$E$2:$E$1421,Documents!$A$2:$A$1421,$A14,Documents!$C$2:$C$1421,"dive_prices")),"") | L14: =IFERROR(IF(maxifs(Documents!$E$2:$E$1421,Documents!$A$2:$A$1421,$A14,Documents!$C$2:$C$1421,"excursions")=0,"",maxifs(Documents!$E$2:$E$1421,Documents!$A$2:$A$1421,$A14,Documents!$C$2:$C$1421,"excursions")),"") | M14: =IFERROR(IF(maxifs(Documents!$E$2:$E$1421,Documents!$A$2:$A$1421,$A14,Documents!$C$2:$C$1421,"kids")=0,"",maxifs(Documents!$E$2:$E$1421,Documents!$A$2:$A$1421,$A14,Documents!$C$2:$C$1421,"kids")),"") | N14: =IFERROR(IF(maxifs(Documents!$E$2:$E$1421,Documents!$A$2:$A$1421,$A14,Documents!$C$2:$C$1421,"villa_plans")=0,"",maxifs(Documents!$E$2:$E$1421,Documents!$A$2:$A$1421,$A14,Documents!$C$2:$C$1421,"villa_plans")),"") | O14: =IFERROR(IF(maxifs(Documents!$E$2:$E$1421,Documents!$A$2:$A$1421,$A14,Documents!$C$2:$C$1421,"all_inclusive")=0,"",maxifs(Documents!$E$2:$E$1421,Documents!$A$2:$A$1421,$A14,Documents!$C$2:$C$1421,"all_inclusive")),"") | P14: =IFERROR(IF(maxifs(Documents!$E$2:$E$1421,Documents!$A$2:$A$1421,$A14,Documents!$C$2:$C$1421,"sustainability")=0,"",maxifs(Documents!$E$2:$E$1421,Documents!$A$2:$A$1421,$A14,Documents!$C$2:$C$1421,"sustainability")),"") | Q14: =IFERROR(IF(maxifs(Documents!$E$2:$E$1421,Documents!$A$2:$A$1421,$A14,Documents!$C$2:$C$1421,"calendar")=0,"",maxifs(Documents!$E$2:$E$1421,Documents!$A$2:$A$1421,$A14,Documents!$C$2:$C$1421,"calendar")),"") | R14: =IFERROR(IF(maxifs(Documents!$E$2:$E$1421,Documents!$A$2:$A$1421,$A14,Documents!$C$2:$C$1421,"brochure")=0,"",maxifs(Documents!$E$2:$E$1421,Documents!$A$2:$A$1421,$A14,Documents!$C$2:$C$1421,"brochure")),"") | S14: =IFERROR(IF(maxifs(Documents!$E$2:$E$1421,Documents!$A$2:$A$1421,$A14,Documents!$C$2:$C$1421,"press_kit")=0,"",maxifs(Documents!$E$2:$E$1421,Documents!$A$2:$A$1421,$A14,Documents!$C$2:$C$1421,"press_kit")),"") | T14: =IFERROR(IF(maxifs(Documents!$E$2:$E$1421,Documents!$A$2:$A$1421,$A14,Documents!$C$2:$C$1421,"other")=0,"",maxifs(Documents!$E$2:$E$1421,Documents!$A$2:$A$1421,$A14,Documents!$C$2:$C$1421,"other")),"") | U14: =IFERROR(IF(maxifs(Documents!$E$2:$E$1421,Documents!$A$2:$A$1421,$A14,Documents!$C$2:$C$1421,"obsolete")=0,"",maxifs(Documents!$E$2:$E$1421,Documents!$A$2:$A$1421,$A14,Documents!$C$2:$C$1421,"obsolete")),"") | V14: =COUNTIFS(Documents!$A$2:$A$1421,$A14) -> 33 | W14: =COUNTIFS(Documents!$A$2:$A$1421,$A14,Documents!$R$2:$R$1421,"current") -> 2 | Y14: factsheet, wedding
A15: 14 | B15: Baglioni Resort Maldives | C15: blocked | D15: =IFERROR(IF(maxifs(Documents!$E$2:$E$1421,Documents!$A$2:$A$1421,$A15,Documents!$C$2:$C$1421,"factsheet")=0,"",maxifs(Documents!$E$2:$E$1421,Documents!$A$2:$A$1421,$A15,Documents!$C$2:$C$1421,"factsheet")),"") | E15: =IFERROR(IF(maxifs(Documents!$E$2:$E$1421,Documents!$A$2:$A$1421,$A15,Documents!$C$2:$C$1421,"wedding")=0,"",maxifs(Documents!$E$2:$E$1421,Documents!$A$2:$A$1421,$A15,Documents!$C$2:$C$1421,"wedding")),"") | F15: =IFERROR(IF(maxifs(Documents!$E$2:$E$1421,Documents!$A$2:$A$1421,$A15,Documents!$C$2:$C$1421,"events")=0,"",maxifs(Documents!$E$2:$E$1421,Documents!$A$2:$A$1421,$A15,Documents!$C$2:$C$1421,"events")),"") | G15: =IFERROR(IF(maxifs(Documents!$E$2:$E$1421,Documents!$A$2:$A$1421,$A15,Documents!$C$2:$C$1421,"map")=0,"",maxifs(Documents!$E$2:$E$1421,Documents!$A$2:$A$1421,$A15,Documents!$C$2:$C$1421,"map")),"") | H15: =IFERROR(IF(maxifs(Documents!$E$2:$E$1421,Documents!$A$2:$A$1421,$A15,Documents!$C$2:$C$1421,"dive_map")=0,"",maxifs(Documents!$E$2:$E$1421,Documents!$A$2:$A$1421,$A15,Documents!$C$2:$C$1421,"dive_map")),"") | I15: =IFERROR(IF(maxifs(Documents!$E$2:$E$1421,Documents!$A$2:$A$1421,$A15,Documents!$C$2:$C$1421,"spa_menu")=0,"",maxifs(Documents!$E$2:$E$1421,Documents!$A$2:$A$1421,$A15,Documents!$C$2:$C$1421,"spa_menu")),"") | J15: =IFERROR(IF(maxifs(Documents!$E$2:$E$1421,Documents!$A$2:$A$1421,$A15,Documents!$C$2:$C$1421,"dining_menu")=0,"",maxifs(Documents!$E$2:$E$1421,Documents!$A$2:$A$1421,$A15,Documents!$C$2:$C$1421,"dining_menu")),"") | K15: =IFERROR(IF(maxifs(Documents!$E$2:$E$1421,Documents!$A$2:$A$1421,$A15,Documents!$C$2:$C$1421,"dive_prices")=0,"",maxifs(Documents!$E$2:$E$1421,Documents!$A$2:$A$1421,$A15,Documents!$C$2:$C$1421,"dive_prices")),"") | L15: =IFERROR(IF(maxifs(Documents!$E$2:$E$1421,Documents!$A$2:$A$1421,$A15,Documents!$C$2:$C$1421,"excursions")=0,"",maxifs(Documents!$E$2:$E$1421,Documents!$A$2:$A$1421,$A15,Documents!$C$2:$C$1421,"excursions")),"") | M15: =IFERROR(IF(maxifs(Documents!$E$2:$E$1421,Documents!$A$2:$A$1421,$A15,Documents!$C$2:$C$1421,"kids")=0,"",maxifs(Documents!$E$2:$E$1421,Documents!$A$2:$A$1421,$A15,Documents!$C$2:$C$1421,"kids")),"") | N15: =IFERROR(IF(maxifs(Documents!$E$2:$E$1421,Documents!$A$2:$A$1421,$A15,Documents!$C$2:$C$1421,"villa_plans")=0,"",maxifs(Documents!$E$2:$E$1421,Documents!$A$2:$A$1421,$A15,Documents!$C$2:$C$1421,"villa_plans")),"") | O15: =IFERROR(IF(maxifs(Documents!$E$2:$E$1421,Documents!$A$2:$A$1421,$A15,Documents!$C$2:$C$1421,"all_inclusive")=0,"",maxifs(Documents!$E$2:$E$1421,Documents!$A$2:$A$1421,$A15,Documents!$C$2:$C$1421,"all_inclusive")),"") | P15: =IFERROR(IF(maxifs(Documents!$E$2:$E$1421,Documents!$A$2:$A$1421,$A15,Documents!$C$2:$C$1421,"sustainability")=0,"",maxifs(Documents!$E$2:$E$1421,Documents!$A$2:$A$1421,$A15,Documents!$C$2:$C$1421,"sustainability")),"") | Q15: =IFERROR(IF(maxifs(Documents!$E$2:$E$1421,Documents!$A$2:$A$1421,$A15,Documents!$C$2:$C$1421,"calendar")=0,"",maxifs(Documents!$E$2:$E$1421,Documents!$A$2:$A$1421,$A15,Documents!$C$2:$C$1421,"calendar")),"") | R15: =IFERROR(IF(maxifs(Documents!$E$2:$E$1421,Documents!$A$2:$A$1421,$A15,Documents!$C$2:$C$1421,"brochure")=0,"",maxifs(Documents!$E$2:$E$1421,Documents!$A$2:$A$1421,$A15,Documents!$C$2:$C$1421,"brochure")),"") | S15: =IFERROR(IF(maxifs(Documents!$E$2:$E$1421,Documents!$A$2:$A$1421,$A15,Documents!$C$2:$C$1421,"press_kit")=0,"",maxifs(Documents!$E$2:$E$1421,Documents!$A$2:$A$1421,$A15,Documents!$C$2:$C$1421,"press_kit")),"") | T15: =IFERROR(IF(maxifs(Documents!$E$2:$E$1421,Documents!$A$2:$A$1421,$A15,Documents!$C$2:$C$1421,"other")=0,"",maxifs(Documents!$E$2:$E$1421,Documents!$A$2:$A$1421,$A15,Documents!$C$2:$C$1421,"other")),"") | U15: =IFERROR(IF(maxifs(Documents!$E$2:$E$1421,Documents!$A$2:$A$1421,$A15,Documents!$C$2:$C$1421,"obsolete")=0,"",maxifs(Documents!$E$2:$E$1421,Documents!$A$2:$A$1421,$A15,Documents!$C$2:$C$1421,"obsolete")),"") | V15: =COUNTIFS(Documents!$A$2:$A$1421,$A15) -> 0 | W15: =COUNTIFS(Documents!$A$2:$A$1421,$A15,Documents!$R$2:$R$1421,"current") -> 0 | Y15: factsheet, wedding, events
A16: 15 | B16: Alila Kothaifaru Maldives | C16: blocked | D16: =IFERROR(IF(maxifs(Documents!$E$2:$E$1421,Documents!$A$2:$A$1421,$A16,Documents!$C$2:$C$1421,"factsheet")=0,"",maxifs(Documents!$E$2:$E$1421,Documents!$A$2:$A$1421,$A16,Documents!$C$2:$C$1421,"factsheet")),"") | E16: =IFERROR(IF(maxifs(Documents!$E$2:$E$1421,Documents!$A$2:$A$1421,$A16,Documents!$C$2:$C$1421,"wedding")=0,"",maxifs(Documents!$E$2:$E$1421,Documents!$A$2:$A$1421,$A16,Documents!$C$2:$C$1421,"wedding")),"") | F16: =IFERROR(IF(maxifs(Documents!$E$2:$E$1421,Documents!$A$2:$A$1421,$A16,Documents!$C$2:$C$1421,"events")=0,"",maxifs(Documents!$E$2:$E$1421,Documents!$A$2:$A$1421,$A16,Documents!$C$2:$C$1421,"events")),"") | G16: =IFERROR(IF(maxifs(Documents!$E$2:$E$1421,Documents!$A$2:$A$1421,$A16,Documents!$C$2:$C$1421,"map")=0,"",maxifs(Documents!$E$2:$E$1421,Documents!$A$2:$A$1421,$A16,Documents!$C$2:$C$1421,"map")),"") | H16: =IFERROR(IF(maxifs(Documents!$E$2:$E$1421,Documents!$A$2:$A$1421,$A16,Documents!$C$2:$C$1421,"dive_map")=0,"",maxifs(Documents!$E$2:$E$1421,Documents!$A$2:$A$1421,$A16,Documents!$C$2:$C$1421,"dive_map")),"") | I16: =IFERROR(IF(maxifs(Documents!$E$2:$E$1421,Documents!$A$2:$A$1421,$A16,Documents!$C$2:$C$1421,"spa_menu")=0,"",maxifs(Documents!$E$2:$E$1421,Documents!$A$2:$A$1421,$A16,Documents!$C$2:$C$1421,"spa_menu")),"") | J16: =IFERROR(IF(maxifs(Documents!$E$2:$E$1421,Documents!$A$2:$A$1421,$A16,Documents!$C$2:$C$1421,"dining_menu")=0,"",maxifs(Documents!$E$2:$E$1421,Documents!$A$2:$A$1421,$A16,Documents!$C$2:$C$1421,"dining_menu")),"") | K16: =IFERROR(IF(maxifs(Documents!$E$2:$E$1421,Documents!$A$2:$A$1421,$A16,Documents!$C$2:$C$1421,"dive_prices")=0,"",maxifs(Documents!$E$2:$E$1421,Documents!$A$2:$A$1421,$A16,Documents!$C$2:$C$1421,"dive_prices")),"") | L16: =IFERROR(IF(maxifs(Documents!$E$2:$E$1421,Documents!$A$2:$A$1421,$A16,Documents!$C$2:$C$1421,"excursions")=0,"",maxifs(Documents!$E$2:$E$1421,Documents!$A$2:$A$1421,$A16,Documents!$C$2:$C$1421,"excursions")),"") | M16: =IFERROR(IF(maxifs(Documents!$E$2:$E$1421,Documents!$A$2:$A$1421,$A16,Documents!$C$2:$C$1421,"kids")=0,"",maxifs(Documents!$E$2:$E$1421,Documents!$A$2:$A$1421,$A16,Documents!$C$2:$C$1421,"kids")),"") | N16: =IFERROR(IF(maxifs(Documents!$E$2:$E$1421,Documents!$A$2:$A$1421,$A16,Documents!$C$2:$C$1421,"villa_plans")=0,"",maxifs(Documents!$E$2:$E$1421,Documents!$A$2:$A$1421,$A16,Documents!$C$2:$C$1421,"villa_plans")),"") | O16: =IFERROR(IF(maxifs(Documents!$E$2:$E$1421,Documents!$A$2:$A$1421,$A16,Documents!$C$2:$C$1421,"all_inclusive")=0,"",maxifs(Documents!$E$2:$E$1421,Documents!$A$2:$A$1421,$A16,Documents!$C$2:$C$1421,"all_inclusive")),"") | P16: =IFERROR(IF(maxifs(Documents!$E$2:$E$1421,Documents!$A$2:$A$1421,$A16,Documents!$C$2:$C$1421,"sustainability")=0,"",maxifs(Documents!$E$2:$E$1421,Documents!$A$2:$A$1421,$A16,Documents!$C$2:$C$1421,"sustainability")),"") | Q16: =IFERROR(IF(maxifs(Documents!$E$2:$E$1421,Documents!$A$2:$A$1421,$A16,Documents!$C$2:$C$1421,"calendar")=0,"",maxifs(Documents!$E$2:$E$1421,Documents!$A$2:$A$1421,$A16,Documents!$C$2:$C$1421,"calendar")),"") | R16: =IFERROR(IF(maxifs(Documents!$E$2:$E$1421,Documents!$A$2:$A$1421,$A16,Documents!$C$2:$C$1421,"brochure")=0,"",maxifs(Documents!$E$2:$E$1421,Documents!$A$2:$A$1421,$A16,Documents!$C$2:$C$1421,"brochure")),"") | S16: =IFERROR(IF(maxifs(Documents!$E$2:$E$1421,Documents!$A$2:$A$1421,$A16,Documents!$C$2:$C$1421,"press_kit")=0,"",maxifs(Documents!$E$2:$E$1421,Documents!$A$2:$A$1421,$A16,Documents!$C$2:$C$1421,"press_kit")),"") | T16: =IFERROR(IF(maxifs(Documents!$E$2:$E$1421,Documents!$A$2:$A$1421,$A16,Documents!$C$2:$C$1421,"other")=0,"",maxifs(Documents!$E$2:$E$1421,Documents!$A$2:$A$1421,$A16,Documents!$C$2:$C$1421,"other")),"") | U16: =IFERROR(IF(maxifs(Documents!$E$2:$E$1421,Documents!$A$2:$A$1421,$A16,Documents!$C$2:$C$1421,"obsolete")=0,"",maxifs(Documents!$E$2:$E$1421,Documents!$A$2:$A$1421,$A16,Documents!$C$2:$C$1421,"obsolete")),"") | V16: =COUNTIFS(Documents!$A$2:$A$1421,$A16) -> 2 | W16: =COUNTIFS(Documents!$A$2:$A$1421,$A16,Documents!$R$2:$R$1421,"current") -> 0 | X16: =HYPERLINK("https://www.neoscapesmaldives.com/wp-content/uploads/Alila-Kothaifaru-Maldives-Factsheet-2022.pdf","2022_Alila-Kothaifaru-Maldives-Factsheet") -> 2022_Alila-Kothaifaru-Maldives-Factsheet | Y16: wedding, events
A17: 16 | B17: JW Marriott Kaafu Atoll Island Resort | C17: blocked | D17: =IFERROR(IF(maxifs(Documents!$E$2:$E$1421,Documents!$A$2:$A$1421,$A17,Documents!$C$2:$C$1421,"factsheet")=0,"",maxifs(Documents!$E$2:$E$1421,Documents!$A$2:$A$1421,$A17,Documents!$C$2:$C$1421,"factsheet")),"") | E17: =IFERROR(IF(maxifs(Documents!$E$2:$E$1421,Documents!$A$2:$A$1421,$A17,Documents!$C$2:$C$1421,"wedding")=0,"",maxifs(Documents!$E$2:$E$1421,Documents!$A$2:$A$1421,$A17,Documents!$C$2:$C$1421,"wedding")),"") | F17: =IFERROR(IF(maxifs(Documents!$E$2:$E$1421,Documents!$A$2:$A$1421,$A17,Documents!$C$2:$C$1421,"events")=0,"",maxifs(Documents!$E$2:$E$1421,Documents!$A$2:$A$1421,$A17,Documents!$C$2:$C$1421,"events")),"") | G17: =IFERROR(IF(maxifs(Documents!$E$2:$E$1421,Documents!$A$2:$A$1421,$A17,Documents!$C$2:$C$1421,"map")=0,"",maxifs(Documents!$E$2:$E$1421,Documents!$A$2:$A$1421,$A17,Documents!$C$2:$C$1421,"map")),"") | H17: =IFERROR(IF(maxifs(Documents!$E$2:$E$1421,Documents!$A$2:$A$1421,$A17,Documents!$C$2:$C$1421,"dive_map")=0,"",maxifs(Documents!$E$2:$E$1421,Documents!$A$2:$A$1421,$A17,Documents!$C$2:$C$1421,"dive_map")),"") | I17: =IFERROR(IF(maxifs(Documents!$E$2:$E$1421,Documents!$A$2:$A$1421,$A17,Documents!$C$2:$C$1421,"spa_menu")=0,"",maxifs(Documents!$E$2:$E$1421,Documents!$A$2:$A$1421,$A17,Documents!$C$2:$C$1421,"spa_menu")),"") | J17: =IFERROR(IF(maxifs(Documents!$E$2:$E$1421,Documents!$A$2:$A$1421,$A17,Documents!$C$2:$C$1421,"dining_menu")=0,"",maxifs(Documents!$E$2:$E$1421,Documents!$A$2:$A$1421,$A17,Documents!$C$2:$C$1421,"dining_menu")),"") | K17: =IFERROR(IF(maxifs(Documents!$E$2:$E$1421,Documents!$A$2:$A$1421,$A17,Documents!$C$2:$C$1421,"dive_prices")=0,"",maxifs(Documents!$E$2:$E$1421,Documents!$A$2:$A$1421,$A17,Documents!$C$2:$C$1421,"dive_prices")),"") | L17: =IFERROR(IF(maxifs(Documents!$E$2:$E$1421,Documents!$A$2:$A$1421,$A17,Documents!$C$2:$C$1421,"excursions")=0,"",maxifs(Documents!$E$2:$E$1421,Documents!$A$2:$A$1421,$A17,Documents!$C$2:$C$1421,"excursions")),"") | M17: =IFERROR(IF(maxifs(Documents!$E$2:$E$1421,Documents!$A$2:$A$1421,$A17,Documents!$C$2:$C$1421,"kids")=0,"",maxifs(Documents!$E$2:$E$1421,Documents!$A$2:$A$1421,$A17,Documents!$C$2:$C$1421,"kids")),"") | N17: =IFERROR(IF(maxifs(Documents!$E$2:$E$1421,Documents!$A$2:$A$1421,$A17,Documents!$C$2:$C$1421,"villa_plans")=0,"",maxifs(Documents!$E$2:$E$1421,Documents!$A$2:$A$1421,$A17,Documents!$C$2:$C$1421,"villa_plans")),"") | O17: =IFERROR(IF(maxifs(Documents!$E$2:$E$1421,Documents!$A$2:$A$1421,$A17,Documents!$C$2:$C$1421,"all_inclusive")=0,"",maxifs(Documents!$E$2:$E$1421,Documents!$A$2:$A$1421,$A17,Documents!$C$2:$C$1421,"all_inclusive")),"") | P17: =IFERROR(IF(maxifs(Documents!$E$2:$E$1421,Documents!$A$2:$A$1421,$A17,Documents!$C$2:$C$1421,"sustainability")=0,"",maxifs(Documents!$E$2:$E$1421,Documents!$A$2:$A$1421,$A17,Documents!$C$2:$C$1421,"sustainability")),"") | Q17: =IFERROR(IF(maxifs(Documents!$E$2:$E$1421,Documents!$A$2:$A$1421,$A17,Documents!$C$2:$C$1421,"calendar")=0,"",maxifs(Documents!$E$2:$E$1421,Documents!$A$2:$A$1421,$A17,Documents!$C$2:$C$1421,"calendar")),"") | R17: =IFERROR(IF(maxifs(Documents!$E$2:$E$1421,Documents!$A$2:$A$1421,$A17,Documents!$C$2:$C$1421,"brochure")=0,"",maxifs(Documents!$E$2:$E$1421,Documents!$A$2:$A$1421,$A17,Documents!$C$2:$C$1421,"brochure")),"") | S17: =IFERROR(IF(maxifs(Documents!$E$2:$E$1421,Documents!$A$2:$A$1421,$A17,Documents!$C$2:$C$1421,"press_kit")=0,"",maxifs(Documents!$E$2:$E$1421,Documents!$A$2:$A$1421,$A17,Documents!$C$2:$C$1421,"press_kit")),"") | T17: =IFERROR(IF(maxifs(Documents!$E$2:$E$1421,Documents!$A$2:$A$1421,$A17,Documents!$C$2:$C$1421,"other")=0,"",maxifs(Documents!$E$2:$E$1421,Documents!$A$2:$A$1421,$A17,Documents!$C$2:$C$1421,"other")),"") | U17: =IFERROR(IF(maxifs(Documents!$E$2:$E$1421,Documents!$A$2:$A$1421,$A17,Documents!$C$2:$C$1421,"obsolete")=0,"",maxifs(Documents!$E$2:$E$1421,Documents!$A$2:$A$1421,$A17,Documents!$C$2:$C$1421,"obsolete")),"") | V17: =COUNTIFS(Documents!$A$2:$A$1421,$A17) -> 2 | W17: =COUNTIFS(Documents!$A$2:$A$1421,$A17,Documents!$R$2:$R$1421,"current") -> 0 | Y17: factsheet, wedding, events
A18: 17 | B18: Rihiveli Maldives Resort | C18: unverified | D18: =IFERROR(IF(maxifs(Documents!$E$2:$E$1421,Documents!$A$2:$A$1421,$A18,Documents!$C$2:$C$1421,"factsheet")=0,"",maxifs(Documents!$E$2:$E$1421,Documents!$A$2:$A$1421,$A18,Documents!$C$2:$C$1421,"factsheet")),"") | E18: =IFERROR(IF(maxifs(Documents!$E$2:$E$1421,Documents!$A$2:$A$1421,$A18,Documents!$C$2:$C$1421,"wedding")=0,"",maxifs(Documents!$E$2:$E$1421,Documents!$A$2:$A$1421,$A18,Documents!$C$2:$C$1421,"wedding")),"") | F18: =IFERROR(IF(maxifs(Documents!$E$2:$E$1421,Documents!$A$2:$A$1421,$A18,Documents!$C$2:$C$1421,"events")=0,"",maxifs(Documents!$E$2:$E$1421,Documents!$A$2:$A$1421,$A18,Documents!$C$2:$C$1421,"events")),"") | G18: =IFERROR(IF(maxifs(Documents!$E$2:$E$1421,Documents!$A$2:$A$1421,$A18,Documents!$C$2:$C$1421,"map")=0,"",maxifs(Documents!$E$2:$E$1421,Documents!$A$2:$A$1421,$A18,Documents!$C$2:$C$1421,"map")),"") | H18: =IFERROR(IF(maxifs(Documents!$E$2:$E$1421,Documents!$A$2:$A$1421,$A18,Documents!$C$2:$C$1421,"dive_map")=0,"",maxifs(Documents!$E$2:$E$1421,Documents!$A$2:$A$1421,$A18,Documents!$C$2:$C$1421,"dive_map")),"") | I18: =IFERROR(IF(maxifs(Documents!$E$2:$E$1421,Documents!$A$2:$A$1421,$A18,Documents!$C$2:$C$1421,"spa_menu")=0,"",maxifs(Documents!$E$2:$E$1421,Documents!$A$2:$A$1421,$A18,Documents!$C$2:$C$1421,"spa_menu")),"") | J18: =IFERROR(IF(maxifs(Documents!$E$2:$E$1421,Documents!$A$2:$A$1421,$A18,Documents!$C$2:$C$1421,"dining_menu")=0,"",maxifs(Documents!$E$2:$E$1421,Documents!$A$2:$A$1421,$A18,Documents!$C$2:$C$1421,"dining_menu")),"") | K18: =IFERROR(IF(maxifs(Documents!$E$2:$E$1421,Documents!$A$2:$A$1421,$A18,Documents!$C$2:$C$1421,"dive_prices")=0,"",maxifs(Documents!$E$2:$E$1421,Documents!$A$2:$A$1421,$A18,Documents!$C$2:$C$1421,"dive_prices")),"") | L18: =IFERROR(IF(maxifs(Documents!$E$2:$E$1421,Documents!$A$2:$A$1421,$A18,Documents!$C$2:$C$1421,"excursions")=0,"",maxifs(Documents!$E$2:$E$1421,Documents!$A$2:$A$1421,$A18,Documents!$C$2:$C$1421,"excursions")),"") | M18: =IFERROR(IF(maxifs(Documents!$E$2:$E$1421,Documents!$A$2:$A$1421,$A18,Documents!$C$2:$C$1421,"kids")=0,"",maxifs(Documents!$E$2:$E$1421,Documents!$A$2:$A$1421,$A18,Documents!$C$2:$C$1421,"kids")),"") | N18: =IFERROR(IF(maxifs(Documents!$E$2:$E$1421,Documents!$A$2:$A$1421,$A18,Documents!$C$2:$C$1421,"villa_plans")=0,"",maxifs(Documents!$E$2:$E$1421,Documents!$A$2:$A$1421,$A18,Documents!$C$2:$C$1421,"villa_plans")),"") | O18: =IFERROR(IF(maxifs(Documents!$E$2:$E$1421,Documents!$A$2:$A$1421,$A18,Documents!$C$2:$C$1421,"all_inclusive")=0,"",maxifs(Documents!$E$2:$E$1421,Documents!$A$2:$A$1421,$A18,Documents!$C$2:$C$1421,"all_inclusive")),"") | P18: =IFERROR(IF(maxifs(Documents!$E$2:$E$1421,Documents!$A$2:$A$1421,$A18,Documents!$C$2:$C$1421,"sustainability")=0,"",maxifs(Documents!$E$2:$E$1421,Documents!$A$2:$A$1421,$A18,Documents!$C$2:$C$1421,"sustainability")),"") | Q18: =IFERROR(IF(maxifs(Documents!$E$2:$E$1421,Documents!$A$2:$A$1421,$A18,Documents!$C$2:$C$1421,"calendar")=0,"",maxifs(Documents!$E$2:$E$1421,Documents!$A$2:$A$1421,$A18,Documents!$C$2:$C$1421,"calendar")),"") | R18: =IFERROR(IF(maxifs(Documents!$E$2:$E$1421,Documents!$A$2:$A$1421,$A18,Documents!$C$2:$C$1421,"brochure")=0,"",maxifs(Documents!$E$2:$E$1421,Documents!$A$2:$A$1421,$A18,Documents!$C$2:$C$1421,"brochure")),"") | S18: =IFERROR(IF(maxifs(Documents!$E$2:$E$1421,Documents!$A$2:$A$1421,$A18,Documents!$C$2:$C$1421,"press_kit")=0,"",maxifs(Documents!$E$2:$E$1421,Documents!$A$2:$A$1421,$A18,Documents!$C$2:$C$1421,"press_kit")),"") | T18: =IFERROR(IF(maxifs(Documents!$E$2:$E$1421,Documents!$A$2:$A$1421,$A18,Documents!$C$2:$C$1421,"other")=0,"",maxifs(Documents!$E$2:$E$1421,Documents!$A$2:$A$1421,$A18,Documents!$C$2:$C$1421,"other")),"") | U18: =IFERROR(IF(maxifs(Documents!$E$2:$E$1421,Documents!$A$2:$A$1421,$A18,Documents!$C$2:$C$1421,"obsolete")=0,"",maxifs(Documents!$E$2:$E$1421,Documents!$A$2:$A$1421,$A18,Documents!$C$2:$C$1421,"obsolete")),"") | V18: =COUNTIFS(Documents!$A$2:$A$1421,$A18) -> 0 | W18: =COUNTIFS(Documents!$A$2:$A$1421,$A18,Documents!$R$2:$R$1421,"current") -> 0 | Y18: factsheet, wedding, events | Z18: site redirects to expireddomains.com
A19: 18 | B19: JW Marriott Maldives Resort & Spa | C19: blocked | D19: =IFERROR(IF(maxifs(Documents!$E$2:$E$1421,Documents!$A$2:$A$1421,$A19,Documents!$C$2:$C$1421,"factsheet")=0,"",maxifs(Documents!$E$2:$E$1421,Documents!$A$2:$A$1421,$A19,Documents!$C$2:$C$1421,"factsheet")),"") | E19: =IFERROR(IF(maxifs(Documents!$E$2:$E$1421,Documents!$A$2:$A$1421,$A19,Documents!$C$2:$C$1421,"wedding")=0,"",maxifs(Documents!$E$2:$E$1421,Documents!$A$2:$A$1421,$A19,Documents!$C$2:$C$1421,"wedding")),"") | F19: =IFERROR(IF(maxifs(Documents!$E$2:$E$1421,Documents!$A$2:$A$1421,$A19,Documents!$C$2:$C$1421,"events")=0,"",maxifs(Documents!$E$2:$E$1421,Documents!$A$2:$A$1421,$A19,Documents!$C$2:$C$1421,"events")),"") | G19: =IFERROR(IF(maxifs(Documents!$E$2:$E$1421,Documents!$A$2:$A$1421,$A19,Documents!$C$2:$C$1421,"map")=0,"",maxifs(Documents!$E$2:$E$1421,Documents!$A$2:$A$1421,$A19,Documents!$C$2:$C$1421,"map")),"") | H19: =IFERROR(IF(maxifs(Documents!$E$2:$E$1421,Documents!$A$2:$A$1421,$A19,Documents!$C$2:$C$1421,"dive_map")=0,"",maxifs(Documents!$E$2:$E$1421,Documents!$A$2:$A$1421,$A19,Documents!$C$2:$C$1421,"dive_map")),"") | I19: =IFERROR(IF(maxifs(Documents!$E$2:$E$1421,Documents!$A$2:$A$1421,$A19,Documents!$C$2:$C$1421,"spa_menu")=0,"",maxifs(Documents!$E$2:$E$1421,Documents!$A$2:$A$1421,$A19,Documents!$C$2:$C$1421,"spa_menu")),"") | J19: =IFERROR(IF(maxifs(Documents!$E$2:$E$1421,Documents!$A$2:$A$1421,$A19,Documents!$C$2:$C$1421,"dining_menu")=0,"",maxifs(Documents!$E$2:$E$1421,Documents!$A$2:$A$1421,$A19,Documents!$C$2:$C$1421,"dining_menu")),"") | K19: =IFERROR(IF(maxifs(Documents!$E$2:$E$1421,Documents!$A$2:$A$1421,$A19,Documents!$C$2:$C$1421,"dive_prices")=0,"",maxifs(Documents!$E$2:$E$1421,Documents!$A$2:$A$1421,$A19,Documents!$C$2:$C$1421,"dive_prices")),"") | L19: =IFERROR(IF(maxifs(Documents!$E$2:$E$1421,Documents!$A$2:$A$1421,$A19,Documents!$C$2:$C$1421,"excursions")=0,"",maxifs(Documents!$E$2:$E$1421,Documents!$A$2:$A$1421,$A19,Documents!$C$2:$C$1421,"excursions")),"") | M19: =IFERROR(IF(maxifs(Documents!$E$2:$E$1421,Documents!$A$2:$A$1421,$A19,Documents!$C$2:$C$1421,"kids")=0,"",maxifs(Documents!$E$2:$E$1421,Documents!$A$2:$A$1421,$A19,Documents!$C$2:$C$1421,"kids")),"") | N19: =IFERROR(IF(maxifs(Documents!$E$2:$E$1421,Documents!$A$2:$A$1421,$A19,Documents!$C$2:$C$1421,"villa_plans")=0,"",maxifs(Documents!$E$2:$E$1421,Documents!$A$2:$A$1421,$A19,Documents!$C$2:$C$1421,"villa_plans")),"") | O19: =IFERROR(IF(maxifs(Documents!$E$2:$E$1421,Documents!$A$2:$A$1421,$A19,Documents!$C$2:$C$1421,"all_inclusive")=0,"",maxifs(Documents!$E$2:$E$1421,Documents!$A$2:$A$1421,$A19,Documents!$C$2:$C$1421,"all_inclusive")),"") | P19: =IFERROR(IF(maxifs(Documents!$E$2:$E$1421,Documents!$A$2:$A$1421,$A19,Documents!$C$2:$C$1421,"sustainability")=0,"",maxifs(Documents!$E$2:$E$1421,Documents!$A$2:$A$1421,$A19,Documents!$C$2:$C$1421,"sustainability")),"") | Q19: =IFERROR(IF(maxifs(Documents!$E$2:$E$1421,Documents!$A$2:$A$1421,$A19,Documents!$C$2:$C$1421,"calendar")=0,"",maxifs(Documents!$E$2:$E$1421,Documents!$A$2:$A$1421,$A19,Documents!$C$2:$C$1421,"calendar")),"") | R19: =IFERROR(IF(maxifs(Documents!$E$2:$E$1421,Documents!$A$2:$A$1421,$A19,Documents!$C$2:$C$1421,"brochure")=0,"",maxifs(Documents!$E$2:$E$1421,Documents!$A$2:$A$1421,$A19,Documents!$C$2:$C$1421,"brochure")),"") | S19: =IFERROR(IF(maxifs(Documents!$E$2:$E$1421,Documents!$A$2:$A$1421,$A19,Documents!$C$2:$C$1421,"press_kit")=0,"",maxifs(Documents!$E$2:$E$1421,Documents!$A$2:$A$1421,$A19,Documents!$C$2:$C$1421,"press_kit")),"") | T19: =IFERROR(IF(maxifs(Documents!$E$2:$E$1421,Documents!$A$2:$A$1421,$A19,Documents!$C$2:$C$1421,"other")=0,"",maxifs(Documents!$E$2:$E$1421,Documents!$A$2:$A$1421,$A19,Documents!$C$2:$C$1421,"other")),"") | U19: =IFERROR(IF(maxifs(Documents!$E$2:$E$1421,Documents!$A$2:$A$1421,$A19,Documents!$C$2:$C$1421,"obsolete")=0,"",maxifs(Documents!$E$2:$E$1421,Documents!$A$2:$A$1421,$A19,Documents!$C$2:$C$1421,"obsolete")),"") | V19: =COUNTIFS(Documents!$A$2:$A$1421,$A19) -> 2 | W19: =COUNTIFS(Documents!$A$2:$A$1421,$A19,Documents!$R$2:$R$1421,"current") -> 1 | X19: =HYPERLINK("https://www.neoscapesmaldives.com/wp-content/uploads/JW-Marriott-Maldives-Resort-Spa-Factsheet-2023.pdf","2023_JW-Marriott-Maldives-Resort-Spa-Fac") -> 2023_JW-Marriott-Maldives-Resort-Spa-Fac | Y19: wedding, events
A20: 19 | B20: The Residence Maldives | C20: ok | D20: =IFERROR(IF(maxifs(Documents!$E$2:$E$1421,Documents!$A$2:$A$1421,$A20,Documents!$C$2:$C$1421,"factsheet")=0,"",maxifs(Documents!$E$2:$E$1421,Documents!$A$2:$A$1421,$A20,Documents!$C$2:$C$1421,"factsheet")),"") | E20: =IFERROR(IF(maxifs(Documents!$E$2:$E$1421,Documents!$A$2:$A$1421,$A20,Documents!$C$2:$C$1421,"wedding")=0,"",maxifs(Documents!$E$2:$E$1421,Documents!$A$2:$A$1421,$A20,Documents!$C$2:$C$1421,"wedding")),"") | F20: =IFERROR(IF(maxifs(Documents!$E$2:$E$1421,Documents!$A$2:$A$1421,$A20,Documents!$C$2:$C$1421,"events")=0,"",maxifs(Documents!$E$2:$E$1421,Documents!$A$2:$A$1421,$A20,Documents!$C$2:$C$1421,"events")),"") | G20: =IFERROR(IF(maxifs(Documents!$E$2:$E$1421,Documents!$A$2:$A$1421,$A20,Documents!$C$2:$C$1421,"map")=0,"",maxifs(Documents!$E$2:$E$1421,Documents!$A$2:$A$1421,$A20,Documents!$C$2:$C$1421,"map")),"") | H20: =IFERROR(IF(maxifs(Documents!$E$2:$E$1421,Documents!$A$2:$A$1421,$A20,Documents!$C$2:$C$1421,"dive_map")=0,"",maxifs(Documents!$E$2:$E$1421,Documents!$A$2:$A$1421,$A20,Documents!$C$2:$C$1421,"dive_map")),"") | I20: =IFERROR(IF(maxifs(Documents!$E$2:$E$1421,Documents!$A$2:$A$1421,$A20,Documents!$C$2:$C$1421,"spa_menu")=0,"",maxifs(Documents!$E$2:$E$1421,Documents!$A$2:$A$1421,$A20,Documents!$C$2:$C$1421,"spa_menu")),"") | J20: =IFERROR(IF(maxifs(Documents!$E$2:$E$1421,Documents!$A$2:$A$1421,$A20,Documents!$C$2:$C$1421,"dining_menu")=0,"",maxifs(Documents!$E$2:$E$1421,Documents!$A$2:$A$1421,$A20,Documents!$C$2:$C$1421,"dining_menu")),"") | K20: =IFERROR(IF(maxifs(Documents!$E$2:$E$1421,Documents!$A$2:$A$1421,$A20,Documents!$C$2:$C$1421,"dive_prices")=0,"",maxifs(Documents!$E$2:$E$1421,Documents!$A$2:$A$1421,$A20,Documents!$C$2:$C$1421,"dive_prices")),"") | L20: =IFERROR(IF(maxifs(Documents!$E$2:$E$1421,Documents!$A$2:$A$1421,$A20,Documents!$C$2:$C$1421,"excursions")=0,"",maxifs(Documents!$E$2:$E$1421,Documents!$A$2:$A$1421,$A20,Documents!$C$2:$C$1421,"excursions")),"") | M20: =IFERROR(IF(maxifs(Documents!$E$2:$E$1421,Documents!$A$2:$A$1421,$A20,Documents!$C$2:$C$1421,"kids")=0,"",maxifs(Documents!$E$2:$E$1421,Documents!$A$2:$A$1421,$A20,Documents!$C$2:$C$1421,"kids")),"") | N20: =IFERROR(IF(maxifs(Documents!$E$2:$E$1421,Documents!$A$2:$A$1421,$A20,Documents!$C$2:$C$1421,"villa_plans")=0,"",maxifs(Documents!$E$2:$E$1421,Documents!$A$2:$A$1421,$A20,Documents!$C$2:$C$1421,"villa_plans")),"") | O20: =IFERROR(IF(maxifs(Documents!$E$2:$E$1421,Documents!$A$2:$A$1421,$A20,Documents!$C$2:$C$1421,"all_inclusive")=0,"",maxifs(Documents!$E$2:$E$1421,Documents!$A$2:$A$1421,$A20,Documents!$C$2:$C$1421,"all_inclusive")),"") | P20: =IFERROR(IF(maxifs(Documents!$E$2:$E$1421,Documents!$A$2:$A$1421,$A20,Documents!$C$2:$C$1421,"sustainability")=0,"",maxifs(Documents!$E$2:$E$1421,Documents!$A$2:$A$1421,$A20,Documents!$C$2:$C$1421,"sustainability")),"") | Q20: =IFERROR(IF(maxifs(Documents!$E$2:$E$1421,Documents!$A$2:$A$1421,$A20,Documents!$C$2:$C$1421,"calendar")=0,"",maxifs(Documents!$E$2:$E$1421,Documents!$A$2:$A$1421,$A20,Documents!$C$2:$C$1421,"calendar")),"") | R20: =IFERROR(IF(maxifs(Documents!$E$2:$E$1421,Documents!$A$2:$A$1421,$A20,Documents!$C$2:$C$1421,"brochure")=0,"",maxifs(Documents!$E$2:$E$1421,Documents!$A$2:$A$1421,$A20,Documents!$C$2:$C$1421,"brochure")),"") | S20: =IFERROR(IF(maxifs(Documents!$E$2:$E$1421,Documents!$A$2:$A$1421,$A20,Documents!$C$2:$C$1421,"press_kit")=0,"",maxifs(Documents!$E$2:$E$1421,Documents!$A$2:$A$1421,$A20,Documents!$C$2:$C$1421,"press_kit")),"") | T20: =IFERROR(IF(maxifs(Documents!$E$2:$E$1421,Documents!$A$2:$A$1421,$A20,Documents!$C$2:$C$1421,"other")=0,"",maxifs(Documents!$E$2:$E$1421,Documents!$A$2:$A$1421,$A20,Documents!$C$2:$C$1421,"other")),"") | U20: =IFERROR(IF(maxifs(Documents!$E$2:$E$1421,Documents!$A$2:$A$1421,$A20,Documents!$C$2:$C$1421,"obsolete")=0,"",maxifs(Documents!$E$2:$E$1421,Documents!$A$2:$A$1421,$A20,Documents!$C$2:$C$1421,"obsolete")),"") | V20: =COUNTIFS(Documents!$A$2:$A$1421,$A20) -> 20 | W20: =COUNTIFS(Documents!$A$2:$A$1421,$A20,Documents!$R$2:$R$1421,"current") -> 13 | Y20: factsheet
A21: 20 | B21: The Residence Maldives At Dhigurah | C21: ok | D21: =IFERROR(IF(maxifs(Documents!$E$2:$E$1421,Documents!$A$2:$A$1421,$A21,Documents!$C$2:$C$1421,"factsheet")=0,"",maxifs(Documents!$E$2:$E$1421,Documents!$A$2:$A$1421,$A21,Documents!$C$2:$C$1421,"factsheet")),"") | E21: =IFERROR(IF(maxifs(Documents!$E$2:$E$1421,Documents!$A$2:$A$1421,$A21,Documents!$C$2:$C$1421,"wedding")=0,"",maxifs(Documents!$E$2:$E$1421,Documents!$A$2:$A$1421,$A21,Documents!$C$2:$C$1421,"wedding")),"") | F21: =IFERROR(IF(maxifs(Documents!$E$2:$E$1421,Documents!$A$2:$A$1421,$A21,Documents!$C$2:$C$1421,"events")=0,"",maxifs(Documents!$E$2:$E$1421,Documents!$A$2:$A$1421,$A21,Documents!$C$2:$C$1421,"events")),"") | G21: =IFERROR(IF(maxifs(Documents!$E$2:$E$1421,Documents!$A$2:$A$1421,$A21,Documents!$C$2:$C$1421,"map")=0,"",maxifs(Documents!$E$2:$E$1421,Documents!$A$2:$A$1421,$A21,Documents!$C$2:$C$1421,"map")),"") | H21: =IFERROR(IF(maxifs(Documents!$E$2:$E$1421,Documents!$A$2:$A$1421,$A21,Documents!$C$2:$C$1421,"dive_map")=0,"",maxifs(Documents!$E$2:$E$1421,Documents!$A$2:$A$1421,$A21,Documents!$C$2:$C$1421,"dive_map")),"") | I21: =IFERROR(IF(maxifs(Documents!$E$2:$E$1421,Documents!$A$2:$A$1421,$A21,Documents!$C$2:$C$1421,"spa_menu")=0,"",maxifs(Documents!$E$2:$E$1421,Documents!$A$2:$A$1421,$A21,Documents!$C$2:$C$1421,"spa_menu")),"") | J21: =IFERROR(IF(maxifs(Documents!$E$2:$E$1421,Documents!$A$2:$A$1421,$A21,Documents!$C$2:$C$1421,"dining_menu")=0,"",maxifs(Documents!$E$2:$E$1421,Documents!$A$2:$A$1421,$A21,Documents!$C$2:$C$1421,"dining_menu")),"") | K21: =IFERROR(IF(maxifs(Documents!$E$2:$E$1421,Documents!$A$2:$A$1421,$A21,Documents!$C$2:$C$1421,"dive_prices")=0,"",maxifs(Documents!$E$2:$E$1421,Documents!$A$2:$A$1421,$A21,Documents!$C$2:$C$1421,"dive_prices")),"") | L21: =IFERROR(IF(maxifs(Documents!$E$2:$E$1421,Documents!$A$2:$A$1421,$A21,Documents!$C$2:$C$1421,"excursions")=0,"",maxifs(Documents!$E$2:$E$1421,Documents!$A$2:$A$1421,$A21,Documents!$C$2:$C$1421,"excursions")),"") | M21: =IFERROR(IF(maxifs(Documents!$E$2:$E$1421,Documents!$A$2:$A$1421,$A21,Documents!$C$2:$C$1421,"kids")=0,"",maxifs(Documents!$E$2:$E$1421,Documents!$A$2:$A$1421,$A21,Documents!$C$2:$C$1421,"kids")),"") | N21: =IFERROR(IF(maxifs(Documents!$E$2:$E$1421,Documents!$A$2:$A$1421,$A21,Documents!$C$2:$C$1421,"villa_plans")=0,"",maxifs(Documents!$E$2:$E$1421,Documents!$A$2:$A$1421,$A21,Documents!$C$2:$C$1421,"villa_plans")),"") | O21: =IFERROR(IF(maxifs(Documents!$E$2:$E$1421,Documents!$A$2:$A$1421,$A21,Documents!$C$2:$C$1421,"all_inclusive")=0,"",maxifs(Documents!$E$2:$E$1421,Documents!$A$2:$A$1421,$A21,Documents!$C$2:$C$1421,"all_inclusive")),"") | P21: =IFERROR(IF(maxifs(Documents!$E$2:$E$1421,Documents!$A$2:$A$1421,$A21,Documents!$C$2:$C$1421,"sustainability")=0,"",maxifs(Documents!$E$2:$E$1421,Documents!$A$2:$A$1421,$A21,Documents!$C$2:$C$1421,"sustainability")),"") | Q21: =IFERROR(IF(maxifs(Documents!$E$2:$E$1421,Documents!$A$2:$A$1421,$A21,Documents!$C$2:$C$1421,"calendar")=0,"",maxifs(Documents!$E$2:$E$1421,Documents!$A$2:$A$1421,$A21,Documents!$C$2:$C$1421,"calendar")),"") | R21: =IFERROR(IF(maxifs(Documents!$E$2:$E$1421,Documents!$A$2:$A$1421,$A21,Documents!$C$2:$C$1421,"brochure")=0,"",maxifs(Documents!$E$2:$E$1421,Documents!$A$2:$A$1421,$A21,Documents!$C$2:$C$1421,"brochure")),"") | S21: =IFERROR(IF(maxifs(Documents!$E$2:$E$1421,Documents!$A$2:$A$1421,$A21,Documents!$C$2:$C$1421,"press_kit")=0,"",maxifs(Documents!$E$2:$E$1421,Documents!$A$2:$A$1421,$A21,Documents!$C$2:$C$1421,"press_kit")),"") | T21: =IFERROR(IF(maxifs(Documents!$E$2:$E$1421,Documents!$A$2:$A$1421,$A21,Documents!$C$2:$C$1421,"other")=0,"",maxifs(Documents!$E$2:$E$1421,Documents!$A$2:$A$1421,$A21,Documents!$C$2:$C$1421,"other")),"") | U21: =IFERROR(IF(maxifs(Documents!$E$2:$E$1421,Documents!$A$2:$A$1421,$A21,Documents!$C$2:$C$1421,"obsolete")=0,"",maxifs(Documents!$E$2:$E$1421,Documents!$A$2:$A$1421,$A21,Documents!$C$2:$C$1421,"obsolete")),"") | V21: =COUNTIFS(Documents!$A$2:$A$1421,$A21) -> 13 | W21: =COUNTIFS(Documents!$A$2:$A$1421,$A21,Documents!$R$2:$R$1421,"current") -> 9 | Y21: factsheet, events
A22: 21 | B22: Brennia Kottefaru | C22: ok | D22: =IFERROR(IF(maxifs(Documents!$E$2:$E$1421,Documents!$A$2:$A$1421,$A22,Documents!$C$2:$C$1421,"factsheet")=0,"",maxifs(Documents!$E$2:$E$1421,Documents!$A$2:$A$1421,$A22,Documents!$C$2:$C$1421,"factsheet")),"") | E22: =IFERROR(IF(maxifs(Documents!$E$2:$E$1421,Documents!$A$2:$A$1421,$A22,Documents!$C$2:$C$1421,"wedding")=0,"",maxifs(Documents!$E$2:$E$1421,Documents!$A$2:$A$1421,$A22,Documents!$C$2:$C$1421,"wedding")),"") | F22: =IFERROR(IF(maxifs(Documents!$E$2:$E$1421,Documents!$A$2:$A$1421,$A22,Documents!$C$2:$C$1421,"events")=0,"",maxifs(Documents!$E$2:$E$1421,Documents!$A$2:$A$1421,$A22,Documents!$C$2:$C$1421,"events")),"") | G22: =IFERROR(IF(maxifs(Documents!$E$2:$E$1421,Documents!$A$2:$A$1421,$A22,Documents!$C$2:$C$1421,"map")=0,"",maxifs(Documents!$E$2:$E$1421,Documents!$A$2:$A$1421,$A22,Documents!$C$2:$C$1421,"map")),"") | H22: =IFERROR(IF(maxifs(Documents!$E$2:$E$1421,Documents!$A$2:$A$1421,$A22,Documents!$C$2:$C$1421,"dive_map")=0,"",maxifs(Documents!$E$2:$E$1421,Documents!$A$2:$A$1421,$A22,Documents!$C$2:$C$1421,"dive_map")),"") | I22: =IFERROR(IF(maxifs(Documents!$E$2:$E$1421,Documents!$A$2:$A$1421,$A22,Documents!$C$2:$C$1421,"spa_menu")=0,"",maxifs(Documents!$E$2:$E$1421,Documents!$A$2:$A$1421,$A22,Documents!$C$2:$C$1421,"spa_menu")),"") | J22: =IFERROR(IF(maxifs(Documents!$E$2:$E$1421,Documents!$A$2:$A$1421,$A22,Documents!$C$2:$C$1421,"dining_menu")=0,"",maxifs(Documents!$E$2:$E$1421,Documents!$A$2:$A$1421,$A22,Documents!$C$2:$C$1421,"dining_menu")),"") | K22: =IFERROR(IF(maxifs(Documents!$E$2:$E$1421,Documents!$A$2:$A$1421,$A22,Documents!$C$2:$C$1421,"dive_prices")=0,"",maxifs(Documents!$E$2:$E$1421,Documents!$A$2:$A$1421,$A22,Documents!$C$2:$C$1421,"dive_prices")),"") | L22: =IFERROR(IF(maxifs(Documents!$E$2:$E$1421,Documents!$A$2:$A$1421,$A22,Documents!$C$2:$C$1421,"excursions")=0,"",maxifs(Documents!$E$2:$E$1421,Documents!$A$2:$A$1421,$A22,Documents!$C$2:$C$1421,"excursions")),"") | M22: =IFERROR(IF(maxifs(Documents!$E$2:$E$1421,Documents!$A$2:$A$1421,$A22,Documents!$C$2:$C$1421,"kids")=0,"",maxifs(Documents!$E$2:$E$1421,Documents!$A$2:$A$1421,$A22,Documents!$C$2:$C$1421,"kids")),"") | N22: =IFERROR(IF(maxifs(Documents!$E$2:$E$1421,Documents!$A$2:$A$1421,$A22,Documents!$C$2:$C$1421,"villa_plans")=0,"",maxifs(Documents!$E$2:$E$1421,Documents!$A$2:$A$1421,$A22,Documents!$C$2:$C$1421,"villa_plans")),"") | O22: =IFERROR(IF(maxifs(Documents!$E$2:$E$1421,Documents!$A$2:$A$1421,$A22,Documents!$C$2:$C$1421,"all_inclusive")=0,"",maxifs(Documents!$E$2:$E$1421,Documents!$A$2:$A$1421,$A22,Documents!$C$2:$C$1421,"all_inclusive")),"") | P22: =IFERROR(IF(maxifs(Documents!$E$2:$E$1421,Documents!$A$2:$A$1421,$A22,Documents!$C$2:$C$1421,"sustainability")=0,"",maxifs(Documents!$E$2:$E$1421,Documents!$A$2:$A$1421,$A22,Documents!$C$2:$C$1421,"sustainability")),"") | Q22: =IFERROR(IF(maxifs(Documents!$E$2:$E$1421,Documents!$A$2:$A$1421,$A22,Documents!$C$2:$C$1421,"calendar")=0,"",maxifs(Documents!$E$2:$E$1421,Documents!$A$2:$A$1421,$A22,Documents!$C$2:$C$1421,"calendar")),"") | R22: =IFERROR(IF(maxifs(Documents!$E$2:$E$1421,Documents!$A$2:$A$1421,$A22,Documents!$C$2:$C$1421,"brochure")=0,"",maxifs(Documents!$E$2:$E$1421,Documents!$A$2:$A$1421,$A22,Documents!$C$2:$C$1421,"brochure")),"") | S22: =IFERROR(IF(maxifs(Documents!$E$2:$E$1421,Documents!$A$2:$A$1421,$A22,Documents!$C$2:$C$1421,"press_kit")=0,"",maxifs(Documents!$E$2:$E$1421,Documents!$A$2:$A$1421,$A22,Documents!$C$2:$C$1421,"press_kit")),"") | T22: =IFERROR(IF(maxifs(Documents!$E$2:$E$1421,Documents!$A$2:$A$1421,$A22,Documents!$C$2:$C$1421,"other")=0,"",maxifs(Documents!$E$2:$E$1421,Documents!$A$2:$A$1421,$A22,Documents!$C$2:$C$1421,"other")),"") | U22: =IFERROR(IF(maxifs(Documents!$E$2:$E$1421,Documents!$A$2:$A$1421,$A22,Documents!$C$2:$C$1421,"obsolete")=0,"",maxifs(Documents!$E$2:$E$1421,Documents!$A$2:$A$1421,$A22,Documents!$C$2:$C$1421,"obsolete")),"") | V22: =COUNTIFS(Documents!$A$2:$A$1421,$A22) -> 10 | W22: =COUNTIFS(Documents!$A$2:$A$1421,$A22,Documents!$R$2:$R$1421,"current") -> 7 | X22: =HYPERLINK("https://www.neoscapesmaldives.com/wp-content/uploads/English-Fact-Sheet-Resort-Map.pdf","2025_English-Fact-Sheet-Resort-Map.pdf") -> 2025_English-Fact-Sheet-Resort-Map.pdf | Y22: wedding, events
A23: 22 | B23: Barceló Whale Lagoon Maldives | C23: unverified | D23: =IFERROR(IF(maxifs(Documents!$E$2:$E$1421,Documents!$A$2:$A$1421,$A23,Documents!$C$2:$C$1421,"factsheet")=0,"",maxifs(Documents!$E$2:$E$1421,Documents!$A$2:$A$1421,$A23,Documents!$C$2:$C$1421,"factsheet")),"") | E23: =IFERROR(IF(maxifs(Documents!$E$2:$E$1421,Documents!$A$2:$A$1421,$A23,Documents!$C$2:$C$1421,"wedding")=0,"",maxifs(Documents!$E$2:$E$1421,Documents!$A$2:$A$1421,$A23,Documents!$C$2:$C$1421,"wedding")),"") | F23: =IFERROR(IF(maxifs(Documents!$E$2:$E$1421,Documents!$A$2:$A$1421,$A23,Documents!$C$2:$C$1421,"events")=0,"",maxifs(Documents!$E$2:$E$1421,Documents!$A$2:$A$1421,$A23,Documents!$C$2:$C$1421,"events")),"") | G23: =IFERROR(IF(maxifs(Documents!$E$2:$E$1421,Documents!$A$2:$A$1421,$A23,Documents!$C$2:$C$1421,"map")=0,"",maxifs(Documents!$E$2:$E$1421,Documents!$A$2:$A$1421,$A23,Documents!$C$2:$C$1421,"map")),"") | H23: =IFERROR(IF(maxifs(Documents!$E$2:$E$1421,Documents!$A$2:$A$1421,$A23,Documents!$C$2:$C$1421,"dive_map")=0,"",maxifs(Documents!$E$2:$E$1421,Documents!$A$2:$A$1421,$A23,Documents!$C$2:$C$1421,"dive_map")),"") | I23: =IFERROR(IF(maxifs(Documents!$E$2:$E$1421,Documents!$A$2:$A$1421,$A23,Documents!$C$2:$C$1421,"spa_menu")=0,"",maxifs(Documents!$E$2:$E$1421,Documents!$A$2:$A$1421,$A23,Documents!$C$2:$C$1421,"spa_menu")),"") | J23: =IFERROR(IF(maxifs(Documents!$E$2:$E$1421,Documents!$A$2:$A$1421,$A23,Documents!$C$2:$C$1421,"dining_menu")=0,"",maxifs(Documents!$E$2:$E$1421,Documents!$A$2:$A$1421,$A23,Documents!$C$2:$C$1421,"dining_menu")),"") | K23: =IFERROR(IF(maxifs(Documents!$E$2:$E$1421,Documents!$A$2:$A$1421,$A23,Documents!$C$2:$C$1421,"dive_prices")=0,"",maxifs(Documents!$E$2:$E$1421,Documents!$A$2:$A$1421,$A23,Documents!$C$2:$C$1421,"dive_prices")),"") | L23: =IFERROR(IF(maxifs(Documents!$E$2:$E$1421,Documents!$A$2:$A$1421,$A23,Documents!$C$2:$C$1421,"excursions")=0,"",maxifs(Documents!$E$2:$E$1421,Documents!$A$2:$A$1421,$A23,Documents!$C$2:$C$1421,"excursions")),"") | M23: =IFERROR(IF(maxifs(Documents!$E$2:$E$1421,Documents!$A$2:$A$1421,$A23,Documents!$C$2:$C$1421,"kids")=0,"",maxifs(Documents!$E$2:$E$1421,Documents!$A$2:$A$1421,$A23,Documents!$C$2:$C$1421,"kids")),"") | N23: =IFERROR(IF(maxifs(Documents!$E$2:$E$1421,Documents!$A$2:$A$1421,$A23,Documents!$C$2:$C$1421,"villa_plans")=0,"",maxifs(Documents!$E$2:$E$1421,Documents!$A$2:$A$1421,$A23,Documents!$C$2:$C$1421,"villa_plans")),"") | O23: =IFERROR(IF(maxifs(Documents!$E$2:$E$1421,Documents!$A$2:$A$1421,$A23,Documents!$C$2:$C$1421,"all_inclusive")=0,"",maxifs(Documents!$E$2:$E$1421,Documents!$A$2:$A$1421,$A23,Documents!$C$2:$C$1421,"all_inclusive")),"") | P23: =IFERROR(IF(maxifs(Documents!$E$2:$E$1421,Documents!$A$2:$A$1421,$A23,Documents!$C$2:$C$1421,"sustainability")=0,"",maxifs(Documents!$E$2:$E$1421,Documents!$A$2:$A$1421,$A23,Documents!$C$2:$C$1421,"sustainability")),"") | Q23: =IFERROR(IF(maxifs(Documents!$E$2:$E$1421,Documents!$A$2:$A$1421,$A23,Documents!$C$2:$C$1421,"calendar")=0,"",maxifs(Documents!$E$2:$E$1421,Documents!$A$2:$A$1421,$A23,Documents!$C$2:$C$1421,"calendar")),"") | R23: =IFERROR(IF(maxifs(Documents!$E$2:$E$1421,Documents!$A$2:$A$1421,$A23,Documents!$C$2:$C$1421,"brochure")=0,"",maxifs(Documents!$E$2:$E$1421,Documents!$A$2:$A$1421,$A23,Documents!$C$2:$C$1421,"brochure")),"") | S23: =IFERROR(IF(maxifs(Documents!$E$2:$E$1421,Documents!$A$2:$A$1421,$A23,Documents!$C$2:$C$1421,"press_kit")=0,"",maxifs(Documents!$E$2:$E$1421,Documents!$A$2:$A$1421,$A23,Documents!$C$2:$C$1421,"press_kit")),"") | T23: =IFERROR(IF(maxifs(Documents!$E$2:$E$1421,Documents!$A$2:$A$1421,$A23,Documents!$C$2:$C$1421,"other")=0,"",maxifs(Documents!$E$2:$E$1421,Documents!$A$2:$A$1421,$A23,Documents!$C$2:$C$1421,"other")),"") | U23: =IFERROR(IF(maxifs(Documents!$E$2:$E$1421,Documents!$A$2:$A$1421,$A23,Documents!$C$2:$C$1421,"obsolete")=0,"",maxifs(Documents!$E$2:$E$1421,Documents!$A$2:$A$1421,$A23,Documents!$C$2:$C$1421,"obsolete")),"") | V23: =COUNTIFS(Documents!$A$2:$A$1421,$A23) -> 2 | W23: =COUNTIFS(Documents!$A$2:$A$1421,$A23,Documents!$R$2:$R$1421,"current") -> 2 | X23: =HYPERLINK("https://www.neoscapesmaldives.com/wp-content/uploads/Factsheet_MWLM_March2026_Digital-updated.pdf","2026_Factsheet_MWLM_March2026_Digital-up") -> 2026_Factsheet_MWLM_March2026_Digital-up | Y23: wedding, events | Z23: Meliá Whale Lagoon Maldives
A24: 23 | B24: Nooe Maldives Kunavashi | C24: unreachable | D24: =IFERROR(IF(maxifs(Documents!$E$2:$E$1421,Documents!$A$2:$A$1421,$A24,Documents!$C$2:$C$1421,"factsheet")=0,"",maxifs(Documents!$E$2:$E$1421,Documents!$A$2:$A$1421,$A24,Documents!$C$2:$C$1421,"factsheet")),"") | E24: =IFERROR(IF(maxifs(Documents!$E$2:$E$1421,Documents!$A$2:$A$1421,$A24,Documents!$C$2:$C$1421,"wedding")=0,"",maxifs(Documents!$E$2:$E$1421,Documents!$A$2:$A$1421,$A24,Documents!$C$2:$C$1421,"wedding")),"") | F24: =IFERROR(IF(maxifs(Documents!$E$2:$E$1421,Documents!$A$2:$A$1421,$A24,Documents!$C$2:$C$1421,"events")=0,"",maxifs(Documents!$E$2:$E$1421,Documents!$A$2:$A$1421,$A24,Documents!$C$2:$C$1421,"events")),"") | G24: =IFERROR(IF(maxifs(Documents!$E$2:$E$1421,Documents!$A$2:$A$1421,$A24,Documents!$C$2:$C$1421,"map")=0,"",maxifs(Documents!$E$2:$E$1421,Documents!$A$2:$A$1421,$A24,Documents!$C$2:$C$1421,"map")),"") | H24: =IFERROR(IF(maxifs(Documents!$E$2:$E$1421,Documents!$A$2:$A$1421,$A24,Documents!$C$2:$C$1421,"dive_map")=0,"",maxifs(Documents!$E$2:$E$1421,Documents!$A$2:$A$1421,$A24,Documents!$C$2:$C$1421,"dive_map")),"") | I24: =IFERROR(IF(maxifs(Documents!$E$2:$E$1421,Documents!$A$2:$A$1421,$A24,Documents!$C$2:$C$1421,"spa_menu")=0,"",maxifs(Documents!$E$2:$E$1421,Documents!$A$2:$A$1421,$A24,Documents!$C$2:$C$1421,"spa_menu")),"") | J24: =IFERROR(IF(maxifs(Documents!$E$2:$E$1421,Documents!$A$2:$A$1421,$A24,Documents!$C$2:$C$1421,"dining_menu")=0,"",maxifs(Documents!$E$2:$E$1421,Documents!$A$2:$A$1421,$A24,Documents!$C$2:$C$1421,"dining_menu")),"") | K24: =IFERROR(IF(maxifs(Documents!$E$2:$E$1421,Documents!$A$2:$A$1421,$A24,Documents!$C$2:$C$1421,"dive_prices")=0,"",maxifs(Documents!$E$2:$E$1421,Documents!$A$2:$A$1421,$A24,Documents!$C$2:$C$1421,"dive_prices")),"") | L24: =IFERROR(IF(maxifs(Documents!$E$2:$E$1421,Documents!$A$2:$A$1421,$A24,Documents!$C$2:$C$1421,"excursions")=0,"",maxifs(Documents!$E$2:$E$1421,Documents!$A$2:$A$1421,$A24,Documents!$C$2:$C$1421,"excursions")),"") | M24: =IFERROR(IF(maxifs(Documents!$E$2:$E$1421,Documents!$A$2:$A$1421,$A24,Documents!$C$2:$C$1421,"kids")=0,"",maxifs(Documents!$E$2:$E$1421,Documents!$A$2:$A$1421,$A24,Documents!$C$2:$C$1421,"kids")),"") | N24: =IFERROR(IF(maxifs(Documents!$E$2:$E$1421,Documents!$A$2:$A$1421,$A24,Documents!$C$2:$C$1421,"villa_plans")=0,"",maxifs(Documents!$E$2:$E$1421,Documents!$A$2:$A$1421,$A24,Documents!$C$2:$C$1421,"villa_plans")),"") | O24: =IFERROR(IF(maxifs(Documents!$E$2:$E$1421,Documents!$A$2:$A$1421,$A24,Documents!$C$2:$C$1421,"all_inclusive")=0,"",maxifs(Documents!$E$2:$E$1421,Documents!$A$2:$A$1421,$A24,Documents!$C$2:$C$1421,"all_inclusive")),"") | P24: =IFERROR(IF(maxifs(Documents!$E$2:$E$1421,Documents!$A$2:$A$1421,$A24,Documents!$C$2:$C$1421,"sustainability")=0,"",maxifs(Documents!$E$2:$E$1421,Documents!$A$2:$A$1421,$A24,Documents!$C$2:$C$1421,"sustainability")),"") | Q24: =IFERROR(IF(maxifs(Documents!$E$2:$E$1421,Documents!$A$2:$A$1421,$A24,Documents!$C$2:$C$1421,"calendar")=0,"",maxifs(Documents!$E$2:$E$1421,Documents!$A$2:$A$1421,$A24,Documents!$C$2:$C$1421,"calendar")),"") | R24: =IFERROR(IF(maxifs(Documents!$E$2:$E$1421,Documents!$A$2:$A$1421,$A24,Documents!$C$2:$C$1421,"brochure")=0,"",maxifs(Documents!$E$2:$E$1421,Documents!$A$2:$A$1421,$A24,Documents!$C$2:$C$1421,"brochure")),"") | S24: =IFERROR(IF(maxifs(Documents!$E$2:$E$1421,Documents!$A$2:$A$1421,$A24,Documents!$C$2:$C$1421,"press_kit")=0,"",maxifs(Documents!$E$2:$E$1421,Documents!$A$2:$A$1421,$A24,Documents!$C$2:$C$1421,"press_kit")),"") | T24: =IFERROR(IF(maxifs(Documents!$E$2:$E$1421,Documents!$A$2:$A$1421,$A24,Documents!$C$2:$C$1421,"other")=0,"",maxifs(Documents!$E$2:$E$1421,Documents!$A$2:$A$1421,$A24,Documents!$C$2:$C$1421,"other")),"") | U24: =IFERROR(IF(maxifs(Documents!$E$2:$E$1421,Documents!$A$2:$A$1421,$A24,Documents!$C$2:$C$1421,"obsolete")=0,"",maxifs(Documents!$E$2:$E$1421,Documents!$A$2:$A$1421,$A24,Documents!$C$2:$C$1421,"obsolete")),"") | V24: =COUNTIFS(Documents!$A$2:$A$1421,$A24) -> 3 | W24: =COUNTIFS(Documents!$A$2:$A$1421,$A24,Documents!$R$2:$R$1421,"current") -> 1 | X24: =HYPERLINK("https://www.neoscapesmaldives.com/wp-content/uploads/NOOE-Maldives-Kunaavashi_Fact-Sheet-2024.pdf","2024_NOOE-Maldives-Kunaavashi_Fact-Sheet") -> 2024_NOOE-Maldives-Kunaavashi_Fact-Sheet | Y24: wedding, events
A25: 24 | B25: Canareef Resort Maldives | C25: ok | D25: =IFERROR(IF(maxifs(Documents!$E$2:$E$1421,Documents!$A$2:$A$1421,$A25,Documents!$C$2:$C$1421,"factsheet")=0,"",maxifs(Documents!$E$2:$E$1421,Documents!$A$2:$A$1421,$A25,Documents!$C$2:$C$1421,"factsheet")),"") | E25: =IFERROR(IF(maxifs(Documents!$E$2:$E$1421,Documents!$A$2:$A$1421,$A25,Documents!$C$2:$C$1421,"wedding")=0,"",maxifs(Documents!$E$2:$E$1421,Documents!$A$2:$A$1421,$A25,Documents!$C$2:$C$1421,"wedding")),"") | F25: =IFERROR(IF(maxifs(Documents!$E$2:$E$1421,Documents!$A$2:$A$1421,$A25,Documents!$C$2:$C$1421,"events")=0,"",maxifs(Documents!$E$2:$E$1421,Documents!$A$2:$A$1421,$A25,Documents!$C$2:$C$1421,"events")),"") | G25: =IFERROR(IF(maxifs(Documents!$E$2:$E$1421,Documents!$A$2:$A$1421,$A25,Documents!$C$2:$C$1421,"map")=0,"",maxifs(Documents!$E$2:$E$1421,Documents!$A$2:$A$1421,$A25,Documents!$C$2:$C$1421,"map")),"") | H25: =IFERROR(IF(maxifs(Documents!$E$2:$E$1421,Documents!$A$2:$A$1421,$A25,Documents!$C$2:$C$1421,"dive_map")=0,"",maxifs(Documents!$E$2:$E$1421,Documents!$A$2:$A$1421,$A25,Documents!$C$2:$C$1421,"dive_map")),"") | I25: =IFERROR(IF(maxifs(Documents!$E$2:$E$1421,Documents!$A$2:$A$1421,$A25,Documents!$C$2:$C$1421,"spa_menu")=0,"",maxifs(Documents!$E$2:$E$1421,Documents!$A$2:$A$1421,$A25,Documents!$C$2:$C$1421,"spa_menu")),"") | J25: =IFERROR(IF(maxifs(Documents!$E$2:$E$1421,Documents!$A$2:$A$1421,$A25,Documents!$C$2:$C$1421,"dining_menu")=0,"",maxifs(Documents!$E$2:$E$1421,Documents!$A$2:$A$1421,$A25,Documents!$C$2:$C$1421,"dining_menu")),"") | K25: =IFERROR(IF(maxifs(Documents!$E$2:$E$1421,Documents!$A$2:$A$1421,$A25,Documents!$C$2:$C$1421,"dive_prices")=0,"",maxifs(Documents!$E$2:$E$1421,Documents!$A$2:$A$1421,$A25,Documents!$C$2:$C$1421,"dive_prices")),"") | L25: =IFERROR(IF(maxifs(Documents!$E$2:$E$1421,Documents!$A$2:$A$1421,$A25,Documents!$C$2:$C$1421,"excursions")=0,"",maxifs(Documents!$E$2:$E$1421,Documents!$A$2:$A$1421,$A25,Documents!$C$2:$C$1421,"excursions")),"") | M25: =IFERROR(IF(maxifs(Documents!$E$2:$E$1421,Documents!$A$2:$A$1421,$A25,Documents!$C$2:$C$1421,"kids")=0,"",maxifs(Documents!$E$2:$E$1421,Documents!$A$2:$A$1421,$A25,Documents!$C$2:$C$1421,"kids")),"") | N25: =IFERROR(IF(maxifs(Documents!$E$2:$E$1421,Documents!$A$2:$A$1421,$A25,Documents!$C$2:$C$1421,"villa_plans")=0,"",maxifs(Documents!$E$2:$E$1421,Documents!$A$2:$A$1421,$A25,Documents!$C$2:$C$1421,"villa_plans")),"") | O25: =IFERROR(IF(maxifs(Documents!$E$2:$E$1421,Documents!$A$2:$A$1421,$A25,Documents!$C$2:$C$1421,"all_inclusive")=0,"",maxifs(Documents!$E$2:$E$1421,Documents!$A$2:$A$1421,$A25,Documents!$C$2:$C$1421,"all_inclusive")),"") | P25: =IFERROR(IF(maxifs(Documents!$E$2:$E$1421,Documents!$A$2:$A$1421,$A25,Documents!$C$2:$C$1421,"sustainability")=0,"",maxifs(Documents!$E$2:$E$1421,Documents!$A$2:$A$1421,$A25,Documents!$C$2:$C$1421,"sustainability")),"") | Q25: =IFERROR(IF(maxifs(Documents!$E$2:$E$1421,Documents!$A$2:$A$1421,$A25,Documents!$C$2:$C$1421,"calendar")=0,"",maxifs(Documents!$E$2:$E$1421,Documents!$A$2:$A$1421,$A25,Documents!$C$2:$C$1421,"calendar")),"") | R25: =IFERROR(IF(maxifs(Documents!$E$2:$E$1421,Documents!$A$2:$A$1421,$A25,Documents!$C$2:$C$1421,"brochure")=0,"",maxifs(Documents!$E$2:$E$1421,Documents!$A$2:$A$1421,$A25,Documents!$C$2:$C$1421,"brochure")),"") | S25: =IFERROR(IF(maxifs(Documents!$E$2:$E$1421,Documents!$A$2:$A$1421,$A25,Documents!$C$2:$C$1421,"press_kit")=0,"",maxifs(Documents!$E$2:$E$1421,Documents!$A$2:$A$1421,$A25,Documents!$C$2:$C$1421,"press_kit")),"") | T25: =IFERROR(IF(maxifs(Documents!$E$2:$E$1421,Documents!$A$2:$A$1421,$A25,Documents!$C$2:$C$1421,"other")=0,"",maxifs(Documents!$E$2:$E$1421,Documents!$A$2:$A$1421,$A25,Documents!$C$2:$C$1421,"other")),"") | U25: =IFERROR(IF(maxifs(Documents!$E$2:$E$1421,Documents!$A$2:$A$1421,$A25,Documents!$C$2:$C$1421,"obsolete")=0,"",maxifs(Documents!$E$2:$E$1421,Documents!$A$2:$A$1421,$A25,Documents!$C$2:$C$1421,"obsolete")),"") | V25: =COUNTIFS(Documents!$A$2:$A$1421,$A25) -> 5 | W25: =COUNTIFS(Documents!$A$2:$A$1421,$A25,Documents!$R$2:$R$1421,"current") -> 1 | Y25: factsheet, wedding, events
A26: 25 | B26: Raffles Maldives Meradhoo Resort | C26: blocked | D26: =IFERROR(IF(maxifs(Documents!$E$2:$E$1421,Documents!$A$2:$A$1421,$A26,Documents!$C$2:$C$1421,"factsheet")=0,"",maxifs(Documents!$E$2:$E$1421,Documents!$A$2:$A$1421,$A26,Documents!$C$2:$C$1421,"factsheet")),"") | E26: =IFERROR(IF(maxifs(Documents!$E$2:$E$1421,Documents!$A$2:$A$1421,$A26,Documents!$C$2:$C$1421,"wedding")=0,"",maxifs(Documents!$E$2:$E$1421,Documents!$A$2:$A$1421,$A26,Documents!$C$2:$C$1421,"wedding")),"") | F26: =IFERROR(IF(maxifs(Documents!$E$2:$E$1421,Documents!$A$2:$A$1421,$A26,Documents!$C$2:$C$1421,"events")=0,"",maxifs(Documents!$E$2:$E$1421,Documents!$A$2:$A$1421,$A26,Documents!$C$2:$C$1421,"events")),"") | G26: =IFERROR(IF(maxifs(Documents!$E$2:$E$1421,Documents!$A$2:$A$1421,$A26,Documents!$C$2:$C$1421,"map")=0,"",maxifs(Documents!$E$2:$E$1421,Documents!$A$2:$A$1421,$A26,Documents!$C$2:$C$1421,"map")),"") | H26: =IFERROR(IF(maxifs(Documents!$E$2:$E$1421,Documents!$A$2:$A$1421,$A26,Documents!$C$2:$C$1421,"dive_map")=0,"",maxifs(Documents!$E$2:$E$1421,Documents!$A$2:$A$1421,$A26,Documents!$C$2:$C$1421,"dive_map")),"") | I26: =IFERROR(IF(maxifs(Documents!$E$2:$E$1421,Documents!$A$2:$A$1421,$A26,Documents!$C$2:$C$1421,"spa_menu")=0,"",maxifs(Documents!$E$2:$E$1421,Documents!$A$2:$A$1421,$A26,Documents!$C$2:$C$1421,"spa_menu")),"") | J26: =IFERROR(IF(maxifs(Documents!$E$2:$E$1421,Documents!$A$2:$A$1421,$A26,Documents!$C$2:$C$1421,"dining_menu")=0,"",maxifs(Documents!$E$2:$E$1421,Documents!$A$2:$A$1421,$A26,Documents!$C$2:$C$1421,"dining_menu")),"") | K26: =IFERROR(IF(maxifs(Documents!$E$2:$E$1421,Documents!$A$2:$A$1421,$A26,Documents!$C$2:$C$1421,"dive_prices")=0,"",maxifs(Documents!$E$2:$E$1421,Documents!$A$2:$A$1421,$A26,Documents!$C$2:$C$1421,"dive_prices")),"") | L26: =IFERROR(IF(maxifs(Documents!$E$2:$E$1421,Documents!$A$2:$A$1421,$A26,Documents!$C$2:$C$1421,"excursions")=0,"",maxifs(Documents!$E$2:$E$1421,Documents!$A$2:$A$1421,$A26,Documents!$C$2:$C$1421,"excursions")),"") | M26: =IFERROR(IF(maxifs(Documents!$E$2:$E$1421,Documents!$A$2:$A$1421,$A26,Documents!$C$2:$C$1421,"kids")=0,"",maxifs(Documents!$E$2:$E$1421,Documents!$A$2:$A$1421,$A26,Documents!$C$2:$C$1421,"kids")),"") | N26: =IFERROR(IF(maxifs(Documents!$E$2:$E$1421,Documents!$A$2:$A$1421,$A26,Documents!$C$2:$C$1421,"villa_plans")=0,"",maxifs(Documents!$E$2:$E$1421,Documents!$A$2:$A$1421,$A26,Documents!$C$2:$C$1421,"villa_plans")),"") | O26: =IFERROR(IF(maxifs(Documents!$E$2:$E$1421,Documents!$A$2:$A$1421,$A26,Documents!$C$2:$C$1421,"all_inclusive")=0,"",maxifs(Documents!$E$2:$E$1421,Documents!$A$2:$A$1421,$A26,Documents!$C$2:$C$1421,"all_inclusive")),"") | P26: =IFERROR(IF(maxifs(Documents!$E$2:$E$1421,Documents!$A$2:$A$1421,$A26,Documents!$C$2:$C$1421,"sustainability")=0,"",maxifs(Documents!$E$2:$E$1421,Documents!$A$2:$A$1421,$A26,Documents!$C$2:$C$1421,"sustainability")),"") | Q26: =IFERROR(IF(maxifs(Documents!$E$2:$E$1421,Documents!$A$2:$A$1421,$A26,Documents!$C$2:$C$1421,"calendar")=0,"",maxifs(Documents!$E$2:$E$1421,Documents!$A$2:$A$1421,$A26,Documents!$C$2:$C$1421,"calendar")),"") | R26: =IFERROR(IF(maxifs(Documents!$E$2:$E$1421,Documents!$A$2:$A$1421,$A26,Documents!$C$2:$C$1421,"brochure")=0,"",maxifs(Documents!$E$2:$E$1421,Documents!$A$2:$A$1421,$A26,Documents!$C$2:$C$1421,"brochure")),"") | S26: =IFERROR(IF(maxifs(Documents!$E$2:$E$1421,Documents!$A$2:$A$1421,$A26,Documents!$C$2:$C$1421,"press_kit")=0,"",maxifs(Documents!$E$2:$E$1421,Documents!$A$2:$A$1421,$A26,Documents!$C$2:$C$1421,"press_kit")),"") | T26: =IFERROR(IF(maxifs(Documents!$E$2:$E$1421,Documents!$A$2:$A$1421,$A26,Documents!$C$2:$C$1421,"other")=0,"",maxifs(Documents!$E$2:$E$1421,Documents!$A$2:$A$1421,$A26,Documents!$C$2:$C$1421,"other")),"") | U26: =IFERROR(IF(maxifs(Documents!$E$2:$E$1421,Documents!$A$2:$A$1421,$A26,Documents!$C$2:$C$1421,"obsolete")=0,"",maxifs(Documents!$E$2:$E$1421,Documents!$A$2:$A$1421,$A26,Documents!$C$2:$C$1421,"obsolete")),"") | V26: =COUNTIFS(Documents!$A$2:$A$1421,$A26) -> 3 | W26: =COUNTIFS(Documents!$A$2:$A$1421,$A26,Documents!$R$2:$R$1421,"current") -> 3 | X26: =HYPERLINK("https://www.neoscapesmaldives.com/wp-content/uploads/Halcyon-Maldives-Factsheet-2026.pdf","2026_Halcyon-Maldives-Factsheet-2026.pdf") -> 2026_Halcyon-Maldives-Factsheet-2026.pdf | Y26: wedding, events | Z26: Halcyon Maldives
A27: 26 | B27: Centara Ras Fushi Resort & Spa | C27: ok | D27: =IFERROR(IF(maxifs(Documents!$E$2:$E$1421,Documents!$A$2:$A$1421,$A27,Documents!$C$2:$C$1421,"factsheet")=0,"",maxifs(Documents!$E$2:$E$1421,Documents!$A$2:$A$1421,$A27,Documents!$C$2:$C$1421,"factsheet")),"") | E27: =IFERROR(IF(maxifs(Documents!$E$2:$E$1421,Documents!$A$2:$A$1421,$A27,Documents!$C$2:$C$1421,"wedding")=0,"",maxifs(Documents!$E$2:$E$1421,Documents!$A$2:$A$1421,$A27,Documents!$C$2:$C$1421,"wedding")),"") | F27: =IFERROR(IF(maxifs(Documents!$E$2:$E$1421,Documents!$A$2:$A$1421,$A27,Documents!$C$2:$C$1421,"events")=0,"",maxifs(Documents!$E$2:$E$1421,Documents!$A$2:$A$1421,$A27,Documents!$C$2:$C$1421,"events")),"") | G27: =IFERROR(IF(maxifs(Documents!$E$2:$E$1421,Documents!$A$2:$A$1421,$A27,Documents!$C$2:$C$1421,"map")=0,"",maxifs(Documents!$E$2:$E$1421,Documents!$A$2:$A$1421,$A27,Documents!$C$2:$C$1421,"map")),"") | H27: =IFERROR(IF(maxifs(Documents!$E$2:$E$1421,Documents!$A$2:$A$1421,$A27,Documents!$C$2:$C$1421,"dive_map")=0,"",maxifs(Documents!$E$2:$E$1421,Documents!$A$2:$A$1421,$A27,Documents!$C$2:$C$1421,"dive_map")),"") | I27: =IFERROR(IF(maxifs(Documents!$E$2:$E$1421,Documents!$A$2:$A$1421,$A27,Documents!$C$2:$C$1421,"spa_menu")=0,"",maxifs(Documents!$E$2:$E$1421,Documents!$A$2:$A$1421,$A27,Documents!$C$2:$C$1421,"spa_menu")),"") | J27: =IFERROR(IF(maxifs(Documents!$E$2:$E$1421,Documents!$A$2:$A$1421,$A27,Documents!$C$2:$C$1421,"dining_menu")=0,"",maxifs(Documents!$E$2:$E$1421,Documents!$A$2:$A$1421,$A27,Documents!$C$2:$C$1421,"dining_menu")),"") | K27: =IFERROR(IF(maxifs(Documents!$E$2:$E$1421,Documents!$A$2:$A$1421,$A27,Documents!$C$2:$C$1421,"dive_prices")=0,"",maxifs(Documents!$E$2:$E$1421,Documents!$A$2:$A$1421,$A27,Documents!$C$2:$C$1421,"dive_prices")),"") | L27: =IFERROR(IF(maxifs(Documents!$E$2:$E$1421,Documents!$A$2:$A$1421,$A27,Documents!$C$2:$C$1421,"excursions")=0,"",maxifs(Documents!$E$2:$E$1421,Documents!$A$2:$A$1421,$A27,Documents!$C$2:$C$1421,"excursions")),"") | M27: =IFERROR(IF(maxifs(Documents!$E$2:$E$1421,Documents!$A$2:$A$1421,$A27,Documents!$C$2:$C$1421,"kids")=0,"",maxifs(Documents!$E$2:$E$1421,Documents!$A$2:$A$1421,$A27,Documents!$C$2:$C$1421,"kids")),"") | N27: =IFERROR(IF(maxifs(Documents!$E$2:$E$1421,Documents!$A$2:$A$1421,$A27,Documents!$C$2:$C$1421,"villa_plans")=0,"",maxifs(Documents!$E$2:$E$1421,Documents!$A$2:$A$1421,$A27,Documents!$C$2:$C$1421,"villa_plans")),"") | O27: =IFERROR(IF(maxifs(Documents!$E$2:$E$1421,Documents!$A$2:$A$1421,$A27,Documents!$C$2:$C$1421,"all_inclusive")=0,"",maxifs(Documents!$E$2:$E$1421,Documents!$A$2:$A$1421,$A27,Documents!$C$2:$C$1421,"all_inclusive")),"") | P27: =IFERROR(IF(maxifs(Documents!$E$2:$E$1421,Documents!$A$2:$A$1421,$A27,Documents!$C$2:$C$1421,"sustainability")=0,"",maxifs(Documents!$E$2:$E$1421,Documents!$A$2:$A$1421,$A27,Documents!$C$2:$C$1421,"sustainability")),"") | Q27: =IFERROR(IF(maxifs(Documents!$E$2:$E$1421,Documents!$A$2:$A$1421,$A27,Documents!$C$2:$C$1421,"calendar")=0,"",maxifs(Documents!$E$2:$E$1421,Documents!$A$2:$A$1421,$A27,Documents!$C$2:$C$1421,"calendar")),"") | R27: =IFERROR(IF(maxifs(Documents!$E$2:$E$1421,Documents!$A$2:$A$1421,$A27,Documents!$C$2:$C$1421,"brochure")=0,"",maxifs(Documents!$E$2:$E$1421,Documents!$A$2:$A$1421,$A27,Documents!$C$2:$C$1421,"brochure")),"") | S27: =IFERROR(IF(maxifs(Documents!$E$2:$E$1421,Documents!$A$2:$A$1421,$A27,Documents!$C$2:$C$1421,"press_kit")=0,"",maxifs(Documents!$E$2:$E$1421,Documents!$A$2:$A$1421,$A27,Documents!$C$2:$C$1421,"press_kit")),"") | T27: =IFERROR(IF(maxifs(Documents!$E$2:$E$1421,Documents!$A$2:$A$1421,$A27,Documents!$C$2:$C$1421,"other")=0,"",maxifs(Documents!$E$2:$E$1421,Documents!$A$2:$A$1421,$A27,Documents!$C$2:$C$1421,"other")),"") | U27: =IFERROR(IF(maxifs(Documents!$E$2:$E$1421,Documents!$A$2:$A$1421,$A27,Documents!$C$2:$C$1421,"obsolete")=0,"",maxifs(Documents!$E$2:$E$1421,Documents!$A$2:$A$1421,$A27,Documents!$C$2:$C$1421,"obsolete")),"") | V27: =COUNTIFS(Documents!$A$2:$A$1421,$A27) -> 6 | W27: =COUNTIFS(Documents!$A$2:$A$1421,$A27,Documents!$R$2:$R$1421,"current") -> 4 | X27: =HYPERLINK("https://www.centarahotelsresorts.com/centara/sites/centara-centara/files/2025-12/609_CRF_Factsheet_Y251203.pdf","2025_609_CRF_Factsheet_Y251203.pdf") -> 2025_609_CRF_Factsheet_Y251203.pdf | Y27: events
A28: 27 | B28: Grand Park Kodhipparu Maldives | C28: ok | D28: =IFERROR(IF(maxifs(Documents!$E$2:$E$1421,Documents!$A$2:$A$1421,$A28,Documents!$C$2:$C$1421,"factsheet")=0,"",maxifs(Documents!$E$2:$E$1421,Documents!$A$2:$A$1421,$A28,Documents!$C$2:$C$1421,"factsheet")),"") | E28: =IFERROR(IF(maxifs(Documents!$E$2:$E$1421,Documents!$A$2:$A$1421,$A28,Documents!$C$2:$C$1421,"wedding")=0,"",maxifs(Documents!$E$2:$E$1421,Documents!$A$2:$A$1421,$A28,Documents!$C$2:$C$1421,"wedding")),"") | F28: =IFERROR(IF(maxifs(Documents!$E$2:$E$1421,Documents!$A$2:$A$1421,$A28,Documents!$C$2:$C$1421,"events")=0,"",maxifs(Documents!$E$2:$E$1421,Documents!$A$2:$A$1421,$A28,Documents!$C$2:$C$1421,"events")),"") | G28: =IFERROR(IF(maxifs(Documents!$E$2:$E$1421,Documents!$A$2:$A$1421,$A28,Documents!$C$2:$C$1421,"map")=0,"",maxifs(Documents!$E$2:$E$1421,Documents!$A$2:$A$1421,$A28,Documents!$C$2:$C$1421,"map")),"") | H28: =IFERROR(IF(maxifs(Documents!$E$2:$E$1421,Documents!$A$2:$A$1421,$A28,Documents!$C$2:$C$1421,"dive_map")=0,"",maxifs(Documents!$E$2:$E$1421,Documents!$A$2:$A$1421,$A28,Documents!$C$2:$C$1421,"dive_map")),"") | I28: =IFERROR(IF(maxifs(Documents!$E$2:$E$1421,Documents!$A$2:$A$1421,$A28,Documents!$C$2:$C$1421,"spa_menu")=0,"",maxifs(Documents!$E$2:$E$1421,Documents!$A$2:$A$1421,$A28,Documents!$C$2:$C$1421,"spa_menu")),"") | J28: =IFERROR(IF(maxifs(Documents!$E$2:$E$1421,Documents!$A$2:$A$1421,$A28,Documents!$C$2:$C$1421,"dining_menu")=0,"",maxifs(Documents!$E$2:$E$1421,Documents!$A$2:$A$1421,$A28,Documents!$C$2:$C$1421,"dining_menu")),"") | K28: =IFERROR(IF(maxifs(Documents!$E$2:$E$1421,Documents!$A$2:$A$1421,$A28,Documents!$C$2:$C$1421,"dive_prices")=0,"",maxifs(Documents!$E$2:$E$1421,Documents!$A$2:$A$1421,$A28,Documents!$C$2:$C$1421,"dive_prices")),"") | L28: =IFERROR(IF(maxifs(Documents!$E$2:$E$1421,Documents!$A$2:$A$1421,$A28,Documents!$C$2:$C$1421,"excursions")=0,"",maxifs(Documents!$E$2:$E$1421,Documents!$A$2:$A$1421,$A28,Documents!$C$2:$C$1421,"excursions")),"") | M28: =IFERROR(IF(maxifs(Documents!$E$2:$E$1421,Documents!$A$2:$A$1421,$A28,Documents!$C$2:$C$1421,"kids")=0,"",maxifs(Documents!$E$2:$E$1421,Documents!$A$2:$A$1421,$A28,Documents!$C$2:$C$1421,"kids")),"") | N28: =IFERROR(IF(maxifs(Documents!$E$2:$E$1421,Documents!$A$2:$A$1421,$A28,Documents!$C$2:$C$1421,"villa_plans")=0,"",maxifs(Documents!$E$2:$E$1421,Documents!$A$2:$A$1421,$A28,Documents!$C$2:$C$1421,"villa_plans")),"") | O28: =IFERROR(IF(maxifs(Documents!$E$2:$E$1421,Documents!$A$2:$A$1421,$A28,Documents!$C$2:$C$1421,"all_inclusive")=0,"",maxifs(Documents!$E$2:$E$1421,Documents!$A$2:$A$1421,$A28,Documents!$C$2:$C$1421,"all_inclusive")),"") | P28: =IFERROR(IF(maxifs(Documents!$E$2:$E$1421,Documents!$A$2:$A$1421,$A28,Documents!$C$2:$C$1421,"sustainability")=0,"",maxifs(Documents!$E$2:$E$1421,Documents!$A$2:$A$1421,$A28,Documents!$C$2:$C$1421,"sustainability")),"") | Q28: =IFERROR(IF(maxifs(Documents!$E$2:$E$1421,Documents!$A$2:$A$1421,$A28,Documents!$C$2:$C$1421,"calendar")=0,"",maxifs(Documents!$E$2:$E$1421,Documents!$A$2:$A$1421,$A28,Documents!$C$2:$C$1421,"calendar")),"") | R28: =IFERROR(IF(maxifs(Documents!$E$2:$E$1421,Documents!$A$2:$A$1421,$A28,Documents!$C$2:$C$1421,"brochure")=0,"",maxifs(Documents!$E$2:$E$1421,Documents!$A$2:$A$1421,$A28,Documents!$C$2:$C$1421,"brochure")),"") | S28: =IFERROR(IF(maxifs(Documents!$E$2:$E$1421,Documents!$A$2:$A$1421,$A28,Documents!$C$2:$C$1421,"press_kit")=0,"",maxifs(Documents!$E$2:$E$1421,Documents!$A$2:$A$1421,$A28,Documents!$C$2:$C$1421,"press_kit")),"") | T28: =IFERROR(IF(maxifs(Documents!$E$2:$E$1421,Documents!$A$2:$A$1421,$A28,Documents!$C$2:$C$1421,"other")=0,"",maxifs(Documents!$E$2:$E$1421,Documents!$A$2:$A$1421,$A28,Documents!$C$2:$C$1421,"other")),"") | U28: =IFERROR(IF(maxifs(Documents!$E$2:$E$1421,Documents!$A$2:$A$1421,$A28,Documents!$C$2:$C$1421,"obsolete")=0,"",maxifs(Documents!$E$2:$E$1421,Documents!$A$2:$A$1421,$A28,Documents!$C$2:$C$1421,"obsolete")),"") | V28: =COUNTIFS(Documents!$A$2:$A$1421,$A28) -> 5 | W28: =COUNTIFS(Documents!$A$2:$A$1421,$A28,Documents!$R$2:$R$1421,"current") -> 1 | X28: =HYPERLINK("https://www.neoscapesmaldives.com/wp-content/uploads/GPKD-Resort-Factsheet-2022.pdf","2022_GPKD-Resort-Factsheet-2022.pdf") -> 2022_GPKD-Resort-Factsheet-2022.pdf | Y28: wedding, events
A29: 28 | B29: Kudadoo Maldives Private island | C29: ok | D29: =IFERROR(IF(maxifs(Documents!$E$2:$E$1421,Documents!$A$2:$A$1421,$A29,Documents!$C$2:$C$1421,"factsheet")=0,"",maxifs(Documents!$E$2:$E$1421,Documents!$A$2:$A$1421,$A29,Documents!$C$2:$C$1421,"factsheet")),"") | E29: =IFERROR(IF(maxifs(Documents!$E$2:$E$1421,Documents!$A$2:$A$1421,$A29,Documents!$C$2:$C$1421,"wedding")=0,"",maxifs(Documents!$E$2:$E$1421,Documents!$A$2:$A$1421,$A29,Documents!$C$2:$C$1421,"wedding")),"") | F29: =IFERROR(IF(maxifs(Documents!$E$2:$E$1421,Documents!$A$2:$A$1421,$A29,Documents!$C$2:$C$1421,"events")=0,"",maxifs(Documents!$E$2:$E$1421,Documents!$A$2:$A$1421,$A29,Documents!$C$2:$C$1421,"events")),"") | G29: =IFERROR(IF(maxifs(Documents!$E$2:$E$1421,Documents!$A$2:$A$1421,$A29,Documents!$C$2:$C$1421,"map")=0,"",maxifs(Documents!$E$2:$E$1421,Documents!$A$2:$A$1421,$A29,Documents!$C$2:$C$1421,"map")),"") | H29: =IFERROR(IF(maxifs(Documents!$E$2:$E$1421,Documents!$A$2:$A$1421,$A29,Documents!$C$2:$C$1421,"dive_map")=0,"",maxifs(Documents!$E$2:$E$1421,Documents!$A$2:$A$1421,$A29,Documents!$C$2:$C$1421,"dive_map")),"") | I29: =IFERROR(IF(maxifs(Documents!$E$2:$E$1421,Documents!$A$2:$A$1421,$A29,Documents!$C$2:$C$1421,"spa_menu")=0,"",maxifs(Documents!$E$2:$E$1421,Documents!$A$2:$A$1421,$A29,Documents!$C$2:$C$1421,"spa_menu")),"") | J29: =IFERROR(IF(maxifs(Documents!$E$2:$E$1421,Documents!$A$2:$A$1421,$A29,Documents!$C$2:$C$1421,"dining_menu")=0,"",maxifs(Documents!$E$2:$E$1421,Documents!$A$2:$A$1421,$A29,Documents!$C$2:$C$1421,"dining_menu")),"") | K29: =IFERROR(IF(maxifs(Documents!$E$2:$E$1421,Documents!$A$2:$A$1421,$A29,Documents!$C$2:$C$1421,"dive_prices")=0,"",maxifs(Documents!$E$2:$E$1421,Documents!$A$2:$A$1421,$A29,Documents!$C$2:$C$1421,"dive_prices")),"") | L29: =IFERROR(IF(maxifs(Documents!$E$2:$E$1421,Documents!$A$2:$A$1421,$A29,Documents!$C$2:$C$1421,"excursions")=0,"",maxifs(Documents!$E$2:$E$1421,Documents!$A$2:$A$1421,$A29,Documents!$C$2:$C$1421,"excursions")),"") | M29: =IFERROR(IF(maxifs(Documents!$E$2:$E$1421,Documents!$A$2:$A$1421,$A29,Documents!$C$2:$C$1421,"kids")=0,"",maxifs(Documents!$E$2:$E$1421,Documents!$A$2:$A$1421,$A29,Documents!$C$2:$C$1421,"kids")),"") | N29: =IFERROR(IF(maxifs(Documents!$E$2:$E$1421,Documents!$A$2:$A$1421,$A29,Documents!$C$2:$C$1421,"villa_plans")=0,"",maxifs(Documents!$E$2:$E$1421,Documents!$A$2:$A$1421,$A29,Documents!$C$2:$C$1421,"villa_plans")),"") | O29: =IFERROR(IF(maxifs(Documents!$E$2:$E$1421,Documents!$A$2:$A$1421,$A29,Documents!$C$2:$C$1421,"all_inclusive")=0,"",maxifs(Documents!$E$2:$E$1421,Documents!$A$2:$A$1421,$A29,Documents!$C$2:$C$1421,"all_inclusive")),"") | P29: =IFERROR(IF(maxifs(Documents!$E$2:$E$1421,Documents!$A$2:$A$1421,$A29,Documents!$C$2:$C$1421,"sustainability")=0,"",maxifs(Documents!$E$2:$E$1421,Documents!$A$2:$A$1421,$A29,Documents!$C$2:$C$1421,"sustainability")),"") | Q29: =IFERROR(IF(maxifs(Documents!$E$2:$E$1421,Documents!$A$2:$A$1421,$A29,Documents!$C$2:$C$1421,"calendar")=0,"",maxifs(Documents!$E$2:$E$1421,Documents!$A$2:$A$1421,$A29,Documents!$C$2:$C$1421,"calendar")),"") | R29: =IFERROR(IF(maxifs(Documents!$E$2:$E$1421,Documents!$A$2:$A$1421,$A29,Documents!$C$2:$C$1421,"brochure")=0,"",maxifs(Documents!$E$2:$E$1421,Documents!$A$2:$A$1421,$A29,Documents!$C$2:$C$1421,"brochure")),"") | S29: =IFERROR(IF(maxifs(Documents!$E$2:$E$1421,Documents!$A$2:$A$1421,$A29,Documents!$C$2:$C$1421,"press_kit")=0,"",maxifs(Documents!$E$2:$E$1421,Documents!$A$2:$A$1421,$A29,Documents!$C$2:$C$1421,"press_kit")),"") | T29: =IFERROR(IF(maxifs(Documents!$E$2:$E$1421,Documents!$A$2:$A$1421,$A29,Documents!$C$2:$C$1421,"other")=0,"",maxifs(Documents!$E$2:$E$1421,Documents!$A$2:$A$1421,$A29,Documents!$C$2:$C$1421,"other")),"") | U29: =IFERROR(IF(maxifs(Documents!$E$2:$E$1421,Documents!$A$2:$A$1421,$A29,Documents!$C$2:$C$1421,"obsolete")=0,"",maxifs(Documents!$E$2:$E$1421,Documents!$A$2:$A$1421,$A29,Documents!$C$2:$C$1421,"obsolete")),"") | V29: =COUNTIFS(Documents!$A$2:$A$1421,$A29) -> 14 | W29: =COUNTIFS(Documents!$A$2:$A$1421,$A29,Documents!$R$2:$R$1421,"current") -> 6 | X29: =HYPERLINK("https://sales.crownandchamparesorts.com/wp-content/uploads/2025/12/KudadooFactsheet110125103126Ver0526255.pdf","2025_KudadooFactsheet110125103126Ver0526") -> 2025_KudadooFactsheet110125103126Ver0526 | Y29: wedding, events
A30: 29 | B30: Dheruhfinolhu by Jawakara Islands Maldives | C30: ok | D30: =IFERROR(IF(maxifs(Documents!$E$2:$E$1421,Documents!$A$2:$A$1421,$A30,Documents!$C$2:$C$1421,"factsheet")=0,"",maxifs(Documents!$E$2:$E$1421,Documents!$A$2:$A$1421,$A30,Documents!$C$2:$C$1421,"factsheet")),"") | E30: =IFERROR(IF(maxifs(Documents!$E$2:$E$1421,Documents!$A$2:$A$1421,$A30,Documents!$C$2:$C$1421,"wedding")=0,"",maxifs(Documents!$E$2:$E$1421,Documents!$A$2:$A$1421,$A30,Documents!$C$2:$C$1421,"wedding")),"") | F30: =IFERROR(IF(maxifs(Documents!$E$2:$E$1421,Documents!$A$2:$A$1421,$A30,Documents!$C$2:$C$1421,"events")=0,"",maxifs(Documents!$E$2:$E$1421,Documents!$A$2:$A$1421,$A30,Documents!$C$2:$C$1421,"events")),"") | G30: =IFERROR(IF(maxifs(Documents!$E$2:$E$1421,Documents!$A$2:$A$1421,$A30,Documents!$C$2:$C$1421,"map")=0,"",maxifs(Documents!$E$2:$E$1421,Documents!$A$2:$A$1421,$A30,Documents!$C$2:$C$1421,"map")),"") | H30: =IFERROR(IF(maxifs(Documents!$E$2:$E$1421,Documents!$A$2:$A$1421,$A30,Documents!$C$2:$C$1421,"dive_map")=0,"",maxifs(Documents!$E$2:$E$1421,Documents!$A$2:$A$1421,$A30,Documents!$C$2:$C$1421,"dive_map")),"") | I30: =IFERROR(IF(maxifs(Documents!$E$2:$E$1421,Documents!$A$2:$A$1421,$A30,Documents!$C$2:$C$1421,"spa_menu")=0,"",maxifs(Documents!$E$2:$E$1421,Documents!$A$2:$A$1421,$A30,Documents!$C$2:$C$1421,"spa_menu")),"") | J30: =IFERROR(IF(maxifs(Documents!$E$2:$E$1421,Documents!$A$2:$A$1421,$A30,Documents!$C$2:$C$1421,"dining_menu")=0,"",maxifs(Documents!$E$2:$E$1421,Documents!$A$2:$A$1421,$A30,Documents!$C$2:$C$1421,"dining_menu")),"") | K30: =IFERROR(IF(maxifs(Documents!$E$2:$E$1421,Documents!$A$2:$A$1421,$A30,Documents!$C$2:$C$1421,"dive_prices")=0,"",maxifs(Documents!$E$2:$E$1421,Documents!$A$2:$A$1421,$A30,Documents!$C$2:$C$1421,"dive_prices")),"") | L30: =IFERROR(IF(maxifs(Documents!$E$2:$E$1421,Documents!$A$2:$A$1421,$A30,Documents!$C$2:$C$1421,"excursions")=0,"",maxifs(Documents!$E$2:$E$1421,Documents!$A$2:$A$1421,$A30,Documents!$C$2:$C$1421,"excursions")),"") | M30: =IFERROR(IF(maxifs(Documents!$E$2:$E$1421,Documents!$A$2:$A$1421,$A30,Documents!$C$2:$C$1421,"kids")=0,"",maxifs(Documents!$E$2:$E$1421,Documents!$A$2:$A$1421,$A30,Documents!$C$2:$C$1421,"kids")),"") | N30: =IFERROR(IF(maxifs(Documents!$E$2:$E$1421,Documents!$A$2:$A$1421,$A30,Documents!$C$2:$C$1421,"villa_plans")=0,"",maxifs(Documents!$E$2:$E$1421,Documents!$A$2:$A$1421,$A30,Documents!$C$2:$C$1421,"villa_plans")),"") | O30: =IFERROR(IF(maxifs(Documents!$E$2:$E$1421,Documents!$A$2:$A$1421,$A30,Documents!$C$2:$C$1421,"all_inclusive")=0,"",maxifs(Documents!$E$2:$E$1421,Documents!$A$2:$A$1421,$A30,Documents!$C$2:$C$1421,"all_inclusive")),"") | P30: =IFERROR(IF(maxifs(Documents!$E$2:$E$1421,Documents!$A$2:$A$1421,$A30,Documents!$C$2:$C$1421,"sustainability")=0,"",maxifs(Documents!$E$2:$E$1421,Documents!$A$2:$A$1421,$A30,Documents!$C$2:$C$1421,"sustainability")),"") | Q30: =IFERROR(IF(maxifs(Documents!$E$2:$E$1421,Documents!$A$2:$A$1421,$A30,Documents!$C$2:$C$1421,"calendar")=0,"",maxifs(Documents!$E$2:$E$1421,Documents!$A$2:$A$1421,$A30,Documents!$C$2:$C$1421,"calendar")),"") | R30: =IFERROR(IF(maxifs(Documents!$E$2:$E$1421,Documents!$A$2:$A$1421,$A30,Documents!$C$2:$C$1421,"brochure")=0,"",maxifs(Documents!$E$2:$E$1421,Documents!$A$2:$A$1421,$A30,Documents!$C$2:$C$1421,"brochure")),"") | S30: =IFERROR(IF(maxifs(Documents!$E$2:$E$1421,Documents!$A$2:$A$1421,$A30,Documents!$C$2:$C$1421,"press_kit")=0,"",maxifs(Documents!$E$2:$E$1421,Documents!$A$2:$A$1421,$A30,Documents!$C$2:$C$1421,"press_kit")),"") | T30: =IFERROR(IF(maxifs(Documents!$E$2:$E$1421,Documents!$A$2:$A$1421,$A30,Documents!$C$2:$C$1421,"other")=0,"",maxifs(Documents!$E$2:$E$1421,Documents!$A$2:$A$1421,$A30,Documents!$C$2:$C$1421,"other")),"") | U30: =IFERROR(IF(maxifs(Documents!$E$2:$E$1421,Documents!$A$2:$A$1421,$A30,Documents!$C$2:$C$1421,"obsolete")=0,"",maxifs(Documents!$E$2:$E$1421,Documents!$A$2:$A$1421,$A30,Documents!$C$2:$C$1421,"obsolete")),"") | V30: =COUNTIFS(Documents!$A$2:$A$1421,$A30) -> 3 | W30: =COUNTIFS(Documents!$A$2:$A$1421,$A30,Documents!$R$2:$R$1421,"current") -> 1 | X30: =HYPERLINK("https://sales.crownandchamparesorts.com/wp-content/uploads/2026/04/NalaMaldivesFactsheet011125311026Ver030426.pdf","2025_NalaMaldivesFactsheet011125311026Ve") -> 2025_NalaMaldivesFactsheet011125311026Ve | Y30: wedding, events | Z30: Jawakara Islands (shared documents)
A31: 30 | B31: Hurawalhi Island Resort | C31: ok | D31: =IFERROR(IF(maxifs(Documents!$E$2:$E$1421,Documents!$A$2:$A$1421,$A31,Documents!$C$2:$C$1421,"factsheet")=0,"",maxifs(Documents!$E$2:$E$1421,Documents!$A$2:$A$1421,$A31,Documents!$C$2:$C$1421,"factsheet")),"") | E31: =IFERROR(IF(maxifs(Documents!$E$2:$E$1421,Documents!$A$2:$A$1421,$A31,Documents!$C$2:$C$1421,"wedding")=0,"",maxifs(Documents!$E$2:$E$1421,Documents!$A$2:$A$1421,$A31,Documents!$C$2:$C$1421,"wedding")),"") | F31: =IFERROR(IF(maxifs(Documents!$E$2:$E$1421,Documents!$A$2:$A$1421,$A31,Documents!$C$2:$C$1421,"events")=0,"",maxifs(Documents!$E$2:$E$1421,Documents!$A$2:$A$1421,$A31,Documents!$C$2:$C$1421,"events")),"") | G31: =IFERROR(IF(maxifs(Documents!$E$2:$E$1421,Documents!$A$2:$A$1421,$A31,Documents!$C$2:$C$1421,"map")=0,"",maxifs(Documents!$E$2:$E$1421,Documents!$A$2:$A$1421,$A31,Documents!$C$2:$C$1421,"map")),"") | H31: =IFERROR(IF(maxifs(Documents!$E$2:$E$1421,Documents!$A$2:$A$1421,$A31,Documents!$C$2:$C$1421,"dive_map")=0,"",maxifs(Documents!$E$2:$E$1421,Documents!$A$2:$A$1421,$A31,Documents!$C$2:$C$1421,"dive_map")),"") | I31: =IFERROR(IF(maxifs(Documents!$E$2:$E$1421,Documents!$A$2:$A$1421,$A31,Documents!$C$2:$C$1421,"spa_menu")=0,"",maxifs(Documents!$E$2:$E$1421,Documents!$A$2:$A$1421,$A31,Documents!$C$2:$C$1421,"spa_menu")),"") | J31: =IFERROR(IF(maxifs(Documents!$E$2:$E$1421,Documents!$A$2:$A$1421,$A31,Documents!$C$2:$C$1421,"dining_menu")=0,"",maxifs(Documents!$E$2:$E$1421,Documents!$A$2:$A$1421,$A31,Documents!$C$2:$C$1421,"dining_menu")),"") | K31: =IFERROR(IF(maxifs(Documents!$E$2:$E$1421,Documents!$A$2:$A$1421,$A31,Documents!$C$2:$C$1421,"dive_prices")=0,"",maxifs(Documents!$E$2:$E$1421,Documents!$A$2:$A$1421,$A31,Documents!$C$2:$C$1421,"dive_prices")),"") | L31: =IFERROR(IF(maxifs(Documents!$E$2:$E$1421,Documents!$A$2:$A$1421,$A31,Documents!$C$2:$C$1421,"excursions")=0,"",maxifs(Documents!$E$2:$E$1421,Documents!$A$2:$A$1421,$A31,Documents!$C$2:$C$1421,"excursions")),"") | M31: =IFERROR(IF(maxifs(Documents!$E$2:$E$1421,Documents!$A$2:$A$1421,$A31,Documents!$C$2:$C$1421,"kids")=0,"",maxifs(Documents!$E$2:$E$1421,Documents!$A$2:$A$1421,$A31,Documents!$C$2:$C$1421,"kids")),"") | N31: =IFERROR(IF(maxifs(Documents!$E$2:$E$1421,Documents!$A$2:$A$1421,$A31,Documents!$C$2:$C$1421,"villa_plans")=0,"",maxifs(Documents!$E$2:$E$1421,Documents!$A$2:$A$1421,$A31,Documents!$C$2:$C$1421,"villa_plans")),"") | O31: =IFERROR(IF(maxifs(Documents!$E$2:$E$1421,Documents!$A$2:$A$1421,$A31,Documents!$C$2:$C$1421,"all_inclusive")=0,"",maxifs(Documents!$E$2:$E$1421,Documents!$A$2:$A$1421,$A31,Documents!$C$2:$C$1421,"all_inclusive")),"") | P31: =IFERROR(IF(maxifs(Documents!$E$2:$E$1421,Documents!$A$2:$A$1421,$A31,Documents!$C$2:$C$1421,"sustainability")=0,"",maxifs(Documents!$E$2:$E$1421,Documents!$A$2:$A$1421,$A31,Documents!$C$2:$C$1421,"sustainability")),"") | Q31: =IFERROR(IF(maxifs(Documents!$E$2:$E$1421,Documents!$A$2:$A$1421,$A31,Documents!$C$2:$C$1421,"calendar")=0,"",maxifs(Documents!$E$2:$E$1421,Documents!$A$2:$A$1421,$A31,Documents!$C$2:$C$1421,"calendar")),"") | R31: =IFERROR(IF(maxifs(Documents!$E$2:$E$1421,Documents!$A$2:$A$1421,$A31,Documents!$C$2:$C$1421,"brochure")=0,"",maxifs(Documents!$E$2:$E$1421,Documents!$A$2:$A$1421,$A31,Documents!$C$2:$C$1421,"brochure")),"") | S31: =IFERROR(IF(maxifs(Documents!$E$2:$E$1421,Documents!$A$2:$A$1421,$A31,Documents!$C$2:$C$1421,"press_kit")=0,"",maxifs(Documents!$E$2:$E$1421,Documents!$A$2:$A$1421,$A31,Documents!$C$2:$C$1421,"press_kit")),"") | T31: =IFERROR(IF(maxifs(Documents!$E$2:$E$1421,Documents!$A$2:$A$1421,$A31,Documents!$C$2:$C$1421,"other")=0,"",maxifs(Documents!$E$2:$E$1421,Documents!$A$2:$A$1421,$A31,Documents!$C$2:$C$1421,"other")),"") | U31: =IFERROR(IF(maxifs(Documents!$E$2:$E$1421,Documents!$A$2:$A$1421,$A31,Documents!$C$2:$C$1421,"obsolete")=0,"",maxifs(Documents!$E$2:$E$1421,Documents!$A$2:$A$1421,$A31,Documents!$C$2:$C$1421,"obsolete")),"") | V31: =COUNTIFS(Documents!$A$2:$A$1421,$A31) -> 8 | W31: =COUNTIFS(Documents!$A$2:$A$1421,$A31,Documents!$R$2:$R$1421,"current") -> 0 | X31: =HYPERLINK("https://sales.crownandchamparesorts.com/wp-content/uploads/2023/08/FactSheetHurawalhi110123103124Ver030123.pdf","2023_FactSheetHurawalhi110123103124Ver03") -> 2023_FactSheetHurawalhi110123103124Ver03 | Y31: events
A32: 31 | B32: Innahura Maldives Resort | C32: unverified | D32: =IFERROR(IF(maxifs(Documents!$E$2:$E$1421,Documents!$A$2:$A$1421,$A32,Documents!$C$2:$C$1421,"factsheet")=0,"",maxifs(Documents!$E$2:$E$1421,Documents!$A$2:$A$1421,$A32,Documents!$C$2:$C$1421,"factsheet")),"") | E32: =IFERROR(IF(maxifs(Documents!$E$2:$E$1421,Documents!$A$2:$A$1421,$A32,Documents!$C$2:$C$1421,"wedding")=0,"",maxifs(Documents!$E$2:$E$1421,Documents!$A$2:$A$1421,$A32,Documents!$C$2:$C$1421,"wedding")),"") | F32: =IFERROR(IF(maxifs(Documents!$E$2:$E$1421,Documents!$A$2:$A$1421,$A32,Documents!$C$2:$C$1421,"events")=0,"",maxifs(Documents!$E$2:$E$1421,Documents!$A$2:$A$1421,$A32,Documents!$C$2:$C$1421,"events")),"") | G32: =IFERROR(IF(maxifs(Documents!$E$2:$E$1421,Documents!$A$2:$A$1421,$A32,Documents!$C$2:$C$1421,"map")=0,"",maxifs(Documents!$E$2:$E$1421,Documents!$A$2:$A$1421,$A32,Documents!$C$2:$C$1421,"map")),"") | H32: =IFERROR(IF(maxifs(Documents!$E$2:$E$1421,Documents!$A$2:$A$1421,$A32,Documents!$C$2:$C$1421,"dive_map")=0,"",maxifs(Documents!$E$2:$E$1421,Documents!$A$2:$A$1421,$A32,Documents!$C$2:$C$1421,"dive_map")),"") | I32: =IFERROR(IF(maxifs(Documents!$E$2:$E$1421,Documents!$A$2:$A$1421,$A32,Documents!$C$2:$C$1421,"spa_menu")=0,"",maxifs(Documents!$E$2:$E$1421,Documents!$A$2:$A$1421,$A32,Documents!$C$2:$C$1421,"spa_menu")),"") | J32: =IFERROR(IF(maxifs(Documents!$E$2:$E$1421,Documents!$A$2:$A$1421,$A32,Documents!$C$2:$C$1421,"dining_menu")=0,"",maxifs(Documents!$E$2:$E$1421,Documents!$A$2:$A$1421,$A32,Documents!$C$2:$C$1421,"dining_menu")),"") | K32: =IFERROR(IF(maxifs(Documents!$E$2:$E$1421,Documents!$A$2:$A$1421,$A32,Documents!$C$2:$C$1421,"dive_prices")=0,"",maxifs(Documents!$E$2:$E$1421,Documents!$A$2:$A$1421,$A32,Documents!$C$2:$C$1421,"dive_prices")),"") | L32: =IFERROR(IF(maxifs(Documents!$E$2:$E$1421,Documents!$A$2:$A$1421,$A32,Documents!$C$2:$C$1421,"excursions")=0,"",maxifs(Documents!$E$2:$E$1421,Documents!$A$2:$A$1421,$A32,Documents!$C$2:$C$1421,"excursions")),"") | M32: =IFERROR(IF(maxifs(Documents!$E$2:$E$1421,Documents!$A$2:$A$1421,$A32,Documents!$C$2:$C$1421,"kids")=0,"",maxifs(Documents!$E$2:$E$1421,Documents!$A$2:$A$1421,$A32,Documents!$C$2:$C$1421,"kids")),"") | N32: =IFERROR(IF(maxifs(Documents!$E$2:$E$1421,Documents!$A$2:$A$1421,$A32,Documents!$C$2:$C$1421,"villa_plans")=0,"",maxifs(Documents!$E$2:$E$1421,Documents!$A$2:$A$1421,$A32,Documents!$C$2:$C$1421,"villa_plans")),"") | O32: =IFERROR(IF(maxifs(Documents!$E$2:$E$1421,Documents!$A$2:$A$1421,$A32,Documents!$C$2:$C$1421,"all_inclusive")=0,"",maxifs(Documents!$E$2:$E$1421,Documents!$A$2:$A$1421,$A32,Documents!$C$2:$C$1421,"all_inclusive")),"") | P32: =IFERROR(IF(maxifs(Documents!$E$2:$E$1421,Documents!$A$2:$A$1421,$A32,Documents!$C$2:$C$1421,"sustainability")=0,"",maxifs(Documents!$E$2:$E$1421,Documents!$A$2:$A$1421,$A32,Documents!$C$2:$C$1421,"sustainability")),"") | Q32: =IFERROR(IF(maxifs(Documents!$E$2:$E$1421,Documents!$A$2:$A$1421,$A32,Documents!$C$2:$C$1421,"calendar")=0,"",maxifs(Documents!$E$2:$E$1421,Documents!$A$2:$A$1421,$A32,Documents!$C$2:$C$1421,"calendar")),"") | R32: =IFERROR(IF(maxifs(Documents!$E$2:$E$1421,Documents!$A$2:$A$1421,$A32,Documents!$C$2:$C$1421,"brochure")=0,"",maxifs(Documents!$E$2:$E$1421,Documents!$A$2:$A$1421,$A32,Documents!$C$2:$C$1421,"brochure")),"") | S32: =IFERROR(IF(maxifs(Documents!$E$2:$E$1421,Documents!$A$2:$A$1421,$A32,Documents!$C$2:$C$1421,"press_kit")=0,"",maxifs(Documents!$E$2:$E$1421,Documents!$A$2:$A$1421,$A32,Documents!$C$2:$C$1421,"press_kit")),"") | T32: =IFERROR(IF(maxifs(Documents!$E$2:$E$1421,Documents!$A$2:$A$1421,$A32,Documents!$C$2:$C$1421,"other")=0,"",maxifs(Documents!$E$2:$E$1421,Documents!$A$2:$A$1421,$A32,Documents!$C$2:$C$1421,"other")),"") | U32: =IFERROR(IF(maxifs(Documents!$E$2:$E$1421,Documents!$A$2:$A$1421,$A32,Documents!$C$2:$C$1421,"obsolete")=0,"",maxifs(Documents!$E$2:$E$1421,Documents!$A$2:$A$1421,$A32,Documents!$C$2:$C$1421,"obsolete")),"") | V32: =COUNTIFS(Documents!$A$2:$A$1421,$A32) -> 4 | W32: =COUNTIFS(Documents!$A$2:$A$1421,$A32,Documents!$R$2:$R$1421,"current") -> 0 | X32: =HYPERLINK("https://sales.crownandchamparesorts.com/wp-content/uploads/2023/08/FactSheetInnahura110121103122Ver110121.pdf","2021_FactSheetInnahura110121103122Ver110") -> 2021_FactSheetInnahura110121103122Ver110 | Y32: wedding, events
A33: 32 | B33: Cocoon Maldives | C33: ok | D33: =IFERROR(IF(maxifs(Documents!$E$2:$E$1421,Documents!$A$2:$A$1421,$A33,Documents!$C$2:$C$1421,"factsheet")=0,"",maxifs(Documents!$E$2:$E$1421,Documents!$A$2:$A$1421,$A33,Documents!$C$2:$C$1421,"factsheet")),"") | E33: =IFERROR(IF(maxifs(Documents!$E$2:$E$1421,Documents!$A$2:$A$1421,$A33,Documents!$C$2:$C$1421,"wedding")=0,"",maxifs(Documents!$E$2:$E$1421,Documents!$A$2:$A$1421,$A33,Documents!$C$2:$C$1421,"wedding")),"") | F33: =IFERROR(IF(maxifs(Documents!$E$2:$E$1421,Documents!$A$2:$A$1421,$A33,Documents!$C$2:$C$1421,"events")=0,"",maxifs(Documents!$E$2:$E$1421,Documents!$A$2:$A$1421,$A33,Documents!$C$2:$C$1421,"events")),"") | G33: =IFERROR(IF(maxifs(Documents!$E$2:$E$1421,Documents!$A$2:$A$1421,$A33,Documents!$C$2:$C$1421,"map")=0,"",maxifs(Documents!$E$2:$E$1421,Documents!$A$2:$A$1421,$A33,Documents!$C$2:$C$1421,"map")),"") | H33: =IFERROR(IF(maxifs(Documents!$E$2:$E$1421,Documents!$A$2:$A$1421,$A33,Documents!$C$2:$C$1421,"dive_map")=0,"",maxifs(Documents!$E$2:$E$1421,Documents!$A$2:$A$1421,$A33,Documents!$C$2:$C$1421,"dive_map")),"") | I33: =IFERROR(IF(maxifs(Documents!$E$2:$E$1421,Documents!$A$2:$A$1421,$A33,Documents!$C$2:$C$1421,"spa_menu")=0,"",maxifs(Documents!$E$2:$E$1421,Documents!$A$2:$A$1421,$A33,Documents!$C$2:$C$1421,"spa_menu")),"") | J33: =IFERROR(IF(maxifs(Documents!$E$2:$E$1421,Documents!$A$2:$A$1421,$A33,Documents!$C$2:$C$1421,"dining_menu")=0,"",maxifs(Documents!$E$2:$E$1421,Documents!$A$2:$A$1421,$A33,Documents!$C$2:$C$1421,"dining_menu")),"") | K33: =IFERROR(IF(maxifs(Documents!$E$2:$E$1421,Documents!$A$2:$A$1421,$A33,Documents!$C$2:$C$1421,"dive_prices")=0,"",maxifs(Documents!$E$2:$E$1421,Documents!$A$2:$A$1421,$A33,Documents!$C$2:$C$1421,"dive_prices")),"") | L33: =IFERROR(IF(maxifs(Documents!$E$2:$E$1421,Documents!$A$2:$A$1421,$A33,Documents!$C$2:$C$1421,"excursions")=0,"",maxifs(Documents!$E$2:$E$1421,Documents!$A$2:$A$1421,$A33,Documents!$C$2:$C$1421,"excursions")),"") | M33: =IFERROR(IF(maxifs(Documents!$E$2:$E$1421,Documents!$A$2:$A$1421,$A33,Documents!$C$2:$C$1421,"kids")=0,"",maxifs(Documents!$E$2:$E$1421,Documents!$A$2:$A$1421,$A33,Documents!$C$2:$C$1421,"kids")),"") | N33: =IFERROR(IF(maxifs(Documents!$E$2:$E$1421,Documents!$A$2:$A$1421,$A33,Documents!$C$2:$C$1421,"villa_plans")=0,"",maxifs(Documents!$E$2:$E$1421,Documents!$A$2:$A$1421,$A33,Documents!$C$2:$C$1421,"villa_plans")),"") | O33: =IFERROR(IF(maxifs(Documents!$E$2:$E$1421,Documents!$A$2:$A$1421,$A33,Documents!$C$2:$C$1421,"all_inclusive")=0,"",maxifs(Documents!$E$2:$E$1421,Documents!$A$2:$A$1421,$A33,Documents!$C$2:$C$1421,"all_inclusive")),"") | P33: =IFERROR(IF(maxifs(Documents!$E$2:$E$1421,Documents!$A$2:$A$1421,$A33,Documents!$C$2:$C$1421,"sustainability")=0,"",maxifs(Documents!$E$2:$E$1421,Documents!$A$2:$A$1421,$A33,Documents!$C$2:$C$1421,"sustainability")),"") | Q33: =IFERROR(IF(maxifs(Documents!$E$2:$E$1421,Documents!$A$2:$A$1421,$A33,Documents!$C$2:$C$1421,"calendar")=0,"",maxifs(Documents!$E$2:$E$1421,Documents!$A$2:$A$1421,$A33,Documents!$C$2:$C$1421,"calendar")),"") | R33: =IFERROR(IF(maxifs(Documents!$E$2:$E$1421,Documents!$A$2:$A$1421,$A33,Documents!$C$2:$C$1421,"brochure")=0,"",maxifs(Documents!$E$2:$E$1421,Documents!$A$2:$A$1421,$A33,Documents!$C$2:$C$1421,"brochure")),"") | S33: =IFERROR(IF(maxifs(Documents!$E$2:$E$1421,Documents!$A$2:$A$1421,$A33,Documents!$C$2:$C$1421,"press_kit")=0,"",maxifs(Documents!$E$2:$E$1421,Documents!$A$2:$A$1421,$A33,Documents!$C$2:$C$1421,"press_kit")),"") | T33: =IFERROR(IF(maxifs(Documents!$E$2:$E$1421,Documents!$A$2:$A$1421,$A33,Documents!$C$2:$C$1421,"other")=0,"",maxifs(Documents!$E$2:$E$1421,Documents!$A$2:$A$1421,$A33,Documents!$C$2:$C$1421,"other")),"") | U33: =IFERROR(IF(maxifs(Documents!$E$2:$E$1421,Documents!$A$2:$A$1421,$A33,Documents!$C$2:$C$1421,"obsolete")=0,"",maxifs(Documents!$E$2:$E$1421,Documents!$A$2:$A$1421,$A33,Documents!$C$2:$C$1421,"obsolete")),"") | V33: =COUNTIFS(Documents!$A$2:$A$1421,$A33) -> 5 | W33: =COUNTIFS(Documents!$A$2:$A$1421,$A33,Documents!$R$2:$R$1421,"current") -> 2 | X33: =HYPERLINK("https://www.neoscapesmaldives.com/wp-content/uploads/Cocoon-Maldives-_-Fact-Sheet.pdf","2025_Cocoon-Maldives-_-Fact-Sheet.pdf") -> 2025_Cocoon-Maldives-_-Fact-Sheet.pdf | Y33: wedding, events
A34: 33 | B34: Dhigali Maldives | C34: ok | D34: =IFERROR(IF(maxifs(Documents!$E$2:$E$1421,Documents!$A$2:$A$1421,$A34,Documents!$C$2:$C$1421,"factsheet")=0,"",maxifs(Documents!$E$2:$E$1421,Documents!$A$2:$A$1421,$A34,Documents!$C$2:$C$1421,"factsheet")),"") | E34: =IFERROR(IF(maxifs(Documents!$E$2:$E$1421,Documents!$A$2:$A$1421,$A34,Documents!$C$2:$C$1421,"wedding")=0,"",maxifs(Documents!$E$2:$E$1421,Documents!$A$2:$A$1421,$A34,Documents!$C$2:$C$1421,"wedding")),"") | F34: =IFERROR(IF(maxifs(Documents!$E$2:$E$1421,Documents!$A$2:$A$1421,$A34,Documents!$C$2:$C$1421,"events")=0,"",maxifs(Documents!$E$2:$E$1421,Documents!$A$2:$A$1421,$A34,Documents!$C$2:$C$1421,"events")),"") | G34: =IFERROR(IF(maxifs(Documents!$E$2:$E$1421,Documents!$A$2:$A$1421,$A34,Documents!$C$2:$C$1421,"map")=0,"",maxifs(Documents!$E$2:$E$1421,Documents!$A$2:$A$1421,$A34,Documents!$C$2:$C$1421,"map")),"") | H34: =IFERROR(IF(maxifs(Documents!$E$2:$E$1421,Documents!$A$2:$A$1421,$A34,Documents!$C$2:$C$1421,"dive_map")=0,"",maxifs(Documents!$E$2:$E$1421,Documents!$A$2:$A$1421,$A34,Documents!$C$2:$C$1421,"dive_map")),"") | I34: =IFERROR(IF(maxifs(Documents!$E$2:$E$1421,Documents!$A$2:$A$1421,$A34,Documents!$C$2:$C$1421,"spa_menu")=0,"",maxifs(Documents!$E$2:$E$1421,Documents!$A$2:$A$1421,$A34,Documents!$C$2:$C$1421,"spa_menu")),"") | J34: =IFERROR(IF(maxifs(Documents!$E$2:$E$1421,Documents!$A$2:$A$1421,$A34,Documents!$C$2:$C$1421,"dining_menu")=0,"",maxifs(Documents!$E$2:$E$1421,Documents!$A$2:$A$1421,$A34,Documents!$C$2:$C$1421,"dining_menu")),"") | K34: =IFERROR(IF(maxifs(Documents!$E$2:$E$1421,Documents!$A$2:$A$1421,$A34,Documents!$C$2:$C$1421,"dive_prices")=0,"",maxifs(Documents!$E$2:$E$1421,Documents!$A$2:$A$1421,$A34,Documents!$C$2:$C$1421,"dive_prices")),"") | L34: =IFERROR(IF(maxifs(Documents!$E$2:$E$1421,Documents!$A$2:$A$1421,$A34,Documents!$C$2:$C$1421,"excursions")=0,"",maxifs(Documents!$E$2:$E$1421,Documents!$A$2:$A$1421,$A34,Documents!$C$2:$C$1421,"excursions")),"") | M34: =IFERROR(IF(maxifs(Documents!$E$2:$E$1421,Documents!$A$2:$A$1421,$A34,Documents!$C$2:$C$1421,"kids")=0,"",maxifs(Documents!$E$2:$E$1421,Documents!$A$2:$A$1421,$A34,Documents!$C$2:$C$1421,"kids")),"") | N34: =IFERROR(IF(maxifs(Documents!$E$2:$E$1421,Documents!$A$2:$A$1421,$A34,Documents!$C$2:$C$1421,"villa_plans")=0,"",maxifs(Documents!$E$2:$E$1421,Documents!$A$2:$A$1421,$A34,Documents!$C$2:$C$1421,"villa_plans")),"") | O34: =IFERROR(IF(maxifs(Documents!$E$2:$E$1421,Documents!$A$2:$A$1421,$A34,Documents!$C$2:$C$1421,"all_inclusive")=0,"",maxifs(Documents!$E$2:$E$1421,Documents!$A$2:$A$1421,$A34,Documents!$C$2:$C$1421,"all_inclusive")),"") | P34: =IFERROR(IF(maxifs(Documents!$E$2:$E$1421,Documents!$A$2:$A$1421,$A34,Documents!$C$2:$C$1421,"sustainability")=0,"",maxifs(Documents!$E$2:$E$1421,Documents!$A$2:$A$1421,$A34,Documents!$C$2:$C$1421,"sustainability")),"") | Q34: =IFERROR(IF(maxifs(Documents!$E$2:$E$1421,Documents!$A$2:$A$1421,$A34,Documents!$C$2:$C$1421,"calendar")=0,"",maxifs(Documents!$E$2:$E$1421,Documents!$A$2:$A$1421,$A34,Documents!$C$2:$C$1421,"calendar")),"") | R34: =IFERROR(IF(maxifs(Documents!$E$2:$E$1421,Documents!$A$2:$A$1421,$A34,Documents!$C$2:$C$1421,"brochure")=0,"",maxifs(Documents!$E$2:$E$1421,Documents!$A$2:$A$1421,$A34,Documents!$C$2:$C$1421,"brochure")),"") | S34: =IFERROR(IF(maxifs(Documents!$E$2:$E$1421,Documents!$A$2:$A$1421,$A34,Documents!$C$2:$C$1421,"press_kit")=0,"",maxifs(Documents!$E$2:$E$1421,Documents!$A$2:$A$1421,$A34,Documents!$C$2:$C$1421,"press_kit")),"") | T34: =IFERROR(IF(maxifs(Documents!$E$2:$E$1421,Documents!$A$2:$A$1421,$A34,Documents!$C$2:$C$1421,"other")=0,"",maxifs(Documents!$E$2:$E$1421,Documents!$A$2:$A$1421,$A34,Documents!$C$2:$C$1421,"other")),"") | U34: =IFERROR(IF(maxifs(Documents!$E$2:$E$1421,Documents!$A$2:$A$1421,$A34,Documents!$C$2:$C$1421,"obsolete")=0,"",maxifs(Documents!$E$2:$E$1421,Documents!$A$2:$A$1421,$A34,Documents!$C$2:$C$1421,"obsolete")),"") | V34: =COUNTIFS(Documents!$A$2:$A$1421,$A34) -> 89 | W34: =COUNTIFS(Documents!$A$2:$A$1421,$A34,Documents!$R$2:$R$1421,"current") -> 75 | X34: =HYPERLINK("https://www.nivadhigali.com/wp-content/uploads/2026/01/DHIGALI_Factsheet.pdf","2026_DHIGALI_Factsheet.pdf") -> 2026_DHIGALI_Factsheet.pdf | Y34: wedding, events | Z34: NIVA Dhigali; site redirects to www.nivadhigali.com
A35: 34 | B35: Adaaran Select Meedhupparu | C35: ok | D35: =IFERROR(IF(maxifs(Documents!$E$2:$E$1421,Documents!$A$2:$A$1421,$A35,Documents!$C$2:$C$1421,"factsheet")=0,"",maxifs(Documents!$E$2:$E$1421,Documents!$A$2:$A$1421,$A35,Documents!$C$2:$C$1421,"factsheet")),"") | E35: =IFERROR(IF(maxifs(Documents!$E$2:$E$1421,Documents!$A$2:$A$1421,$A35,Documents!$C$2:$C$1421,"wedding")=0,"",maxifs(Documents!$E$2:$E$1421,Documents!$A$2:$A$1421,$A35,Documents!$C$2:$C$1421,"wedding")),"") | F35: =IFERROR(IF(maxifs(Documents!$E$2:$E$1421,Documents!$A$2:$A$1421,$A35,Documents!$C$2:$C$1421,"events")=0,"",maxifs(Documents!$E$2:$E$1421,Documents!$A$2:$A$1421,$A35,Documents!$C$2:$C$1421,"events")),"") | G35: =IFERROR(IF(maxifs(Documents!$E$2:$E$1421,Documents!$A$2:$A$1421,$A35,Documents!$C$2:$C$1421,"map")=0,"",maxifs(Documents!$E$2:$E$1421,Documents!$A$2:$A$1421,$A35,Documents!$C$2:$C$1421,"map")),"") | H35: =IFERROR(IF(maxifs(Documents!$E$2:$E$1421,Documents!$A$2:$A$1421,$A35,Documents!$C$2:$C$1421,"dive_map")=0,"",maxifs(Documents!$E$2:$E$1421,Documents!$A$2:$A$1421,$A35,Documents!$C$2:$C$1421,"dive_map")),"") | I35: =IFERROR(IF(maxifs(Documents!$E$2:$E$1421,Documents!$A$2:$A$1421,$A35,Documents!$C$2:$C$1421,"spa_menu")=0,"",maxifs(Documents!$E$2:$E$1421,Documents!$A$2:$A$1421,$A35,Documents!$C$2:$C$1421,"spa_menu")),"") | J35: =IFERROR(IF(maxifs(Documents!$E$2:$E$1421,Documents!$A$2:$A$1421,$A35,Documents!$C$2:$C$1421,"dining_menu")=0,"",maxifs(Documents!$E$2:$E$1421,Documents!$A$2:$A$1421,$A35,Documents!$C$2:$C$1421,"dining_menu")),"") | K35: =IFERROR(IF(maxifs(Documents!$E$2:$E$1421,Documents!$A$2:$A$1421,$A35,Documents!$C$2:$C$1421,"dive_prices")=0,"",maxifs(Documents!$E$2:$E$1421,Documents!$A$2:$A$1421,$A35,Documents!$C$2:$C$1421,"dive_prices")),"") | L35: =IFERROR(IF(maxifs(Documents!$E$2:$E$1421,Documents!$A$2:$A$1421,$A35,Documents!$C$2:$C$1421,"excursions")=0,"",maxifs(Documents!$E$2:$E$1421,Documents!$A$2:$A$1421,$A35,Documents!$C$2:$C$1421,"excursions")),"") | M35: =IFERROR(IF(maxifs(Documents!$E$2:$E$1421,Documents!$A$2:$A$1421,$A35,Documents!$C$2:$C$1421,"kids")=0,"",maxifs(Documents!$E$2:$E$1421,Documents!$A$2:$A$1421,$A35,Documents!$C$2:$C$1421,"kids")),"") | N35: =IFERROR(IF(maxifs(Documents!$E$2:$E$1421,Documents!$A$2:$A$1421,$A35,Documents!$C$2:$C$1421,"villa_plans")=0,"",maxifs(Documents!$E$2:$E$1421,Documents!$A$2:$A$1421,$A35,Documents!$C$2:$C$1421,"villa_plans")),"") | O35: =IFERROR(IF(maxifs(Documents!$E$2:$E$1421,Documents!$A$2:$A$1421,$A35,Documents!$C$2:$C$1421,"all_inclusive")=0,"",maxifs(Documents!$E$2:$E$1421,Documents!$A$2:$A$1421,$A35,Documents!$C$2:$C$1421,"all_inclusive")),"") | P35: =IFERROR(IF(maxifs(Documents!$E$2:$E$1421,Documents!$A$2:$A$1421,$A35,Documents!$C$2:$C$1421,"sustainability")=0,"",maxifs(Documents!$E$2:$E$1421,Documents!$A$2:$A$1421,$A35,Documents!$C$2:$C$1421,"sustainability")),"") | Q35: =IFERROR(IF(maxifs(Documents!$E$2:$E$1421,Documents!$A$2:$A$1421,$A35,Documents!$C$2:$C$1421,"calendar")=0,"",maxifs(Documents!$E$2:$E$1421,Documents!$A$2:$A$1421,$A35,Documents!$C$2:$C$1421,"calendar")),"") | R35: =IFERROR(IF(maxifs(Documents!$E$2:$E$1421,Documents!$A$2:$A$1421,$A35,Documents!$C$2:$C$1421,"brochure")=0,"",maxifs(Documents!$E$2:$E$1421,Documents!$A$2:$A$1421,$A35,Documents!$C$2:$C$1421,"brochure")),"") | S35: =IFERROR(IF(maxifs(Documents!$E$2:$E$1421,Documents!$A$2:$A$1421,$A35,Documents!$C$2:$C$1421,"press_kit")=0,"",maxifs(Documents!$E$2:$E$1421,Documents!$A$2:$A$1421,$A35,Documents!$C$2:$C$1421,"press_kit")),"") | T35: =IFERROR(IF(maxifs(Documents!$E$2:$E$1421,Documents!$A$2:$A$1421,$A35,Documents!$C$2:$C$1421,"other")=0,"",maxifs(Documents!$E$2:$E$1421,Documents!$A$2:$A$1421,$A35,Documents!$C$2:$C$1421,"other")),"") | U35: =IFERROR(IF(maxifs(Documents!$E$2:$E$1421,Documents!$A$2:$A$1421,$A35,Documents!$C$2:$C$1421,"obsolete")=0,"",maxifs(Documents!$E$2:$E$1421,Documents!$A$2:$A$1421,$A35,Documents!$C$2:$C$1421,"obsolete")),"") | V35: =COUNTIFS(Documents!$A$2:$A$1421,$A35) -> 13 | W35: =COUNTIFS(Documents!$A$2:$A$1421,$A35,Documents!$R$2:$R$1421,"current") -> 8 | X35: =HYPERLINK("https://www.adaaran.com/selectmeedhupparu/view-download/?id=asm-factsheet","2026_document.pdf") -> 2026_document.pdf | Y35: events
A36: 35 | B36: Heritance Aarah | C36: ok | D36: =IFERROR(IF(maxifs(Documents!$E$2:$E$1421,Documents!$A$2:$A$1421,$A36,Documents!$C$2:$C$1421,"factsheet")=0,"",maxifs(Documents!$E$2:$E$1421,Documents!$A$2:$A$1421,$A36,Documents!$C$2:$C$1421,"factsheet")),"") | E36: =IFERROR(IF(maxifs(Documents!$E$2:$E$1421,Documents!$A$2:$A$1421,$A36,Documents!$C$2:$C$1421,"wedding")=0,"",maxifs(Documents!$E$2:$E$1421,Documents!$A$2:$A$1421,$A36,Documents!$C$2:$C$1421,"wedding")),"") | F36: =IFERROR(IF(maxifs(Documents!$E$2:$E$1421,Documents!$A$2:$A$1421,$A36,Documents!$C$2:$C$1421,"events")=0,"",maxifs(Documents!$E$2:$E$1421,Documents!$A$2:$A$1421,$A36,Documents!$C$2:$C$1421,"events")),"") | G36: =IFERROR(IF(maxifs(Documents!$E$2:$E$1421,Documents!$A$2:$A$1421,$A36,Documents!$C$2:$C$1421,"map")=0,"",maxifs(Documents!$E$2:$E$1421,Documents!$A$2:$A$1421,$A36,Documents!$C$2:$C$1421,"map")),"") | H36: =IFERROR(IF(maxifs(Documents!$E$2:$E$1421,Documents!$A$2:$A$1421,$A36,Documents!$C$2:$C$1421,"dive_map")=0,"",maxifs(Documents!$E$2:$E$1421,Documents!$A$2:$A$1421,$A36,Documents!$C$2:$C$1421,"dive_map")),"") | I36: =IFERROR(IF(maxifs(Documents!$E$2:$E$1421,Documents!$A$2:$A$1421,$A36,Documents!$C$2:$C$1421,"spa_menu")=0,"",maxifs(Documents!$E$2:$E$1421,Documents!$A$2:$A$1421,$A36,Documents!$C$2:$C$1421,"spa_menu")),"") | J36: =IFERROR(IF(maxifs(Documents!$E$2:$E$1421,Documents!$A$2:$A$1421,$A36,Documents!$C$2:$C$1421,"dining_menu")=0,"",maxifs(Documents!$E$2:$E$1421,Documents!$A$2:$A$1421,$A36,Documents!$C$2:$C$1421,"dining_menu")),"") | K36: =IFERROR(IF(maxifs(Documents!$E$2:$E$1421,Documents!$A$2:$A$1421,$A36,Documents!$C$2:$C$1421,"dive_prices")=0,"",maxifs(Documents!$E$2:$E$1421,Documents!$A$2:$A$1421,$A36,Documents!$C$2:$C$1421,"dive_prices")),"") | L36: =IFERROR(IF(maxifs(Documents!$E$2:$E$1421,Documents!$A$2:$A$1421,$A36,Documents!$C$2:$C$1421,"excursions")=0,"",maxifs(Documents!$E$2:$E$1421,Documents!$A$2:$A$1421,$A36,Documents!$C$2:$C$1421,"excursions")),"") | M36: =IFERROR(IF(maxifs(Documents!$E$2:$E$1421,Documents!$A$2:$A$1421,$A36,Documents!$C$2:$C$1421,"kids")=0,"",maxifs(Documents!$E$2:$E$1421,Documents!$A$2:$A$1421,$A36,Documents!$C$2:$C$1421,"kids")),"") | N36: =IFERROR(IF(maxifs(Documents!$E$2:$E$1421,Documents!$A$2:$A$1421,$A36,Documents!$C$2:$C$1421,"villa_plans")=0,"",maxifs(Documents!$E$2:$E$1421,Documents!$A$2:$A$1421,$A36,Documents!$C$2:$C$1421,"villa_plans")),"") | O36: =IFERROR(IF(maxifs(Documents!$E$2:$E$1421,Documents!$A$2:$A$1421,$A36,Documents!$C$2:$C$1421,"all_inclusive")=0,"",maxifs(Documents!$E$2:$E$1421,Documents!$A$2:$A$1421,$A36,Documents!$C$2:$C$1421,"all_inclusive")),"") | P36: =IFERROR(IF(maxifs(Documents!$E$2:$E$1421,Documents!$A$2:$A$1421,$A36,Documents!$C$2:$C$1421,"sustainability")=0,"",maxifs(Documents!$E$2:$E$1421,Documents!$A$2:$A$1421,$A36,Documents!$C$2:$C$1421,"sustainability")),"") | Q36: =IFERROR(IF(maxifs(Documents!$E$2:$E$1421,Documents!$A$2:$A$1421,$A36,Documents!$C$2:$C$1421,"calendar")=0,"",maxifs(Documents!$E$2:$E$1421,Documents!$A$2:$A$1421,$A36,Documents!$C$2:$C$1421,"calendar")),"") | R36: =IFERROR(IF(maxifs(Documents!$E$2:$E$1421,Documents!$A$2:$A$1421,$A36,Documents!$C$2:$C$1421,"brochure")=0,"",maxifs(Documents!$E$2:$E$1421,Documents!$A$2:$A$1421,$A36,Documents!$C$2:$C$1421,"brochure")),"") | S36: =IFERROR(IF(maxifs(Documents!$E$2:$E$1421,Documents!$A$2:$A$1421,$A36,Documents!$C$2:$C$1421,"press_kit")=0,"",maxifs(Documents!$E$2:$E$1421,Documents!$A$2:$A$1421,$A36,Documents!$C$2:$C$1421,"press_kit")),"") | T36: =IFERROR(IF(maxifs(Documents!$E$2:$E$1421,Documents!$A$2:$A$1421,$A36,Documents!$C$2:$C$1421,"other")=0,"",maxifs(Documents!$E$2:$E$1421,Documents!$A$2:$A$1421,$A36,Documents!$C$2:$C$1421,"other")),"") | U36: =IFERROR(IF(maxifs(Documents!$E$2:$E$1421,Documents!$A$2:$A$1421,$A36,Documents!$C$2:$C$1421,"obsolete")=0,"",maxifs(Documents!$E$2:$E$1421,Documents!$A$2:$A$1421,$A36,Documents!$C$2:$C$1421,"obsolete")),"") | V36: =COUNTIFS(Documents!$A$2:$A$1421,$A36) -> 190 | W36: =COUNTIFS(Documents!$A$2:$A$1421,$A36,Documents!$R$2:$R$1421,"current") -> 138 | X36: =HYPERLINK("https://heritancehotels.eme-devops.com/sites/2/2026/09/Heritance-Aarah-Fact-Sheet.pdf","2026_Heritance-Aarah-Fact-Sheet.pdf") -> 2026_Heritance-Aarah-Fact-Sheet.pdf | Y36: events
A37: 36 | B37: Coastline Residences | C37: unreachable | D37: =IFERROR(IF(maxifs(Documents!$E$2:$E$1421,Documents!$A$2:$A$1421,$A37,Documents!$C$2:$C$1421,"factsheet")=0,"",maxifs(Documents!$E$2:$E$1421,Documents!$A$2:$A$1421,$A37,Documents!$C$2:$C$1421,"factsheet")),"") | E37: =IFERROR(IF(maxifs(Documents!$E$2:$E$1421,Documents!$A$2:$A$1421,$A37,Documents!$C$2:$C$1421,"wedding")=0,"",maxifs(Documents!$E$2:$E$1421,Documents!$A$2:$A$1421,$A37,Documents!$C$2:$C$1421,"wedding")),"") | F37: =IFERROR(IF(maxifs(Documents!$E$2:$E$1421,Documents!$A$2:$A$1421,$A37,Documents!$C$2:$C$1421,"events")=0,"",maxifs(Documents!$E$2:$E$1421,Documents!$A$2:$A$1421,$A37,Documents!$C$2:$C$1421,"events")),"") | G37: =IFERROR(IF(maxifs(Documents!$E$2:$E$1421,Documents!$A$2:$A$1421,$A37,Documents!$C$2:$C$1421,"map")=0,"",maxifs(Documents!$E$2:$E$1421,Documents!$A$2:$A$1421,$A37,Documents!$C$2:$C$1421,"map")),"") | H37: =IFERROR(IF(maxifs(Documents!$E$2:$E$1421,Documents!$A$2:$A$1421,$A37,Documents!$C$2:$C$1421,"dive_map")=0,"",maxifs(Documents!$E$2:$E$1421,Documents!$A$2:$A$1421,$A37,Documents!$C$2:$C$1421,"dive_map")),"") | I37: =IFERROR(IF(maxifs(Documents!$E$2:$E$1421,Documents!$A$2:$A$1421,$A37,Documents!$C$2:$C$1421,"spa_menu")=0,"",maxifs(Documents!$E$2:$E$1421,Documents!$A$2:$A$1421,$A37,Documents!$C$2:$C$1421,"spa_menu")),"") | J37: =IFERROR(IF(maxifs(Documents!$E$2:$E$1421,Documents!$A$2:$A$1421,$A37,Documents!$C$2:$C$1421,"dining_menu")=0,"",maxifs(Documents!$E$2:$E$1421,Documents!$A$2:$A$1421,$A37,Documents!$C$2:$C$1421,"dining_menu")),"") | K37: =IFERROR(IF(maxifs(Documents!$E$2:$E$1421,Documents!$A$2:$A$1421,$A37,Documents!$C$2:$C$1421,"dive_prices")=0,"",maxifs(Documents!$E$2:$E$1421,Documents!$A$2:$A$1421,$A37,Documents!$C$2:$C$1421,"dive_prices")),"") | L37: =IFERROR(IF(maxifs(Documents!$E$2:$E$1421,Documents!$A$2:$A$1421,$A37,Documents!$C$2:$C$1421,"excursions")=0,"",maxifs(Documents!$E$2:$E$1421,Documents!$A$2:$A$1421,$A37,Documents!$C$2:$C$1421,"excursions")),"") | M37: =IFERROR(IF(maxifs(Documents!$E$2:$E$1421,Documents!$A$2:$A$1421,$A37,Documents!$C$2:$C$1421,"kids")=0,"",maxifs(Documents!$E$2:$E$1421,Documents!$A$2:$A$1421,$A37,Documents!$C$2:$C$1421,"kids")),"") | N37: =IFERROR(IF(maxifs(Documents!$E$2:$E$1421,Documents!$A$2:$A$1421,$A37,Documents!$C$2:$C$1421,"villa_plans")=0,"",maxifs(Documents!$E$2:$E$1421,Documents!$A$2:$A$1421,$A37,Documents!$C$2:$C$1421,"villa_plans")),"") | O37: =IFERROR(IF(maxifs(Documents!$E$2:$E$1421,Documents!$A$2:$A$1421,$A37,Documents!$C$2:$C$1421,"all_inclusive")=0,"",maxifs(Documents!$E$2:$E$1421,Documents!$A$2:$A$1421,$A37,Documents!$C$2:$C$1421,"all_inclusive")),"") | P37: =IFERROR(IF(maxifs(Documents!$E$2:$E$1421,Documents!$A$2:$A$1421,$A37,Documents!$C$2:$C$1421,"sustainability")=0,"",maxifs(Documents!$E$2:$E$1421,Documents!$A$2:$A$1421,$A37,Documents!$C$2:$C$1421,"sustainability")),"") | Q37: =IFERROR(IF(maxifs(Documents!$E$2:$E$1421,Documents!$A$2:$A$1421,$A37,Documents!$C$2:$C$1421,"calendar")=0,"",maxifs(Documents!$E$2:$E$1421,Documents!$A$2:$A$1421,$A37,Documents!$C$2:$C$1421,"calendar")),"") | R37: =IFERROR(IF(maxifs(Documents!$E$2:$E$1421,Documents!$A$2:$A$1421,$A37,Documents!$C$2:$C$1421,"brochure")=0,"",maxifs(Documents!$E$2:$E$1421,Documents!$A$2:$A$1421,$A37,Documents!$C$2:$C$1421,"brochure")),"") | S37: =IFERROR(IF(maxifs(Documents!$E$2:$E$1421,Documents!$A$2:$A$1421,$A37,Documents!$C$2:$C$1421,"press_kit")=0,"",maxifs(Documents!$E$2:$E$1421,Documents!$A$2:$A$1421,$A37,Documents!$C$2:$C$1421,"press_kit")),"") | T37: =IFERROR(IF(maxifs(Documents!$E$2:$E$1421,Documents!$A$2:$A$1421,$A37,Documents!$C$2:$C$1421,"other")=0,"",maxifs(Documents!$E$2:$E$1421,Documents!$A$2:$A$1421,$A37,Documents!$C$2:$C$1421,"other")),"") | U37: =IFERROR(IF(maxifs(Documents!$E$2:$E$1421,Documents!$A$2:$A$1421,$A37,Documents!$C$2:$C$1421,"obsolete")=0,"",maxifs(Documents!$E$2:$E$1421,Documents!$A$2:$A$1421,$A37,Documents!$C$2:$C$1421,"obsolete")),"") | V37: =COUNTIFS(Documents!$A$2:$A$1421,$A37) -> 0 | W37: =COUNTIFS(Documents!$A$2:$A$1421,$A37,Documents!$R$2:$R$1421,"current") -> 0 | Y37: factsheet, wedding, events
A38: 37 | B38: The Ritz Carlton Maldives Fari Islands | C38: unreachable | D38: =IFERROR(IF(maxifs(Documents!$E$2:$E$1421,Documents!$A$2:$A$1421,$A38,Documents!$C$2:$C$1421,"factsheet")=0,"",maxifs(Documents!$E$2:$E$1421,Documents!$A$2:$A$1421,$A38,Documents!$C$2:$C$1421,"factsheet")),"") | E38: =IFERROR(IF(maxifs(Documents!$E$2:$E$1421,Documents!$A$2:$A$1421,$A38,Documents!$C$2:$C$1421,"wedding")=0,"",maxifs(Documents!$E$2:$E$1421,Documents!$A$2:$A$1421,$A38,Documents!$C$2:$C$1421,"wedding")),"") | F38: =IFERROR(IF(maxifs(Documents!$E$2:$E$1421,Documents!$A$2:$A$1421,$A38,Documents!$C$2:$C$1421,"events")=0,"",maxifs(Documents!$E$2:$E$1421,Documents!$A$2:$A$1421,$A38,Documents!$C$2:$C$1421,"events")),"") | G38: =IFERROR(IF(maxifs(Documents!$E$2:$E$1421,Documents!$A$2:$A$1421,$A38,Documents!$C$2:$C$1421,"map")=0,"",maxifs(Documents!$E$2:$E$1421,Documents!$A$2:$A$1421,$A38,Documents!$C$2:$C$1421,"map")),"") | H38: =IFERROR(IF(maxifs(Documents!$E$2:$E$1421,Documents!$A$2:$A$1421,$A38,Documents!$C$2:$C$1421,"dive_map")=0,"",maxifs(Documents!$E$2:$E$1421,Documents!$A$2:$A$1421,$A38,Documents!$C$2:$C$1421,"dive_map")),"") | I38: =IFERROR(IF(maxifs(Documents!$E$2:$E$1421,Documents!$A$2:$A$1421,$A38,Documents!$C$2:$C$1421,"spa_menu")=0,"",maxifs(Documents!$E$2:$E$1421,Documents!$A$2:$A$1421,$A38,Documents!$C$2:$C$1421,"spa_menu")),"") | J38: =IFERROR(IF(maxifs(Documents!$E$2:$E$1421,Documents!$A$2:$A$1421,$A38,Documents!$C$2:$C$1421,"dining_menu")=0,"",maxifs(Documents!$E$2:$E$1421,Documents!$A$2:$A$1421,$A38,Documents!$C$2:$C$1421,"dining_menu")),"") | K38: =IFERROR(IF(maxifs(Documents!$E$2:$E$1421,Documents!$A$2:$A$1421,$A38,Documents!$C$2:$C$1421,"dive_prices")=0,"",maxifs(Documents!$E$2:$E$1421,Documents!$A$2:$A$1421,$A38,Documents!$C$2:$C$1421,"dive_prices")),"") | L38: =IFERROR(IF(maxifs(Documents!$E$2:$E$1421,Documents!$A$2:$A$1421,$A38,Documents!$C$2:$C$1421,"excursions")=0,"",maxifs(Documents!$E$2:$E$1421,Documents!$A$2:$A$1421,$A38,Documents!$C$2:$C$1421,"excursions")),"") | M38: =IFERROR(IF(maxifs(Documents!$E$2:$E$1421,Documents!$A$2:$A$1421,$A38,Documents!$C$2:$C$1421,"kids")=0,"",maxifs(Documents!$E$2:$E$1421,Documents!$A$2:$A$1421,$A38,Documents!$C$2:$C$1421,"kids")),"") | N38: =IFERROR(IF(maxifs(Documents!$E$2:$E$1421,Documents!$A$2:$A$1421,$A38,Documents!$C$2:$C$1421,"villa_plans")=0,"",maxifs(Documents!$E$2:$E$1421,Documents!$A$2:$A$1421,$A38,Documents!$C$2:$C$1421,"villa_plans")),"") | O38: =IFERROR(IF(maxifs(Documents!$E$2:$E$1421,Documents!$A$2:$A$1421,$A38,Documents!$C$2:$C$1421,"all_inclusive")=0,"",maxifs(Documents!$E$2:$E$1421,Documents!$A$2:$A$1421,$A38,Documents!$C$2:$C$1421,"all_inclusive")),"") | P38: =IFERROR(IF(maxifs(Documents!$E$2:$E$1421,Documents!$A$2:$A$1421,$A38,Documents!$C$2:$C$1421,"sustainability")=0,"",maxifs(Documents!$E$2:$E$1421,Documents!$A$2:$A$1421,$A38,Documents!$C$2:$C$1421,"sustainability")),"") | Q38: =IFERROR(IF(maxifs(Documents!$E$2:$E$1421,Documents!$A$2:$A$1421,$A38,Documents!$C$2:$C$1421,"calendar")=0,"",maxifs(Documents!$E$2:$E$1421,Documents!$A$2:$A$1421,$A38,Documents!$C$2:$C$1421,"calendar")),"") | R38: =IFERROR(IF(maxifs(Documents!$E$2:$E$1421,Documents!$A$2:$A$1421,$A38,Documents!$C$2:$C$1421,"brochure")=0,"",maxifs(Documents!$E$2:$E$1421,Documents!$A$2:$A$1421,$A38,Documents!$C$2:$C$1421,"brochure")),"") | S38: =IFERROR(IF(maxifs(Documents!$E$2:$E$1421,Documents!$A$2:$A$1421,$A38,Documents!$C$2:$C$1421,"press_kit")=0,"",maxifs(Documents!$E$2:$E$1421,Documents!$A$2:$A$1421,$A38,Documents!$C$2:$C$1421,"press_kit")),"") | T38: =IFERROR(IF(maxifs(Documents!$E$2:$E$1421,Documents!$A$2:$A$1421,$A38,Documents!$C$2:$C$1421,"other")=0,"",maxifs(Documents!$E$2:$E$1421,Documents!$A$2:$A$1421,$A38,Documents!$C$2:$C$1421,"other")),"") | U38: =IFERROR(IF(maxifs(Documents!$E$2:$E$1421,Documents!$A$2:$A$1421,$A38,Documents!$C$2:$C$1421,"obsolete")=0,"",maxifs(Documents!$E$2:$E$1421,Documents!$A$2:$A$1421,$A38,Documents!$C$2:$C$1421,"obsolete")),"") | V38: =COUNTIFS(Documents!$A$2:$A$1421,$A38) -> 2 | W38: =COUNTIFS(Documents!$A$2:$A$1421,$A38,Documents!$R$2:$R$1421,"current") -> 0 | X38: =HYPERLINK("https://www.neoscapesmaldives.com/wp-content/uploads/The-Ritz-Carlton-Maldives-Factsheet.pdf","2021_The-Ritz-Carlton-Maldives-Factsheet") -> 2021_The-Ritz-Carlton-Maldives-Factsheet | Y38: wedding, events
A39: 38 | B39: Veligandu Maldives Resort Island | C39: ok | D39: =IFERROR(IF(maxifs(Documents!$E$2:$E$1421,Documents!$A$2:$A$1421,$A39,Documents!$C$2:$C$1421,"factsheet")=0,"",maxifs(Documents!$E$2:$E$1421,Documents!$A$2:$A$1421,$A39,Documents!$C$2:$C$1421,"factsheet")),"") | E39: =IFERROR(IF(maxifs(Documents!$E$2:$E$1421,Documents!$A$2:$A$1421,$A39,Documents!$C$2:$C$1421,"wedding")=0,"",maxifs(Documents!$E$2:$E$1421,Documents!$A$2:$A$1421,$A39,Documents!$C$2:$C$1421,"wedding")),"") | F39: =IFERROR(IF(maxifs(Documents!$E$2:$E$1421,Documents!$A$2:$A$1421,$A39,Documents!$C$2:$C$1421,"events")=0,"",maxifs(Documents!$E$2:$E$1421,Documents!$A$2:$A$1421,$A39,Documents!$C$2:$C$1421,"events")),"") | G39: =IFERROR(IF(maxifs(Documents!$E$2:$E$1421,Documents!$A$2:$A$1421,$A39,Documents!$C$2:$C$1421,"map")=0,"",maxifs(Documents!$E$2:$E$1421,Documents!$A$2:$A$1421,$A39,Documents!$C$2:$C$1421,"map")),"") | H39: =IFERROR(IF(maxifs(Documents!$E$2:$E$1421,Documents!$A$2:$A$1421,$A39,Documents!$C$2:$C$1421,"dive_map")=0,"",maxifs(Documents!$E$2:$E$1421,Documents!$A$2:$A$1421,$A39,Documents!$C$2:$C$1421,"dive_map")),"") | I39: =IFERROR(IF(maxifs(Documents!$E$2:$E$1421,Documents!$A$2:$A$1421,$A39,Documents!$C$2:$C$1421,"spa_menu")=0,"",maxifs(Documents!$E$2:$E$1421,Documents!$A$2:$A$1421,$A39,Documents!$C$2:$C$1421,"spa_menu")),"") | J39: =IFERROR(IF(maxifs(Documents!$E$2:$E$1421,Documents!$A$2:$A$1421,$A39,Documents!$C$2:$C$1421,"dining_menu")=0,"",maxifs(Documents!$E$2:$E$1421,Documents!$A$2:$A$1421,$A39,Documents!$C$2:$C$1421,"dining_menu")),"") | K39: =IFERROR(IF(maxifs(Documents!$E$2:$E$1421,Documents!$A$2:$A$1421,$A39,Documents!$C$2:$C$1421,"dive_prices")=0,"",maxifs(Documents!$E$2:$E$1421,Documents!$A$2:$A$1421,$A39,Documents!$C$2:$C$1421,"dive_prices")),"") | L39: =IFERROR(IF(maxifs(Documents!$E$2:$E$1421,Documents!$A$2:$A$1421,$A39,Documents!$C$2:$C$1421,"excursions")=0,"",maxifs(Documents!$E$2:$E$1421,Documents!$A$2:$A$1421,$A39,Documents!$C$2:$C$1421,"excursions")),"") | M39: =IFERROR(IF(maxifs(Documents!$E$2:$E$1421,Documents!$A$2:$A$1421,$A39,Documents!$C$2:$C$1421,"kids")=0,"",maxifs(Documents!$E$2:$E$1421,Documents!$A$2:$A$1421,$A39,Documents!$C$2:$C$1421,"kids")),"") | N39: =IFERROR(IF(maxifs(Documents!$E$2:$E$1421,Documents!$A$2:$A$1421,$A39,Documents!$C$2:$C$1421,"villa_plans")=0,"",maxifs(Documents!$E$2:$E$1421,Documents!$A$2:$A$1421,$A39,Documents!$C$2:$C$1421,"villa_plans")),"") | O39: =IFERROR(IF(maxifs(Documents!$E$2:$E$1421,Documents!$A$2:$A$1421,$A39,Documents!$C$2:$C$1421,"all_inclusive")=0,"",maxifs(Documents!$E$2:$E$1421,Documents!$A$2:$A$1421,$A39,Documents!$C$2:$C$1421,"all_inclusive")),"") | P39: =IFERROR(IF(maxifs(Documents!$E$2:$E$1421,Documents!$A$2:$A$1421,$A39,Documents!$C$2:$C$1421,"sustainability")=0,"",maxifs(Documents!$E$2:$E$1421,Documents!$A$2:$A$1421,$A39,Documents!$C$2:$C$1421,"sustainability")),"") | Q39: =IFERROR(IF(maxifs(Documents!$E$2:$E$1421,Documents!$A$2:$A$1421,$A39,Documents!$C$2:$C$1421,"calendar")=0,"",maxifs(Documents!$E$2:$E$1421,Documents!$A$2:$A$1421,$A39,Documents!$C$2:$C$1421,"calendar")),"") | R39: =IFERROR(IF(maxifs(Documents!$E$2:$E$1421,Documents!$A$2:$A$1421,$A39,Documents!$C$2:$C$1421,"brochure")=0,"",maxifs(Documents!$E$2:$E$1421,Documents!$A$2:$A$1421,$A39,Documents!$C$2:$C$1421,"brochure")),"") | S39: =IFERROR(IF(maxifs(Documents!$E$2:$E$1421,Documents!$A$2:$A$1421,$A39,Documents!$C$2:$C$1421,"press_kit")=0,"",maxifs(Documents!$E$2:$E$1421,Documents!$A$2:$A$1421,$A39,Documents!$C$2:$C$1421,"press_kit")),"") | T39: =IFERROR(IF(maxifs(Documents!$E$2:$E$1421,Documents!$A$2:$A$1421,$A39,Documents!$C$2:$C$1421,"other")=0,"",maxifs(Documents!$E$2:$E$1421,Documents!$A$2:$A$1421,$A39,Documents!$C$2:$C$1421,"other")),"") | U39: =IFERROR(IF(maxifs(Documents!$E$2:$E$1421,Documents!$A$2:$A$1421,$A39,Documents!$C$2:$C$1421,"obsolete")=0,"",maxifs(Documents!$E$2:$E$1421,Documents!$A$2:$A$1421,$A39,Documents!$C$2:$C$1421,"obsolete")),"") | V39: =COUNTIFS(Documents!$A$2:$A$1421,$A39) -> 51 | W39: =COUNTIFS(Documents!$A$2:$A$1421,$A39,Documents!$R$2:$R$1421,"current") -> 30 | X39: =HYPERLINK("https://veligandu.com/wp-content/uploads/2025/06/Factsheet-W25-26S26Ver17062025.pdf","2025_Factsheet-W25-26S26Ver17062025.pdf") -> 2025_Factsheet-W25-26S26Ver17062025.pdf | Y39: events | Z39: 'Veli' in Crown & Champa filenames
A40: 39 | B40: NH Collection Maldives Havodda Resort | C40: blocked | D40: =IFERROR(IF(maxifs(Documents!$E$2:$E$1421,Documents!$A$2:$A$1421,$A40,Documents!$C$2:$C$1421,"factsheet")=0,"",maxifs(Documents!$E$2:$E$1421,Documents!$A$2:$A$1421,$A40,Documents!$C$2:$C$1421,"factsheet")),"") | E40: =IFERROR(IF(maxifs(Documents!$E$2:$E$1421,Documents!$A$2:$A$1421,$A40,Documents!$C$2:$C$1421,"wedding")=0,"",maxifs(Documents!$E$2:$E$1421,Documents!$A$2:$A$1421,$A40,Documents!$C$2:$C$1421,"wedding")),"") | F40: =IFERROR(IF(maxifs(Documents!$E$2:$E$1421,Documents!$A$2:$A$1421,$A40,Documents!$C$2:$C$1421,"events")=0,"",maxifs(Documents!$E$2:$E$1421,Documents!$A$2:$A$1421,$A40,Documents!$C$2:$C$1421,"events")),"") | G40: =IFERROR(IF(maxifs(Documents!$E$2:$E$1421,Documents!$A$2:$A$1421,$A40,Documents!$C$2:$C$1421,"map")=0,"",maxifs(Documents!$E$2:$E$1421,Documents!$A$2:$A$1421,$A40,Documents!$C$2:$C$1421,"map")),"") | H40: =IFERROR(IF(maxifs(Documents!$E$2:$E$1421,Documents!$A$2:$A$1421,$A40,Documents!$C$2:$C$1421,"dive_map")=0,"",maxifs(Documents!$E$2:$E$1421,Documents!$A$2:$A$1421,$A40,Documents!$C$2:$C$1421,"dive_map")),"") | I40: =IFERROR(IF(maxifs(Documents!$E$2:$E$1421,Documents!$A$2:$A$1421,$A40,Documents!$C$2:$C$1421,"spa_menu")=0,"",maxifs(Documents!$E$2:$E$1421,Documents!$A$2:$A$1421,$A40,Documents!$C$2:$C$1421,"spa_menu")),"") | J40: =IFERROR(IF(maxifs(Documents!$E$2:$E$1421,Documents!$A$2:$A$1421,$A40,Documents!$C$2:$C$1421,"dining_menu")=0,"",maxifs(Documents!$E$2:$E$1421,Documents!$A$2:$A$1421,$A40,Documents!$C$2:$C$1421,"dining_menu")),"") | K40: =IFERROR(IF(maxifs(Documents!$E$2:$E$1421,Documents!$A$2:$A$1421,$A40,Documents!$C$2:$C$1421,"dive_prices")=0,"",maxifs(Documents!$E$2:$E$1421,Documents!$A$2:$A$1421,$A40,Documents!$C$2:$C$1421,"dive_prices")),"") | L40: =IFERROR(IF(maxifs(Documents!$E$2:$E$1421,Documents!$A$2:$A$1421,$A40,Documents!$C$2:$C$1421,"excursions")=0,"",maxifs(Documents!$E$2:$E$1421,Documents!$A$2:$A$1421,$A40,Documents!$C$2:$C$1421,"excursions")),"") | M40: =IFERROR(IF(maxifs(Documents!$E$2:$E$1421,Documents!$A$2:$A$1421,$A40,Documents!$C$2:$C$1421,"kids")=0,"",maxifs(Documents!$E$2:$E$1421,Documents!$A$2:$A$1421,$A40,Documents!$C$2:$C$1421,"kids")),"") | N40: =IFERROR(IF(maxifs(Documents!$E$2:$E$1421,Documents!$A$2:$A$1421,$A40,Documents!$C$2:$C$1421,"villa_plans")=0,"",maxifs(Documents!$E$2:$E$1421,Documents!$A$2:$A$1421,$A40,Documents!$C$2:$C$1421,"villa_plans")),"") | O40: =IFERROR(IF(maxifs(Documents!$E$2:$E$1421,Documents!$A$2:$A$1421,$A40,Documents!$C$2:$C$1421,"all_inclusive")=0,"",maxifs(Documents!$E$2:$E$1421,Documents!$A$2:$A$1421,$A40,Documents!$C$2:$C$1421,"all_inclusive")),"") | P40: =IFERROR(IF(maxifs(Documents!$E$2:$E$1421,Documents!$A$2:$A$1421,$A40,Documents!$C$2:$C$1421,"sustainability")=0,"",maxifs(Documents!$E$2:$E$1421,Documents!$A$2:$A$1421,$A40,Documents!$C$2:$C$1421,"sustainability")),"") | Q40: =IFERROR(IF(maxifs(Documents!$E$2:$E$1421,Documents!$A$2:$A$1421,$A40,Documents!$C$2:$C$1421,"calendar")=0,"",maxifs(Documents!$E$2:$E$1421,Documents!$A$2:$A$1421,$A40,Documents!$C$2:$C$1421,"calendar")),"") | R40: =IFERROR(IF(maxifs(Documents!$E$2:$E$1421,Documents!$A$2:$A$1421,$A40,Documents!$C$2:$C$1421,"brochure")=0,"",maxifs(Documents!$E$2:$E$1421,Documents!$A$2:$A$1421,$A40,Documents!$C$2:$C$1421,"brochure")),"") | S40: =IFERROR(IF(maxifs(Documents!$E$2:$E$1421,Documents!$A$2:$A$1421,$A40,Documents!$C$2:$C$1421,"press_kit")=0,"",maxifs(Documents!$E$2:$E$1421,Documents!$A$2:$A$1421,$A40,Documents!$C$2:$C$1421,"press_kit")),"") | T40: =IFERROR(IF(maxifs(Documents!$E$2:$E$1421,Documents!$A$2:$A$1421,$A40,Documents!$C$2:$C$1421,"other")=0,"",maxifs(Documents!$E$2:$E$1421,Documents!$A$2:$A$1421,$A40,Documents!$C$2:$C$1421,"other")),"") | U40: =IFERROR(IF(maxifs(Documents!$E$2:$E$1421,Documents!$A$2:$A$1421,$A40,Documents!$C$2:$C$1421,"obsolete")=0,"",maxifs(Documents!$E$2:$E$1421,Documents!$A$2:$A$1421,$A40,Documents!$C$2:$C$1421,"obsolete")),"") | V40: =COUNTIFS(Documents!$A$2:$A$1421,$A40) -> 2 | W40: =COUNTIFS(Documents!$A$2:$A$1421,$A40,Documents!$R$2:$R$1421,"current") -> 0 | X40: =HYPERLINK("https://neoscapesmaldives.com/wp-content/uploads/Amari-Havodda-Factsheet.pdf","2018_Amari-Havodda-Factsheet.pdf") -> 2018_Amari-Havodda-Factsheet.pdf | Y40: wedding, events | Z40: Amari Havodda (older name)
A41: 40 | B41: Le Méridien Maldives Resort and Spa | C41: blocked | D41: =IFERROR(IF(maxifs(Documents!$E$2:$E$1421,Documents!$A$2:$A$1421,$A41,Documents!$C$2:$C$1421,"factsheet")=0,"",maxifs(Documents!$E$2:$E$1421,Documents!$A$2:$A$1421,$A41,Documents!$C$2:$C$1421,"factsheet")),"") | E41: =IFERROR(IF(maxifs(Documents!$E$2:$E$1421,Documents!$A$2:$A$1421,$A41,Documents!$C$2:$C$1421,"wedding")=0,"",maxifs(Documents!$E$2:$E$1421,Documents!$A$2:$A$1421,$A41,Documents!$C$2:$C$1421,"wedding")),"") | F41: =IFERROR(IF(maxifs(Documents!$E$2:$E$1421,Documents!$A$2:$A$1421,$A41,Documents!$C$2:$C$1421,"events")=0,"",maxifs(Documents!$E$2:$E$1421,Documents!$A$2:$A$1421,$A41,Documents!$C$2:$C$1421,"events")),"") | G41: =IFERROR(IF(maxifs(Documents!$E$2:$E$1421,Documents!$A$2:$A$1421,$A41,Documents!$C$2:$C$1421,"map")=0,"",maxifs(Documents!$E$2:$E$1421,Documents!$A$2:$A$1421,$A41,Documents!$C$2:$C$1421,"map")),"") | H41: =IFERROR(IF(maxifs(Documents!$E$2:$E$1421,Documents!$A$2:$A$1421,$A41,Documents!$C$2:$C$1421,"dive_map")=0,"",maxifs(Documents!$E$2:$E$1421,Documents!$A$2:$A$1421,$A41,Documents!$C$2:$C$1421,"dive_map")),"") | I41: =IFERROR(IF(maxifs(Documents!$E$2:$E$1421,Documents!$A$2:$A$1421,$A41,Documents!$C$2:$C$1421,"spa_menu")=0,"",maxifs(Documents!$E$2:$E$1421,Documents!$A$2:$A$1421,$A41,Documents!$C$2:$C$1421,"spa_menu")),"") | J41: =IFERROR(IF(maxifs(Documents!$E$2:$E$1421,Documents!$A$2:$A$1421,$A41,Documents!$C$2:$C$1421,"dining_menu")=0,"",maxifs(Documents!$E$2:$E$1421,Documents!$A$2:$A$1421,$A41,Documents!$C$2:$C$1421,"dining_menu")),"") | K41: =IFERROR(IF(maxifs(Documents!$E$2:$E$1421,Documents!$A$2:$A$1421,$A41,Documents!$C$2:$C$1421,"dive_prices")=0,"",maxifs(Documents!$E$2:$E$1421,Documents!$A$2:$A$1421,$A41,Documents!$C$2:$C$1421,"dive_prices")),"") | L41: =IFERROR(IF(maxifs(Documents!$E$2:$E$1421,Documents!$A$2:$A$1421,$A41,Documents!$C$2:$C$1421,"excursions")=0,"",maxifs(Documents!$E$2:$E$1421,Documents!$A$2:$A$1421,$A41,Documents!$C$2:$C$1421,"excursions")),"") | M41: =IFERROR(IF(maxifs(Documents!$E$2:$E$1421,Documents!$A$2:$A$1421,$A41,Documents!$C$2:$C$1421,"kids")=0,"",maxifs(Documents!$E$2:$E$1421,Documents!$A$2:$A$1421,$A41,Documents!$C$2:$C$1421,"kids")),"") | N41: =IFERROR(IF(maxifs(Documents!$E$2:$E$1421,Documents!$A$2:$A$1421,$A41,Documents!$C$2:$C$1421,"villa_plans")=0,"",maxifs(Documents!$E$2:$E$1421,Documents!$A$2:$A$1421,$A41,Documents!$C$2:$C$1421,"villa_plans")),"") | O41: =IFERROR(IF(maxifs(Documents!$E$2:$E$1421,Documents!$A$2:$A$1421,$A41,Documents!$C$2:$C$1421,"all_inclusive")=0,"",maxifs(Documents!$E$2:$E$1421,Documents!$A$2:$A$1421,$A41,Documents!$C$2:$C$1421,"all_inclusive")),"") | P41: =IFERROR(IF(maxifs(Documents!$E$2:$E$1421,Documents!$A$2:$A$1421,$A41,Documents!$C$2:$C$1421,"sustainability")=0,"",maxifs(Documents!$E$2:$E$1421,Documents!$A$2:$A$1421,$A41,Documents!$C$2:$C$1421,"sustainability")),"") | Q41: =IFERROR(IF(maxifs(Documents!$E$2:$E$1421,Documents!$A$2:$A$1421,$A41,Documents!$C$2:$C$1421,"calendar")=0,"",maxifs(Documents!$E$2:$E$1421,Documents!$A$2:$A$1421,$A41,Documents!$C$2:$C$1421,"calendar")),"") | R41: =IFERROR(IF(maxifs(Documents!$E$2:$E$1421,Documents!$A$2:$A$1421,$A41,Documents!$C$2:$C$1421,"brochure")=0,"",maxifs(Documents!$E$2:$E$1421,Documents!$A$2:$A$1421,$A41,Documents!$C$2:$C$1421,"brochure")),"") | S41: =IFERROR(IF(maxifs(Documents!$E$2:$E$1421,Documents!$A$2:$A$1421,$A41,Documents!$C$2:$C$1421,"press_kit")=0,"",maxifs(Documents!$E$2:$E$1421,Documents!$A$2:$A$1421,$A41,Documents!$C$2:$C$1421,"press_kit")),"") | T41: =IFERROR(IF(maxifs(Documents!$E$2:$E$1421,Documents!$A$2:$A$1421,$A41,Documents!$C$2:$C$1421,"other")=0,"",maxifs(Documents!$E$2:$E$1421,Documents!$A$2:$A$1421,$A41,Documents!$C$2:$C$1421,"other")),"") | U41: =IFERROR(IF(maxifs(Documents!$E$2:$E$1421,Documents!$A$2:$A$1421,$A41,Documents!$C$2:$C$1421,"obsolete")=0,"",maxifs(Documents!$E$2:$E$1421,Documents!$A$2:$A$1421,$A41,Documents!$C$2:$C$1421,"obsolete")),"") | V41: =COUNTIFS(Documents!$A$2:$A$1421,$A41) -> 2 | W41: =COUNTIFS(Documents!$A$2:$A$1421,$A41,Documents!$R$2:$R$1421,"current") -> 0 | X41: =HYPERLINK("https://www.neoscapesmaldives.com/wp-content/uploads/Resort-Factsheet-Le-Meridien-Maldives.pdf","2022_Resort-Factsheet-Le-Meridien-Maldiv") -> 2022_Resort-Factsheet-Le-Meridien-Maldiv | Y41: wedding, events
A42: 41 | B42: Ozen By Atmosphere At Maadhoo | C42: unverified | D42: =IFERROR(IF(maxifs(Documents!$E$2:$E$1421,Documents!$A$2:$A$1421,$A42,Documents!$C$2:$C$1421,"factsheet")=0,"",maxifs(Documents!$E$2:$E$1421,Documents!$A$2:$A$1421,$A42,Documents!$C$2:$C$1421,"factsheet")),"") | E42: =IFERROR(IF(maxifs(Documents!$E$2:$E$1421,Documents!$A$2:$A$1421,$A42,Documents!$C$2:$C$1421,"wedding")=0,"",maxifs(Documents!$E$2:$E$1421,Documents!$A$2:$A$1421,$A42,Documents!$C$2:$C$1421,"wedding")),"") | F42: =IFERROR(IF(maxifs(Documents!$E$2:$E$1421,Documents!$A$2:$A$1421,$A42,Documents!$C$2:$C$1421,"events")=0,"",maxifs(Documents!$E$2:$E$1421,Documents!$A$2:$A$1421,$A42,Documents!$C$2:$C$1421,"events")),"") | G42: =IFERROR(IF(maxifs(Documents!$E$2:$E$1421,Documents!$A$2:$A$1421,$A42,Documents!$C$2:$C$1421,"map")=0,"",maxifs(Documents!$E$2:$E$1421,Documents!$A$2:$A$1421,$A42,Documents!$C$2:$C$1421,"map")),"") | H42: =IFERROR(IF(maxifs(Documents!$E$2:$E$1421,Documents!$A$2:$A$1421,$A42,Documents!$C$2:$C$1421,"dive_map")=0,"",maxifs(Documents!$E$2:$E$1421,Documents!$A$2:$A$1421,$A42,Documents!$C$2:$C$1421,"dive_map")),"") | I42: =IFERROR(IF(maxifs(Documents!$E$2:$E$1421,Documents!$A$2:$A$1421,$A42,Documents!$C$2:$C$1421,"spa_menu")=0,"",maxifs(Documents!$E$2:$E$1421,Documents!$A$2:$A$1421,$A42,Documents!$C$2:$C$1421,"spa_menu")),"") | J42: =IFERROR(IF(maxifs(Documents!$E$2:$E$1421,Documents!$A$2:$A$1421,$A42,Documents!$C$2:$C$1421,"dining_menu")=0,"",maxifs(Documents!$E$2:$E$1421,Documents!$A$2:$A$1421,$A42,Documents!$C$2:$C$1421,"dining_menu")),"") | K42: =IFERROR(IF(maxifs(Documents!$E$2:$E$1421,Documents!$A$2:$A$1421,$A42,Documents!$C$2:$C$1421,"dive_prices")=0,"",maxifs(Documents!$E$2:$E$1421,Documents!$A$2:$A$1421,$A42,Documents!$C$2:$C$1421,"dive_prices")),"") | L42: =IFERROR(IF(maxifs(Documents!$E$2:$E$1421,Documents!$A$2:$A$1421,$A42,Documents!$C$2:$C$1421,"excursions")=0,"",maxifs(Documents!$E$2:$E$1421,Documents!$A$2:$A$1421,$A42,Documents!$C$2:$C$1421,"excursions")),"") | M42: =IFERROR(IF(maxifs(Documents!$E$2:$E$1421,Documents!$A$2:$A$1421,$A42,Documents!$C$2:$C$1421,"kids")=0,"",maxifs(Documents!$E$2:$E$1421,Documents!$A$2:$A$1421,$A42,Documents!$C$2:$C$1421,"kids")),"") | N42: =IFERROR(IF(maxifs(Documents!$E$2:$E$1421,Documents!$A$2:$A$1421,$A42,Documents!$C$2:$C$1421,"villa_plans")=0,"",maxifs(Documents!$E$2:$E$1421,Documents!$A$2:$A$1421,$A42,Documents!$C$2:$C$1421,"villa_plans")),"") | O42: =IFERROR(IF(maxifs(Documents!$E$2:$E$1421,Documents!$A$2:$A$1421,$A42,Documents!$C$2:$C$1421,"all_inclusive")=0,"",maxifs(Documents!$E$2:$E$1421,Documents!$A$2:$A$1421,$A42,Documents!$C$2:$C$1421,"all_inclusive")),"") | P42: =IFERROR(IF(maxifs(Documents!$E$2:$E$1421,Documents!$A$2:$A$1421,$A42,Documents!$C$2:$C$1421,"sustainability")=0,"",maxifs(Documents!$E$2:$E$1421,Documents!$A$2:$A$1421,$A42,Documents!$C$2:$C$1421,"sustainability")),"") | Q42: =IFERROR(IF(maxifs(Documents!$E$2:$E$1421,Documents!$A$2:$A$1421,$A42,Documents!$C$2:$C$1421,"calendar")=0,"",maxifs(Documents!$E$2:$E$1421,Documents!$A$2:$A$1421,$A42,Documents!$C$2:$C$1421,"calendar")),"") | R42: =IFERROR(IF(maxifs(Documents!$E$2:$E$1421,Documents!$A$2:$A$1421,$A42,Documents!$C$2:$C$1421,"brochure")=0,"",maxifs(Documents!$E$2:$E$1421,Documents!$A$2:$A$1421,$A42,Documents!$C$2:$C$1421,"brochure")),"") | S42: =IFERROR(IF(maxifs(Documents!$E$2:$E$1421,Documents!$A$2:$A$1421,$A42,Documents!$C$2:$C$1421,"press_kit")=0,"",maxifs(Documents!$E$2:$E$1421,Documents!$A$2:$A$1421,$A42,Documents!$C$2:$C$1421,"press_kit")),"") | T42: =IFERROR(IF(maxifs(Documents!$E$2:$E$1421,Documents!$A$2:$A$1421,$A42,Documents!$C$2:$C$1421,"other")=0,"",maxifs(Documents!$E$2:$E$1421,Documents!$A$2:$A$1421,$A42,Documents!$C$2:$C$1421,"other")),"") | U42: =IFERROR(IF(maxifs(Documents!$E$2:$E$1421,Documents!$A$2:$A$1421,$A42,Documents!$C$2:$C$1421,"obsolete")=0,"",maxifs(Documents!$E$2:$E$1421,Documents!$A$2:$A$1421,$A42,Documents!$C$2:$C$1421,"obsolete")),"") | V42: =COUNTIFS(Documents!$A$2:$A$1421,$A42) -> 3 | W42: =COUNTIFS(Documents!$A$2:$A$1421,$A42,Documents!$R$2:$R$1421,"current") -> 1 | X42: =HYPERLINK("https://www.neoscapesmaldives.com/wp-content/uploads/OZEN-LIFE-MAADHOO-Fact-Sheet-2025.pdf","2025_OZEN-LIFE-MAADHOO-Fact-Sheet-2025.p") -> 2025_OZEN-LIFE-MAADHOO-Fact-Sheet-2025.p | Y42: wedding, events | Z42: OZEN Life Maadhoo
A43: 42 | B43: Dhiggiri Tourist Resort | C43: unverified | D43: =IFERROR(IF(maxifs(Documents!$E$2:$E$1421,Documents!$A$2:$A$1421,$A43,Documents!$C$2:$C$1421,"factsheet")=0,"",maxifs(Documents!$E$2:$E$1421,Documents!$A$2:$A$1421,$A43,Documents!$C$2:$C$1421,"factsheet")),"") | E43: =IFERROR(IF(maxifs(Documents!$E$2:$E$1421,Documents!$A$2:$A$1421,$A43,Documents!$C$2:$C$1421,"wedding")=0,"",maxifs(Documents!$E$2:$E$1421,Documents!$A$2:$A$1421,$A43,Documents!$C$2:$C$1421,"wedding")),"") | F43: =IFERROR(IF(maxifs(Documents!$E$2:$E$1421,Documents!$A$2:$A$1421,$A43,Documents!$C$2:$C$1421,"events")=0,"",maxifs(Documents!$E$2:$E$1421,Documents!$A$2:$A$1421,$A43,Documents!$C$2:$C$1421,"events")),"") | G43: =IFERROR(IF(maxifs(Documents!$E$2:$E$1421,Documents!$A$2:$A$1421,$A43,Documents!$C$2:$C$1421,"map")=0,"",maxifs(Documents!$E$2:$E$1421,Documents!$A$2:$A$1421,$A43,Documents!$C$2:$C$1421,"map")),"") | H43: =IFERROR(IF(maxifs(Documents!$E$2:$E$1421,Documents!$A$2:$A$1421,$A43,Documents!$C$2:$C$1421,"dive_map")=0,"",maxifs(Documents!$E$2:$E$1421,Documents!$A$2:$A$1421,$A43,Documents!$C$2:$C$1421,"dive_map")),"") | I43: =IFERROR(IF(maxifs(Documents!$E$2:$E$1421,Documents!$A$2:$A$1421,$A43,Documents!$C$2:$C$1421,"spa_menu")=0,"",maxifs(Documents!$E$2:$E$1421,Documents!$A$2:$A$1421,$A43,Documents!$C$2:$C$1421,"spa_menu")),"") | J43: =IFERROR(IF(maxifs(Documents!$E$2:$E$1421,Documents!$A$2:$A$1421,$A43,Documents!$C$2:$C$1421,"dining_menu")=0,"",maxifs(Documents!$E$2:$E$1421,Documents!$A$2:$A$1421,$A43,Documents!$C$2:$C$1421,"dining_menu")),"") | K43: =IFERROR(IF(maxifs(Documents!$E$2:$E$1421,Documents!$A$2:$A$1421,$A43,Documents!$C$2:$C$1421,"dive_prices")=0,"",maxifs(Documents!$E$2:$E$1421,Documents!$A$2:$A$1421,$A43,Documents!$C$2:$C$1421,"dive_prices")),"") | L43: =IFERROR(IF(maxifs(Documents!$E$2:$E$1421,Documents!$A$2:$A$1421,$A43,Documents!$C$2:$C$1421,"excursions")=0,"",maxifs(Documents!$E$2:$E$1421,Documents!$A$2:$A$1421,$A43,Documents!$C$2:$C$1421,"excursions")),"") | M43: =IFERROR(IF(maxifs(Documents!$E$2:$E$1421,Documents!$A$2:$A$1421,$A43,Documents!$C$2:$C$1421,"kids")=0,"",maxifs(Documents!$E$2:$E$1421,Documents!$A$2:$A$1421,$A43,Documents!$C$2:$C$1421,"kids")),"") | N43: =IFERROR(IF(maxifs(Documents!$E$2:$E$1421,Documents!$A$2:$A$1421,$A43,Documents!$C$2:$C$1421,"villa_plans")=0,"",maxifs(Documents!$E$2:$E$1421,Documents!$A$2:$A$1421,$A43,Documents!$C$2:$C$1421,"villa_plans")),"") | O43: =IFERROR(IF(maxifs(Documents!$E$2:$E$1421,Documents!$A$2:$A$1421,$A43,Documents!$C$2:$C$1421,"all_inclusive")=0,"",maxifs(Documents!$E$2:$E$1421,Documents!$A$2:$A$1421,$A43,Documents!$C$2:$C$1421,"all_inclusive")),"") | P43: =IFERROR(IF(maxifs(Documents!$E$2:$E$1421,Documents!$A$2:$A$1421,$A43,Documents!$C$2:$C$1421,"sustainability")=0,"",maxifs(Documents!$E$2:$E$1421,Documents!$A$2:$A$1421,$A43,Documents!$C$2:$C$1421,"sustainability")),"") | Q43: =IFERROR(IF(maxifs(Documents!$E$2:$E$1421,Documents!$A$2:$A$1421,$A43,Documents!$C$2:$C$1421,"calendar")=0,"",maxifs(Documents!$E$2:$E$1421,Documents!$A$2:$A$1421,$A43,Documents!$C$2:$C$1421,"calendar")),"") | R43: =IFERROR(IF(maxifs(Documents!$E$2:$E$1421,Documents!$A$2:$A$1421,$A43,Documents!$C$2:$C$1421,"brochure")=0,"",maxifs(Documents!$E$2:$E$1421,Documents!$A$2:$A$1421,$A43,Documents!$C$2:$C$1421,"brochure")),"") | S43: =IFERROR(IF(maxifs(Documents!$E$2:$E$1421,Documents!$A$2:$A$1421,$A43,Documents!$C$2:$C$1421,"press_kit")=0,"",maxifs(Documents!$E$2:$E$1421,Documents!$A$2:$A$1421,$A43,Documents!$C$2:$C$1421,"press_kit")),"") | T43: =IFERROR(IF(maxifs(Documents!$E$2:$E$1421,Documents!$A$2:$A$1421,$A43,Documents!$C$2:$C$1421,"other")=0,"",maxifs(Documents!$E$2:$E$1421,Documents!$A$2:$A$1421,$A43,Documents!$C$2:$C$1421,"other")),"") | U43: =IFERROR(IF(maxifs(Documents!$E$2:$E$1421,Documents!$A$2:$A$1421,$A43,Documents!$C$2:$C$1421,"obsolete")=0,"",maxifs(Documents!$E$2:$E$1421,Documents!$A$2:$A$1421,$A43,Documents!$C$2:$C$1421,"obsolete")),"") | V43: =COUNTIFS(Documents!$A$2:$A$1421,$A43) -> 0 | W43: =COUNTIFS(Documents!$A$2:$A$1421,$A43,Documents!$R$2:$R$1421,"current") -> 0 | Y43: factsheet, wedding, events
A44: 43 | B44: Dhigufaru Island Resort | C44: ok | D44: =IFERROR(IF(maxifs(Documents!$E$2:$E$1421,Documents!$A$2:$A$1421,$A44,Documents!$C$2:$C$1421,"factsheet")=0,"",maxifs(Documents!$E$2:$E$1421,Documents!$A$2:$A$1421,$A44,Documents!$C$2:$C$1421,"factsheet")),"") | E44: =IFERROR(IF(maxifs(Documents!$E$2:$E$1421,Documents!$A$2:$A$1421,$A44,Documents!$C$2:$C$1421,"wedding")=0,"",maxifs(Documents!$E$2:$E$1421,Documents!$A$2:$A$1421,$A44,Documents!$C$2:$C$1421,"wedding")),"") | F44: =IFERROR(IF(maxifs(Documents!$E$2:$E$1421,Documents!$A$2:$A$1421,$A44,Documents!$C$2:$C$1421,"events")=0,"",maxifs(Documents!$E$2:$E$1421,Documents!$A$2:$A$1421,$A44,Documents!$C$2:$C$1421,"events")),"") | G44: =IFERROR(IF(maxifs(Documents!$E$2:$E$1421,Documents!$A$2:$A$1421,$A44,Documents!$C$2:$C$1421,"map")=0,"",maxifs(Documents!$E$2:$E$1421,Documents!$A$2:$A$1421,$A44,Documents!$C$2:$C$1421,"map")),"") | H44: =IFERROR(IF(maxifs(Documents!$E$2:$E$1421,Documents!$A$2:$A$1421,$A44,Documents!$C$2:$C$1421,"dive_map")=0,"",maxifs(Documents!$E$2:$E$1421,Documents!$A$2:$A$1421,$A44,Documents!$C$2:$C$1421,"dive_map")),"") | I44: =IFERROR(IF(maxifs(Documents!$E$2:$E$1421,Documents!$A$2:$A$1421,$A44,Documents!$C$2:$C$1421,"spa_menu")=0,"",maxifs(Documents!$E$2:$E$1421,Documents!$A$2:$A$1421,$A44,Documents!$C$2:$C$1421,"spa_menu")),"") | J44: =IFERROR(IF(maxifs(Documents!$E$2:$E$1421,Documents!$A$2:$A$1421,$A44,Documents!$C$2:$C$1421,"dining_menu")=0,"",maxifs(Documents!$E$2:$E$1421,Documents!$A$2:$A$1421,$A44,Documents!$C$2:$C$1421,"dining_menu")),"") | K44: =IFERROR(IF(maxifs(Documents!$E$2:$E$1421,Documents!$A$2:$A$1421,$A44,Documents!$C$2:$C$1421,"dive_prices")=0,"",maxifs(Documents!$E$2:$E$1421,Documents!$A$2:$A$1421,$A44,Documents!$C$2:$C$1421,"dive_prices")),"") | L44: =IFERROR(IF(maxifs(Documents!$E$2:$E$1421,Documents!$A$2:$A$1421,$A44,Documents!$C$2:$C$1421,"excursions")=0,"",maxifs(Documents!$E$2:$E$1421,Documents!$A$2:$A$1421,$A44,Documents!$C$2:$C$1421,"excursions")),"") | M44: =IFERROR(IF(maxifs(Documents!$E$2:$E$1421,Documents!$A$2:$A$1421,$A44,Documents!$C$2:$C$1421,"kids")=0,"",maxifs(Documents!$E$2:$E$1421,Documents!$A$2:$A$1421,$A44,Documents!$C$2:$C$1421,"kids")),"") | N44: =IFERROR(IF(maxifs(Documents!$E$2:$E$1421,Documents!$A$2:$A$1421,$A44,Documents!$C$2:$C$1421,"villa_plans")=0,"",maxifs(Documents!$E$2:$E$1421,Documents!$A$2:$A$1421,$A44,Documents!$C$2:$C$1421,"villa_plans")),"") | O44: =IFERROR(IF(maxifs(Documents!$E$2:$E$1421,Documents!$A$2:$A$1421,$A44,Documents!$C$2:$C$1421,"all_inclusive")=0,"",maxifs(Documents!$E$2:$E$1421,Documents!$A$2:$A$1421,$A44,Documents!$C$2:$C$1421,"all_inclusive")),"") | P44: =IFERROR(IF(maxifs(Documents!$E$2:$E$1421,Documents!$A$2:$A$1421,$A44,Documents!$C$2:$C$1421,"sustainability")=0,"",maxifs(Documents!$E$2:$E$1421,Documents!$A$2:$A$1421,$A44,Documents!$C$2:$C$1421,"sustainability")),"") | Q44: =IFERROR(IF(maxifs(Documents!$E$2:$E$1421,Documents!$A$2:$A$1421,$A44,Documents!$C$2:$C$1421,"calendar")=0,"",maxifs(Documents!$E$2:$E$1421,Documents!$A$2:$A$1421,$A44,Documents!$C$2:$C$1421,"calendar")),"") | R44: =IFERROR(IF(maxifs(Documents!$E$2:$E$1421,Documents!$A$2:$A$1421,$A44,Documents!$C$2:$C$1421,"brochure")=0,"",maxifs(Documents!$E$2:$E$1421,Documents!$A$2:$A$1421,$A44,Documents!$C$2:$C$1421,"brochure")),"") | S44: =IFERROR(IF(maxifs(Documents!$E$2:$E$1421,Documents!$A$2:$A$1421,$A44,Documents!$C$2:$C$1421,"press_kit")=0,"",maxifs(Documents!$E$2:$E$1421,Documents!$A$2:$A$1421,$A44,Documents!$C$2:$C$1421,"press_kit")),"") | T44: =IFERROR(IF(maxifs(Documents!$E$2:$E$1421,Documents!$A$2:$A$1421,$A44,Documents!$C$2:$C$1421,"other")=0,"",maxifs(Documents!$E$2:$E$1421,Documents!$A$2:$A$1421,$A44,Documents!$C$2:$C$1421,"other")),"") | U44: =IFERROR(IF(maxifs(Documents!$E$2:$E$1421,Documents!$A$2:$A$1421,$A44,Documents!$C$2:$C$1421,"obsolete")=0,"",maxifs(Documents!$E$2:$E$1421,Documents!$A$2:$A$1421,$A44,Documents!$C$2:$C$1421,"obsolete")),"") | V44: =COUNTIFS(Documents!$A$2:$A$1421,$A44) -> 10 | W44: =COUNTIFS(Documents!$A$2:$A$1421,$A44,Documents!$R$2:$R$1421,"current") -> 1 | X44: =HYPERLINK("https://dhigufaru.com/app/wp-content/uploads/2026/06/Dhigufaru-Fact-Sheet-English.pdf","2025_Dhigufaru-Fact-Sheet-English.pdf") -> 2025_Dhigufaru-Fact-Sheet-English.pdf | Y44: events
A45: 44 | B45: Hard Rock Hotel Maldives | C45: ok | D45: =IFERROR(IF(maxifs(Documents!$E$2:$E$1421,Documents!$A$2:$A$1421,$A45,Documents!$C$2:$C$1421,"factsheet")=0,"",maxifs(Documents!$E$2:$E$1421,Documents!$A$2:$A$1421,$A45,Documents!$C$2:$C$1421,"factsheet")),"") | E45: =IFERROR(IF(maxifs(Documents!$E$2:$E$1421,Documents!$A$2:$A$1421,$A45,Documents!$C$2:$C$1421,"wedding")=0,"",maxifs(Documents!$E$2:$E$1421,Documents!$A$2:$A$1421,$A45,Documents!$C$2:$C$1421,"wedding")),"") | F45: =IFERROR(IF(maxifs(Documents!$E$2:$E$1421,Documents!$A$2:$A$1421,$A45,Documents!$C$2:$C$1421,"events")=0,"",maxifs(Documents!$E$2:$E$1421,Documents!$A$2:$A$1421,$A45,Documents!$C$2:$C$1421,"events")),"") | G45: =IFERROR(IF(maxifs(Documents!$E$2:$E$1421,Documents!$A$2:$A$1421,$A45,Documents!$C$2:$C$1421,"map")=0,"",maxifs(Documents!$E$2:$E$1421,Documents!$A$2:$A$1421,$A45,Documents!$C$2:$C$1421,"map")),"") | H45: =IFERROR(IF(maxifs(Documents!$E$2:$E$1421,Documents!$A$2:$A$1421,$A45,Documents!$C$2:$C$1421,"dive_map")=0,"",maxifs(Documents!$E$2:$E$1421,Documents!$A$2:$A$1421,$A45,Documents!$C$2:$C$1421,"dive_map")),"") | I45: =IFERROR(IF(maxifs(Documents!$E$2:$E$1421,Documents!$A$2:$A$1421,$A45,Documents!$C$2:$C$1421,"spa_menu")=0,"",maxifs(Documents!$E$2:$E$1421,Documents!$A$2:$A$1421,$A45,Documents!$C$2:$C$1421,"spa_menu")),"") | J45: =IFERROR(IF(maxifs(Documents!$E$2:$E$1421,Documents!$A$2:$A$1421,$A45,Documents!$C$2:$C$1421,"dining_menu")=0,"",maxifs(Documents!$E$2:$E$1421,Documents!$A$2:$A$1421,$A45,Documents!$C$2:$C$1421,"dining_menu")),"") | K45: =IFERROR(IF(maxifs(Documents!$E$2:$E$1421,Documents!$A$2:$A$1421,$A45,Documents!$C$2:$C$1421,"dive_prices")=0,"",maxifs(Documents!$E$2:$E$1421,Documents!$A$2:$A$1421,$A45,Documents!$C$2:$C$1421,"dive_prices")),"") | L45: =IFERROR(IF(maxifs(Documents!$E$2:$E$1421,Documents!$A$2:$A$1421,$A45,Documents!$C$2:$C$1421,"excursions")=0,"",maxifs(Documents!$E$2:$E$1421,Documents!$A$2:$A$1421,$A45,Documents!$C$2:$C$1421,"excursions")),"") | M45: =IFERROR(IF(maxifs(Documents!$E$2:$E$1421,Documents!$A$2:$A$1421,$A45,Documents!$C$2:$C$1421,"kids")=0,"",maxifs(Documents!$E$2:$E$1421,Documents!$A$2:$A$1421,$A45,Documents!$C$2:$C$1421,"kids")),"") | N45: =IFERROR(IF(maxifs(Documents!$E$2:$E$1421,Documents!$A$2:$A$1421,$A45,Documents!$C$2:$C$1421,"villa_plans")=0,"",maxifs(Documents!$E$2:$E$1421,Documents!$A$2:$A$1421,$A45,Documents!$C$2:$C$1421,"villa_plans")),"") | O45: =IFERROR(IF(maxifs(Documents!$E$2:$E$1421,Documents!$A$2:$A$1421,$A45,Documents!$C$2:$C$1421,"all_inclusive")=0,"",maxifs(Documents!$E$2:$E$1421,Documents!$A$2:$A$1421,$A45,Documents!$C$2:$C$1421,"all_inclusive")),"") | P45: =IFERROR(IF(maxifs(Documents!$E$2:$E$1421,Documents!$A$2:$A$1421,$A45,Documents!$C$2:$C$1421,"sustainability")=0,"",maxifs(Documents!$E$2:$E$1421,Documents!$A$2:$A$1421,$A45,Documents!$C$2:$C$1421,"sustainability")),"") | Q45: =IFERROR(IF(maxifs(Documents!$E$2:$E$1421,Documents!$A$2:$A$1421,$A45,Documents!$C$2:$C$1421,"calendar")=0,"",maxifs(Documents!$E$2:$E$1421,Documents!$A$2:$A$1421,$A45,Documents!$C$2:$C$1421,"calendar")),"") | R45: =IFERROR(IF(maxifs(Documents!$E$2:$E$1421,Documents!$A$2:$A$1421,$A45,Documents!$C$2:$C$1421,"brochure")=0,"",maxifs(Documents!$E$2:$E$1421,Documents!$A$2:$A$1421,$A45,Documents!$C$2:$C$1421,"brochure")),"") | S45: =IFERROR(IF(maxifs(Documents!$E$2:$E$1421,Documents!$A$2:$A$1421,$A45,Documents!$C$2:$C$1421,"press_kit")=0,"",maxifs(Documents!$E$2:$E$1421,Documents!$A$2:$A$1421,$A45,Documents!$C$2:$C$1421,"press_kit")),"") | T45: =IFERROR(IF(maxifs(Documents!$E$2:$E$1421,Documents!$A$2:$A$1421,$A45,Documents!$C$2:$C$1421,"other")=0,"",maxifs(Documents!$E$2:$E$1421,Documents!$A$2:$A$1421,$A45,Documents!$C$2:$C$1421,"other")),"") | U45: =IFERROR(IF(maxifs(Documents!$E$2:$E$1421,Documents!$A$2:$A$1421,$A45,Documents!$C$2:$C$1421,"obsolete")=0,"",maxifs(Documents!$E$2:$E$1421,Documents!$A$2:$A$1421,$A45,Documents!$C$2:$C$1421,"obsolete")),"") | V45: =COUNTIFS(Documents!$A$2:$A$1421,$A45) -> 34 | W45: =COUNTIFS(Documents!$A$2:$A$1421,$A45,Documents!$R$2:$R$1421,"current") -> 27 | Y45: factsheet, events | Z45: site redirects to hotel.hardrock.com
A46: 45 | B46: Saii Lagoon Maldives | C46: ok | D46: =IFERROR(IF(maxifs(Documents!$E$2:$E$1421,Documents!$A$2:$A$1421,$A46,Documents!$C$2:$C$1421,"factsheet")=0,"",maxifs(Documents!$E$2:$E$1421,Documents!$A$2:$A$1421,$A46,Documents!$C$2:$C$1421,"factsheet")),"") | E46: =IFERROR(IF(maxifs(Documents!$E$2:$E$1421,Documents!$A$2:$A$1421,$A46,Documents!$C$2:$C$1421,"wedding")=0,"",maxifs(Documents!$E$2:$E$1421,Documents!$A$2:$A$1421,$A46,Documents!$C$2:$C$1421,"wedding")),"") | F46: =IFERROR(IF(maxifs(Documents!$E$2:$E$1421,Documents!$A$2:$A$1421,$A46,Documents!$C$2:$C$1421,"events")=0,"",maxifs(Documents!$E$2:$E$1421,Documents!$A$2:$A$1421,$A46,Documents!$C$2:$C$1421,"events")),"") | G46: =IFERROR(IF(maxifs(Documents!$E$2:$E$1421,Documents!$A$2:$A$1421,$A46,Documents!$C$2:$C$1421,"map")=0,"",maxifs(Documents!$E$2:$E$1421,Documents!$A$2:$A$1421,$A46,Documents!$C$2:$C$1421,"map")),"") | H46: =IFERROR(IF(maxifs(Documents!$E$2:$E$1421,Documents!$A$2:$A$1421,$A46,Documents!$C$2:$C$1421,"dive_map")=0,"",maxifs(Documents!$E$2:$E$1421,Documents!$A$2:$A$1421,$A46,Documents!$C$2:$C$1421,"dive_map")),"") | I46: =IFERROR(IF(maxifs(Documents!$E$2:$E$1421,Documents!$A$2:$A$1421,$A46,Documents!$C$2:$C$1421,"spa_menu")=0,"",maxifs(Documents!$E$2:$E$1421,Documents!$A$2:$A$1421,$A46,Documents!$C$2:$C$1421,"spa_menu")),"") | J46: =IFERROR(IF(maxifs(Documents!$E$2:$E$1421,Documents!$A$2:$A$1421,$A46,Documents!$C$2:$C$1421,"dining_menu")=0,"",maxifs(Documents!$E$2:$E$1421,Documents!$A$2:$A$1421,$A46,Documents!$C$2:$C$1421,"dining_menu")),"") | K46: =IFERROR(IF(maxifs(Documents!$E$2:$E$1421,Documents!$A$2:$A$1421,$A46,Documents!$C$2:$C$1421,"dive_prices")=0,"",maxifs(Documents!$E$2:$E$1421,Documents!$A$2:$A$1421,$A46,Documents!$C$2:$C$1421,"dive_prices")),"") | L46: =IFERROR(IF(maxifs(Documents!$E$2:$E$1421,Documents!$A$2:$A$1421,$A46,Documents!$C$2:$C$1421,"excursions")=0,"",maxifs(Documents!$E$2:$E$1421,Documents!$A$2:$A$1421,$A46,Documents!$C$2:$C$1421,"excursions")),"") | M46: =IFERROR(IF(maxifs(Documents!$E$2:$E$1421,Documents!$A$2:$A$1421,$A46,Documents!$C$2:$C$1421,"kids")=0,"",maxifs(Documents!$E$2:$E$1421,Documents!$A$2:$A$1421,$A46,Documents!$C$2:$C$1421,"kids")),"") | N46: =IFERROR(IF(maxifs(Documents!$E$2:$E$1421,Documents!$A$2:$A$1421,$A46,Documents!$C$2:$C$1421,"villa_plans")=0,"",maxifs(Documents!$E$2:$E$1421,Documents!$A$2:$A$1421,$A46,Documents!$C$2:$C$1421,"villa_plans")),"") | O46: =IFERROR(IF(maxifs(Documents!$E$2:$E$1421,Documents!$A$2:$A$1421,$A46,Documents!$C$2:$C$1421,"all_inclusive")=0,"",maxifs(Documents!$E$2:$E$1421,Documents!$A$2:$A$1421,$A46,Documents!$C$2:$C$1421,"all_inclusive")),"") | P46: =IFERROR(IF(maxifs(Documents!$E$2:$E$1421,Documents!$A$2:$A$1421,$A46,Documents!$C$2:$C$1421,"sustainability")=0,"",maxifs(Documents!$E$2:$E$1421,Documents!$A$2:$A$1421,$A46,Documents!$C$2:$C$1421,"sustainability")),"") | Q46: =IFERROR(IF(maxifs(Documents!$E$2:$E$1421,Documents!$A$2:$A$1421,$A46,Documents!$C$2:$C$1421,"calendar")=0,"",maxifs(Documents!$E$2:$E$1421,Documents!$A$2:$A$1421,$A46,Documents!$C$2:$C$1421,"calendar")),"") | R46: =IFERROR(IF(maxifs(Documents!$E$2:$E$1421,Documents!$A$2:$A$1421,$A46,Documents!$C$2:$C$1421,"brochure")=0,"",maxifs(Documents!$E$2:$E$1421,Documents!$A$2:$A$1421,$A46,Documents!$C$2:$C$1421,"brochure")),"") | S46: =IFERROR(IF(maxifs(Documents!$E$2:$E$1421,Documents!$A$2:$A$1421,$A46,Documents!$C$2:$C$1421,"press_kit")=0,"",maxifs(Documents!$E$2:$E$1421,Documents!$A$2:$A$1421,$A46,Documents!$C$2:$C$1421,"press_kit")),"") | T46: =IFERROR(IF(maxifs(Documents!$E$2:$E$1421,Documents!$A$2:$A$1421,$A46,Documents!$C$2:$C$1421,"other")=0,"",maxifs(Documents!$E$2:$E$1421,Documents!$A$2:$A$1421,$A46,Documents!$C$2:$C$1421,"other")),"") | U46: =IFERROR(IF(maxifs(Documents!$E$2:$E$1421,Documents!$A$2:$A$1421,$A46,Documents!$C$2:$C$1421,"obsolete")=0,"",maxifs(Documents!$E$2:$E$1421,Documents!$A$2:$A$1421,$A46,Documents!$C$2:$C$1421,"obsolete")),"") | V46: =COUNTIFS(Documents!$A$2:$A$1421,$A46) -> 67 | W46: =COUNTIFS(Documents!$A$2:$A$1421,$A46,Documents!$R$2:$R$1421,"current") -> 63 | X46: =HYPERLINK("https://www.saiihotels.com/wp-content/uploads/2025/10/SAii-Lagoon-Maldives-Factsheet-2025.pdf","2025_SAii-Lagoon-Maldives-Factsheet-2025") -> 2025_SAii-Lagoon-Maldives-Factsheet-2025 | Y46: wedding | Z46: site redirects to www.saiihotels.com
A47: 46 | B47: SO/ Maldives | C47: ok | D47: =IFERROR(IF(maxifs(Documents!$E$2:$E$1421,Documents!$A$2:$A$1421,$A47,Documents!$C$2:$C$1421,"factsheet")=0,"",maxifs(Documents!$E$2:$E$1421,Documents!$A$2:$A$1421,$A47,Documents!$C$2:$C$1421,"factsheet")),"") | E47: =IFERROR(IF(maxifs(Documents!$E$2:$E$1421,Documents!$A$2:$A$1421,$A47,Documents!$C$2:$C$1421,"wedding")=0,"",maxifs(Documents!$E$2:$E$1421,Documents!$A$2:$A$1421,$A47,Documents!$C$2:$C$1421,"wedding")),"") | F47: =IFERROR(IF(maxifs(Documents!$E$2:$E$1421,Documents!$A$2:$A$1421,$A47,Documents!$C$2:$C$1421,"events")=0,"",maxifs(Documents!$E$2:$E$1421,Documents!$A$2:$A$1421,$A47,Documents!$C$2:$C$1421,"events")),"") | G47: =IFERROR(IF(maxifs(Documents!$E$2:$E$1421,Documents!$A$2:$A$1421,$A47,Documents!$C$2:$C$1421,"map")=0,"",maxifs(Documents!$E$2:$E$1421,Documents!$A$2:$A$1421,$A47,Documents!$C$2:$C$1421,"map")),"") | H47: =IFERROR(IF(maxifs(Documents!$E$2:$E$1421,Documents!$A$2:$A$1421,$A47,Documents!$C$2:$C$1421,"dive_map")=0,"",maxifs(Documents!$E$2:$E$1421,Documents!$A$2:$A$1421,$A47,Documents!$C$2:$C$1421,"dive_map")),"") | I47: =IFERROR(IF(maxifs(Documents!$E$2:$E$1421,Documents!$A$2:$A$1421,$A47,Documents!$C$2:$C$1421,"spa_menu")=0,"",maxifs(Documents!$E$2:$E$1421,Documents!$A$2:$A$1421,$A47,Documents!$C$2:$C$1421,"spa_menu")),"") | J47: =IFERROR(IF(maxifs(Documents!$E$2:$E$1421,Documents!$A$2:$A$1421,$A47,Documents!$C$2:$C$1421,"dining_menu")=0,"",maxifs(Documents!$E$2:$E$1421,Documents!$A$2:$A$1421,$A47,Documents!$C$2:$C$1421,"dining_menu")),"") | K47: =IFERROR(IF(maxifs(Documents!$E$2:$E$1421,Documents!$A$2:$A$1421,$A47,Documents!$C$2:$C$1421,"dive_prices")=0,"",maxifs(Documents!$E$2:$E$1421,Documents!$A$2:$A$1421,$A47,Documents!$C$2:$C$1421,"dive_prices")),"") | L47: =IFERROR(IF(maxifs(Documents!$E$2:$E$1421,Documents!$A$2:$A$1421,$A47,Documents!$C$2:$C$1421,"excursions")=0,"",maxifs(Documents!$E$2:$E$1421,Documents!$A$2:$A$1421,$A47,Documents!$C$2:$C$1421,"excursions")),"") | M47: =IFERROR(IF(maxifs(Documents!$E$2:$E$1421,Documents!$A$2:$A$1421,$A47,Documents!$C$2:$C$1421,"kids")=0,"",maxifs(Documents!$E$2:$E$1421,Documents!$A$2:$A$1421,$A47,Documents!$C$2:$C$1421,"kids")),"") | N47: =IFERROR(IF(maxifs(Documents!$E$2:$E$1421,Documents!$A$2:$A$1421,$A47,Documents!$C$2:$C$1421,"villa_plans")=0,"",maxifs(Documents!$E$2:$E$1421,Documents!$A$2:$A$1421,$A47,Documents!$C$2:$C$1421,"villa_plans")),"") | O47: =IFERROR(IF(maxifs(Documents!$E$2:$E$1421,Documents!$A$2:$A$1421,$A47,Documents!$C$2:$C$1421,"all_inclusive")=0,"",maxifs(Documents!$E$2:$E$1421,Documents!$A$2:$A$1421,$A47,Documents!$C$2:$C$1421,"all_inclusive")),"") | P47: =IFERROR(IF(maxifs(Documents!$E$2:$E$1421,Documents!$A$2:$A$1421,$A47,Documents!$C$2:$C$1421,"sustainability")=0,"",maxifs(Documents!$E$2:$E$1421,Documents!$A$2:$A$1421,$A47,Documents!$C$2:$C$1421,"sustainability")),"") | Q47: =IFERROR(IF(maxifs(Documents!$E$2:$E$1421,Documents!$A$2:$A$1421,$A47,Documents!$C$2:$C$1421,"calendar")=0,"",maxifs(Documents!$E$2:$E$1421,Documents!$A$2:$A$1421,$A47,Documents!$C$2:$C$1421,"calendar")),"") | R47: =IFERROR(IF(maxifs(Documents!$E$2:$E$1421,Documents!$A$2:$A$1421,$A47,Documents!$C$2:$C$1421,"brochure")=0,"",maxifs(Documents!$E$2:$E$1421,Documents!$A$2:$A$1421,$A47,Documents!$C$2:$C$1421,"brochure")),"") | S47: =IFERROR(IF(maxifs(Documents!$E$2:$E$1421,Documents!$A$2:$A$1421,$A47,Documents!$C$2:$C$1421,"press_kit")=0,"",maxifs(Documents!$E$2:$E$1421,Documents!$A$2:$A$1421,$A47,Documents!$C$2:$C$1421,"press_kit")),"") | T47: =IFERROR(IF(maxifs(Documents!$E$2:$E$1421,Documents!$A$2:$A$1421,$A47,Documents!$C$2:$C$1421,"other")=0,"",maxifs(Documents!$E$2:$E$1421,Documents!$A$2:$A$1421,$A47,Documents!$C$2:$C$1421,"other")),"") | U47: =IFERROR(IF(maxifs(Documents!$E$2:$E$1421,Documents!$A$2:$A$1421,$A47,Documents!$C$2:$C$1421,"obsolete")=0,"",maxifs(Documents!$E$2:$E$1421,Documents!$A$2:$A$1421,$A47,Documents!$C$2:$C$1421,"obsolete")),"") | V47: =COUNTIFS(Documents!$A$2:$A$1421,$A47) -> 57 | W47: =COUNTIFS(Documents!$A$2:$A$1421,$A47,Documents!$R$2:$R$1421,"current") -> 51 | X47: =HYPERLINK("https://www.neoscapesmaldives.com/wp-content/uploads/SO-Maldives-Factsheet_Eng.pdf","2025_SO-Maldives-Factsheet_Eng.pdf") -> 2025_SO-Maldives-Factsheet_Eng.pdf
A48: 47 | B48: Park Hyatt Maldives, Hadahaa | C48: unverified | D48: =IFERROR(IF(maxifs(Documents!$E$2:$E$1421,Documents!$A$2:$A$1421,$A48,Documents!$C$2:$C$1421,"factsheet")=0,"",maxifs(Documents!$E$2:$E$1421,Documents!$A$2:$A$1421,$A48,Documents!$C$2:$C$1421,"factsheet")),"") | E48: =IFERROR(IF(maxifs(Documents!$E$2:$E$1421,Documents!$A$2:$A$1421,$A48,Documents!$C$2:$C$1421,"wedding")=0,"",maxifs(Documents!$E$2:$E$1421,Documents!$A$2:$A$1421,$A48,Documents!$C$2:$C$1421,"wedding")),"") | F48: =IFERROR(IF(maxifs(Documents!$E$2:$E$1421,Documents!$A$2:$A$1421,$A48,Documents!$C$2:$C$1421,"events")=0,"",maxifs(Documents!$E$2:$E$1421,Documents!$A$2:$A$1421,$A48,Documents!$C$2:$C$1421,"events")),"") | G48: =IFERROR(IF(maxifs(Documents!$E$2:$E$1421,Documents!$A$2:$A$1421,$A48,Documents!$C$2:$C$1421,"map")=0,"",maxifs(Documents!$E$2:$E$1421,Documents!$A$2:$A$1421,$A48,Documents!$C$2:$C$1421,"map")),"") | H48: =IFERROR(IF(maxifs(Documents!$E$2:$E$1421,Documents!$A$2:$A$1421,$A48,Documents!$C$2:$C$1421,"dive_map")=0,"",maxifs(Documents!$E$2:$E$1421,Documents!$A$2:$A$1421,$A48,Documents!$C$2:$C$1421,"dive_map")),"") | I48: =IFERROR(IF(maxifs(Documents!$E$2:$E$1421,Documents!$A$2:$A$1421,$A48,Documents!$C$2:$C$1421,"spa_menu")=0,"",maxifs(Documents!$E$2:$E$1421,Documents!$A$2:$A$1421,$A48,Documents!$C$2:$C$1421,"spa_menu")),"") | J48: =IFERROR(IF(maxifs(Documents!$E$2:$E$1421,Documents!$A$2:$A$1421,$A48,Documents!$C$2:$C$1421,"dining_menu")=0,"",maxifs(Documents!$E$2:$E$1421,Documents!$A$2:$A$1421,$A48,Documents!$C$2:$C$1421,"dining_menu")),"") | K48: =IFERROR(IF(maxifs(Documents!$E$2:$E$1421,Documents!$A$2:$A$1421,$A48,Documents!$C$2:$C$1421,"dive_prices")=0,"",maxifs(Documents!$E$2:$E$1421,Documents!$A$2:$A$1421,$A48,Documents!$C$2:$C$1421,"dive_prices")),"") | L48: =IFERROR(IF(maxifs(Documents!$E$2:$E$1421,Documents!$A$2:$A$1421,$A48,Documents!$C$2:$C$1421,"excursions")=0,"",maxifs(Documents!$E$2:$E$1421,Documents!$A$2:$A$1421,$A48,Documents!$C$2:$C$1421,"excursions")),"") | M48: =IFERROR(IF(maxifs(Documents!$E$2:$E$1421,Documents!$A$2:$A$1421,$A48,Documents!$C$2:$C$1421,"kids")=0,"",maxifs(Documents!$E$2:$E$1421,Documents!$A$2:$A$1421,$A48,Documents!$C$2:$C$1421,"kids")),"") | N48: =IFERROR(IF(maxifs(Documents!$E$2:$E$1421,Documents!$A$2:$A$1421,$A48,Documents!$C$2:$C$1421,"villa_plans")=0,"",maxifs(Documents!$E$2:$E$1421,Documents!$A$2:$A$1421,$A48,Documents!$C$2:$C$1421,"villa_plans")),"") | O48: =IFERROR(IF(maxifs(Documents!$E$2:$E$1421,Documents!$A$2:$A$1421,$A48,Documents!$C$2:$C$1421,"all_inclusive")=0,"",maxifs(Documents!$E$2:$E$1421,Documents!$A$2:$A$1421,$A48,Documents!$C$2:$C$1421,"all_inclusive")),"") | P48: =IFERROR(IF(maxifs(Documents!$E$2:$E$1421,Documents!$A$2:$A$1421,$A48,Documents!$C$2:$C$1421,"sustainability")=0,"",maxifs(Documents!$E$2:$E$1421,Documents!$A$2:$A$1421,$A48,Documents!$C$2:$C$1421,"sustainability")),"") | Q48: =IFERROR(IF(maxifs(Documents!$E$2:$E$1421,Documents!$A$2:$A$1421,$A48,Documents!$C$2:$C$1421,"calendar")=0,"",maxifs(Documents!$E$2:$E$1421,Documents!$A$2:$A$1421,$A48,Documents!$C$2:$C$1421,"calendar")),"") | R48: =IFERROR(IF(maxifs(Documents!$E$2:$E$1421,Documents!$A$2:$A$1421,$A48,Documents!$C$2:$C$1421,"brochure")=0,"",maxifs(Documents!$E$2:$E$1421,Documents!$A$2:$A$1421,$A48,Documents!$C$2:$C$1421,"brochure")),"") | S48: =IFERROR(IF(maxifs(Documents!$E$2:$E$1421,Documents!$A$2:$A$1421,$A48,Documents!$C$2:$C$1421,"press_kit")=0,"",maxifs(Documents!$E$2:$E$1421,Documents!$A$2:$A$1421,$A48,Documents!$C$2:$C$1421,"press_kit")),"") | T48: =IFERROR(IF(maxifs(Documents!$E$2:$E$1421,Documents!$A$2:$A$1421,$A48,Documents!$C$2:$C$1421,"other")=0,"",maxifs(Documents!$E$2:$E$1421,Documents!$A$2:$A$1421,$A48,Documents!$C$2:$C$1421,"other")),"") | U48: =IFERROR(IF(maxifs(Documents!$E$2:$E$1421,Documents!$A$2:$A$1421,$A48,Documents!$C$2:$C$1421,"obsolete")=0,"",maxifs(Documents!$E$2:$E$1421,Documents!$A$2:$A$1421,$A48,Documents!$C$2:$C$1421,"obsolete")),"") | V48: =COUNTIFS(Documents!$A$2:$A$1421,$A48) -> 0 | W48: =COUNTIFS(Documents!$A$2:$A$1421,$A48,Documents!$R$2:$R$1421,"current") -> 0 | Y48: factsheet, wedding, events
